Workbook
Name A___Bonificação__lucros: #REF!
Name B_1___Administração_Central: #REF!
Name B_2___Seguro___Garantia: #REF!
Name B_3___Risco: #REF!
Name B_4___Despesas_Financeiras: #REF!
Name C_1___PIS___uso_do_REIDI: #REF!
Name C_2___ISS: #REF!
Name C_3___COFINS____Uso_do_Reidi: #REF!
Name C_4___CPRB: #REF!

Sheet Resumo
B3: FUNDO DE DESENVOLVIMENTO DA INFRAESTRUTURA REGIONAL SUSTENTÁVEL - FDIRS (“FDIRS”)
B5: ESTRUTURAÇÃO DE PROJETO DE CONCESSÃO DO PERÍMETRO IRRIGADO DO JAÍBA (ETAPAS 3 E 4)
J6: =SUMIF($A$11:$A$147,A94,$I$11:$I$147) -> 40996864 | K6: =J6/2 -> 20498432
B7: PLANILHA RESUMO DO ORÇAMENTO | J7: =SUMIF($A$11:$A$147,Cronograma!F2,$I$11:$I$147) -> 30120630
H8: DATA BASE: | I8: 45839 | J8: =SUMIF($A$11:$A$147,A105,$I$11:$I$147) -> 58404735
H9: BDI: | I9: =+BDI!C16 -> 0.2527
B10: ITEM | C10: FONTE | D10: CÓDIGO | E10: DESCRIÇÃO DA ATIVIDADE/SERVIÇO | F10: UNIDADE | G10: QUANTIDADE | H10: CUSTO UNITÁRIO (R$) | I10: CUSTO TOTAL (R$)
B11: 0 | C11: 0 | D11: 0 | E11: VALOR TOTAL DO PROJETO | F11: 0 | G11: 0 | H11: 0 | I11: =+I13+I161+I163+I165+I167+I169+I171 -> 4.7205359e+08
B13: A | C13: - | D13: - | E13: CANTEIRO DE OBRAS | F13: - | G13: 0 | H13: 0 | I13: =+Planilha!I13 -> 34844063
B15: B | C15: - | D15: - | E15: ETAPA 3 | F15: - | G15: 0 | H15: 0 | I15: =+Planilha!I19 -> 1.8505383e+08
B16: B1 | C16: - | D16: - | E16: SERVIÇOS TÉCNICOS DE ENGENHARIA | F16: - | G16: 0 | H16: 0 | I16: =+Planilha!I20 -> 12187104
B17: B2 | C17: - | D17: - | E17: OBRAS CIVIS | F17: - | G17: 0 | H17: 0 | I17: =+I18+I38+I50+I68+I71+I73+I75 -> 1.6180211e+08
B18: 1 | C18: - | D18: - | E18: CANAIS | F18: - | G18: 0 | H18: 0 | I18: =+I19+I25+I27+I29+I35 -> 1.3433664e+08
B19: 0 | C19: - | D19: - | E19: Canal: CS19 | F19: - | G19: 0 | H19: 0 | I19: =SUM(I20:I24) -> 61302489
B20: 1.1 | C20: - | D20: - | E20: Canal: CS19 - Trecho 1 | F20: - | G20: 0 | H20: 0 | I20: =+Planilha!I27 -> 2871252.9
B21: 1.2 | C21: - | D21: - | E21: Canal: CS19 - Trecho 2 | F21: - | G21: 0 | H21: 0 | I21: =+Planilha!I64 -> 15394371
B22: 1.3 | C22: - | D22: - | E22: Canal: CS19 - Trecho 3 | F22: - | G22: 0 | H22: 0 | I22: =+Planilha!I101 -> 14208007
B23: 1.4 | C23: - | D23: - | E23: Canal: CS19 - Trecho 4 | F23: - | G23: 0 | H23: 0 | I23: =+Planilha!I138 -> 12551586
B24: 1.5 | C24: - | D24: - | E24: Canal: CS19 - Trecho 5 | F24: - | G24: 0 | H24: 0 | I24: =+Planilha!I175 -> 16277272
B25: 0 | C25: - | D25: - | E25: Canal: CT1-CS19 | F25: - | G25: 0 | H25: 0 | I25: =SUM(I26:I26) -> 11436090
B26: 1.6 | C26: - | D26: - | E26: Canal: CT1-CS19 - Trecho 1 | F26: - | G26: 0 | H26: 0 | I26: =+Planilha!I213 -> 11436090
B27: 0 | C27: - | D27: - | E27: Canal: CS21 | F27: - | G27: 0 | H27: 0 | I27: =+I28 -> 5299527.5
B28: 1.7 | C28: - | D28: - | E28: Canal: CS21 | F28: - | G28: 0 | H28: 0 | I28: =+Planilha!I251 -> 5299527.5
B29: 0 | C29: - | D29: - | E29: Canal: CS21a | F29: - | G29: 0 | H29: 0 | I29: =SUM(I30:I34) -> 50460642
B30: 1.8 | C30: - | D30: - | E30: Canal: CS21a - Trecho 1 | F30: - | G30: 0 | H30: 0 | I30: =+Planilha!I289 -> 12223393
B31: 1.9 | C31: - | D31: - | E31: Canal: CS21a - Trecho 2 | F31: - | G31: 0 | H31: 0 | I31: =+Planilha!I326 -> 12110017
B32: 1.10 | C32: - | D32: - | E32: Canal: CS21a - Trecho 3 | F32: - | G32: 0 | H32: 0 | I32: =+Planilha!I363 -> 9927442.3
B33: 1.11 | C33: - | D33: - | E33: Canal: CS21a - Trecho 4 | F33: - | G33: 0 | H33: 0 | I33: =+Planilha!I400 -> 5463595.6
B34: 1.12 | C34: - | D34: - | E34: Canal: CS21a - Trecho 5 | F34: - | G34: 0 | H34: 0 | I34: =+Planilha!I437 -> 10736194
B35: 0 | C35: - | D35: - | E35: Canal: CT2-S21 | F35: - | G35: 0 | H35: 0 | I35: =+I36 -> 5837894.6
B36: 1.13 | C36: - | D36: - | E36: Canal: CT2-S21 | F36: - | G36: 0 | H36: 0 | I36: =+Planilha!I475 -> 5837894.6
B38: 2 | C38: - | D38: - | E38: ESTRUTURAS DE CONTROLE | F38: - | G38: 0 | H38: 0 | I38: =+I39+I44 -> 1505387.6
B39: 0 | C39: - | D39: - | E39: Canal: CS19 | F39: - | G39: 0 | H39: 0 | I39: =SUM(I40:I43) -> 716959.09
B40: 2.1 | C40: - | D40: - | E40: EC2 - CS19 | F40: - | G40: 0 | H40: 0 | I40: =+Planilha!I515 -> 195266.4
B41: 2.1 | C41: - | D41: - | E41: EC3 - CS19 | F41: - | G41: 0 | H41: 0 | I41: =+Planilha!I530 -> 181932.65
B42: 2.2 | C42: - | D42: - | E42: EC4 - CS19 | F42: - | G42: 0 | H42: 0 | I42: =+Planilha!I545 -> 181932.65
B43: 2.3 | C43: - | D43: - | E43: EC5 - CS19 | F43: - | G43: 0 | H43: 0 | I43: =+Planilha!I560 -> 157827.39
B44: 0 | C44: - | D44: - | E44: Canal: CS21a | F44: - | G44: 0 | H44: 0 | I44: =SUM(I45:I48) -> 788428.54
B45: 2.4 | C45: - | D45: - | E45: EC2 - CS21a | F45: - | G45: 0 | H45: 0 | I45: =+Planilha!I576 -> 217980.61
B46: 2.5 | C46: - | D46: - | E46: EC3 - CS21a | F46: - | G46: 0 | H46: 0 | I46: =+Planilha!I591 -> 201193.49
B47: 2.6 | C47: - | D47: - | E47: EC4 - CS21a | F47: - | G47: 0 | H47: 0 | I47: =+Planilha!I606 -> 193837.92
B48: 2.7 | C48: - | D48: - | E48: EC5 - CS21a | F48: - | G48: 0 | H48: 0 | I48: =+Planilha!I621 -> 175416.52
B50: 3 | C50: - | D50: - | E50: EXTRAVASORES | F50: - | G50: 0 | H50: 0 | I50: =+I51+I56+I58+I60+I65 -> 9312430.7
B51: 0 | C51: - | D51: - | E51: Canal: CS19 | F51: - | G51: 0 | H51: 0 | I51: =SUM(I52:I55) -> 3368975.4
B52: 3.1 | C52: - | D52: - | E52: EX-1 - CS19-Trecho 2 - km 4+200 | F52: - | G52: 0 | H52: 0 | I52: =+Planilha!I639 -> 1220950.9
B53: 3.2 | C53: - | D53: - | E53: EX-2 - CS19-Trecho 3 - km 9+400 | F53: - | G53: 0 | H53: 0 | I53: =+Planilha!I644 -> 869934.87
B54: 3.3 | C54: - | D54: - | E54: EX-3 - CS19-Trecho 4 - km 10+750 | F54: - | G54: 0 | H54: 0 | I54: =+Planilha!I649 -> 639044.8
B55: 3.4 | C55: - | D55: - | E55: EX-4 - CS19-Trecho 5 - km 19+500 | F55: - | G55: 0 | H55: 0 | I55: =+Planilha!I654 -> 639044.8
B56: 0 | C56: - | D56: - | E56: Canal: CT1-CS19 | F56: - | G56: 0 | H56: 0 | I56: =SUM(I57:I57) -> 389271.07
B57: 3.5 | C57: - | D57: - | E57: EX-5 - CT1-CS19-Trecho 1 - km 3+950 | F57: - | G57: 0 | H57: 0 | I57: =+Planilha!I660 -> 389271.07
B58: 0 | C58: - | D58: - | E58: Canal: CS21 | F58: - | G58: 0 | H58: 0 | I58: =+I59 -> 1509589.2
B59: 3.6 | C59: - | D59: - | E59: EX-1 - CS21 - km 1+350 | F59: - | G59: 0 | H59: 0 | I59: =+Planilha!I666 -> 1509589.2
B60: 0 | C60: - | D60: - | E60: Canal: CS21a | F60: - | G60: 0 | H60: 0 | I60: =SUM(I61:I64) -> 3727989
B61: 3.7 | C61: - | D61: - | E61: EX-2 - CS21a - Trecho 1 - km 3+300 | F61: - | G61: 0 | H61: 0 | I61: =+Planilha!I672 -> 1051457.8
B62: 3.8 | C62: - | D62: - | E62: EX-3 - CS21a - Trecho 2 - km 7+900 | F62: - | G62: 0 | H62: 0 | I62: =+Planilha!I677 -> 1265840.3
B63: 3.9 | C63: - | D63: - | E63: EX-4 - CS21a - Trecho 3.1 - km 11+700 | F63: - | G63: 0 | H63: 0 | I63: =+Planilha!I682 -> 887764.91
B64: 3.10 | C64: - | D64: - | E64: EX-5 - CS21a - Trecho 4 - km 15+900 | F64: - | G64: 0 | H64: 0 | I64: =+Planilha!I687 -> 522925.95
B65: 0 | C65: - | D65: - | E65: Canal: CT2-S21 | F65: - | G65: 0 | H65: 0 | I65: =+I66 -> 316606.02
B66: 3.11 | C66: - | D66: - | E66: EX-7 - CT2-S21 - km 2+200 | F66: - | G66: 0 | H66: 0 | I66: =+Planilha!I693 -> 316606.02
B68: 4 | C68: - | D68: - | E68: ESCADA HIDRÁULICA | F68: - | G68: 0 | H68: 0 | I68: =+I69 -> 2120756.3
B69: 4.1 | C69: - | D69: - | E69: ESCADA HIDRÁULICA CS21a | I69: =+Planilha!I700 -> 2120756.3
B71: 5 | C71: - | D71: - | E71: GALERIAS DE TRANSPOSIÇÃO | F71: - | G71: 0 | H71: 0 | I71: =+Planilha!I709 -> 869613.09
B73: 6 | C73: - | D73: - | E73: TRECHOS EM TUBULAÇÃO | F73: - | G73: 0 | H73: 0 | I73: =+Planilha!I765 -> 12404391
B75: 7 | C75: - | D75: - | E75: ESTAÇÃO DE RECALQUE | F75: - | G75: 0 | H75: 0 | I75: =+I76 -> 1252889.9
B76: 7.1 | C76: - | D76: - | E76: ESTAÇÃO DE RECALQUE ER1 | I76: =+Planilha!I776 -> 1252889.9
B78: B3 | C78: - | D78: - | E78: INSTALAÇÕES | F78: - | G78: 0 | H78: 0 | I78: =+I79 -> 11064618
B79: 1 | C79: - | D79: - | E79: EQUIPAMENTOS | F79: - | G79: 0 | H79: 0 | I79: =SUM(I80:I84) -> 11064618
B80: 1.1 | C80: - | D80: - | E80: CONJUNTO MOTOBOMBAS | F80: - | G80: 0 | H80: 0 | I80: =+Planilha!I789 -> 7544692.1
B81: 1.2 | C81: - | D81: - | E81: TUBULAÇÃO | F81: - | G81: 0 | H81: 0 | I81: =+Planilha!I792 -> 553999.62
B82: 1.3 | C82: - | D82: - | E82: COMPORTAS E GRADES | F82: - | G82: 0 | H82: 0 | I82: =+Planilha!I795 -> 1033778.1
B83: 1.4 | C83: - | D83: - | E83: EQUIPAMENTOS ELÉTRICOS | F83: - | G83: 0 | H83: 0 | I83: =+Planilha!I805 -> 1475525
B84: 1.5 | C84: - | D84: - | E84: PEÇAS E ACESSÓRIOS | F84: - | G84: 0 | H84: 0 | I84: =+Planilha!I807 -> 456623.49
B86: - | C86: - | D86: - | E86: SUBTOTAL ETAPA 3 (B2 + B3) | F86: - | G86: - | H86: - | I86: =+I17+I78 -> 1.7286673e+08
B87: - | C87: - | D87: - | E87: SERVIÇOS TÉCNICOS DE ENGENHARIA (B1) | F87: % | G87: - | H87: - | I87: =+I16 -> 12187104
B88: - | C88: - | D88: - | E88: TOTAL ETAPA 3 | F88: - | G88: - | H88: - | I88: =SUM(I86:I87) -> 1.8505383e+08
B90: C | C90: - | D90: - | E90: ETAPA 4 | F90: - | G90: 0 | H90: 0 | I90: =+Planilha!I1453 -> 1.5404225e+08
B91: C1 | C91: - | D91: - | E91: SERVIÇOS TÉCNICOS DE ENGENHARIA | F91: - | G91: 0 | H91: 0 | I91: =+Planilha!I815 -> 10144772
B92: C2 | C92: - | D92: - | E92: OBRAS CIVIS | F92: - | G92: 0 | H92: 0 | I92: =+I93+I111+I119+I136+I139+I143+I141 -> 1.2952223e+08
B93: 1 | C93: - | D93: - | E93: CANAIS | F93: - | G93: 0 | H93: 0 | I93: =+I94+I98+I101+I103+I105+I108 -> 84709229
A94: E4-L1 | B94: 0 | C94: - | D94: - | E94: Canal: CP3 | F94: - | G94: 0 | H94: 0 | I94: =SUM(I95:I97) -> 32679055
B95: 1.1 | C95: - | D95: - | E95: Canal: CP3 - Trecho 1 | F95: - | G95: 0 | H95: 0 | I95: =+Planilha!I822 -> 7307178.1
B96: 1.2 | C96: - | D96: - | E96: Canal: CP3 - Trecho 2 | F96: - | G96: 0 | H96: 0 | I96: =+Planilha!I859 -> 16259302
B97: 1.3 | C97: - | D97: - | E97: Canal: CP3 - Trecho 3 | F97: - | G97: 0 | H97: 0 | I97: =+Planilha!I896 -> 9112574.3
A98: E4-L2 | B98: 0 | C98: - | D98: - | E98: Canal: CP3a | F98: - | G98: 0 | H98: 0 | I98: =SUM(I99:I100) -> 20912363
B99: 1.4 | C99: - | D99: - | E99: Canal: CP3a - Trecho 1 | F99: - | G99: 0 | H99: 0 | I99: =+Planilha!I934 -> 13552805
B100: 1.5 | C100: - | D100: - | E100: Canal: CP3a - Trecho 2 | F100: - | G100: 0 | H100: 0 | I100: =+Planilha!I971 -> 7359558.7
A101: E4-L2 | B101: 0 | C101: - | D101: - | E101: Canal: CP3b | F101: - | G101: 0 | H101: 0 | I101: =SUM(I102:I102) -> 4625944.2
B102: 1.6 | C102: - | D102: - | E102: Canal: CP3b - Trecho 1 | F102: - | G102: 0 | H102: 0 | I102: =+Planilha!I1009 -> 4625944.2
A103: E4-L1 | B103: 0 | C103: - | D103: - | E103: Canal: CS23 | F103: - | G103: 0 | H103: 0 | I103: =+I104 -> 4387791.4
B104: 1.7 | C104: - | D104: - | E104: Canal: CS23 | F104: - | G104: 0 | H104: 0 | I104: =+Planilha!I1047 -> 4387791.4
A105: E4-L3 | B105: 0 | C105: - | D105: - | E105: Canal: CS25 | F105: - | G105: 0 | H105: 0 | I105: =SUM(I106:I107) -> 16562874
B106: 1.8 | C106: - | D106: - | E106: Canal: CS25 - Trecho 1 | F106: - | G106: 0 | H106: 0 | I106: =+Planilha!I1085 -> 8816295.7
B107: 1.9 | C107: - | D107: - | E107: Canal: CS25 - Trecho 2 | F107: - | G107: 0 | H107: 0 | I107: =+Planilha!I1122 -> 7746578.4
A108: E4-L3 | B108: 0 | C108: - | D108: - | E108: Canal: CS27 | F108: - | G108: 0 | H108: 0 | I108: =+I109 -> 5541200.9
B109: 1.10 | C109: - | D109: - | E109: Canal: CS27 | F109: - | G109: 0 | H109: 0 | I109: =+Planilha!I1160 -> 5541200.9
B111: 2 | C111: - | D111: - | E111: ESTRUTURAS DE CONTROLE | F111: - | G111: 0 | H111: 0 | I111: =+I112+I114+I116 -> 572810.63
A112: E4-L1 | B112: 0 | C112: - | D112: - | E112: Canal: CP3 | F112: - | G112: 0 | H112: 0 | I112: =+I113 -> 220237.87
B113: 2.1 | C113: - | D113: - | E113: EC2 - CP3 | F113: - | G113: 0 | H113: 0 | I113: =+Planilha!I1200 -> 220237.87
A114: E4-L2 | B114: 0 | C114: - | D114: - | E114: Canal: CP3a | F114: - | G114: 0 | H114: 0 | I114: =+I115 -> 183639.03
B115: 2.2 | C115: - | D115: - | E115: EC3 - CP3a | F115: - | G115: 0 | H115: 0 | I115: =+Planilha!I1216 -> 183639.03
...

Sheet Planilha
B3: FUNDO DE DESENVOLVIMENTO DA INFRAESTRUTURA REGIONAL SUSTENTÁVEL - FDIRS (“FDIRS”)
B5: ESTRUTURAÇÃO DE PROJETO DE CONCESSÃO DO PERÍMETRO IRRIGADO DO JAÍBA (ETAPAS 3 E 4)
B7: PLANILHA DE ORÇAMENTO
H8: DATA BASE: | I8: 45839
H9: BDI: | I9: =+BDI!C16 -> 0.2527
A10: 1 | B10: ITEM | C10: FONTE | D10: CÓDIGO | E10: DESCRIÇÃO DA ATIVIDADE/SERVIÇO | F10: UNIDADE | G10: QUANTIDADE | H10: CUSTO UNITÁRIO (R$) | I10: CUSTO TOTAL (R$) | J10: Aux_Cronograma
B11: 0 | C11: 0 | D11: 0 | E11: VALOR TOTAL DO PROJETO | F11: 0 | G11: 0 | H11: 0 | I11: =I13+I1455+I1457+I1460+I1466+I1470+I1473 -> 4.7205359e+08
B13: A | C13: - | D13: - | E13: CANTEIRO DE OBRAS | F13: - | G13: 0 | H13: 0 | I13: =SUM(I14:I17) -> 34844063 | J13: CANTEIRO
B14: 1 | C14: COMPOSIÇÃO | D14: 1 | E14: Instalação do Canteiro | F14: % | G14: 2 | H14: =+$I$1455-$I$20-$I$815 -> 3.1676421e+08 | I14: =+G14*H14/100 -> 6335284.1
B15: 2 | C15: COMPOSIÇÃO | D15: 1 | E15: Operação e Manutenção do Canteiro | F15: % | G15: 2.5 | H15: =+$I$1455-$I$20-$I$815 -> 3.1676421e+08 | I15: =+G15*H15/100 -> 7919105.2
B16: 3 | C16: COMPOSIÇÃO | D16: 1 | E16: Administração Local | F16: % | G16: 6 | H16: =+$I$1455-$I$20-$I$815 -> 3.1676421e+08 | I16: =+G16*H16/100 -> 19005852
B17: 4 | C17: COMPOSIÇÃO | D17: 1 | E17: Mobilização e Desmobilização de Equipamentos | F17: % | G17: 0.5 | H17: =+$I$1455-$I$20-$I$815 -> 3.1676421e+08 | I17: =+G17*H17/100 -> 1583821
B19: B | C19: - | D19: - | E19: ETAPA 3 | F19: - | G19: 0 | H19: 0 | I19: =+I812 -> 1.8505383e+08
B20: B1 | C20: - | D20: - | E20: SERVIÇOS TÉCNICOS DE ENGENHARIA | F20: - | G20: 0 | H20: 0 | I20: =SUM(I21:I23) -> 12187104
B21: 1 | C21: COMPOSIÇÃO | D21: 1 | E21: Projetos Básico/Executivo | F21: % | G21: 4 | H21: =+$I$809+$I$810 -> 1.7286673e+08 | I21: =+G21*H21/100 -> 6914669.2 | J21: PROJETO3
B22: 2 | C22: COMPOSIÇÃO | D22: 1 | E22: Gerenciamento/Supervisão de Obras | F22: % | G22: 3 | H22: =+$I$809+$I$810 -> 1.7286673e+08 | I22: =+G22*H22/100 -> 5186001.9 | J22: SUP3
B23: 3 | C23: COMPOSIÇÃO | D23: 1 | E23: Controles Tecnológicos | F23: % | G23: 0.05 | H23: =+$I$809+$I$810 -> 1.7286673e+08 | I23: =+G23*H23/100 -> 86433.365 | J23: SUP3
B24: B2 | C24: - | D24: - | E24: OBRAS CIVIS | F24: - | G24: 0 | H24: 0 | I24: =+I25+I513+I637+I699+I775+I709+I765 -> 1.6180211e+08
B25: 1 | C25: - | D25: - | E25: CANAIS | F25: - | G25: 0 | H25: 0 | I25: =+I26+I212+I250+I288+I474 -> 1.3433664e+08
B26: 0 | C26: - | D26: - | E26: Canal: CS19 | F26: - | G26: 0 | H26: 0 | I26: =+I27+I64+I101+I138+I175 -> 61302489
A27: E3-L1 | B27: 1.1 | C27: - | D27: - | E27: Canal: CS19 - Trecho 1 | F27: - | G27: 0 | H27: 0 | I27: =SUM(I28:I63) -> 2871252.9 | J27: E3-L1
B28: 1.1.1 | C28: - | D28: - | E28: TERRAPLENAGEM E TRATAMENTOS
B29: 1.1.1.1 | C29: SICRO | D29: 5501700 | E29: =VLOOKUP($D29,'Preços Unitários'!$B:$G,2,FALSE) -> Desmatamento, destocamento e limpeza de área com árvores de diâmetro até 0,15 m | F29: =VLOOKUP($D29,'Preços Unitários'!$B:$G,3,FALSE) -> m² | G29: =+'MC Canais'!J5 -> 34000 | H29: =VLOOKUP($D29,'Preços Unitários'!$B:$G,6,FALSE) -> 0.87689 | I29: =+G29*H29 -> 29814.26
B30: 1.1.1.2 | C30: SICRO | D30: 5502114 | E30: =VLOOKUP($D30,'Preços Unitários'!$B:$G,2,FALSE) -> Escavação, carga e transporte de material de 1ª categoria - DMT de 1.000 a 1.200 m - caminho de serviço em leito natural - com escavadeira e caminhão basculante de 14 m³ | F30: =VLOOKUP($D30,'Preços Unitários'!$B:$G,3,FALSE) -> m³ | G30: =+'MC Canais'!J6 -> 1218.69 | H30: =VLOOKUP($D30,'Preços Unitários'!$B:$G,6,FALSE) -> 10.673004 | I30: =+G30*H30 -> 13007.083
B31: 1.1.1.3 | C31: SICRO | D31: 5502978 | E31: =VLOOKUP($D31,'Preços Unitários'!$B:$G,2,FALSE) -> Compactação de aterros a 100% do Proctor normal | F31: =VLOOKUP($D31,'Preços Unitários'!$B:$G,3,FALSE) -> m³ | G31: =+'MC Canais'!J7 -> 40104.47 | H31: =VLOOKUP($D31,'Preços Unitários'!$B:$G,6,FALSE) -> 7.102809 | I31: =+G31*H31 -> 284854.39
B32: 1.1.1.4 | C32: SICRO | D32: 5915319 | E32: =VLOOKUP($D32,'Preços Unitários'!$B:$G,2,FALSE) -> Transporte com caminhão basculante de 14 m³ - rodovia em leito natural | F32: =VLOOKUP($D32,'Preços Unitários'!$B:$G,3,FALSE) -> tkm | G32: =+'MC Canais'!J8 -> 272200.46 | H32: =VLOOKUP($D32,'Preços Unitários'!$B:$G,6,FALSE) -> 1.165011 | I32: =+G32*H32 -> 317116.53
B33: 1.1.1.5 | C33: SICRO | D33: 4413986 | E33: =VLOOKUP($D33,'Preços Unitários'!$B:$G,2,FALSE) -> Regularização de superfície com motoniveladora | F33: =VLOOKUP($D33,'Preços Unitários'!$B:$G,3,FALSE) -> m² | G33: =+'MC Canais'!J9 -> 1530 | H33: =VLOOKUP($D33,'Preços Unitários'!$B:$G,6,FALSE) -> 0.100216 | I33: =+G33*H33 -> 153.33048
B34: 1.1.1.6 | C34: COMPOSIÇÃO | D34: CPU-CAN002 | E34: Fornecimento e instalação de geocomposto drenante para os taludes | F34: m² | G34: =+'MC Canais'!J10 -> 1901 | H34: =+'Composições de Preços'!$F$87 -> 59.387949 | I34: =+G34*H34 -> 112896.49
B35: 1.1.1.7 | C35: COMPOSIÇÃO | D35: CPU-CAN004 | E35: Regularização dos taludes do canal com solo-cimento (5% de cimento) | F35: m³ | G35: =+'MC Canais'!J11 -> 1520.6 | H35: =+'Composições de Preços'!$F$446 -> 99.894988 | I35: =+G35*H35 -> 151900.32
B36: 1.1.1.8 | C36: COMPOSIÇÃO | D36: CPU-CAN001 | E36: Fornecimento e aplicação de geomembrana sintética para impermeabilização do canal, 1,00 mm de espessura (PEAD) | F36: m² | G36: =+'MC Canais'!J12 -> 7603 | H36: =+'Composições de Preços'!$F$44 -> 73.117919 | I36: =+G36*H36 -> 555915.54
B37: 1.1.1.9 | C37: COMPOSIÇÃO | D37: CPU-CAN005 | E37: Ancoragem da geomembrana com escavação de material de 1ª e 2ª categorias | F37: m³ | G37: =+'MC Canais'!J13 -> 1700 | H37: =+'Composições de Preços'!$F$492 -> 107.93859 | I37: =+G37*H37 -> 183495.61
B38: 1.1.1.10 | C38: SICRO | D38: 1106280 | E38: =VLOOKUP($D38,'Preços Unitários'!$B:$G,2,FALSE) -> Concreto para bombeamento fck = 30 MPa - confecção em central dosadora de 30 m³/h - areia e brita comerciais | F38: =VLOOKUP($D38,'Preços Unitários'!$B:$G,3,FALSE) -> m³ | G38: =+'MC Canais'!J14 -> 532.21 | H38: =VLOOKUP($D38,'Preços Unitários'!$B:$G,6,FALSE) -> 575.92882 | I38: =+G38*H38 -> 306515.08
B39: 1.1.1.11 | C39: SICRO | D39: 1106088 | E39: =VLOOKUP($D39,'Preços Unitários'!$B:$G,2,FALSE) -> Lançamento mecânico de concreto com bomba rebocável com capacidade de 30 m³/h - confecção em central dosadora de 30 m³/h | F39: =VLOOKUP($D39,'Preços Unitários'!$B:$G,3,FALSE) -> m³ | G39: =+'MC Canais'!J15 -> 532.21 | H39: =VLOOKUP($D39,'Preços Unitários'!$B:$G,6,FALSE) -> 86.285976 | I39: =+G39*H39 -> 45922.259
B40: 1.1.1.12 | C40: SICRO | D40: 0307084 | E40: =VLOOKUP($D40,'Preços Unitários'!$B:$G,2,FALSE) -> Lábios poliméricos em junta de pavimento de concreto - L = 20 mm e H = 30 mm - confecção e assentamento | F40: =VLOOKUP($D40,'Preços Unitários'!$B:$G,3,FALSE) -> m | G40: =+'MC Canais'!J16 -> 4333.3 | H40: =VLOOKUP($D40,'Preços Unitários'!$B:$G,6,FALSE) -> 39.635428 | I40: =+G40*H40 -> 171752.2
B41: 1.1.1.13 | C41: COMPOSIÇÃO | D41: CPU-CAN003 | E41: Guias de proteção em concreto pré-moldado | F41: m | G41: =+'MC Canais'!J17 -> 1700 | H41: =+'Composições de Preços'!$F$130 -> 37.70077 | I41: =+G41*H41 -> 64091.308
B42: 1.1.1.14 | C42: SICRO | D42: 4415673 | E42: =VLOOKUP($D42,'Preços Unitários'!$B:$G,2,FALSE) -> Revestimento vegetal com grama em mudas em superfícies inclinadas | F42: =VLOOKUP($D42,'Preços Unitários'!$B:$G,3,FALSE) -> m² | G42: =+'MC Canais'!J18 -> 10200 | H42: =VLOOKUP($D42,'Preços Unitários'!$B:$G,6,FALSE) -> 9.984019 | I42: =+G42*H42 -> 101836.99
B43: 1.1.2 | C43: - | D43: - | E43: DRENAGEM INTERNA DOS CANAIS | G43: =+'MC Canais'!J19 -> 0
B44: 1.1.2.1 | C44: SICRO | D44: 4805757 | E44: =VLOOKUP($D44,'Preços Unitários'!$B:$G,2,FALSE) -> Escavação mecânica de vala em material de 1ª categoria | F44: =VLOOKUP($D44,'Preços Unitários'!$B:$G,3,FALSE) -> m³ | G44: =+'MC Canais'!J20 -> 714 | H44: =VLOOKUP($D44,'Preços Unitários'!$B:$G,6,FALSE) -> 8.731319 | I44: =+G44*H44 -> 6234.1618
B45: 1.1.2.2 | C45: SICRO | D45: 4815671 | E45: =VLOOKUP($D45,'Preços Unitários'!$B:$G,2,FALSE) -> Reaterro e compactação com soquete vibratório | F45: =VLOOKUP($D45,'Preços Unitários'!$B:$G,3,FALSE) -> m³ | G45: =+'MC Canais'!J21 -> 408 | H45: =VLOOKUP($D45,'Preços Unitários'!$B:$G,6,FALSE) -> 22.611235 | I45: =+G45*H45 -> 9225.3839
B46: 1.1.2.3 | C46: SICRO | D46: 5915319 | E46: =VLOOKUP($D46,'Preços Unitários'!$B:$G,2,FALSE) -> Transporte com caminhão basculante de 14 m³ - rodovia em leito natural | F46: =VLOOKUP($D46,'Preços Unitários'!$B:$G,3,FALSE) -> tkm | G46: =+'MC Canais'!J22 -> 2142 | H46: =VLOOKUP($D46,'Preços Unitários'!$B:$G,6,FALSE) -> 1.165011 | I46: =+G46*H46 -> 2495.4536
B47: 1.1.2.4 | C47: COMPOSIÇÃO | D47: CPU-DRE001 | E47: Fornecimento e aplicação de manta geotêxtil (Execução de dreno com manta geotêxtil 400 g/m2) | F47: m² | G47: =+'MC Canais'!J23 -> 2040 | H47: =+'Composições de Preços'!$F$173 -> 26.052133 | I47: =+G47*H47 -> 53146.35
B48: 1.1.2.5 | C48: SICRO | D48: 2003851 | E48: =VLOOKUP($D48,'Preços Unitários'!$B:$G,2,FALSE) -> Tubo de concreto perfurado produzido na obra para drenagem - D = 0,40 m - fornecimento e instalação | F48: =VLOOKUP($D48,'Preços Unitários'!$B:$G,3,FALSE) -> m | G48: =+'MC Canais'!J24 -> 850 | H48: =VLOOKUP($D48,'Preços Unitários'!$B:$G,6,FALSE) -> 116.76417 | I48: =+G48*H48 -> 99249.542
B49: 1.1.2.6 | C49: SICRO | D49: 2003850 | E49: =VLOOKUP($D49,'Preços Unitários'!$B:$G,2,FALSE) -> Lastro de brita comercial compactado com soquete vibratório - espalhamento manual | F49: =VLOOKUP($D49,'Preços Unitários'!$B:$G,3,FALSE) -> m³ | G49: =+'MC Canais'!J25 -> 199.24 | H49: =VLOOKUP($D49,'Preços Unitários'!$B:$G,6,FALSE) -> 239.34086 | I49: =+G49*H49 -> 47686.273
B50: 1.1.2.7 | C50: SICRO | D50: 2003767 | E50: =VLOOKUP($D50,'Preços Unitários'!$B:$G,2,FALSE) -> Lastro de areia comercial - espalhamento manual | F50: =VLOOKUP($D50,'Preços Unitários'!$B:$G,3,FALSE) -> m³ | G50: =+'MC Canais'!J26 -> 102 | H50: =VLOOKUP($D50,'Preços Unitários'!$B:$G,6,FALSE) -> 198.0644 | I50: =+G50*H50 -> 20202.568
B51: 1.1.3 | C51: - | D51: - | E51: OBRAS DE DRENAGEM SUPERFICIAL - VALETAS, SARJETAS, BUEIROS, GALERIAS E PASSAGENS MOLHADAS | G51: =+'MC Canais'!J27 -> 0
B52: 1.1.3.1 | C52: SICRO | D52: 2003305 | E52: =VLOOKUP($D52,'Preços Unitários'!$B:$G,2,FALSE) -> Valeta de proteção de cortes com revestimento vegetal - VPCG 120-30 - escavação mecânica | F52: =VLOOKUP($D52,'Preços Unitários'!$B:$G,3,FALSE) -> m | G52: =+'MC Canais'!J28 -> 1700 | H52: =VLOOKUP($D52,'Preços Unitários'!$B:$G,6,FALSE) -> 51.961996 | I52: =+G52*H52 -> 88335.393
B53: 1.1.3.2 | C53: SICRO | D53: 2003338 | E53: =VLOOKUP($D53,'Preços Unitários'!$B:$G,2,FALSE) -> Sarjeta triangular de grama - STG 125-25 - escavação mecânica | F53: =VLOOKUP($D53,'Preços Unitários'!$B:$G,3,FALSE) -> m | G53: =+'MC Canais'!J29 -> 1700 | H53: =VLOOKUP($D53,'Preços Unitários'!$B:$G,6,FALSE) -> 29.776679 | I53: =+G53*H53 -> 50620.354
B54: 1.1.3.3 | C54: SICRO | D54: 0804029 | E54: =VLOOKUP($D54,'Preços Unitários'!$B:$G,2,FALSE) -> Corpo de BSTC D = 0,80 m PA1 - areia, brita e pedra de mão comerciais | F54: =VLOOKUP($D54,'Preços Unitários'!$B:$G,3,FALSE) -> m | G54: =+'MC Canais'!J30 -> 0 | H54: =VLOOKUP($D54,'Preços Unitários'!$B:$G,6,FALSE) -> 799.67357 | I54: =+G54*H54 -> 0
B55: 1.1.3.4 | C55: SICRO | D55: 0804101 | E55: =VLOOKUP($D55,'Preços Unitários'!$B:$G,2,FALSE) -> Boca de BSTC D = 0,80 m - esconsidade 0° - areia e brita comerciais - alas retas | F55: =VLOOKUP($D55,'Preços Unitários'!$B:$G,3,FALSE) -> un | G55: =+'MC Canais'!J31 -> 0 | H55: =VLOOKUP($D55,'Preços Unitários'!$B:$G,6,FALSE) -> 1606.688 | I55: =+G55*H55 -> 0
B56: 1.1.4 | C56: - | D56: - | E56: ESTRADAS LATERAIS | G56: =+'MC Canais'!J32 -> 0
B57: 1.1.4.1 | C57: SICRO | D57: 5501706 | E57: =VLOOKUP($D57,'Preços Unitários'!$B:$G,2,FALSE) -> Escavação mecânica com retroescavadeira em material de 1ª categoria | F57: =VLOOKUP($D57,'Preços Unitários'!$B:$G,3,FALSE) -> m³ | G57: =+'MC Canais'!J33 -> 892.5 | H57: =VLOOKUP($D57,'Preços Unitários'!$B:$G,6,FALSE) -> 8.731319 | I57: =+G57*H57 -> 7792.7022
B58: 1.1.4.2 | C58: SICRO | D58: 5502978 | E58: =VLOOKUP($D58,'Preços Unitários'!$B:$G,2,FALSE) -> Compactação de aterros a 100% do Proctor normal | F58: =VLOOKUP($D58,'Preços Unitários'!$B:$G,3,FALSE) -> m³ | G58: =+'MC Canais'!J34 -> 595 | H58: =VLOOKUP($D58,'Preços Unitários'!$B:$G,6,FALSE) -> 7.102809 | I58: =+G58*H58 -> 4226.1714
B59: 1.1.4.3 | C59: SICRO | D59: 5915319 | E59: =VLOOKUP($D59,'Preços Unitários'!$B:$G,2,FALSE) -> Transporte com caminhão basculante de 14 m³ - rodovia em leito natural | F59: =VLOOKUP($D59,'Preços Unitários'!$B:$G,3,FALSE) -> tkm | G59: =+'MC Canais'!J35 -> 297.5 | H59: =VLOOKUP($D59,'Preços Unitários'!$B:$G,6,FALSE) -> 1.165011 | I59: =+G59*H59 -> 346.59077
B60: 1.1.4.4 | C60: SICRO | D60: 4413986 | E60: =VLOOKUP($D60,'Preços Unitários'!$B:$G,2,FALSE) -> Regularização de superfície com motoniveladora | F60: =VLOOKUP($D60,'Preços Unitários'!$B:$G,3,FALSE) -> m² | G60: =+'MC Canais'!J36 -> 5950 | H60: =VLOOKUP($D60,'Preços Unitários'!$B:$G,6,FALSE) -> 0.100216 | I60: =+G60*H60 -> 596.2852
B61: 1.1.4.5 | C61: COMPOSIÇÃO | D61: CPU-PAV001 | E61: Revestimento primário para as pistas laterais | F61: m³ | G61: =+'MC Canais'!J37 -> 446.25 | H61: =+'Composições de Preços'!$F$216 -> 214.4002 | I61: =+G61*H61 -> 95676.089
B62: 1.1.5 | C62: - | D62: - | E62: SERVIÇOS COMPLEMENTARES | G62: =+'MC Canais'!J38 -> 0
B63: 1.1.5.1 | C63: SICRO | D63: 3713613 | E63: =VLOOKUP($D63,'Preços Unitários'!$B:$G,2,FALSE) -> Cerca com 4 fios de arame liso galvanizado e mourão de madeira a cada 2,5 m e esticador a cada 50 m | F63: =VLOOKUP($D63,'Preços Unitários'!$B:$G,3,FALSE) -> m | G63: =+'MC Canais'!J39 -> 1700 | H63: =VLOOKUP($D63,'Preços Unitários'!$B:$G,6,FALSE) -> 27.146009 | I63: =+G63*H63 -> 46148.215
A64: E3-L1 | B64: 1.2 | C64: - | D64: - | E64: Canal: CS19 - Trecho 2 | F64: - | G64: 0 | H64: 0 | I64: =SUM(I65:I100) -> 15394371 | J64: E3-L1
B65: 1.2.1 | C65: - | D65: - | E65: TERRAPLENAGEM E TRATAMENTOS
B66: 1.2.1.1 | C66: SICRO | D66: 5501700 | E66: =VLOOKUP($D66,'Preços Unitários'!$B:$G,2,FALSE) -> Desmatamento, destocamento e limpeza de área com árvores de diâmetro até 0,15 m | F66: =VLOOKUP($D66,'Preços Unitários'!$B:$G,3,FALSE) -> m² | G66: =+'MC Canais'!J43 -> 198000 | H66: =VLOOKUP($D66,'Preços Unitários'!$B:$G,6,FALSE) -> 0.87689 | I66: =+G66*H66 -> 173624.22
B67: 1.2.1.2 | C67: SICRO | D67: 5502114 | E67: =VLOOKUP($D67,'Preços Unitários'!$B:$G,2,FALSE) -> Escavação, carga e transporte de material de 1ª categoria - DMT de 1.000 a 1.200 m - caminho de serviço em leito natural - com escavadeira e caminhão basculante de 14 m³ | F67: =VLOOKUP($D67,'Preços Unitários'!$B:$G,3,FALSE) -> m³ | G67: =+'MC Canais'!J44 -> 187330.72 | H67: =VLOOKUP($D67,'Preços Unitários'!$B:$G,6,FALSE) -> 10.673004 | I67: =+G67*H67 -> 1999381.5
B68: 1.2.1.3 | C68: SICRO | D68: 5502978 | E68: =VLOOKUP($D68,'Preços Unitários'!$B:$G,2,FALSE) -> Compactação de aterros a 100% do Proctor normal | F68: =VLOOKUP($D68,'Preços Unitários'!$B:$G,3,FALSE) -> m³ | G68: =+'MC Canais'!J45 -> 23759.27 | H68: =VLOOKUP($D68,'Preços Unitários'!$B:$G,6,FALSE) -> 7.102809 | I68: =+G68*H68 -> 168757.56
B69: 1.2.1.4 | C69: SICRO | D69: 5915319 | E69: =VLOOKUP($D69,'Preços Unitários'!$B:$G,2,FALSE) -> Transporte com caminhão basculante de 14 m³ - rodovia em leito natural | F69: =VLOOKUP($D69,'Preços Unitários'!$B:$G,3,FALSE) -> tkm | G69: =+'MC Canais'!J46 -> 1145000.1 | H69: =VLOOKUP($D69,'Preços Unitários'!$B:$G,6,FALSE) -> 1.165011 | I69: =+G69*H69 -> 1333937.8
B70: 1.2.1.5 | C70: SICRO | D70: 4413986 | E70: =VLOOKUP($D70,'Preços Unitários'!$B:$G,2,FALSE) -> Regularização de superfície com motoniveladora | F70: =VLOOKUP($D70,'Preços Unitários'!$B:$G,3,FALSE) -> m² | G70: =+'MC Canais'!J47 -> 7425 | H70: =VLOOKUP($D70,'Preços Unitários'!$B:$G,6,FALSE) -> 0.100216 | I70: =+G70*H70 -> 744.1038
B71: 1.2.1.6 | C71: COMPOSIÇÃO | D71: CPU-CAN002 | E71: Fornecimento e instalação de geocomposto drenante para os taludes | F71: m² | G71: =+'MC Canais'!J48 -> 9210 | H71: =+'Composições de Preços'!$F$87 -> 59.387949 | I71: =+G71*H71 -> 546963.01
B72: 1.2.1.7 | C72: COMPOSIÇÃO | D72: CPU-CAN004 | E72: Regularização dos taludes do canal com solo-cimento (5% de cimento) | F72: m³ | G72: =+'MC Canais'!J49 -> 7368 | H72: =+'Composições de Preços'!$F$446 -> 99.894988 | I72: =+G72*H72 -> 736026.27
B73: 1.2.1.8 | C73: COMPOSIÇÃO | D73: CPU-CAN001 | E73: Fornecimento e aplicação de geomembrana sintética para impermeabilização do canal, 1,00 mm de espessura (PEAD) | F73: m² | G73: =+'MC Canais'!J50 -> 36840 | H73: =+'Composições de Preços'!$F$44 -> 73.117919 | I73: =+G73*H73 -> 2693664.1
B74: 1.2.1.9 | C74: COMPOSIÇÃO | D74: CPU-CAN005 | E74: Ancoragem da geomembrana com escavação de material de 1ª e 2ª categorias | F74: m³ | G74: =+'MC Canais'!J51 -> 9900 | H74: =+'Composições de Preços'!$F$492 -> 107.93859 | I74: =+G74*H74 -> 1068592.1
B75: 1.2.1.10 | C75: SICRO | D75: 1106280 | E75: =VLOOKUP($D75,'Preços Unitários'!$B:$G,2,FALSE) -> Concreto para bombeamento fck = 30 MPa - confecção em central dosadora de 30 m³/h - areia e brita comerciais | F75: =VLOOKUP($D75,'Preços Unitários'!$B:$G,3,FALSE) -> m³ | G75: =+'MC Canais'!J52 -> 2578.8 | H75: =VLOOKUP($D75,'Preços Unitários'!$B:$G,6,FALSE) -> 575.92882 | I75: =+G75*H75 -> 1485205.3
B76: 1.2.1.11 | C76: SICRO | D76: 1106088 | E76: =VLOOKUP($D76,'Preços Unitários'!$B:$G,2,FALSE) -> Lançamento mecânico de concreto com bomba rebocável com capacidade de 30 m³/h - confecção em central dosadora de 30 m³/h | F76: =VLOOKUP($D76,'Preços Unitários'!$B:$G,3,FALSE) -> m³ | G76: =+'MC Canais'!J53 -> 2578.8 | H76: =VLOOKUP($D76,'Preços Unitários'!$B:$G,6,FALSE) -> 86.285976 | I76: =+G76*H76 -> 222514.27
B77: 1.2.1.12 | C77: SICRO | D77: 0307084 | E77: =VLOOKUP($D77,'Preços Unitários'!$B:$G,2,FALSE) -> Lábios poliméricos em junta de pavimento de concreto - L = 20 mm e H = 30 mm - confecção e assentamento | F77: =VLOOKUP($D77,'Preços Unitários'!$B:$G,3,FALSE) -> m | G77: =+'MC Canais'!J54 -> 21017.7 | H77: =VLOOKUP($D77,'Preços Unitários'!$B:$G,6,FALSE) -> 39.635428 | I77: =+G77*H77 -> 833045.54
B78: 1.2.1.13 | C78: COMPOSIÇÃO | D78: CPU-CAN003 | E78: Guias de proteção em concreto pré-moldado | F78: m | G78: =+'MC Canais'!J55 -> 9900 | H78: =+'Composições de Preços'!$F$130 -> 37.70077 | I78: =+G78*H78 -> 373237.62
B79: 1.2.1.14 | C79: SICRO | D79: 4415673 | E79: =VLOOKUP($D79,'Preços Unitários'!$B:$G,2,FALSE) -> Revestimento vegetal com grama em mudas em superfícies inclinadas | F79: =VLOOKUP($D79,'Preços Unitários'!$B:$G,3,FALSE) -> m² | G79: =+'MC Canais'!J56 -> 59400 | H79: =VLOOKUP($D79,'Preços Unitários'!$B:$G,6,FALSE) -> 9.984019 | I79: =+G79*H79 -> 593050.73
B80: 1.2.2 | C80: - | D80: - | E80: DRENAGEM INTERNA DOS CANAIS | G80: =+'MC Canais'!J57 -> 0
B81: 1.2.2.1 | C81: SICRO | D81: 4805757 | E81: =VLOOKUP($D81,'Preços Unitários'!$B:$G,2,FALSE) -> Escavação mecânica de vala em material de 1ª categoria | F81: =VLOOKUP($D81,'Preços Unitários'!$B:$G,3,FALSE) -> m³ | G81: =+'MC Canais'!J58 -> 4158 | H81: =VLOOKUP($D81,'Preços Unitários'!$B:$G,6,FALSE) -> 8.731319 | I81: =+G81*H81 -> 36304.824
B82: 1.2.2.2 | C82: SICRO | D82: 4815671 | E82: =VLOOKUP($D82,'Preços Unitários'!$B:$G,2,FALSE) -> Reaterro e compactação com soquete vibratório | F82: =VLOOKUP($D82,'Preços Unitários'!$B:$G,3,FALSE) -> m³ | G82: =+'MC Canais'!J59 -> 2376 | H82: =VLOOKUP($D82,'Preços Unitários'!$B:$G,6,FALSE) -> 22.611235 | I82: =+G82*H82 -> 53724.294
B83: 1.2.2.3 | C83: SICRO | D83: 5915319 | E83: =VLOOKUP($D83,'Preços Unitários'!$B:$G,2,FALSE) -> Transporte com caminhão basculante de 14 m³ - rodovia em leito natural | F83: =VLOOKUP($D83,'Preços Unitários'!$B:$G,3,FALSE) -> tkm | G83: =+'MC Canais'!J60 -> 12474 | H83: =VLOOKUP($D83,'Preços Unitários'!$B:$G,6,FALSE) -> 1.165011 | I83: =+G83*H83 -> 14532.347
B84: 1.2.2.4 | C84: COMPOSIÇÃO | D84: CPU-DRE001 | E84: Fornecimento e aplicação de manta geotêxtil (Execução de dreno com manta geotêxtil 400 g/m2) | F84: m² | G84: =+'MC Canais'!J61 -> 11880 | H84: =+'Composições de Preços'!$F$173 -> 26.052133 | I84: =+G84*H84 -> 309499.33
B85: 1.2.2.5 | C85: SICRO | D85: 2003851 | E85: =VLOOKUP($D85,'Preços Unitários'!$B:$G,2,FALSE) -> Tubo de concreto perfurado produzido na obra para drenagem - D = 0,40 m - fornecimento e instalação | F85: =VLOOKUP($D85,'Preços Unitários'!$B:$G,3,FALSE) -> m | G85: =+'MC Canais'!J62 -> 4950 | H85: =VLOOKUP($D85,'Preços Unitários'!$B:$G,6,FALSE) -> 116.76417 | I85: =+G85*H85 -> 577982.63
B86: 1.2.2.6 | C86: SICRO | D86: 2003850 | E86: =VLOOKUP($D86,'Preços Unitários'!$B:$G,2,FALSE) -> Lastro de brita comercial compactado com soquete vibratório - espalhamento manual | F86: =VLOOKUP($D86,'Preços Unitários'!$B:$G,3,FALSE) -> m³ | G86: =+'MC Canais'!J63 -> 1160.28 | H86: =VLOOKUP($D86,'Preços Unitários'!$B:$G,6,FALSE) -> 239.34086 | I86: =+G86*H86 -> 277702.42
B87: 1.2.2.7 | C87: SICRO | D87: 2003767 | E87: =VLOOKUP($D87,'Preços Unitários'!$B:$G,2,FALSE) -> Lastro de areia comercial - espalhamento manual | F87: =VLOOKUP($D87,'Preços Unitários'!$B:$G,3,FALSE) -> m³ | G87: =+'MC Canais'!J64 -> 594 | H87: =VLOOKUP($D87,'Preços Unitários'!$B:$G,6,FALSE) -> 198.0644 | I87: =+G87*H87 -> 117650.25
B88: 1.2.3 | C88: - | D88: - | E88: OBRAS DE DRENAGEM SUPERFICIAL - VALETAS, SARJETAS, BUEIROS, GALERIAS E PASSAGENS MOLHADAS | G88: =+'MC Canais'!J65 -> 0
B89: 1.2.3.1 | C89: SICRO | D89: 2003305 | E89: =VLOOKUP($D89,'Preços Unitários'!$B:$G,2,FALSE) -> Valeta de proteção de cortes com revestimento vegetal - VPCG 120-30 - escavação mecânica | F89: =VLOOKUP($D89,'Preços Unitários'!$B:$G,3,FALSE) -> m | G89: =+'MC Canais'!J66 -> 9900 | H89: =VLOOKUP($D89,'Preços Unitários'!$B:$G,6,FALSE) -> 51.961996 | I89: =+G89*H89 -> 514423.76
B90: 1.2.3.2 | C90: SICRO | D90: 2003338 | E90: =VLOOKUP($D90,'Preços Unitários'!$B:$G,2,FALSE) -> Sarjeta triangular de grama - STG 125-25 - escavação mecânica | F90: =VLOOKUP($D90,'Preços Unitários'!$B:$G,3,FALSE) -> m | G90: =+'MC Canais'!J67 -> 9900 | H90: =VLOOKUP($D90,'Preços Unitários'!$B:$G,6,FALSE) -> 29.776679 | I90: =+G90*H90 -> 294789.12
B91: 1.2.3.3 | C91: SICRO | D91: 0804029 | E91: =VLOOKUP($D91,'Preços Unitários'!$B:$G,2,FALSE) -> Corpo de BSTC D = 0,80 m PA1 - areia, brita e pedra de mão comerciais | F91: =VLOOKUP($D91,'Preços Unitários'!$B:$G,3,FALSE) -> m | G91: =+'MC Canais'!J68 -> 72.5 | H91: =VLOOKUP($D91,'Preços Unitários'!$B:$G,6,FALSE) -> 799.67357 | I91: =+G91*H91 -> 57976.334
B92: 1.2.3.4 | C92: SICRO | D92: 0804101 | E92: =VLOOKUP($D92,'Preços Unitários'!$B:$G,2,FALSE) -> Boca de BSTC D = 0,80 m - esconsidade 0° - areia e brita comerciais - alas retas | F92: =VLOOKUP($D92,'Preços Unitários'!$B:$G,3,FALSE) -> un | G92: =+'MC Canais'!J69 -> 6 | H92: =VLOOKUP($D92,'Preços Unitários'!$B:$G,6,FALSE) -> 1606.688 | I92: =+G92*H92 -> 9640.1278
B93: 1.2.4 | C93: - | D93: - | E93: ESTRADAS LATERAIS | G93: =+'MC Canais'!J70 -> 0
B94: 1.2.4.1 | C94: SICRO | D94: 5501706 | E94: =VLOOKUP($D94,'Preços Unitários'!$B:$G,2,FALSE) -> Escavação mecânica com retroescavadeira em material de 1ª categoria | F94: =VLOOKUP($D94,'Preços Unitários'!$B:$G,3,FALSE) -> m³ | G94: =+'MC Canais'!J71 -> 5197.5 | H94: =VLOOKUP($D94,'Preços Unitários'!$B:$G,6,FALSE) -> 8.731319 | I94: =+G94*H94 -> 45381.031
B95: 1.2.4.2 | C95: SICRO | D95: 5502978 | E95: =VLOOKUP($D95,'Preços Unitários'!$B:$G,2,FALSE) -> Compactação de aterros a 100% do Proctor normal | F95: =VLOOKUP($D95,'Preços Unitários'!$B:$G,3,FALSE) -> m³ | G95: =+'MC Canais'!J72 -> 3465 | H95: =VLOOKUP($D95,'Preços Unitários'!$B:$G,6,FALSE) -> 7.102809 | I95: =+G95*H95 -> 24611.233
B96: 1.2.4.3 | C96: SICRO | D96: 5915319 | E96: =VLOOKUP($D96,'Preços Unitários'!$B:$G,2,FALSE) -> Transporte com caminhão basculante de 14 m³ - rodovia em leito natural | F96: =VLOOKUP($D96,'Preços Unitários'!$B:$G,3,FALSE) -> tkm | G96: =+'MC Canais'!J73 -> 1732.5 | H96: =VLOOKUP($D96,'Preços Unitários'!$B:$G,6,FALSE) -> 1.165011 | I96: =+G96*H96 -> 2018.3816
B97: 1.2.4.4 | C97: SICRO | D97: 4413986 | E97: =VLOOKUP($D97,'Preços Unitários'!$B:$G,2,FALSE) -> Regularização de superfície com motoniveladora | F97: =VLOOKUP($D97,'Preços Unitários'!$B:$G,3,FALSE) -> m² | G97: =+'MC Canais'!J74 -> 34650 | H97: =VLOOKUP($D97,'Preços Unitários'!$B:$G,6,FALSE) -> 0.100216 | I97: =+G97*H97 -> 3472.4844
B98: 1.2.4.5 | C98: COMPOSIÇÃO | D98: CPU-PAV001 | E98: Revestimento primário para as pistas laterais | F98: m³ | G98: =+'MC Canais'!J75 -> 2598.75 | H98: =+'Composições de Preços'!$F$216 -> 214.4002 | I98: =+G98*H98 -> 557172.52
B99: 1.2.5 | C99: - | D99: - | E99: SERVIÇOS COMPLEMENTARES | G99: =+'MC Canais'!J76 -> 0
B100: 1.2.5.1 | C100: SICRO | D100: 3713613 | E100: =VLOOKUP($D100,'Preços Unitários'!$B:$G,2,FALSE) -> Cerca com 4 fios de arame liso galvanizado e mourão de madeira a cada 2,5 m e esticador a cada 50 m | F100: =VLOOKUP($D100,'Preços Unitários'!$B:$G,3,FALSE) -> m | G100: =+'MC Canais'!J77 -> 9900 | H100: =VLOOKUP($D100,'Preços Unitários'!$B:$G,6,FALSE) -> 27.146009 | I100: =+G100*H100 -> 268745.49
A101: E3-L1 | B101: 1.3 | C101: - | D101: - | E101: Canal: CS19 - Trecho 3 | F101: - | G101: 0 | H101: 0 | I101: =SUM(I102:I137) -> 14208007 | J101: E3-L1
B102: 1.3.1 | C102: - | D102: - | E102: TERRAPLENAGEM E TRATAMENTOS
B103: 1.3.1.1 | C103: SICRO | D103: 5501700 | E103: =VLOOKUP($D103,'Preços Unitários'!$B:$G,2,FALSE) -> Desmatamento, destocamento e limpeza de área com árvores de diâmetro até 0,15 m | F103: =VLOOKUP($D103,'Preços Unitários'!$B:$G,3,FALSE) -> m² | G103: =+'MC Canais'!J81 -> 171680 | H103: =VLOOKUP($D103,'Preços Unitários'!$B:$G,6,FALSE) -> 0.87689 | I103: =+G103*H103 -> 150544.48
B104: 1.3.1.2 | C104: SICRO | D104: 5502114 | E104: =VLOOKUP($D104,'Preços Unitários'!$B:$G,2,FALSE) -> Escavação, carga e transporte de material de 1ª categoria - DMT de 1.000 a 1.200 m - caminho de serviço em leito natural - com escavadeira e caminhão basculante de 14 m³ | F104: =VLOOKUP($D104,'Preços Unitários'!$B:$G,3,FALSE) -> m³ | G104: =+'MC Canais'!J82 -> 257084.94 | H104: =VLOOKUP($D104,'Preços Unitários'!$B:$G,6,FALSE) -> 10.673004 | I104: =+G104*H104 -> 2743868.6
B105: 1.3.1.3 | C105: SICRO | D105: 5502978 | E105: =VLOOKUP($D105,'Preços Unitários'!$B:$G,2,FALSE) -> Compactação de aterros a 100% do Proctor normal | F105: =VLOOKUP($D105,'Preços Unitários'!$B:$G,3,FALSE) -> m³ | G105: =+'MC Canais'!J83 -> 31272.74 | H105: =VLOOKUP($D105,'Preços Unitários'!$B:$G,6,FALSE) -> 7.102809 | I105: =+G105*H105 -> 222124.3
B106: 1.3.1.4 | C106: SICRO | D106: 5915319 | E106: =VLOOKUP($D106,'Preços Unitários'!$B:$G,2,FALSE) -> Transporte com caminhão basculante de 14 m³ - rodovia em leito natural | F106: =VLOOKUP($D106,'Preços Unitários'!$B:$G,3,FALSE) -> tkm | G106: =+'MC Canais'!J84 -> 1580685.4 | H106: =VLOOKUP($D106,'Preços Unitários'!$B:$G,6,FALSE) -> 1.165011 | I106: =+G106*H106 -> 1841515.9
...

Sheet Cronograma
B1: Cronograma - Alternativa 1 (implantação independente entre Etapas)
B2: Ano de concessão | C2: Proj executivo | D2: Ampliação EB1, 2 e 3 e conexão com CEMIG | E2: E4-L1 | F2: E4-L2 | G2: E4-L3 | H2: E3-L1 | I2: E3-L2 | J2: E3-L3 | K2: E3-L4 | L2: Total | N2: Proj executivo | O2: Ampliação EB1, 2 e 3 e conexão com CEMIG | P2: E4-L1 | Q2: E4-L2 | R2: E4-L3 | S2: E3-L1 | T2: E3-L2 | U2: E3-L3 | V2: E3-L4
B3: 1 | L3: =SUM(C3:K3) -> 0
B4: 2 | C4: =Planilha!I816 -> 5755899.1 | L4: =SUM(C4:K4) -> 5755899.1 | N4: =C4/$K$26 -> #DIV/0!
B5: 3 | D5: =Resumo!I167+Resumo!I169+Resumo!I171+Resumo!I163+Resumo!I165 -> 98113444 | E5: =((SUMIF(Planilha!$A$11:$A$1447,Cronograma!E$2,Planilha!$I$11:$I$1447)/2)+(SUMIF(Planilha!$J$11:$J$1447,"E4-L1i",Planilha!$I$11:$I$1447)/2)*$C$15)+(Planilha!$I$817+Planilha!$I$818)*$D$23+(Planilha!$I$13*$D$21) -> 23675181 | L5: =SUM(C5:K5) -> 1.2178862e+08 | O5: =$D$5/$K$26/2 -> #DIV/0! | P5: =#REF!/$K$26 -> #REF!
B6: 4 | E6: =((SUMIF(Planilha!$A$11:$A$1447,Cronograma!E$2,Planilha!$I$11:$I$1447)/2)+(SUMIF(Planilha!$J$11:$J$1447,"E4-L1i",Planilha!$I$11:$I$1447)/2)*$C$15)+(Planilha!$I$817+Planilha!$I$818)*$E$23+(Planilha!$I$13*$E$21) -> 23675181 | L6: =SUM(C6:K6) -> 23675181 | O6: =$D$5/$K$26/2 -> #DIV/0! | P6: =E6/$K$26 -> #DIV/0!
B7: 5 | F7: =(SUMIF(Planilha!$A$11:$A$1447,Cronograma!F$2,Planilha!$I$11:$I$1447)/2)+((SUMIF(Planilha!$J$11:$J$1447,"E4-L2i",Planilha!$I$11:$I$1447)/2)*$C$15)+(Planilha!$I$817+Planilha!$I$818)*$F$23+(Planilha!$I$13*$F$21) -> 40136311 | L7: =SUM(C7:K7) -> 40136311 | Q7: =F7/$K$26 -> #DIV/0!
B8: 6 | C8: =Planilha!I21 -> 6914669.2 | F8: =(SUMIF(Planilha!$A$11:$A$1447,Cronograma!F$2,Planilha!$I$11:$I$1447)/2)+((SUMIF(Planilha!$J$11:$J$1447,"E4-L2i",Planilha!$I$11:$I$1447)/2)*$C$15) -> 36915970 | G8: =(SUMIF(Planilha!$A$11:$A$1447,Cronograma!G$2,Planilha!$I$11:$I$1447)/2)+((SUMIF(Planilha!$J$11:$J$1447,"E4-L3i",Planilha!$I$11:$I$1447)/2)*$C$15)+(Planilha!$I$817+Planilha!$I$818)*$G$23+(Planilha!$I$13*$G$21) -> 21018609 | L8: =SUM(C8:K8) -> 64849249 | Q8: =F8/$K$26 -> #DIV/0! | R8: =G8/$K$26 -> #DIV/0!
B9: 7 | G9: =(SUMIF(Planilha!$A$11:$A$1447,Cronograma!G$2,Planilha!$I$11:$I$1447)/2)+((SUMIF(Planilha!$J$11:$J$1447,"E4-L3i",Planilha!$I$11:$I$1447)/2)*$C$15)+(Planilha!$I$817+Planilha!$I$818)*$H$23+(Planilha!$I$13*$H$21) -> 17798269 | H9: =(SUMIF(Planilha!$J$11:$J$1447,Cronograma!H$2,Planilha!$I$11:$I$1447)/2)+(SUMIF(Planilha!$J$11:$J$1447,"E3-L1I",Planilha!$I$11:$I$1447)/2)++((SUMIF(Planilha!$J$11:$J$1447,"E3-L1i",Planilha!$I$11:$I$1447)/2)*$C$15)+(Planilha!$I$22+Planilha!$I$23)*$H$24+(Planilha!$I$13*$H$22) -> 26603583 | L9: =SUM(C9:K9) -> 44401852 | N9: =C8/$K$26 -> #DIV/0! | R9: =G9/$K$26 -> #DIV/0!
B10: 8 | H10: =(SUMIF(Planilha!$J$11:$J$1447,Cronograma!H$2,Planilha!$I$11:$I$1447)/2)+(SUMIF(Planilha!$J$11:$J$1447,"E3-L1I",Planilha!$I$11:$I$1447)/2)+((SUMIF(Planilha!$J$11:$J$1447,"E3-L1i",Planilha!$I$11:$I$1447)/2)*$C$15) -> 23455667 | I10: =(SUMIF(Planilha!$J$11:$J$1447,Cronograma!I$2,Planilha!$I$11:$I$1447)/2)+(SUMIF(Planilha!$J$11:$J$1447,"E3-L2I",Planilha!$I$11:$I$1447)/2)+((SUMIF(Planilha!$J$11:$J$1447,"E3-L2i",Planilha!$I$11:$I$1447)/2)*$C$15)+(Planilha!$I$22+Planilha!$I$23)*$I$24+(Planilha!$I$13*$I$22) -> 32123417 | L10: =SUM(C10:K10) -> 55579084 | S10: =H9/$K$26 -> #DIV/0!
B11: 9 | I11: =(SUMIF(Planilha!$J$11:$J$1447,Cronograma!I$2,Planilha!$I$11:$I$1447)/2)+(SUMIF(Planilha!$J$11:$J$1447,"E3-L2I",Planilha!$I$11:$I$1447)/2)+((SUMIF(Planilha!$J$11:$J$1447,"E3-L2i",Planilha!$I$11:$I$1447)/2)*$C$15) -> 25827584 | J11: =(SUMIF(Planilha!$J$11:$J$1447,Cronograma!J$2,Planilha!$I$11:$I$1447)/2)+(SUMIF(Planilha!$J$11:$J$1447,"E3-L3I",Planilha!$I$11:$I$1447)/2)+((SUMIF(Planilha!$J$11:$J$1447,"E3-L3i",Planilha!$I$11:$I$1447)/2)*$C$15)+(Planilha!$I$22+Planilha!$I$23)*$J$24+(Planilha!$I$13*$J$22) -> 27994744 | L11: =SUM(C11:K11) -> 53822329 | S11: =H10/$K$26 -> #DIV/0! | T11: =I10/$K$26 -> #DIV/0!
B12: 10 | J12: =(SUMIF(Planilha!$J$11:$J$1447,Cronograma!J$2,Planilha!$I$11:$I$1447)/2)+(SUMIF(Planilha!$J$11:$J$1447,"E3-L3I",Planilha!$I$11:$I$1447)/2)+((SUMIF(Planilha!$J$11:$J$1447,"E3-L3i",Planilha!$I$11:$I$1447)/2)*$C$15) -> 21698912 | K12: =(SUMIF(Planilha!$J$11:$J$1447,Cronograma!K$2,Planilha!$I$11:$I$1447)/2)+(SUMIF(Planilha!$J$11:$J$1447,"E3-L4I",Planilha!$I$11:$I$1447)/2)++((SUMIF(Planilha!$J$11:$J$1447,"E3-L4i",Planilha!$I$11:$I$1447)/2)*$C$15)+(Planilha!$I$22+Planilha!$I$23)*$K$24+(Planilha!$I$13*$K$22) -> 21747033 | L12: =SUM(C12:K12) -> 43445945 | T12: =I11/$K$26 -> #DIV/0! | U12: =J11/$K$26 -> #DIV/0!
B13: 11 | K13: =(SUMIF(Planilha!$J$11:$J$1447,Cronograma!K$2,Planilha!$I$11:$I$1447)/2)++(SUMIF(Planilha!$J$11:$J$1447,"E3-L4I",Planilha!$I$11:$I$1447)/2)++((SUMIF(Planilha!$J$11:$J$1447,"E3-L4i",Planilha!$I$11:$I$1447)/2)*$C$15)++(Planilha!$I$22+Planilha!$I$23)*$L$24+(Planilha!$I$13*$L$22) -> 18599117 | L13: =SUM(C13:K13) -> 18599117 | U13: =J12/$K$26 -> #DIV/0! | V13: =K12/$K$26 -> #DIV/0!
B15: Equipamentos, peças e acessórios | C15: 0.05 | L15: =SUM(L3:L13) -> 4.7205359e+08
B16: Total Lotes | C16: =SUM(C17:C18) -> 14 | L16: =L15=Planilha!I11 -> TRUE
B17: Lotes E3 | C17: =COUNT($H$3:$K$13) -> 8
B18: Lotes E4 | C18: =COUNT($E$3:$G$13) -> 6
B20: Cronograma | C20: 2 | D20: 3 | E20: 4 | F20: 5 | G20: 6 | H20: 7 | I20: 8 | J20: 9 | K20: 10 | L20: 11
B21: Canteiro de obras - E4 | D21: =1/$C$16 -> 0.071428571 | E21: =1/$C$16 -> 0.071428571 | F21: =1/$C$16 -> 0.071428571 | G21: =1/$C$16*2 -> 0.14285714 | H21: =1/$C$16 -> 0.071428571
B22: Canteiro de obras - E3 | H22: =1/$C$16 -> 0.071428571 | I22: =1/$C$16*2 -> 0.14285714 | J22: =1/$C$16*2 -> 0.14285714 | K22: =1/$C$16*2 -> 0.14285714 | L22: =1/$C$16 -> 0.071428571
B23: Supervisão de obras - E4 | D23: =1/$C$18 -> 0.16666667 | E23: =1/$C$18 -> 0.16666667 | F23: =1/$C$18 -> 0.16666667 | G23: =1/$C$18*2 -> 0.33333333 | H23: =1/$C$18 -> 0.16666667
B24: Supervisão de obras - E3 | H24: =1/$C$17 -> 0.125 | I24: =1/$C$17*2 -> 0.25 | J24: =1/$C$17*2 -> 0.25 | K24: =1/$C$17*2 -> 0.25 | L24: =1/$C$17 -> 0.125
B27: Faseamento Implantação Projeto Jaíba
B28: Etapa | C28: Lote | D28: Canais | E28: Ext. (km) | F28: Blocos | G28: Área (ha) | H28: Obs.
B29: 3 | C29: 1 | D29: CS19 (até EC3) | E29: 10.1 | F29: 7 | G29: 2386.6735
D30: CT1-S19 | E30: 5.35 | F30: 3 | G30: 822.54714
D31: Total | E31: =SUM(E29:E30) -> 15.45 | F31: =SUM(F29:F30) -> 10 | G31: =SUM(G29:G30) -> 3209.2207
C32: 3 | D32: CS19 (até final) | E32: =22.18-E29 -> 12.08 | F32: 7 | G32: 1949.3665
D33: Total | E33: =E32 -> 12.08 | F33: =F32 -> 7 | G33: =G32 -> 1949.3665
C34: 2 | D34: CS21 (até EC3) | E34: 8 | F34: 7 | G34: 2217.8547
D35: CT2-S21 | E35: 2.6 | F35: 4 | G35: 1367.0125
D36: Total | E36: =SUM(E34:E35) -> 10.6 | F36: =F34+F35 -> 11 | G36: =G34+G35 -> 3584.8672
C37: 4 | D37: CS21 (até final) | E37: =19.2-E34 -> 11.2 | F37: 8 | G37: 1973.6512
D38: Total | E38: =E37 -> 11.2 | F38: =F37 -> 8 | G38: =G37 -> 1973.6512 | I38: =G31+G33+G36+G38 -> 10717.106
B39: 4 | C39: 1 | D39: CP3 | E39: 10 | F39: 10 | G39: 2764
D40: CS23 | E40: 2.6 | F40: 1 | G40: 269
D41: Total | E41: =E39+E40 -> 12.6 | F41: =F39+F40 -> 11 | G41: =G39+G40 -> 3033
C42: 2 | D42: CP3a | E42: 9.9 | F42: 9 | G42: 2501
D43: CP3b | E43: 4 | F43: 6 | G43: 1016
D44: TS29 | E44: 1.6 | F44: 1 | G44: 127
D45: Total | E45: =E42+E43+E44 -> 15.5 | F45: =F42+F43+F44 -> 16 | G45: =G42+G43+G44 -> 3644
C46: 3 | D46: CS25 | E46: 7.7 | F46: 8 | G46: 2850
D47: CS27 | E47: 3.2 | F47: 2 | G47: 544
D48: Total | E48: =E46+E47 -> 10.9 | F48: =F46+F47 -> 10 | G48: =G46+G47 -> 3394 | I48: =G41+G45+G48 -> 10071

Sheet Preços Unitários
F4: =+BDI!C16 -> 0.2527
A5: Fonte | B5: Código | C5: Descrição do Serviço | D5: Unidade | E5: Custo Unitário (R$) | F5: BDI | G5: Preço Unitário com BDI (R$)
A6: SICRO | B6: 0307731 | C6: Aparelho de apoio de neoprene fretado para estruturas moldadas no local - fornecimento e instalação | D6: dm³ | E6: 150.12 | F6: =+E6*$F$4 -> 37.935324 | G6: =+E6+F6 -> 188.05532
A7: SICRO | B7: 0307732 | C7: Aparelho de apoio de neoprene fretado para estruturas pré-moldadas - fornecimento e instalação | D7: dm³ | E7: 124.93 | F7: =+E7*$F$4 -> 31.569811 | G7: =+E7+F7 -> 156.49981
A8: SICRO | B8: 0308308 | C8: Aparelho de apoio metálico elastomérico fixo com capacidade de 1.500 kN - fornecimento e instalação | D8: un | E8: 5208.94 | F8: =+E8*$F$4 -> 1316.2991 | G8: =+E8+F8 -> 6525.2391
A9: SICRO | B9: 0308313 | C9: Aparelho de apoio metálico elastomérico fixo com capacidade de 10.000 kN - fornecimento e instalação | D9: un | E9: 32060.18 | F9: =+E9*$F$4 -> 8101.6075 | G9: =+E9+F9 -> 40161.787
A10: SICRO | B10: 0308309 | C10: Aparelho de apoio metálico elastomérico fixo com capacidade de 2.500 kN - fornecimento e instalação | D10: un | E10: 8634.05 | F10: =+E10*$F$4 -> 2181.8244 | G10: =+E10+F10 -> 10815.874
A11: SICRO | B11: 0308310 | C11: Aparelho de apoio metálico elastomérico fixo com capacidade de 4.000 kN - fornecimento e instalação | D11: un | E11: 11540.09 | F11: =+E11*$F$4 -> 2916.1807 | G11: =+E11+F11 -> 14456.271
A12: SICRO | B12: 0308311 | C12: Aparelho de apoio metálico elastomérico fixo com capacidade de 5.500 kN - fornecimento e instalação | D12: un | E12: 16369.55 | F12: =+E12*$F$4 -> 4136.5853 | G12: =+E12+F12 -> 20506.135
A13: SICRO | B13: 0308312 | C13: Aparelho de apoio metálico elastomérico fixo com capacidade de 7.500 kN - fornecimento e instalação | D13: un | E13: 22859.75 | F13: =+E13*$F$4 -> 5776.6588 | G13: =+E13+F13 -> 28636.409
A14: SICRO | B14: 0308307 | C14: Aparelho de apoio metálico elastomérico fixo com capacidade de 700 kN - fornecimento e instalação | D14: un | E14: 3103.37 | F14: =+E14*$F$4 -> 784.2216 | G14: =+E14+F14 -> 3887.5916
A15: SICRO | B15: 0308322 | C15: Aparelho de apoio metálico elastomérico multidirecional com capacidade de 1.500 kN - fornecimento e instalação | D15: un | E15: 4910.86 | F15: =+E15*$F$4 -> 1240.9743 | G15: =+E15+F15 -> 6151.8343
A16: SICRO | B16: 0308327 | C16: Aparelho de apoio metálico elastomérico multidirecional com capacidade de 10.000 kN - fornecimento e instalação | D16: un | E16: 29569.3 | F16: =+E16*$F$4 -> 7472.1621 | G16: =+E16+F16 -> 37041.462
A17: SICRO | B17: 0308323 | C17: Aparelho de apoio metálico elastomérico multidirecional com capacidade de 2.500 kN - fornecimento e instalação | D17: un | E17: 7724.89 | F17: =+E17*$F$4 -> 1952.0797 | G17: =+E17+F17 -> 9676.9697
... A6499: SICRO | B6499: 7107378 | C6499: Tratamento superficial e pintura do fundo do flutuante | D6499: m² | E6499: 190.02 | F6499: =+E6499*$F$4 -> 48.018054 | G6499: =+E6499+F6499 -> 238.03805

Sheet BDI
B2: A - Bonificação (lucros) | C2: 0.08
B4: B - Despesas Indiretas | C4: =SUM(C5:C8) -> 0.0894
B5: B 1 - Administração Central | C5: 0.07
B6: B 2 - Seguro + Garantia | C6: 0.0031
B7: B 3 - Risco | C7: 0.0063
B8: B 4 - Despesas Financeiras | C8: 0.01
B10: C - Tributos | C10: =SUM(C11:C14) -> 0.0833
B11: C 1 - PIS | C11: 0.0081
B12: C 2 - ISS | C12: 0.0376
B13: C 3 - COFINS | C13: 0.0376
B14: C 4 - CPRB | C14: 0
B16: BDI | C16: =+C2+C4+C10 -> 0.2527

Sheet Composições de Preços
A1: DEMONSTRATIVO DAS COMPOSICOES DE PRECOS UNITARIOS DE SERVICOS | F1: DATA BASE: 07/2025
A3: Discriminação: | B3: Fornecimento e aplicação de geomembrana sintética para impermeabilização do canal, 1,00 mm de espessura (PEAD) | E3: CÓDIGO: | F3: CPU-CAN001
E4: UNIDADE: | F4: m²
A6: CÓDIGO DO INSUMO | B6: DESCRIÇÃO | C6: UNIDADE | D6: VALOR UNITÁRIO | E6: COEFICIENTE | F6: VALOR PARCELA
A8: MATERIAL
A9: COTAÇÃO | B9: Manta termoplástica, PEAD, geomembrana texturizada em ambas as faces, e = 1,00 mm (NBR 15352) | C9: m² | D9: 46.22 | E9: 1.05 | F9: =+D9*E9 -> 48.531
F10: =+D10*E10 -> 0
F11: =+D11*E11 -> 0
F12: =+D12*E12 -> 0
F13: =+D13*E13 -> 0
A15: MÃO DE OBRA
A16: P9821 | B16: Pedreiro | C16: hora | D16: 27.5523 | E16: 0.2 | F16: =+D16*E16 -> 5.51046
A17: P9824 | B17: Servente | C17: hora | D17: 21.634 | E17: 0.2 | F17: =+D17*E17 -> 4.3268
F18: =+D18*E18 -> 0
F19: =+D19*E19 -> 0
A21: EQUIPAMENTO
F23: =+D23*E23 -> 0
F24: =+D24*E24 -> 0
F25: =+D25*E25 -> 0
F26: =+D26*E26 -> 0
A28: OUTROS SERVIÇOS
F30: =+D30*E30 -> 0
F31: =+D31*E31 -> 0
F32: =+D32*E32 -> 0
F33: =+D33*E33 -> 0
D35: COMPONENTES DE CUSTO
D36: MATERIAL | E36: =+F36/F$41 -> 0.83146217 | F36: =SUM(F9:F14) -> 48.531
D37: MÃO DE OBRA | E37: =+F37/F$41 -> 0.16853783 | F37: =SUM(F16:F20) -> 9.83726
D38: EQUIPAMENTO | E38: =+F38/F$41 -> 0 | F38: =SUM(F23:F27) -> 0
D39: OUTROS SERVIÇOS | E39: =+F39/F$41 -> 0 | F39: =SUM(F30:F33) -> 0
D41: CUSTO TOTAL | E41: =SUM(E36:E40) -> 1 | F41: =SUM(F36:F40) -> 58.36826
D42: BDI | E42: 0.2527 | F42: =+F41*E42 -> 14.749659
D44: PREÇO TOTAL | F44: =SUM(F41:F43) -> 73.117919
A46: Discriminação: | B46: Fornecimento e instalação de geocomposto drenante para os taludes | E46: CÓDIGO: | F46: CPU-CAN002
E47: UNIDADE: | F47: m²
A49: CÓDIGO DO INSUMO | B49: DESCRIÇÃO | C49: UNIDADE | D49: VALOR UNITÁRIO | E49: COEFICIENTE | F49: VALOR PARCELA
A51: MATERIAL
A52: M0107 | B52: Geocomposto para drenagem | C52: m² | D52: 43.0225 | E52: 1.1 | F52: =+D52*E52 -> 47.32475
F53: =+D53*E53 -> 0
F54: =+D54*E54 -> 0
F55: =+D55*E55 -> 0
F56: =+D56*E56 -> 0
A58: MÃO DE OBRA
A59: P9824 | B59: Servente | C59: hora | D59: 21.634 | E59: =2/520 -> 0.0038461538 | F59: =+D59*E59 -> 0.083207692
F60: =+D60*E60 -> 0
F61: =+D61*E61 -> 0
F62: =+D62*E62 -> 0
A64: EQUIPAMENTO
F66: =+D66*E66 -> 0
F67: =+D67*E67 -> 0
F68: =+D68*E68 -> 0
F69: =+D69*E69 -> 0
A71: OUTROS SERVIÇOS
F73: =+D73*E73 -> 0
F74: =+D74*E74 -> 0
F75: =+D75*E75 -> 0
F76: =+D76*E76 -> 0
D78: COMPONENTES DE CUSTO
D79: MATERIAL | E79: =+F79/F$84 -> 0.99824486 | F79: =SUM(F52:F57) -> 47.32475
D80: MÃO DE OBRA | E80: =+F80/F$84 -> 0.0017551419 | F80: =SUM(F59:F63) -> 0.083207692
D81: EQUIPAMENTO | E81: =+F81/F$84 -> 0 | F81: =SUM(F66:F70) -> 0
D82: OUTROS SERVIÇOS | E82: =+F82/F$84 -> 0 | F82: =SUM(F73:F76) -> 0
D84: CUSTO TOTAL | E84: =SUM(E79:E83) -> 1 | F84: =SUM(F79:F83) -> 47.407958
D85: BDI | E85: 0.2527 | F85: =+F84*E85 -> 11.979991
D87: PREÇO TOTAL | F87: =SUM(F84:F86) -> 59.387949
A89: Discriminação: | B89: Guias de proteção em concreto pré-moldado | E89: CÓDIGO: | F89: CPU-CAN003
E90: UNIDADE: | F90: m
A92: CÓDIGO DO INSUMO | B92: DESCRIÇÃO | C92: UNIDADE | D92: VALOR UNITÁRIO | E92: COEFICIENTE | F92: VALOR PARCELA
A94: MATERIAL
A95: M0424 | B95: Cimento Portland CP II - 32 - saco | C95: kg | D95: 0.5434 | E95: =458.01187*0.002 -> 0.91602374 | F95: =+D95*E95 -> 0.4977673
A96: M0028 | B96: Areia média | C96: m³ | D96: 156.7709 | E96: =1.00435*0.002 -> 0.0020087 | F96: =+D96*E96 -> 0.31490571
A97: 4059 | B97: Meio-fio ou guia de concreto, pre-moldado, comp 1 m, *30 x 12/15* cm (h x l1/l2) | C97: m | D97: 29.04 | E97: 1.005 | F97: =+D97*E97 -> 29.1852
F98: =+D98*E98 -> 0
F99: =+D99*E99 -> 0
A101: MÃO DE OBRA
A102: P9821 | B102: Pedreiro | C102: hora | D102: 27.5523 | E102: =1/4.22*0.002 -> 0.00047393365 | F102: =+D102*E102 -> 0.013057962
A103: P9824 | B103: Servente | C103: hora | D103: 21.634 | E103: =8/4.22*0.002 -> 0.0037914692 | F103: =+D103*E103 -> 0.082024645
F104: =+D104*E104 -> 0
F105: =+D105*E105 -> 0
A107: EQUIPAMENTO
A108: E9519 | B108: Betoneira com motor a gasolina com capacidade de 600 l - 10 kW | C108: hora | D108: 55.6007 | E108: =0.2369*0.002 -> 0.0004738 | F108: =+D108*E108 -> 0.026343612
A109: E9071 | B109: Transportador manual carrinho de mão com capacidade de 80 l | C109: hora | D109: 0.6839 | E109: =0.6993*0.002 -> 0.0013986 | F109: =+D109*E109 -> 0.00095650254
A110: E9064 | B110: Transportador manual gerica com capacidade de 180 l | C110: hora | D110: 1.4915 | E110: =0.5689*0.002 -> 0.0011378 | F110: =+D110*E110 -> 0.0016970287
F111: =+D111*E111 -> 0
F112: =+D112*E112 -> 0
A114: OUTROS SERVIÇOS
F116: =+D116*E116 -> 0
F117: =+D117*E117 -> 0
F118: =+D118*E118 -> 0
F119: =+D119*E119 -> 0
D121: COMPONENTES DE CUSTO
D122: MATERIAL | E122: =+F122/F$127 -> 0.99675248 | F122: =SUM(F95:F100) -> 29.997873
D123: MÃO DE OBRA | E123: =+F123/F$127 -> 0.0031593515 | F123: =SUM(F102:F106) -> 0.095082607
D124: EQUIPAMENTO | E124: =+F124/F$127 -> 8.8170046e-05 | F124: =SUM(F109:F113) -> 0.0026535312
D125: OUTROS SERVIÇOS | E125: =+F125/F$127 -> 0 | F125: =SUM(F116:F119) -> 0
D127: CUSTO TOTAL | E127: =SUM(E122:E126) -> 1 | F127: =SUM(F122:F126) -> 30.095609
D128: BDI | E128: 0.2527 | F128: =+F127*E128 -> 7.6051604
D130: PREÇO TOTAL | F130: =SUM(F127:F129) -> 37.70077
A132: Discriminação: | B132: Fornecimento e aplicação de manta geotêxtil (Execução de dreno com manta geotêxtil 400 g/m2) | E132: CÓDIGO: | F132: CPU-DRE001
E133: UNIDADE: | F133: m²
...

Sheet Critérios
A1: CRITÉRIOS DE QUANTIFICAÇÃO DOS SERVIÇOS
A3: CANAIS
L6: L talude
J7: altura (1,0)
L10: base (1,5)
J11: L talude = √(1,5² + 1,0²) = 1,8028
A16: DESMATAMENTO:
A17: Extensão X 40 metros (faixa de domínio)
A19: TERRAPLENAGEM:
A20: Calculado nos desenhos de projeto
A22: REVESTIMENTO (Geocomposto + Geomembrana):
A23: Taludes 1:1,5
A24: Perímetro = base + 2X L talude + 0,40 (ancoragem)
A26: CONCRETO:
A27: Área REVESTIMENTO X 0,07 m
A29: JUNTAS:
A30: Perímetro X Comprimento do canal ÷ 2 (junta a cada 2,00 metros)
A32: GUIAS:
... A92: L X 2 X 2,20 (h)

Sheet Ficha Canais
A1: FICHA TÉCNICA DOS CANAIS
A3: ETAPA 3 | J3: REVISÃO
A4: SEGMENTO | B4: EXTENSÃO | C4: BASE | D4: ALTURA | E4: REVESTIMENTO MANTA | F4: CONCRETO REVESTIMENTO | G4: ESCAVAÇÃO | H4: ATERRO | I4: GEOCOMPOSTO | J4: EXTENSÃO | K4: REVESTIMENTO MANTA | L4: CONCRETO REVESTIMENTO | M4: ESCAVAÇÃO | N4: ATERRO | O4: GEOCOMPOSTO
A5: Canal: CS19 - Trecho 1 | B5: 850 | C5: 1.8 | D5: 2.11 | E5: 7898 | F5: 552.83 | G5: 1218.69 | H5: 40104.47 | I5: 1974.3913 | J5: 850 | K5: 7603 | L5: 532.21 | M5: 1218.69 | N5: 40104.47 | O5: 1901
A6: Canal: CS19 - Trecho 2 | B6: 4950 | C6: 1.5 | D6: 1.72 | E6: 37535 | F6: 2627.43 | G6: 187330.72 | H6: 23759.27 | I6: 9383.6913 | J6: 4950 | K6: 36840 | L6: 2578.8 | M6: 187330.72 | N6: 23759.27 | O6: 9210
A7: Canal: CS19 - Trecho 3 | B7: 4292 | C7: 1.2 | D7: 1.58 | E7: 26863 | F7: 1880.43 | G7: 257084.94 | H7: 31272.74 | I7: 6715.8087 | J7: 4292 | K7: 26863 | L7: 1880.43 | M7: 257084.94 | N7: 31272.74 | O7: 6715.8087
A8: Canal: CS19 - Trecho 4 | B8: 4192 | C8: 1 | D8: 1.37 | E8: 24524 | F8: 1716.7 | G8: 196281.71 | H8: 825.37 | I8: 6131.0759 | J8: 4192 | K8: 24524 | L8: 1716.7 | M8: 196281.71 | N8: 825.37 | O8: 6131.0759
A9: Canal: CS19 - Trecho 5 | B9: 6192 | C9: 1 | D9: 1.37 | E9: 36225 | F9: 2535.74 | G9: 172403.48 | H9: 59799.23 | I9: 9056.208 | J9: 6192 | K9: 36225 | L9: 2535.74 | M9: 172403.48 | N9: 59799.23 | O9: 9056.208
A10: Canal: CS19 - Trecho 6 | B10: 0 | C10: 0 | D10: 0 | E10: 0 | F10: 0 | G10: 0 | H10: 0 | I10: 0 | J10: 0 | K10: 0 | L10: 0 | M10: 0 | N10: 0 | O10: 0
A11: Canal: CT1-CS19 - Trecho 1 | B11: 5600 | C11: 0.8 | D11: 1.16 | E11: 27643 | F11: 1935 | G11: 60141.74 | H11: 36362.25 | I11: 6910.7211 | J11: 5349 | K11: 26404 | L11: 1848.28 | M11: 54668.67 | N11: 36393.86 | O11: 6601
A12: Canal: CT1-CS19 - Trecho 2 | B12: 5670 | C12: 0.4 | D12: 0.81 | E12: 18536 | F12: 1297.55 | G12: 82739.12 | H12: 43846.24 | I12: 4634.1121 | J12: 0 | K12: 0 | L12: 0 | M12: 0 | N12: 0 | O12: 0
A13: Canal: CS21 | B13: 1670 | C13: 1.8 | D13: 2.29 | E13: 16557 | F13: 1158.96 | G13: 32288.39 | H13: 11965.57 | I13: 4139.1505 | J13: 1670 | K13: 16557 | L13: 1158.96 | M13: 32288.39 | N13: 11965.57 | O13: 4139.1505
A14: Canal: CS21a - Trecho 1 | B14: 4000 | C14: 1.5 | D14: 2.08 | E14: 35486 | F14: 2484 | G14: 10303.58 | H14: 104100.52 | I14: 8871.4224 | J14: 4000 | K14: 35486 | L14: 2484 | M14: 10339.03 | N14: 104054.4 | O14: 8871.4224
A15: Canal: CS21a - Trecho 2 | B15: 3992 | C15: 1.5 | D15: 1.98 | E15: 31129 | F15: 2179.04 | G15: 31229.53 | H15: 137619.45 | I15: 7782.3017 | J15: 3992 | K15: 31129 | L15: 2179.04 | M15: 31221.93 | N15: 137607 | O15: 7782.3017
A16: Canal: CS21a - Trecho 3 | B16: 742 | C16: 1.2 | D16: 1.7 | E16: 5371 | F16: 375.94 | G16: 17518.4 | H16: 758.23 | I16: 1342.6421 | J16: 3292 | K16: 22747 | L16: 1592.29 | M16: 12014.31 | N16: 151425.7 | O16: 5687
... A20: Canal: CT2-S21 | B20: 2600 | C20: 0.8 | D20: 1.21 | E20: 13253 | F20: 927.69 | G20: 33821.54 | H20: 13007.64 | I20: 3313.174 | J20: 2600 | K20: 13253 | L20: 927.69 | M20: 33821.54 | N20: 13007.64 | O20: 3313.174
A21: TOTAL | B21: =SUM(B5:B20) -> 56994 | E21: =SUM(E5:E20) -> 358692 | F21: =SUM(F5:F20) -> 25108.39 | G21: =SUM(G5:G20) -> 1254654 | H21: =SUM(H5:H20) -> 540842.36 | I21: =SUM(I5:I20) -> 89672.826 | J21: =SUM(J5:J20) -> 48376 | K21: =SUM(K5:K20) -> 318105 | L21: =SUM(L5:L20) -> 22267.32 | ... O21: =SUM(O5:O20) -> 79526.141
A23: ETAPA 4
A24: SEGMENTO | B24: EXTENSÃO | C24: BASE | D24: ALTURA | E24: REVESTIMENTO MANTA | F24: CONCRETO REVESTIMENTO | G24: ESCAVAÇÃO | H24: ATERRO | I24: GEOCOMPOSTO | J24: EXTENSÃO | K24: REVESTIMENTO MANTA | L24: CONCRETO REVESTIMENTO | M24: ESCAVAÇÃO | N24: ATERRO | O24: GEOCOMPOSTO
A25: Canal: CP3 - Trecho 1 | B25: 1950 | C25: 1.8 | D25: 2.65 | E25: 21796 | F25: 1525.75 | G25: 1049.11 | H25: 86734.59 | I25: 5449.1036 | J25: 1950 | K25: 21796 | L25: 1525.75 | M25: 1049.11 | N25: 86734.59 | O25: 5449.1036
A26: Canal: CP3 - Trecho 2 | B26: 4900 | C26: 1.8 | D26: 2.56 | E26: 53323 | F26: 3732.6 | G26: 87315.64 | H26: 35943.57 | I26: 13330.718 | J26: 4900 | K26: 53323 | L26: 3732.6 | M26: 87315.64 | N26: 35943.57 | O26: 13330.718
A27: Canal: CP3 - Trecho 3 | B27: 2982 | C27: 1.5 | D27: 2.02 | E27: 25880 | F27: 1811.58 | G27: 72198.38 | H27: 10868.67 | I27: 6469.9214 | J27: 2982 | K27: 25880 | L27: 1811.58 | M27: 72198.38 | N27: 10868.67 | O27: 6469.9214
A28: Canal: CP3a - Trecho 1 | B28: 5000 | C28: 1.2 | D28: 1.72 | E28: 36484 | F28: 2553.85 | G28: 86098.91 | H28: 94515.39 | I28: 9120.905 | J28: 5000 | K28: 36484 | L28: 2553.85 | M28: 86098.91 | N28: 94515.39 | O28: 9120.905
A29: Canal: CP3a - Trecho 2 | B29: 2670 | C29: 1 | D29: 1.4 | E29: 16511 | F29: 1155.79 | G29: 83046.67 | H29: 28206.89 | I29: 4127.8037 | J29: 2670 | K29: 16511 | L29: 1155.79 | M29: 83046.67 | N29: 28206.89 | O29: 4127.8037
A30: Canal: CP3b - Trecho 1 | B30: 2100 | C30: 0.8 | D30: 1.29 | E30: 11290 | F30: 790.3 | G30: 7609.24 | H30: 27541.36 | I30: 2822.5134 | J30: 2100 | K30: 11290 | L30: 790.3 | M30: 7609.24 | N30: 27541.36 | O30: 2822.5134
A31: Canal: CP3b - Trecho 2 | B31: 0 | C31: 0 | D31: 0 | E31: 0 | F31: 0 | G31: 0 | H31: 0 | I31: 0 | J31: 0 | K31: 0 | L31: 0 | M31: 0 | N31: 0 | O31: 0
A32: Canal: CS23 | B32: 2591 | C32: 0.4 | D32: 0.73 | E32: 7755 | F32: 542.86 | G32: 11948.53 | H32: 5884.78 | I32: 1938.7744 | J32: 2591 | K32: 7755 | L32: 542.86 | M32: 11948.53 | N32: 5884.78 | O32: 1938.7744
A33: Canal: CS25 - Trecho 1 | B33: 4000 | C33: 1.2 | D33: 1.56 | E33: 11393 | F33: 797.49 | G33: 9648.14 | H33: 147510.42 | I33: 2848.1733 | J33: 4000 | K33: 11393 | L33: 797.49 | M33: 9648.14 | N33: 147510.42 | O33: 2848.1733
A34: Canal: CS25 - Trecho 2 | B34: 1392 | C34: 0.8 | D34: 1.16 | E34: 26971 | F34: 1888 | G34: 1879.1 | H34: 128031.35 | I34: 6742.8538 | J34: 1392 | K34: 26971 | L34: 1888 | M34: 1879.1 | N34: 128031.35 | O34: 6742.8538
A35: Canal: CS27 | B35: 3186 | C35: 0.6 | D35: 0.85 | E35: 6851 | F35: 479.54 | G35: 42907 | H35: 37839.32 | I35: 1712.6521 | J35: 3186 | K35: 6851 | L35: 479.54 | M35: 42907 | N35: 37839.32 | O35: 1712.6521
A36: Canal: CS29 | B36: 0 | C36: 0 | D36: 0 | E36: 0 | F36: 0 | G36: 0 | H36: 0 | I36: 0 | J36: 0 | K36: 0 | L36: 0 | M36: 0 | N36: 0 | O36: 0
A37: TOTAL | B37: =SUM(B25:B36) -> 30771 | E37: =SUM(E25:E36) -> 218254 | F37: =SUM(F25:F36) -> 15277.76 | G37: =SUM(G25:G36) -> 403700.72 | H37: =SUM(H25:H36) -> 603076.34 | I37: =SUM(I25:I36) -> 54563.419 | J37: =SUM(J25:J36) -> 30771 | K37: =SUM(K25:K36) -> 218254 | L37: =SUM(L25:L36) -> 15277.76 | ... O37: =SUM(O25:O36) -> 54563.419
B39: =+B21+B37 -> 87765 | E39: =+E21+E37 -> 576946 | F39: =+F21+F37 -> 40386.15 | I39: =+I21+I37 -> 144236.24 | J39: =+J21+J37 -> 79147 | K39: =+K21+K37 -> 536359 | L39: =+L21+L37 -> 37545.08 | O39: =+O21+O37 -> 134089.56

Sheet Ficha EC
A1: FICHA TÉCNICA DAS ESTRUTURAS DE CONTROLE
K2: =+BDI!C16 -> 0.2527
A3: ETAPA 3 | G3: COMPORTAS
A4: SEGMENTO | B4: EXTENSÃO | C4: BASE | D4: COTA BERMA | E4: COTA FUNDO | F4: ALTURA | G4: Código | H4: Preço Material | I4: Mão-de-Obra | J4: SUBTOTAL | K4: BDI | L4: TOTAL
A5: EC2 - CS19 | B5: 8 | C5: 3.2 | D5: 474.39 | E5: 472.83 | F5: =+D5-E5 -> 1.56 | G5: CPU-CPT001 | H5: 80000 | I5: =+H5*0.3 -> 24000 | J5: =+H5+I5 -> 104000 | K5: =+J5*$K$2 -> 26280.8 | L5: =+J5+K5 -> 130280.8
A6: EC3 - CS19 | B6: 8 | C6: 2.6 | D6: 473.58 | E6: 472.19 | F6: =+D6-E6 -> 1.39 | G6: CPU-CPT002 | H6: 64000 | I6: =+H6*0.3 -> 19200 | J6: =+H6+I6 -> 83200 | K6: =+J6*$K$2 -> 21024.64 | L6: =+J6+K6 -> 104224.64
A7: EC4 - CS19 | B7: 8 | C7: 2.6 | D7: 472.74 | E7: 471.35 | F7: =+D7-E7 -> 1.39 | G7: CPU-CPT003 | H7: 64000 | I7: =+H7*0.3 -> 19200 | J7: =+H7+I7 -> 83200 | K7: =+J7*$K$2 -> 21024.64 | L7: =+J7+K7 -> 104224.64
A8: EC5 - CS19 | B8: 8 | C8: 1.3 | D8: 471.3 | E8: 470.11 | F8: =+D8-E8 -> 1.19 | G8: CPU-CPT004 | H8: 40800 | I8: =+H8*0.3 -> 12240 | J8: =+H8+I8 -> 53040 | K8: =+J8*$K$2 -> 13403.208 | L8: =+J8+K8 -> 66443.208
A9: EC6 - CT1-S19 | B9: EXCLUÍDO DO ORÇAMENTO REVISADO
A10: EC2 - CS21a | B10: 8 | C10: 4 | D10: 479.76 | E10: 477.8 | F10: =+D10-E10 -> 1.96 | G10: CPU-CPT006 | H10: 124000 | I10: =+H10*0.3 -> 37200 | J10: =+H10+I10 -> 161200 | K10: =+J10*$K$2 -> 40735.24 | L10: =+J10+K10 -> 201935.24
A11: EC3 - CS21a | B11: 8 | C11: 3.3 | D11: 479.12 | E11: 477.4 | F11: =+D11-E11 -> 1.72 | G11: CPU-CPT007 | H11: 93600 | I11: =+H11*0.3 -> 28080 | J11: =+H11+I11 -> 121680 | K11: =+J11*$K$2 -> 30748.536 | L11: =+J11+K11 -> 152428.54
A12: EC4 - CS21a | B12: 8 | C12: 3.1 | D12: 463.48 | E12: 461.92 | F12: =+D12-E12 -> 1.56 | G12: CPU-CPT008 | H12: 81600 | I12: =+H12*0.3 -> 24480 | J12: =+H12+I12 -> 106080 | K12: =+J12*$K$2 -> 26806.416 | L12: =+J12+K12 -> 132886.42
A13: EC5 - CS21a | B13: 8 | C13: 2.3 | D13: 462.63 | E13: 461.32 | F13: =+D13-E13 -> 1.31 | G13: CPU-CPT009 | H13: 86800 | I13: =+H13*0.3 -> 26040 | J13: =+H13+I13 -> 112840 | K13: =+J13*$K$2 -> 28514.668 | L13: =+J13+K13 -> 141354.67
A15: ETAPA 4
A16: SEGMENTO | B16: EXTENSÃO | C16: BASE | D16: COTA BERMA | E16: COTA FUNDO | F16: ALTURA | H16: Preço Material | I16: Mão-de-Obra | J16: SUBTOTAL | K16: BDI | L16: TOTAL
A17: EC2 - CP3 | B17: 8 | C17: 4 | D17: 478.14 | E17: 476.1 | F17: =+D17-E17 -> 2.04 | G17: CPU-CPT010 | H17: 128000 | I17: =+H17*0.3 -> 38400 | J17: =+H17+I17 -> 166400 | K17: =+J17*$K$2 -> 42049.28 | L17: =+J17+K17 -> 208449.28
A18: EC3 - CP3a | B18: 8 | C18: 2.7 | D18: 480.13 | E18: 478.73 | F18: =+D18-E18 -> 1.4 | G18: CPU-CPT011 | H18: 66400 | I18: =+H18*0.3 -> 19920 | J18: =+H18+I18 -> 86320 | K18: =+J18*$K$2 -> 21813.064 | L18: =+J18+K18 -> 108133.06
A19: EC4 - CS25 | B19: 8 | C19: 2.1 | D19: 479.69 | E19: 478.51 | F19: =+D19-E19 -> 1.18 | G19: CPU-CPT012 | H19: 48400 | I19: =+H19*0.3 -> 14520 | J19: =+H19+I19 -> 62920 | K19: =+J19*$K$2 -> 15899.884 | L19: =+J19+K19 -> 78819.884

Sheet Ficha EXTRAV
E2: Dissipador de Energia | M2: Mureta (Dissipador) | S2: Mureta (Enrocamento) | X2: Enrocamento
B3: Obra | C3: Trecho | D3: L (m) | E3: Ainício (m²) | F3: Adegrau (m²) | G3: Afinal (m²) | H3: N degraus (un) | I3: Plat (m) | J3: Pfundo (m) | K3: Forma (m²) | L3: Concreto (m³) | M3: Largura (m) | N3: Alat (m²) | O3: Pfechamento (m) | P3: Pfundo (m) | Q3: Forma (m²) | R3: Concreto (m³) | S3: Comprimento (m) | T3: Altura (m) | U3: Largura (m) | V3: Forma (m²) | W3: Concreto (m³) | X3: L1 (m) | Y3: L2 (m) | Z3: C1 (m) | AA3: C2 (m) | AB3: Altura (m) | AC3: Volume (m³)
B4: EX-1 | C4: CS19-Trecho 2 | D4: 20.5 | E4: 3.22 | F4: 2.18 | G4: 5.37 | H4: 7 | I4: =(1.19+2.41)+(0.96+0.5+1)+(1*H4) -> 13.06 | J4: =(1+1.18)+(1.5+3.09+2.09)+(1.92*H4) -> 22.3 | K4: =I4*D4 -> 267.73 | L4: =($E$4+$F$4*H4+$G$4)*D4 -> 488.925 | M4: 0.4 | N4: 66.38 | O4: 5.15 | P4: 24.47 | Q4: =2*((2*$N$4)+($M$4*$O$4)) -> 269.64 | R4: =$N$4*$M$4 -> 26.552 | S4: =SQRT(((1.5*D4)-2.2)^2+(0.5*D4*0.5)^2) -> 29.006346 | T4: =1.5+AB4 -> 2.5 | U4: =M4 -> 0.4 | V4: =2*((2*S4*$T$4)+($T$4*$U$4)) -> 292.06346 | W4: =S4*$T$4*$U$4*2 -> 58.012693 | X4: =D4 -> 20.5 | Y4: =X4*1.5 -> 30.75 | Z4: 2.2 | AA4: =Y4-$Z$4 -> 28.55 | AB4: 1 | AC4: =AB4*((X4*$Z$4)+((X4+Y4)*0.5*AA4)) -> 776.69375
B5: EX-2 | C5: CS19-Trecho 3 | D5: 14.8 | H5: 7 | I5: =(1.19+2.41)+(0.96+0.5+1)+(1*H5) -> 13.06 | J5: =(1+1.18)+(1.5+3.09+2.09)+(1.92*H5) -> 22.3 | K5: =I5*D5 -> 193.288 | L5: =($E$4+$F$4*H5+$G$4)*D5 -> 352.98 | Q5: =2*((2*$N$4)+($M$4*$O$4)) -> 269.64 | R5: =$N$4*$M$4 -> 26.552 | S5: =SQRT(((1.5*D5)-2.2)^2+(0.5*D5*0.5)^2) -> 20.339371 | V5: =2*((2*S5*$T$4)+($T$4*$U$4)) -> 205.39371 | W5: =S5*$T$4*$U$4*2 -> 40.678741 | X5: =D5 -> 14.8 | Y5: =X5*1.5 -> 22.2 | AA5: =Y5-$Z$4 -> 20 | AB5: 1 | AC5: =AB5*((X5*$Z$4)+((X5+Y5)*0.5*AA5)) -> 402.56
B6: EX-3 | C6: CS19-Trecho 4 | D6: 10.8 | H6: 7 | I6: =(1.19+2.41)+(0.96+0.5+1)+(1*H6) -> 13.06 | J6: =(1+1.18)+(1.5+3.09+2.09)+(1.92*H6) -> 22.3 | K6: =I6*D6 -> 141.048 | L6: =($E$4+$F$4*H6+$G$4)*D6 -> 257.58 | Q6: =2*((2*$N$4)+($M$4*$O$4)) -> 269.64 | R6: =$N$4*$M$4 -> 26.552 | S6: =SQRT(((1.5*D6)-2.2)^2+(0.5*D6*0.5)^2) -> 14.25798 | V6: =2*((2*S6*$T$4)+($T$4*$U$4)) -> 144.5798 | W6: =S6*$T$4*$U$4*2 -> 28.51596 | X6: =D6 -> 10.8 | Y6: =X6*1.5 -> 16.2 | AA6: =Y6-$Z$4 -> 14 | AB6: 1 | AC6: =AB6*((X6*$Z$4)+((X6+Y6)*0.5*AA6)) -> 212.76
B7: EX-4 | C7: CS19-Trecho 5 | D7: 10.8 | H7: 7 | I7: =(1.19+2.41)+(0.96+0.5+1)+(1*H7) -> 13.06 | J7: =(1+1.18)+(1.5+3.09+2.09)+(1.92*H7) -> 22.3 | K7: =I7*D7 -> 141.048 | L7: =($E$4+$F$4*H7+$G$4)*D7 -> 257.58 | Q7: =2*((2*$N$4)+($M$4*$O$4)) -> 269.64 | R7: =$N$4*$M$4 -> 26.552 | S7: =SQRT(((1.5*D7)-2.2)^2+(0.5*D7*0.5)^2) -> 14.25798 | V7: =2*((2*S7*$T$4)+($T$4*$U$4)) -> 144.5798 | W7: =S7*$T$4*$U$4*2 -> 28.51596 | X7: =D7 -> 10.8 | Y7: =X7*1.5 -> 16.2 | AA7: =Y7-$Z$4 -> 14 | AB7: 1 | AC7: =AB7*((X7*$Z$4)+((X7+Y7)*0.5*AA7)) -> 212.76
B8: EX-5 | C8: CT1-CS19-Trecho 1 | D8: 6.2 | H8: 7 | I8: =(1.19+2.41)+(0.96+0.5+1)+(1*H8) -> 13.06 | J8: =(1+1.18)+(1.5+3.09+2.09)+(1.92*H8) -> 22.3 | K8: =I8*D8 -> 80.972 | L8: =($E$4+$F$4*H8+$G$4)*D8 -> 147.87 | Q8: =2*((2*$N$4)+($M$4*$O$4)) -> 269.64 | R8: =$N$4*$M$4 -> 26.552 | S8: =SQRT(((1.5*D8)-2.2)^2+(0.5*D8*0.5)^2) -> 7.2672209 | V8: =2*((2*S8*$T$4)+($T$4*$U$4)) -> 74.672209 | W8: =S8*$T$4*$U$4*2 -> 14.534442 | X8: =D8 -> 6.2 | Y8: =X8*1.5 -> 9.3 | AA8: =Y8-$Z$4 -> 7.1 | AB8: 1 | AC8: =AB8*((X8*$Z$4)+((X8+Y8)*0.5*AA8)) -> 68.665
B9: EX-6 | C9: CT1-CS19-Trecho 2 | H9: 7 | I9: =(1.19+2.41)+(0.96+0.5+1)+(1*H9) -> 13.06 | J9: =(1+1.18)+(1.5+3.09+2.09)+(1.92*H9) -> 22.3 | S9: ELIMINADO | X9: =D9 -> 0 | Y9: =X9*1.5 -> 0 | AA9: =Y9-$Z$4 -> -2.2
B10: EX-1 | C10: CS21 | D10: 24.9 | H10: 7 | I10: =(1.19+2.41)+(0.96+0.5+1)+(1*H10) -> 13.06 | J10: =(1+1.18)+(1.5+3.09+2.09)+(1.92*H10) -> 22.3 | K10: =I10*D10 -> 325.194 | L10: =($E$4+$F$4*H10+$G$4)*D10 -> 593.865 | Q10: =2*((2*$N$4)+($M$4*$O$4)) -> 269.64 | R10: =$N$4*$M$4 -> 26.552 | S10: =SQRT(((1.5*D10)-2.2)^2+(0.5*D10*0.5)^2) -> 35.696962 | V10: =2*((2*S10*$T$4)+($T$4*$U$4)) -> 358.96962 | W10: =S10*$T$4*$U$4*2 -> 71.393925 | X10: =D10 -> 24.9 | Y10: =X10*1.5 -> 37.35 | AA10: =Y10-$Z$4 -> 35.15 | AB10: 1 | AC10: =AB10*((X10*$Z$4)+((X10+Y10)*0.5*AA10)) -> 1148.8237
B11: EX-2 | C11: CS21a-Trecho 1 | D11: 17.8 | H11: 7 | I11: =(1.19+2.41)+(0.96+0.5+1)+(1*H11) -> 13.06 | J11: =(1+1.18)+(1.5+3.09+2.09)+(1.92*H11) -> 22.3 | K11: =I11*D11 -> 232.468 | L11: =($E$4+$F$4*H11+$G$4)*D11 -> 424.53 | Q11: =2*((2*$N$4)+($M$4*$O$4)) -> 269.64 | R11: =$N$4*$M$4 -> 26.552 | S11: =SQRT(((1.5*D11)-2.2)^2+(0.5*D11*0.5)^2) -> 24.900853 | V11: =2*((2*S11*$T$4)+($T$4*$U$4)) -> 251.00853 | W11: =S11*$T$4*$U$4*2 -> 49.801707 | X11: =D11 -> 17.8 | Y11: =X11*1.5 -> 26.7 | AA11: =Y11-$Z$4 -> 24.5 | AB11: 1 | AC11: =AB11*((X11*$Z$4)+((X11+Y11)*0.5*AA11)) -> 584.285
B12: EX-3 | C12: CS21a-Trecho 2 | D12: 21.2 | H12: 7 | I12: =(1.19+2.41)+(0.96+0.5+1)+(1*H12) -> 13.06 | J12: =(1+1.18)+(1.5+3.09+2.09)+(1.92*H12) -> 22.3 | K12: =I12*D12 -> 276.872 | L12: =($E$4+$F$4*H12+$G$4)*D12 -> 505.62 | Q12: =2*((2*$N$4)+($M$4*$O$4)) -> 269.64 | R12: =$N$4*$M$4 -> 26.552 | S12: =SQRT(((1.5*D12)-2.2)^2+(0.5*D12*0.5)^2) -> 30.07075 | V12: =2*((2*S12*$T$4)+($T$4*$U$4)) -> 302.7075 | W12: =S12*$T$4*$U$4*2 -> 60.1415 | X12: =D12 -> 21.2 | Y12: =X12*1.5 -> 31.8 | AA12: =Y12-$Z$4 -> 29.6 | AB12: 1 | AC12: =AB12*((X12*$Z$4)+((X12+Y12)*0.5*AA12)) -> 831.04
B13: EX-4 | C13: CS21a-Trecho 3.1 | D13: 15.1 | H13: 7 | I13: =(1.19+2.41)+(0.96+0.5+1)+(1*H13) -> 13.06 | J13: =(1+1.18)+(1.5+3.09+2.09)+(1.92*H13) -> 22.3 | K13: =I13*D13 -> 197.206 | L13: =($E$4+$F$4*H13+$G$4)*D13 -> 360.135 | Q13: =2*((2*$N$4)+($M$4*$O$4)) -> 269.64 | R13: =$N$4*$M$4 -> 26.552 | S13: =SQRT(((1.5*D13)-2.2)^2+(0.5*D13*0.5)^2) -> 20.795507 | V13: =2*((2*S13*$T$4)+($T$4*$U$4)) -> 209.95507 | W13: =S13*$T$4*$U$4*2 -> 41.591015 | X13: =D13 -> 15.1 | Y13: =X13*1.5 -> 22.65 | AA13: =Y13-$Z$4 -> 20.45 | AB13: 1 | AC13: =AB13*((X13*$Z$4)+((X13+Y13)*0.5*AA13)) -> 419.21375
B14: EX-5 | C14: CS21a-Trecho 4 | D14: 8.7 | H14: 7 | I14: =(1.19+2.41)+(0.96+0.5+1)+(1*H14) -> 13.06 | J14: =(1+1.18)+(1.5+3.09+2.09)+(1.92*H14) -> 22.3 | K14: =I14*D14 -> 113.622 | L14: =($E$4+$F$4*H14+$G$4)*D14 -> 207.495 | Q14: =2*((2*$N$4)+($M$4*$O$4)) -> 269.64 | R14: =$N$4*$M$4 -> 26.552 | S14: =SQRT(((1.5*D14)-2.2)^2+(0.5*D14*0.5)^2) -> 11.065854 | V14: =2*((2*S14*$T$4)+($T$4*$U$4)) -> 112.65854 | W14: =S14*$T$4*$U$4*2 -> 22.131708 | X14: =D14 -> 8.7 | Y14: =X14*1.5 -> 13.05 | AA14: =Y14-$Z$4 -> 10.85 | AB14: 1 | AC14: =AB14*((X14*$Z$4)+((X14+Y14)*0.5*AA14)) -> 137.13375
B15: EX-6 | C15: CS21a-Trecho 5 | H15: 7 | I15: =(1.19+2.41)+(0.96+0.5+1)+(1*H15) -> 13.06 | J15: =(1+1.18)+(1.5+3.09+2.09)+(1.92*H15) -> 22.3 | S15: ELIMINADO | X15: =D15 -> 0 | Y15: =X15*1.5 -> 0 | AA15: =Y15-$Z$4 -> -2.2
B16: CT2-S21 | D16: 4.8 | H16: 7 | I16: =(1.19+2.41)+(0.96+0.5+1)+(1*H16) -> 13.06 | J16: =(1+1.18)+(1.5+3.09+2.09)+(1.92*H16) -> 22.3 | K16: =I16*D16 -> 62.688 | L16: =($E$4+$F$4*H16+$G$4)*D16 -> 114.48 | Q16: =2*((2*$N$4)+($M$4*$O$4)) -> 269.64 | R16: =$N$4*$M$4 -> 26.552 | S16: =SQRT(((1.5*D16)-2.2)^2+(0.5*D16*0.5)^2) -> 5.1419841 | V16: =2*((2*S16*$T$4)+($T$4*$U$4)) -> 53.419841 | W16: =S16*$T$4*$U$4*2 -> 10.283968 | X16: =D16 -> 4.8 | Y16: =X16*1.5 -> 7.2 | AA16: =Y16-$Z$4 -> 5 | AB16: 1 | AC16: =AB16*((X16*$Z$4)+((X16+Y16)*0.5*AA16)) -> 40.56
B17: EX-1 | C17: CP3 - Trecho 2 | D17: 33 | H17: 7 | I17: =(1.19+2.41)+(0.96+0.5+1)+(1*H17) -> 13.06 | J17: =(1+1.18)+(1.5+3.09+2.09)+(1.92*H17) -> 22.3 | K17: =I17*D17 -> 430.98 | L17: =($E$4+$F$4*H17+$G$4)*D17 -> 787.05 | Q17: =2*((2*$N$4)+($M$4*$O$4)) -> 269.64 | R17: =$N$4*$M$4 -> 26.552 | S17: =SQRT(((1.5*D17)-2.2)^2+(0.5*D17*0.5)^2) -> 48.014086 | V17: =2*((2*S17*$T$4)+($T$4*$U$4)) -> 482.14086 | W17: =S17*$T$4*$U$4*2 -> 96.028173 | X17: =D17 -> 33 | Y17: =X17*1.5 -> 49.5 | AA17: =Y17-$Z$4 -> 47.3 | AB17: 1 | AC17: =AB17*((X17*$Z$4)+((X17+Y17)*0.5*AA17)) -> 2023.725
B18: EX-2 | C18: CP3 - Trecho 3 | D18: 16.7 | H18: 7 | I18: =(1.19+2.41)+(0.96+0.5+1)+(1*H18) -> 13.06 | J18: =(1+1.18)+(1.5+3.09+2.09)+(1.92*H18) -> 22.3 | K18: =I18*D18 -> 218.102 | L18: =($E$4+$F$4*H18+$G$4)*D18 -> 398.295 | Q18: =2*((2*$N$4)+($M$4*$O$4)) -> 269.64 | R18: =$N$4*$M$4 -> 26.552 | S18: =SQRT(((1.5*D18)-2.2)^2+(0.5*D18*0.5)^2) -> 23.228283 | V18: =2*((2*S18*$T$4)+($T$4*$U$4)) -> 234.28283 | W18: =S18*$T$4*$U$4*2 -> 46.456566 | X18: =D18 -> 16.7 | Y18: =X18*1.5 -> 25.05 | AA18: =Y18-$Z$4 -> 22.85 | AB18: 1 | AC18: =AB18*((X18*$Z$4)+((X18+Y18)*0.5*AA18)) -> 513.73375
B19: EX-3 | C19: CP3a - Trecho 1 | D19: 18.5 | H19: 7 | I19: =(1.19+2.41)+(0.96+0.5+1)+(1*H19) -> 13.06 | J19: =(1+1.18)+(1.5+3.09+2.09)+(1.92*H19) -> 22.3 | K19: =I19*D19 -> 241.61 | L19: =($E$4+$F$4*H19+$G$4)*D19 -> 441.225 | Q19: =2*((2*$N$4)+($M$4*$O$4)) -> 269.64 | R19: =$N$4*$M$4 -> 26.552 | S19: =SQRT(((1.5*D19)-2.2)^2+(0.5*D19*0.5)^2) -> 25.965229 | V19: =2*((2*S19*$T$4)+($T$4*$U$4)) -> 261.65229 | W19: =S19*$T$4*$U$4*2 -> 51.930458 | X19: =D19 -> 18.5 | Y19: =X19*1.5 -> 27.75 | AA19: =Y19-$Z$4 -> 25.55 | AB19: 1 | AC19: =AB19*((X19*$Z$4)+((X19+Y19)*0.5*AA19)) -> 631.54375
B20: EX-4 | C20: CP3a - Trecho 2 | D20: 11.5 | H20: 7 | I20: =(1.19+2.41)+(0.96+0.5+1)+(1*H20) -> 13.06 | J20: =(1+1.18)+(1.5+3.09+2.09)+(1.92*H20) -> 22.3 | K20: =I20*D20 -> 150.19 | L20: =($E$4+$F$4*H20+$G$4)*D20 -> 274.275 | Q20: =2*((2*$N$4)+($M$4*$O$4)) -> 269.64 | R20: =$N$4*$M$4 -> 26.552 | S20: =SQRT(((1.5*D20)-2.2)^2+(0.5*D20*0.5)^2) -> 15.322145 | V20: =2*((2*S20*$T$4)+($T$4*$U$4)) -> 155.22145 | W20: =S20*$T$4*$U$4*2 -> 30.64429 | X20: =D20 -> 11.5 | Y20: =X20*1.5 -> 17.25 | AA20: =Y20-$Z$4 -> 15.05 | AB20: 1 | AC20: =AB20*((X20*$Z$4)+((X20+Y20)*0.5*AA20)) -> 241.64375
B21: EX-5 | C21: CP3b - Trecho 1 | D21: 8.3 | H21: 7 | I21: =(1.19+2.41)+(0.96+0.5+1)+(1*H21) -> 13.06 | J21: =(1+1.18)+(1.5+3.09+2.09)+(1.92*H21) -> 22.3 | K21: =I21*D21 -> 108.398 | L21: =($E$4+$F$4*H21+$G$4)*D21 -> 197.955 | Q21: =2*((2*$N$4)+($M$4*$O$4)) -> 269.64 | R21: =$N$4*$M$4 -> 26.552 | S21: =SQRT(((1.5*D21)-2.2)^2+(0.5*D21*0.5)^2) -> 10.457922 | V21: =2*((2*S21*$T$4)+($T$4*$U$4)) -> 106.57922 | W21: =S21*$T$4*$U$4*2 -> 20.915843 | X21: =D21 -> 8.3 | Y21: =X21*1.5 -> 12.45 | AA21: =Y21-$Z$4 -> 10.25 | AB21: 1 | AC21: =AB21*((X21*$Z$4)+((X21+Y21)*0.5*AA21)) -> 124.60375
B22: EX-6 | C22: CS23 | D22: 3.1 | H22: 7 | I22: =(1.19+2.41)+(0.96+0.5+1)+(1*H22) -> 13.06 | J22: =(1+1.18)+(1.5+3.09+2.09)+(1.92*H22) -> 22.3 | K22: =I22*D22 -> 40.486 | L22: =($E$4+$F$4*H22+$G$4)*D22 -> 73.935 | Q22: =2*((2*$N$4)+($M$4*$O$4)) -> 269.64 | R22: =$N$4*$M$4 -> 26.552 | S22: =SQRT(((1.5*D22)-2.2)^2+(0.5*D22*0.5)^2) -> 2.5696546 | V22: =2*((2*S22*$T$4)+($T$4*$U$4)) -> 27.696546 | W22: =S22*$T$4*$U$4*2 -> 5.1393093 | X22: =D22 -> 3.1 | Y22: =X22*1.5 -> 4.65 | AA22: =Y22-$Z$4 -> 2.45 | AB22: 1 | AC22: =AB22*((X22*$Z$4)+((X22+Y22)*0.5*AA22)) -> 16.31375
B23: EX-7 | C23: CS25 - Trecho 1 | D23: 14.4 | H23: 7 | I23: =(1.19+2.41)+(0.96+0.5+1)+(1*H23) -> 13.06 | J23: =(1+1.18)+(1.5+3.09+2.09)+(1.92*H23) -> 22.3 | K23: =I23*D23 -> 188.064 | L23: =($E$4+$F$4*H23+$G$4)*D23 -> 343.44 | Q23: =2*((2*$N$4)+($M$4*$O$4)) -> 269.64 | R23: =$N$4*$M$4 -> 26.552 | S23: =SQRT(((1.5*D23)-2.2)^2+(0.5*D23*0.5)^2) -> 19.731194 | V23: =2*((2*S23*$T$4)+($T$4*$U$4)) -> 199.31194 | W23: =S23*$T$4*$U$4*2 -> 39.462387 | X23: =D23 -> 14.4 | Y23: =X23*1.5 -> 21.6 | AA23: =Y23-$Z$4 -> 19.4 | AB23: 1 | AC23: =AB23*((X23*$Z$4)+((X23+Y23)*0.5*AA23)) -> 380.88
B24: EX-8 | C24: CS25 - Trecho 2 | D24: 6.2 | H24: 7 | I24: =(1.19+2.41)+(0.96+0.5+1)+(1*H24) -> 13.06 | J24: =(1+1.18)+(1.5+3.09+2.09)+(1.92*H24) -> 22.3 | K24: =I24*D24 -> 80.972 | L24: =($E$4+$F$4*H24+$G$4)*D24 -> 147.87 | Q24: =2*((2*$N$4)+($M$4*$O$4)) -> 269.64 | R24: =$N$4*$M$4 -> 26.552 | S24: =SQRT(((1.5*D24)-2.2)^2+(0.5*D24*0.5)^2) -> 7.2672209 | V24: =2*((2*S24*$T$4)+($T$4*$U$4)) -> 74.672209 | W24: =S24*$T$4*$U$4*2 -> 14.534442 | X24: =D24 -> 6.2 | Y24: =X24*1.5 -> 9.3 | AA24: =Y24-$Z$4 -> 7.1 | AB24: 1 | AC24: =AB24*((X24*$Z$4)+((X24+Y24)*0.5*AA24)) -> 68.665
B25: EX-9 | C25: CS27 | D25: 2.9 | H25: 7 | I25: =(1.19+2.41)+(0.96+0.5+1)+(1*H25) -> 13.06 | J25: =(1+1.18)+(1.5+3.09+2.09)+(1.92*H25) -> 22.3 | K25: =I25*D25 -> 37.874 | L25: =($E$4+$F$4*H25+$G$4)*D25 -> 69.165 | Q25: =2*((2*$N$4)+($M$4*$O$4)) -> 269.64 | R25: =$N$4*$M$4 -> 26.552 | S25: =SQRT(((1.5*D25)-2.2)^2+(0.5*D25*0.5)^2) -> 2.268948 | V25: =2*((2*S25*$T$4)+($T$4*$U$4)) -> 24.68948 | W25: =S25*$T$4*$U$4*2 -> 4.537896 | X25: =D25 -> 2.9 | Y25: =X25*1.5 -> 4.35 | AA25: =Y25-$Z$4 -> 2.15 | AB25: 1 | AC25: =AB25*((X25*$Z$4)+((X25+Y25)*0.5*AA25)) -> 14.17375
B26: Total = | K26: =SUM(K4:K25) -> 3528.812 | L26: =SUM(L4:L25) -> 6444.27 | Q26: =SUM(Q4:Q25) -> 5392.8 | R26: =SUM(R4:R25) -> 531.04 | V26: =SUM(V4:V25) -> 3716.2549 | W26: =SUM(W4:W25) -> 735.25098 | AC26: =SUM(AC4:AC25) -> 8849.7775
B29: Resumo
B30: Forma | C30: =K26+Q26+V26 -> 12637.867 | D30: m²
B31: Concreto | C31: =L26+R26+W26 -> 7710.561 | D31: m³

Sheet Ficha Bueiros
K8: EXCLUÍDO NO ORÇAMENTO REVISADO

Sheet MC Canais
A1: MEMÓRIA DE CÁLCULO - QUANTITATIVOS DOS CANAIS
A3: ETAPA 3 | B3: =+'Ficha Canais'!A5 -> Canal: CS19 - Trecho 1 | E3: Extensão: | F3: =+'Ficha Canais'!B5 -> 850 | G3: metros | H3: DMT (KM) = | I3: 5
B4: Extensão | C4: Larg faixa | D4: Base | E4: Altura | F4: Perímetro | G4: Área | H4: Volume | I4: Comprimento | J4: Quantitativo | L4: =+Planilha!E28 -> TERRAPLENAGEM E TRATAMENTOS
A5: Desmatamento | B5: =+F3 -> 850 | C5: 40 | D5: 0 | E5: 0 | F5: 0 | G5: =+B5*C5 -> 34000 | H5: 0 | I5: 0 | J5: =SUM(G5:I5) -> 34000 | L5: =+Planilha!E29 -> Desmatamento, destocamento e limpeza de área com árvores de diâmetro até 0,15 m
A6: Escavavação | B6: 0 | C6: 0 | D6: 0 | E6: 0 | F6: 0 | G6: 0 | H6: 1218.69 | I6: 0 | J6: =SUM(G6:I6) -> 1218.69 | L6: =+Planilha!E30 -> Escavação, carga e transporte de material de 1ª categoria - DMT de 1.000 a 1.200 m - caminho de serviço em leito natural - com escavadeira e caminhão basculante de 14 m³
A7: Aterro | B7: 0 | C7: 0 | D7: 0 | E7: 0 | F7: 0 | G7: 0 | H7: 40104.47 | I7: 0 | J7: =SUM(G7:I7) -> 40104.47 | L7: =+Planilha!E31 -> Compactação de aterros a 100% do Proctor normal
A8: Transporte | B8: 0 | C8: 0 | D8: 0 | E8: 0 | F8: 0 | G8: 0 | H8: =+(H7-H6)*1.4*I3 -> 272200.46 | I8: 0 | J8: =SUM(G8:I8) -> 272200.46 | L8: =+Planilha!E32 -> Transporte com caminhão basculante de 14 m³ - rodovia em leito natural
A9: Regularização | B9: =+F3 -> 850 | C9: 0 | D9: =+'Ficha Canais'!$C$5 -> 1.8 | E9: 0 | F9: 0 | G9: =+B9*D9 -> 1530 | H9: 0 | J9: =SUM(G9:I9) -> 1530 | L9: Regularização de superfície com motoniveladora
A10: Geocomposto | B10: =+F3 -> 850 | C10: 0 | D10: 1.8 | E10: 2.11 | F10: =(E10*1.8*2)+D10+0.8 -> 10.196 | G10: 1901 | H10: 0 | I10: 0 | J10: =SUM(G10:I10) -> 1901 | L10: =+Planilha!E34 -> Fornecimento e instalação de geocomposto drenante para os taludes
A11: Solo cimento | B11: 850 | C11: 0 | D11: 0 | E11: 0 | F11: 0 | G11: 0 | H11: =+G12*0.2 -> 1520.6 | I11: 0 | J11: =SUM(G11:I11) -> 1520.6 | L11: Regularização dos taludes do canal com solo-cimento (5% de cimento)
A12: Geomembrana | B12: 0 | C12: 0 | D12: 0 | E12: 0 | F12: 0 | G12: 7603 | H12: 0 | I12: 0 | J12: =SUM(G12:I12) -> 7603 | L12: =+Planilha!E36 -> Fornecimento e aplicação de geomembrana sintética para impermeabilização do canal, 1,00 mm de espessura (PEAD)
A13: Ancoragem | B13: 850 | C13: 0 | D13: 0 | E13: 0 | F13: 0 | G13: 0 | H13: 0 | I13: =+B13*2 -> 1700 | J13: =+I13 -> 1700 | L13: Ancoragem da geomembrana com escavação de material de 1ª e 2ª categorias
A14: Concreto | B14: 0 | C14: 0 | D14: 0 | E14: 0 | F14: 0 | G14: 0 | H14: =+G12*0.07 -> 532.21 | I14: 0 | J14: =SUM(G14:I14) -> 532.21 | L14: =+Planilha!E38 -> Concreto para bombeamento fck = 30 MPa - confecção em central dosadora de 30 m³/h - areia e brita comerciais
A15: Lançamento | B15: 0 | C15: 0 | D15: 0 | E15: 0 | F15: 0 | G15: 0 | H15: =+H14 -> 532.21 | I15: 0 | J15: =SUM(G15:I15) -> 532.21 | L15: =+Planilha!E39 -> Lançamento mecânico de concreto com bomba rebocável com capacidade de 30 m³/h - confecção em central dosadora de 30 m³/h
A16: Junta | B16: =+F3 -> 850 | C16: 0 | D16: 0 | E16: 0 | F16: =+F10 -> 10.196 | G16: 0 | H16: 0 | I16: =+B16/2*F16 -> 4333.3 | J16: =SUM(G16:I16) -> 4333.3 | L16: =+Planilha!E40 -> Lábios poliméricos em junta de pavimento de concreto - L = 20 mm e H = 30 mm - confecção e assentamento
A17: Guia | B17: =+F3 -> 850 | C17: 0 | D17: 0 | E17: 0 | F17: 0 | G17: 0 | H17: 0 | I17: =+B17*2 -> 1700 | J17: =SUM(G17:I17) -> 1700 | L17: =+Planilha!E41 -> Guias de proteção em concreto pré-moldado
A18: Grama | B18: =+F3 -> 850 | C18: 12 | D18: 0 | E18: 0 | F18: 0 | G18: =+B18*C18 -> 10200 | H18: 0 | I18: 0 | J18: =SUM(G18:I18) -> 10200 | L18: =+Planilha!E42 -> Revestimento vegetal com grama em mudas em superfícies inclinadas
B19: Extensão | C19: Larg faixa | D19: Base | E19: Altura | F19: Perímetro | G19: Área | H19: Volume | I19: Comprimento | J19: 0 | L19: =+Planilha!E43 -> DRENAGEM INTERNA DOS CANAIS
A20: Escavação | B20: =+F3 -> 850 | C20: 0 | D20: 1.2 | E20: 0.7 | F20: 0 | G20: 0 | H20: =+B20*D20*E20 -> 714 | I20: 0 | J20: =SUM(G20:I20) -> 714 | L20: =+Planilha!E44 -> Escavação mecânica de vala em material de 1ª categoria
A21: Reaterro | B21: =+F3 -> 850 | D21: 0.6 | E21: 0.6 | H21: =+H20-(B21*D21*E21) -> 408 | J21: =SUM(G21:I21) -> 408 | L21: =+Planilha!E45 -> Reaterro e compactação com soquete vibratório
A22: Transporte | B22: 0 | C22: 0 | D22: 0 | E22: 0 | F22: 0 | G22: 0 | H22: =(H20-H21)*1.4*5 -> 2142 | J22: =SUM(G22:I22) -> 2142 | L22: =+Planilha!E46 -> Transporte com caminhão basculante de 14 m³ - rodovia em leito natural
A23: Manta | B23: =+F3 -> 850 | C23: 0 | D23: 0.6 | E23: 0.6 | F23: 0 | G23: =B23*D23*4 -> 2040 | H23: 0 | I23: 0 | J23: =SUM(G23:I23) -> 2040 | L23: =+Planilha!E47 -> Fornecimento e aplicação de manta geotêxtil (Execução de dreno com manta geotêxtil 400 g/m2)
A24: Tubo | B24: =+F3 -> 850 | C24: 0 | D24: 0 | E24: 0 | F24: 0 | G24: 0 | H24: 0 | I24: =+B24 -> 850 | J24: =SUM(G24:I24) -> 850 | L24: =+Planilha!E48 -> Tubo de concreto perfurado produzido na obra para drenagem - D = 0,40 m - fornecimento e instalação
A25: Brita | B25: =+F3 -> 850 | C25: 0 | D25: 0.6 | E25: 0.6 | F25: 0 | G25: 0 | H25: =B25*D25*E25-(B25*3.14*0.4*0.4/4) -> 199.24 | I25: 0 | J25: =SUM(G25:I25) -> 199.24 | L25: =+Planilha!E49 -> Lastro de brita comercial compactado com soquete vibratório - espalhamento manual
A26: Areia | B26: =+F3 -> 850 | C26: 1.2 | D26: 0 | E26: 0.1 | F26: 0 | G26: 0 | H26: =+B26*C26*E26 -> 102 | J26: =SUM(G26:I26) -> 102 | L26: =+Planilha!E50 -> Lastro de areia comercial - espalhamento manual
B27: Extensão | C27: Larg faixa | D27: Base | E27: Altura | F27: Perímetro | G27: Área | H27: Volume | I27: Comprimento | J27: 0 | L27: =+Planilha!E51 -> OBRAS DE DRENAGEM SUPERFICIAL - VALETAS, SARJETAS, BUEIROS, GALERIAS E PASSAGENS MOLHADAS
A28: Valeta | B28: =+F3 -> 850 | C28: 0 | D28: 0 | E28: 0 | F28: 0 | G28: 0 | H28: 0 | I28: =+B28*2 -> 1700 | J28: =SUM(G28:I28) -> 1700 | L28: =+Planilha!E52 -> Valeta de proteção de cortes com revestimento vegetal - VPCG 120-30 - escavação mecânica
A29: Sarjeta | B29: =+F3 -> 850 | C29: 0 | D29: 0 | E29: 0 | F29: 0 | G29: 0 | H29: 0 | I29: =+B29*2 -> 1700 | J29: =SUM(G29:I29) -> 1700 | L29: =+Planilha!E53 -> Sarjeta triangular de grama - STG 125-25 - escavação mecânica
A30: Bueiro | B30: 0 | C30: 0 | D30: 0 | E30: 0 | F30: 0 | G30: 0 | H30: 0 | I30: 0 | J30: =SUM(G30:I30) -> 0 | L30: =+Planilha!E54 -> Corpo de BSTC D = 0,80 m PA1 - areia, brita e pedra de mão comerciais
A31: Boca | B31: 0 | C31: 0 | D31: 0 | E31: 0 | F31: 0 | G31: 0 | H31: 0 | I31: 0 | J31: =SUM(G31:I31) -> 0 | L31: =+Planilha!E55 -> Boca de BSTC D = 0,80 m - esconsidade 0° - areia e brita comerciais - alas retas
B32: Extensão | C32: Larg faixa | D32: Base | E32: Altura | F32: Perímetro | G32: Área | H32: Volume | I32: Comprimento | J32: 0 | L32: =+Planilha!E56 -> ESTRADAS LATERAIS
A33: Escavação | B33: =+F3 -> 850 | C33: 0 | D33: 3.5 | E33: 0.15 | F33: 0 | G33: 0 | H33: =+B33*D33*E33*2 -> 892.5 | I33: 0 | J33: =SUM(G33:I33) -> 892.5 | L33: =+Planilha!E57 -> Escavação mecânica com retroescavadeira em material de 1ª categoria
A34: Aterro | B34: =+F3 -> 850 | C34: 0 | D34: 3.5 | E34: 0.1 | F34: 0 | G34: 0 | H34: =+B34*D34*E34*2 -> 595 | I34: 0 | J34: =SUM(G34:I34) -> 595 | L34: =+Planilha!E58 -> Compactação de aterros a 100% do Proctor normal
A35: Transporte | B35: 0 | C35: 0 | D35: 0 | E35: 0 | F35: 0 | G35: 0 | H35: =+H33-H34 -> 297.5 | I35: 0 | J35: =SUM(G35:I35) -> 297.5 | L35: =+Planilha!E59 -> Transporte com caminhão basculante de 14 m³ - rodovia em leito natural
A36: Regularização | B36: =+F3 -> 850 | C36: 0 | D36: 3.5 | E36: 0 | F36: 0 | G36: =+B36*D36*2 -> 5950 | H36: 0 | I36: 0 | J36: =SUM(G36:I36) -> 5950 | L36: =+Planilha!E60 -> Regularização de superfície com motoniveladora
A37: Revestimento | B37: =+F3 -> 850 | C37: 0 | D37: 3.5 | E37: 0.15 | F37: 0 | H37: =+B37*D37*E37 -> 446.25 | I37: 0 | J37: =SUM(G37:I37) -> 446.25 | L37: =+Planilha!E61 -> Revestimento primário para as pistas laterais
B38: Extensão | C38: Larg faixa | D38: Base | E38: Altura | F38: Perímetro | G38: Área | H38: Volume | I38: Comprimento | J38: 0 | L38: =+Planilha!E62 -> SERVIÇOS COMPLEMENTARES
A39: Cercas | B39: =+F3 -> 850 | C39: 0 | D39: 0 | E39: 0 | F39: 0 | G39: 0 | H39: 0 | I39: =+B39*2 -> 1700 | J39: =SUM(G39:I39) -> 1700 | L39: =+Planilha!E63 -> Cerca com 4 fios de arame liso galvanizado e mourão de madeira a cada 2,5 m e esticador a cada 50 m
A41: ETAPA 3 | B41: =+'Ficha Canais'!A6 -> Canal: CS19 - Trecho 2 | E41: Extensão: | F41: =+'Ficha Canais'!B6 -> 4950 | G41: metros | H41: DMT (KM) = | I41: =+I3 -> 5
B42: Extensão | C42: Larg faixa | D42: Base | E42: Altura | F42: Perímetro | G42: Área | H42: Volume | I42: Comprimento | J42: Quantitativo
A43: Desmatamento | B43: =+F41 -> 4950 | C43: 40 | D43: 0 | E43: 0 | F43: 0 | G43: =+B43*C43 -> 198000 | H43: 0 | I43: 0 | J43: =SUM(G43:I43) -> 198000
A44: Escavavação | B44: 0 | C44: 0 | D44: 0 | E44: 0 | F44: 0 | G44: 0 | H44: 187330.72 | I44: 0 | J44: =SUM(G44:I44) -> 187330.72
A45: Aterro | B45: 0 | C45: 0 | D45: 0 | E45: 0 | F45: 0 | G45: 0 | H45: 23759.27 | I45: 0 | J45: =SUM(G45:I45) -> 23759.27
A46: Transporte | B46: 0 | C46: 0 | D46: 0 | E46: 0 | F46: 0 | G46: 0 | H46: =-(H45-H44)*1.4*I41 -> 1145000.1 | I46: 0 | J46: =SUM(G46:I46) -> 1145000.1
A47: Regularização | B47: =+F41 -> 4950 | C47: 0 | D47: =+'Ficha Canais'!$C$6 -> 1.5 | E47: 0 | F47: 0 | G47: =+B47*D47 -> 7425 | H47: 0 | J47: =SUM(G47:I47) -> 7425
A48: Geocomposto | B48: =+F41 -> 4950 | C48: 0 | D48: 1.5 | E48: 1.72 | F48: =(E48*1.8*2)+D48+0.8 -> 8.492 | G48: 9210 | H48: 0 | I48: 0 | J48: =SUM(G48:I48) -> 9210
A49: Solo cimento | B49: =+F41 -> 4950 | C49: 0 | D49: 0 | E49: 0 | F49: 0 | G49: 0 | H49: =+G50*0.2 -> 7368 | I49: 0 | J49: =SUM(G49:I49) -> 7368
A50: Geomembrana | B50: 0 | C50: 0 | D50: 0 | E50: 0 | F50: 0 | G50: 36840 | H50: 0 | I50: 0 | J50: =SUM(G50:I50) -> 36840
A51: Ancoragem | B51: =+F41 -> 4950 | C51: 0 | D51: 0 | E51: 0 | F51: 0 | G51: 0 | H51: 0 | I51: =+B51*2 -> 9900 | J51: =+I51 -> 9900
A52: Concreto | B52: 0 | C52: 0 | D52: 0 | E52: 0 | F52: 0 | G52: 0 | H52: =+G50*0.07 -> 2578.8 | I52: 0 | J52: =SUM(G52:I52) -> 2578.8
A53: Lançamento | B53: 0 | C53: 0 | D53: 0 | E53: 0 | F53: 0 | G53: 0 | H53: =+H52 -> 2578.8 | I53: 0 | J53: =SUM(G53:I53) -> 2578.8
A54: Junta | B54: =+F41 -> 4950 | C54: 0 | D54: 0 | E54: 0 | F54: =+F48 -> 8.492 | G54: 0 | H54: 0 | I54: =+B54/2*F54 -> 21017.7 | J54: =SUM(G54:I54) -> 21017.7
A55: Guia | B55: =+F41 -> 4950 | C55: 0 | D55: 0 | E55: 0 | F55: 0 | G55: 0 | H55: 0 | I55: =+B55*2 -> 9900 | J55: =SUM(G55:I55) -> 9900
A56: Grama | B56: =+F41 -> 4950 | C56: 12 | D56: 0 | E56: 0 | F56: 0 | G56: =+B56*C56 -> 59400 | H56: 0 | I56: 0 | J56: =SUM(G56:I56) -> 59400
B57: Extensão | C57: Larg faixa | D57: Base | E57: Altura | F57: Perímetro | G57: Área | H57: Volume | I57: Comprimento | J57: 0
A58: Escavação | B58: =+F41 -> 4950 | C58: 0 | D58: 1.2 | E58: 0.7 | F58: 0 | G58: 0 | H58: =+B58*D58*E58 -> 4158 | I58: 0 | J58: =SUM(G58:I58) -> 4158
A59: Reaterro | B59: =+F41 -> 4950 | D59: 0.6 | E59: 0.6 | H59: =+H58-(B59*D59*E59) -> 2376 | J59: =SUM(G59:I59) -> 2376
A60: Transporte | B60: 0 | C60: 0 | D60: 0 | E60: 0 | F60: 0 | G60: 0 | H60: =(H58-H59)*1.4*5 -> 12474 | J60: =SUM(G60:I60) -> 12474
A61: Manta | B61: =+F41 -> 4950 | C61: 0 | D61: 0.6 | E61: 0.6 | F61: 0 | G61: =B61*D61*4 -> 11880 | H61: 0 | I61: 0 | J61: =SUM(G61:I61) -> 11880
A62: Tubo | B62: =+F41 -> 4950 | C62: 0 | D62: 0 | E62: 0 | F62: 0 | G62: 0 | H62: 0 | I62: =+B62 -> 4950 | J62: =SUM(G62:I62) -> 4950
A63: Brita | B63: =+F41 -> 4950 | C63: 0 | D63: 0.6 | E63: 0.6 | F63: 0 | G63: 0 | H63: =B63*D63*E63-(B63*3.14*0.4*0.4/4) -> 1160.28 | I63: 0 | J63: =SUM(G63:I63) -> 1160.28
A64: Areia | B64: =+F41 -> 4950 | C64: 1.2 | D64: 0 | E64: 0.1 | F64: 0 | G64: 0 | H64: =+B64*C64*E64 -> 594 | J64: =SUM(G64:I64) -> 594
B65: Extensão | C65: Larg faixa | D65: Base | E65: Altura | F65: Perímetro | G65: Área | H65: Volume | I65: Comprimento | J65: 0
A66: Valeta | B66: =+F41 -> 4950 | C66: 0 | D66: 0 | E66: 0 | F66: 0 | G66: 0 | H66: 0 | I66: =+B66*2 -> 9900 | J66: =SUM(G66:I66) -> 9900
A67: Sarjeta | B67: =+F41 -> 4950 | C67: 0 | D67: 0 | E67: 0 | F67: 0 | G67: 0 | H67: 0 | I67: =+B67*2 -> 9900 | J67: =SUM(G67:I67) -> 9900
A68: Bueiro | B68: 0 | C68: 0 | D68: 0 | E68: 0 | F68: 0 | G68: 0 | H68: 0 | I68: =25.5+22+25 -> 72.5 | J68: =SUM(G68:I68) -> 72.5
A69: Boca | B69: 0 | C69: 0 | D69: 0 | E69: 0 | F69: 0 | G69: 0 | H69: 0 | I69: 6 | J69: =SUM(G69:I69) -> 6
B70: Extensão | C70: Larg faixa | D70: Base | E70: Altura | F70: Perímetro | G70: Área | H70: Volume | I70: Comprimento | J70: 0
A71: Escavação | B71: =+F41 -> 4950 | C71: 0 | D71: 3.5 | E71: 0.15 | F71: 0 | G71: 0 | H71: =+B71*D71*E71*2 -> 5197.5 | I71: 0 | J71: =SUM(G71:I71) -> 5197.5
A72: Aterro | B72: =+F41 -> 4950 | C72: 0 | D72: 3.5 | E72: 0.1 | F72: 0 | G72: 0 | H72: =+B72*D72*E72*2 -> 3465 | I72: 0 | J72: =SUM(G72:I72) -> 3465
A73: Transporte | B73: 0 | C73: 0 | D73: 0 | E73: 0 | F73: 0 | G73: 0 | H73: =+H71-H72 -> 1732.5 | I73: 0 | J73: =SUM(G73:I73) -> 1732.5
A74: Regularização | B74: =+F41 -> 4950 | C74: 0 | D74: 3.5 | E74: 0 | F74: 0 | G74: =+B74*D74*2 -> 34650 | H74: 0 | I74: 0 | J74: =SUM(G74:I74) -> 34650
A75: Revestimento | B75: =+F41 -> 4950 | C75: 0 | D75: 3.5 | E75: 0.15 | F75: 0 | H75: =+B75*D75*E75 -> 2598.75 | I75: 0 | J75: =SUM(G75:I75) -> 2598.75
B76: Extensão | C76: Larg faixa | D76: Base | E76: Altura | F76: Perímetro | G76: Área | H76: Volume | I76: Comprimento | J76: 0
A77: Cercas | B77: =+F41 -> 4950 | C77: 0 | D77: 0 | E77: 0 | F77: 0 | G77: 0 | H77: 0 | I77: =+B77*2 -> 9900 | J77: =SUM(G77:I77) -> 9900
A79: ETAPA 3 | B79: =+'Ficha Canais'!A7 -> Canal: CS19 - Trecho 3 | E79: Extensão: | F79: =+'Ficha Canais'!B7 -> 4292 | G79: metros | H79: DMT (KM) = | I79: =+I41 -> 5
B80: Extensão | C80: Larg faixa | D80: Base | E80: Altura | F80: Perímetro | G80: Área | H80: Volume | I80: Comprimento | J80: Quantitativo
A81: Desmatamento | B81: =+F79 -> 4292 | C81: 40 | D81: 0 | E81: 0 | F81: 0 | G81: =+B81*C81 -> 171680 | H81: 0 | I81: 0 | J81: =SUM(G81:I81) -> 171680
A82: Escavavação | B82: 0 | C82: 0 | D82: 0 | E82: 0 | F82: 0 | G82: 0 | H82: 257084.94 | I82: 0 | J82: =SUM(G82:I82) -> 257084.94
A83: Aterro | B83: 0 | C83: 0 | D83: 0 | E83: 0 | F83: 0 | G83: 0 | H83: 31272.74 | I83: 0 | J83: =SUM(G83:I83) -> 31272.74
A84: Transporte | B84: 0 | C84: 0 | D84: 0 | E84: 0 | F84: 0 | G84: 0 | H84: =-(H83-H82)*1.4*I79 -> 1580685.4 | I84: 0 | J84: =SUM(G84:I84) -> 1580685.4
A85: Regularização | B85: =+F79 -> 4292 | C85: 0 | D85: =+'Ficha Canais'!$C$7 -> 1.2 | E85: 0 | F85: 0 | G85: =+B85*D85 -> 5150.4 | H85: 0 | J85: =SUM(G85:I85) -> 5150.4
A86: Geocomposto | B86: =+F79 -> 4292 | C86: 0 | D86: 1.2 | E86: 1.58 | F86: =(E86*1.8*2)+D86+0.8 -> 7.688 | G86: 6715.81 | H86: 0 | I86: 0 | J86: =SUM(G86:I86) -> 6715.81
A87: Solo cimento | B87: =+F79 -> 4292 | C87: 0 | D87: 0 | E87: 0 | F87: 0 | G87: 0 | H87: =+G88*0.2 -> 5372.6 | I87: 0 | J87: =SUM(G87:I87) -> 5372.6
A88: Geomembrana | B88: 0 | C88: 0 | D88: 0 | E88: 0 | F88: 0 | G88: 26863 | H88: 0 | I88: 0 | J88: =SUM(G88:I88) -> 26863
A89: Ancoragem | B89: =+F79 -> 4292 | C89: 0 | D89: 0 | E89: 0 | F89: 0 | G89: 0 | H89: 0 | I89: =+B89*2 -> 8584 | J89: =+I89 -> 8584
A90: Concreto | B90: 0 | C90: 0 | D90: 0 | E90: 0 | F90: 0 | G90: 0 | H90: =+G88*0.07 -> 1880.41 | I90: 0 | J90: =SUM(G90:I90) -> 1880.41
A91: Lançamento | B91: 0 | C91: 0 | D91: 0 | E91: 0 | F91: 0 | G91: 0 | H91: =+H90 -> 1880.41 | I91: 0 | J91: =SUM(G91:I91) -> 1880.41
A92: Junta | B92: =+F79 -> 4292 | C92: 0 | D92: 0 | E92: 0 | F92: =+F86 -> 7.688 | G92: 0 | H92: 0 | I92: =+B92/2*F92 -> 16498.448 | J92: =SUM(G92:I92) -> 16498.448
A93: Guia | B93: =+F79 -> 4292 | C93: 0 | D93: 0 | E93: 0 | F93: 0 | G93: 0 | H93: 0 | I93: =+B93*2 -> 8584 | J93: =SUM(G93:I93) -> 8584
A94: Grama | B94: =+F79 -> 4292 | C94: 12 | D94: 0 | E94: 0 | F94: 0 | G94: =+B94*C94 -> 51504 | H94: 0 | I94: 0 | J94: =SUM(G94:I94) -> 51504
B95: Extensão | C95: Larg faixa | D95: Base | E95: Altura | F95: Perímetro | G95: Área | H95: Volume | I95: Comprimento | J95: 0
A96: Escavação | B96: =+F79 -> 4292 | C96: 0 | D96: 1.2 | E96: 0.7 | F96: 0 | G96: 0 | H96: =+B96*D96*E96 -> 3605.28 | I96: 0 | J96: =SUM(G96:I96) -> 3605.28
A97: Reaterro | B97: =+F79 -> 4292 | D97: 0.6 | E97: 0.6 | H97: =+H96-(B97*D97*E97) -> 2060.16 | J97: =SUM(G97:I97) -> 2060.16
A98: Transporte | B98: 0 | C98: 0 | D98: 0 | E98: 0 | F98: 0 | G98: 0 | H98: =(H96-H97)*1.4*5 -> 10815.84 | J98: =SUM(G98:I98) -> 10815.84
A99: Manta | B99: =+F79 -> 4292 | C99: 0 | D99: 0.6 | E99: 0.6 | F99: 0 | G99: =B99*D99*4 -> 10300.8 | H99: 0 | I99: 0 | J99: =SUM(G99:I99) -> 10300.8
A100: Tubo | B100: =+F79 -> 4292 | C100: 0 | D100: 0 | E100: 0 | F100: 0 | G100: 0 | H100: 0 | I100: =+B100 -> 4292 | J100: =SUM(G100:I100) -> 4292
A101: Brita | B101: =+F79 -> 4292 | C101: 0 | D101: 0.6 | E101: 0.6 | F101: 0 | G101: 0 | H101: =B101*D101*E101-(B101*3.14*0.4*0.4/4) -> 1006.0448 | I101: 0 | J101: =SUM(G101:I101) -> 1006.0448
A102: Areia | B102: =+F79 -> 4292 | C102: 1.2 | D102: 0 | E102: 0.1 | F102: 0 | G102: 0 | H102: =+B102*C102*E102 -> 515.04 | J102: =SUM(G102:I102) -> 515.04
B103: Extensão | C103: Larg faixa | D103: Base | E103: Altura | F103: Perímetro | G103: Área | H103: Volume | I103: Comprimento | J103: 0
...

Sheet MC EC
A1: MEMÓRIA DE CÁLCULO - QUANTITATIVOS DAS ESTRUTURAS DE CONTROLE
A3: ETAPA 3 | B3: =+'Ficha EC'!A5 -> EC2 - CS19 | D3: Extensão: | E3: =+'Ficha EC'!B5 -> 8 | F3: metros
B4: Extensão | C4: Base | D4: Altura | E4: Área | F4: Volume | G4: Peso | H4: Comprimento | I4: Quantitativo
A5: Desmatamento | B5: =+E3 -> 8 | C5: =+'Ficha EC'!C5 -> 3.2 | D5: =+'Ficha EC'!F5 -> 1.56 | E5: =+B5*(C5+20) -> 185.6 | F5: 0 | G5: 0 | H5: 0 | I5: =SUM(E5:H5) -> 185.6 | K5: =+Planilha!E516 -> Desmatamento, destocamento e limpeza de área com árvores de diâmetro até 0,15 m
A6: Escavavação | B6: =+E3 -> 8 | C6: =+C5 -> 3.2 | D6: =+D5 -> 1.56 | E6: 0 | F6: =+B6*(C6+5)*D6 -> 102.336 | G6: 0 | H6: 0 | I6: =SUM(E6:H6) -> 102.336 | K6: =+Planilha!E517 -> Escavação, carga e transporte de material de 1ª categoria - DMT de 1.000 a 1.200 m - caminho de serviço em leito natural - com escavadeira e caminhão basculante de 14 m³
A7: Aterro | B7: =+E3 -> 8 | C7: =+C6 -> 3.2 | D7: =+D6 -> 1.56 | E7: 0 | F7: =+B7*C7*D7 -> 39.936 | G7: 0 | H7: 0 | I7: =SUM(E7:H7) -> 39.936 | K7: =+Planilha!E518 -> Compactação de aterros a 100% do Proctor normal
A8: Transporte | B8: 0 | C8: 0 | D8: 0 | E8: 0 | F8: =(F6-F7)*1.4*5 -> 436.8 | G8: 0 | H8: 0 | I8: =SUM(E8:H8) -> 436.8 | K8: =+Planilha!E519 -> Transporte com caminhão basculante de 14 m³ - rodovia em leito natural
A9: Magro | B9: =+E3 -> 8 | C9: =+C6 -> 3.2 | D9: 0.1 | E9: 0 | F9: =B9*(3*D9+C9)*0.3 -> 8.4 | G9: 0 | H9: 0 | I9: =SUM(E9:H9) -> 8.4 | K9: Concreto magro - confecção em betoneira e lançamento manual - areia e brita comerciais
A10: Concreto | B10: =+E3 -> 8 | C10: =+C7 -> 3.2 | D10: =+D7 -> 1.56 | E10: 0 | F10: =B10*(3*D10+C10)*0.3 -> 18.912 | G10: 0 | H10: 0 | I10: =SUM(E10:H10) -> 18.912 | K10: =+Planilha!E521 -> Concreto para bombeamento fck = 30 MPa - confecção em central dosadora de 30 m³/h - areia e brita comerciais
A11: Lançamento | B11: 0 | C11: 0 | D11: 0 | E11: 0 | F11: =+F10 -> 18.912 | G11: 0 | H11: 0 | I11: =SUM(E11:H11) -> 18.912 | K11: =+Planilha!E522 -> Lançamento mecânico de concreto com bomba rebocável com capacidade de 30 m³/h - confecção em central dosadora de 30 m³/h
A12: Formas | B12: =+E3 -> 8 | C12: =+C10 -> 3.2 | D12: =+D10 -> 1.56 | E12: =B12*(3*D12+C12)*2 -> 126.08 | F12: 0 | G12: 0 | H12: 0 | I12: =SUM(E12:H12) -> 126.08 | K12: =+Planilha!E523 -> Fôrmas de compensado plastificado 12 mm - uso geral - utilização de 1 vez - confecção, instalação e retirada
A13: Armação | B13: 0 | C13: 0 | D13: 0 | E13: 0 | F13: 0 | G13: =+F10*120 -> 2269.44 | H13: 0 | I13: =SUM(E13:H13) -> 2269.44 | K13: =+Planilha!E524 -> Armação em aço CA-50 - fornecimento, preparo e colocação
A14: Guarda-corpo | B14: 0 | C14: =+C12 -> 3.2 | D14: 0 | E14: 0 | F14: 0 | G14: 0 | H14: =+C14*4 -> 12.8 | I14: =SUM(E14:H14) -> 12.8 | K14: =+Planilha!E525 -> Guarda-corpo e corrimão metálico para passarelas para pedestres - fornecimento e instalação
A15: Alambrado | B15: =+E3 -> 8 | C15: 0 | D15: 0 | E15: =+B15*2*2.2 -> 35.2 | F15: 0 | G15: 0 | H15: 0 | I15: =SUM(E15:H15) -> 35.2 | K15: =+Planilha!E526 -> Alambrados
A17: ETAPA 3 | B17: =+'Ficha EC'!A6 -> EC3 - CS19 | D17: Extensão: | E17: =+'Ficha EC'!B6 -> 8 | F17: metros
B18: Extensão | C18: Base | D18: Altura | E18: Área | F18: Volume | G18: Peso | H18: Comprimento | I18: Quantitativo
A19: Desmatamento | B19: =+E17 -> 8 | C19: =+'Ficha EC'!C6 -> 2.6 | D19: =+'Ficha EC'!F6 -> 1.39 | E19: =+B19*(C19+20) -> 180.8 | F19: 0 | G19: 0 | H19: 0 | I19: =SUM(E19:H19) -> 180.8
A20: Escavavação | B20: =+E17 -> 8 | C20: =+C19 -> 2.6 | D20: =+D19 -> 1.39 | E20: 0 | F20: =+B20*(C20+5)*D20 -> 84.512 | G20: 0 | H20: 0 | I20: =SUM(E20:H20) -> 84.512
A21: Aterro | B21: =+E17 -> 8 | C21: =+C20 -> 2.6 | D21: =+D20 -> 1.39 | E21: 0 | F21: =+B21*C21*D21 -> 28.912 | G21: 0 | H21: 0 | I21: =SUM(E21:H21) -> 28.912
A22: Transporte | B22: 0 | C22: 0 | D22: 0 | E22: 0 | F22: =(F20-F21)*1.4*5 -> 389.2 | G22: 0 | H22: 0 | I22: =SUM(E22:H22) -> 389.2
A23: Magro | B23: =+E17 -> 8 | C23: =+C20 -> 2.6 | D23: 0.1 | E23: 0 | F23: =B23*(3*D23+C23)*0.3 -> 6.96 | G23: 0 | H23: 0 | I23: =SUM(E23:H23) -> 6.96
A24: Concreto | B24: =+E17 -> 8 | C24: =+C21 -> 2.6 | D24: =+D21 -> 1.39 | E24: 0 | F24: =B24*(3*D24+C24)*0.3 -> 16.248 | G24: 0 | H24: 0 | I24: =SUM(E24:H24) -> 16.248
A25: Lançamento | B25: 0 | C25: 0 | D25: 0 | E25: 0 | F25: =+F24 -> 16.248 | G25: 0 | H25: 0 | I25: =SUM(E25:H25) -> 16.248
A26: Formas | B26: =+E17 -> 8 | C26: =+C24 -> 2.6 | D26: =+D24 -> 1.39 | E26: =B26*(3*D26+C26)*2 -> 108.32 | F26: 0 | G26: 0 | H26: 0 | I26: =SUM(E26:H26) -> 108.32
A27: Armação | B27: 0 | C27: 0 | D27: 0 | E27: 0 | F27: 0 | G27: =+F24*120 -> 1949.76 | H27: 0 | I27: =SUM(E27:H27) -> 1949.76
A28: Guarda-corpo | B28: 0 | C28: =+C26 -> 2.6 | D28: 0 | E28: 0 | F28: 0 | G28: 0 | H28: =+C28*4 -> 10.4 | I28: =SUM(E28:H28) -> 10.4
A29: Alambrado | B29: =+E17 -> 8 | C29: 0 | D29: 0 | E29: =+B29*2*2.2 -> 35.2 | F29: 0 | G29: 0 | H29: 0 | I29: =SUM(E29:H29) -> 35.2
A31: ETAPA 3 | B31: =+'Ficha EC'!A7 -> EC4 - CS19 | D31: Extensão: | E31: =+'Ficha EC'!B7 -> 8 | F31: metros
B32: Extensão | C32: Base | D32: Altura | E32: Área | F32: Volume | G32: Peso | H32: Comprimento | I32: Quantitativo
A33: Desmatamento | B33: =+E31 -> 8 | C33: =+'Ficha EC'!C7 -> 2.6 | D33: =+'Ficha EC'!F7 -> 1.39 | E33: =+B33*(C33+20) -> 180.8 | F33: 0 | G33: 0 | H33: 0 | I33: =SUM(E33:H33) -> 180.8
A34: Escavavação | B34: =+E31 -> 8 | C34: =+C33 -> 2.6 | D34: =+D33 -> 1.39 | E34: 0 | F34: =+B34*(C34+5)*D34 -> 84.512 | G34: 0 | H34: 0 | I34: =SUM(E34:H34) -> 84.512
A35: Aterro | B35: =+E31 -> 8 | C35: =+C34 -> 2.6 | D35: =+D34 -> 1.39 | E35: 0 | F35: =+B35*C35*D35 -> 28.912 | G35: 0 | H35: 0 | I35: =SUM(E35:H35) -> 28.912
A36: Transporte | B36: 0 | C36: 0 | D36: 0 | E36: 0 | F36: =(F34-F35)*1.4*5 -> 389.2 | G36: 0 | H36: 0 | I36: =SUM(E36:H36) -> 389.2
A37: Magro | B37: =+E31 -> 8 | C37: =+C34 -> 2.6 | D37: 0.1 | E37: 0 | F37: =B37*(3*D37+C37)*0.3 -> 6.96 | G37: 0 | H37: 0 | I37: =SUM(E37:H37) -> 6.96
A38: Concreto | B38: =+E31 -> 8 | C38: =+C35 -> 2.6 | D38: =+D35 -> 1.39 | E38: 0 | F38: =B38*(3*D38+C38)*0.3 -> 16.248 | G38: 0 | H38: 0 | I38: =SUM(E38:H38) -> 16.248
A39: Lançamento | B39: 0 | C39: 0 | D39: 0 | E39: 0 | F39: =+F38 -> 16.248 | G39: 0 | H39: 0 | I39: =SUM(E39:H39) -> 16.248
A40: Formas | B40: =+E31 -> 8 | C40: =+C38 -> 2.6 | D40: =+D38 -> 1.39 | E40: =B40*(3*D40+C40)*2 -> 108.32 | F40: 0 | G40: 0 | H40: 0 | I40: =SUM(E40:H40) -> 108.32
A41: Armação | B41: 0 | C41: 0 | D41: 0 | E41: 0 | F41: 0 | G41: =+F38*120 -> 1949.76 | H41: 0 | I41: =SUM(E41:H41) -> 1949.76
A42: Guarda-corpo | B42: 0 | C42: =+C40 -> 2.6 | D42: 0 | E42: 0 | F42: 0 | G42: 0 | H42: =+C42*4 -> 10.4 | I42: =SUM(E42:H42) -> 10.4
A43: Alambrado | B43: =+E31 -> 8 | C43: 0 | D43: 0 | E43: =+B43*2*2.2 -> 35.2 | F43: 0 | G43: 0 | H43: 0 | I43: =SUM(E43:H43) -> 35.2
A45: ETAPA 3 | B45: =+'Ficha EC'!A8 -> EC5 - CS19 | D45: Extensão: | E45: =+'Ficha EC'!B8 -> 8 | F45: metros
B46: Extensão | C46: Base | D46: Altura | E46: Área | F46: Volume | G46: Peso | H46: Comprimento | I46: Quantitativo
A47: Desmatamento | B47: =+E45 -> 8 | C47: =+'Ficha EC'!C8 -> 1.3 | D47: =+'Ficha EC'!F8 -> 1.19 | E47: =+B47*(C47+20) -> 170.4 | F47: 0 | G47: 0 | H47: 0 | I47: =SUM(E47:H47) -> 170.4
A48: Escavavação | B48: =+E45 -> 8 | C48: =+C47 -> 1.3 | D48: =+D47 -> 1.19 | E48: 0 | F48: =+B48*(C48+5)*D48 -> 59.976 | G48: 0 | H48: 0 | I48: =SUM(E48:H48) -> 59.976
A49: Aterro | B49: =+E45 -> 8 | C49: =+C48 -> 1.3 | D49: =+D48 -> 1.19 | E49: 0 | F49: =+B49*C49*D49 -> 12.376 | G49: 0 | H49: 0 | I49: =SUM(E49:H49) -> 12.376
A50: Transporte | B50: 0 | C50: 0 | D50: 0 | E50: 0 | F50: =(F48-F49)*1.4*5 -> 333.2 | G50: 0 | H50: 0 | I50: =SUM(E50:H50) -> 333.2
A51: Magro | B51: =+E45 -> 8 | C51: =+C48 -> 1.3 | D51: 0.1 | E51: 0 | F51: =B51*(3*D51+C51)*0.3 -> 3.84 | G51: 0 | H51: 0 | I51: =SUM(E51:H51) -> 3.84
A52: Concreto | B52: =+E45 -> 8 | C52: =+C49 -> 1.3 | D52: =+D49 -> 1.19 | E52: 0 | F52: =B52*(3*D52+C52)*0.3 -> 11.688 | G52: 0 | H52: 0 | I52: =SUM(E52:H52) -> 11.688
A53: Lançamento | B53: 0 | C53: 0 | D53: 0 | E53: 0 | F53: =+F52 -> 11.688 | G53: 0 | H53: 0 | I53: =SUM(E53:H53) -> 11.688
A54: Formas | B54: =+E45 -> 8 | C54: =+C52 -> 1.3 | D54: =+D52 -> 1.19 | E54: =B54*(3*D54+C54)*2 -> 77.92 | F54: 0 | G54: 0 | H54: 0 | I54: =SUM(E54:H54) -> 77.92
A55: Armação | B55: 0 | C55: 0 | D55: 0 | E55: 0 | F55: 0 | G55: =+F52*120 -> 1402.56 | H55: 0 | I55: =SUM(E55:H55) -> 1402.56
A56: Guarda-corpo | B56: 0 | C56: =+C54 -> 1.3 | D56: 0 | E56: 0 | F56: 0 | G56: 0 | H56: =+C56*4 -> 5.2 | I56: =SUM(E56:H56) -> 5.2
A57: Alambrado | B57: =+E45 -> 8 | C57: 0 | D57: 0 | E57: =+B57*2*2.2 -> 35.2 | F57: 0 | G57: 0 | H57: 0 | I57: =SUM(E57:H57) -> 35.2
A59: ETAPA 3 | B59: =+'Ficha EC'!A9 -> EC6 - CT1-S19 | D59: Extensão: | E59: 0 | F59: metros
B60: Extensão | C60: Base | D60: Altura | E60: Área | F60: Volume | G60: Peso | H60: Comprimento | I60: Quantitativo
A61: Desmatamento | B61: =+E59 -> 0 | C61: =+'Ficha EC'!C9 -> 0 | D61: =+'Ficha EC'!F9 -> 0 | E61: =+B61*(C61+20) -> 0 | F61: 0 | G61: 0 | H61: 0 | I61: =SUM(E61:H61) -> 0
A62: Escavavação | B62: =+E59 -> 0 | C62: =+C61 -> 0 | D62: =+D61 -> 0 | E62: 0 | F62: =+B62*(C62+5)*D62 -> 0 | G62: 0 | H62: 0 | I62: =SUM(E62:H62) -> 0
A63: Aterro | B63: =+E59 -> 0 | C63: =+C62 -> 0 | D63: =+D62 -> 0 | E63: 0 | F63: =+B63*C63*D63 -> 0 | G63: 0 | H63: 0 | I63: =SUM(E63:H63) -> 0
A64: Transporte | B64: 0 | C64: 0 | D64: 0 | E64: 0 | F64: =(F62-F63)*1.4*5 -> 0 | G64: 0 | H64: 0 | I64: =SUM(E64:H64) -> 0
A65: Magro | B65: =+E59 -> 0 | C65: =+C62 -> 0 | D65: 0 | E65: 0 | F65: =B65*(3*D65+C65)*0.3 -> 0 | G65: 0 | H65: 0 | I65: =SUM(E65:H65) -> 0
A66: Concreto | B66: =+E59 -> 0 | C66: =+C63 -> 0 | D66: =+D63 -> 0 | E66: 0 | F66: =B66*(3*D66+C66)*0.3 -> 0 | G66: 0 | H66: 0 | I66: =SUM(E66:H66) -> 0
A67: Lançamento | B67: 0 | C67: 0 | D67: 0 | E67: 0 | F67: =+F66 -> 0 | G67: 0 | H67: 0 | I67: =SUM(E67:H67) -> 0
A68: Formas | B68: =+E59 -> 0 | C68: =+C66 -> 0 | D68: =+D66 -> 0 | E68: =B68*(3*D68+C68)*2 -> 0 | F68: 0 | G68: 0 | H68: 0 | I68: =SUM(E68:H68) -> 0
A69: Armação | B69: 0 | C69: 0 | D69: 0 | E69: 0 | F69: 0 | G69: =+F66*120 -> 0 | H69: 0 | I69: =SUM(E69:H69) -> 0
A70: Guarda-corpo | B70: 0 | C70: =+C68 -> 0 | D70: 0 | E70: 0 | F70: 0 | G70: 0 | H70: =+C70*4 -> 0 | I70: =SUM(E70:H70) -> 0
A71: Alambrado | B71: =+E59 -> 0 | C71: 0 | D71: 0 | E71: =+B71*2*2.2 -> 0 | F71: 0 | G71: 0 | H71: 0 | I71: =SUM(E71:H71) -> 0
A73: ETAPA 3 | B73: =+'Ficha EC'!A10 -> EC2 - CS21a | D73: Extensão: | E73: =+'Ficha EC'!B10 -> 8 | F73: metros
B74: Extensão | C74: Base | D74: Altura | E74: Área | F74: Volume | G74: Peso | H74: Comprimento | I74: Quantitativo
A75: Desmatamento | B75: =+E73 -> 8 | C75: =+'Ficha EC'!C10 -> 4 | D75: =+'Ficha EC'!F10 -> 1.96 | E75: =+B75*(C75+20) -> 192 | F75: 0 | G75: 0 | H75: 0 | I75: =SUM(E75:H75) -> 192
A76: Escavavação | B76: =+E73 -> 8 | C76: =+C75 -> 4 | D76: =+D75 -> 1.96 | E76: 0 | F76: =+B76*(C76+5)*D76 -> 141.12 | G76: 0 | H76: 0 | I76: =SUM(E76:H76) -> 141.12
A77: Aterro | B77: =+E73 -> 8 | C77: =+C76 -> 4 | D77: =+D76 -> 1.96 | E77: 0 | F77: =+B77*C77*D77 -> 62.72 | G77: 0 | H77: 0 | I77: =SUM(E77:H77) -> 62.72
A78: Transporte | B78: 0 | C78: 0 | D78: 0 | E78: 0 | F78: =(F76-F77)*1.4*5 -> 548.8 | G78: 0 | H78: 0 | I78: =SUM(E78:H78) -> 548.8
A79: Magro | B79: =+E73 -> 8 | C79: =+C76 -> 4 | D79: 0.1 | E79: 0 | F79: =B79*(3*D79+C79)*0.3 -> 10.32 | G79: 0 | H79: 0 | I79: =SUM(E79:H79) -> 10.32
A80: Concreto | B80: =+E73 -> 8 | C80: =+C77 -> 4 | D80: =+D77 -> 1.96 | E80: 0 | F80: =B80*(3*D80+C80)*0.3 -> 23.712 | G80: 0 | H80: 0 | I80: =SUM(E80:H80) -> 23.712
A81: Lançamento | B81: 0 | C81: 0 | D81: 0 | E81: 0 | F81: =+F80 -> 23.712 | G81: 0 | H81: 0 | I81: =SUM(E81:H81) -> 23.712
A82: Formas | B82: =+E73 -> 8 | C82: =+C80 -> 4 | D82: =+D80 -> 1.96 | E82: =B82*(3*D82+C82)*2 -> 158.08 | F82: 0 | G82: 0 | H82: 0 | I82: =SUM(E82:H82) -> 158.08
A83: Armação | B83: 0 | C83: 0 | D83: 0 | E83: 0 | F83: 0 | G83: =+F80*120 -> 2845.44 | H83: 0 | I83: =SUM(E83:H83) -> 2845.44
A84: Guarda-corpo | B84: 0 | C84: =+C82 -> 4 | D84: 0 | E84: 0 | F84: 0 | G84: 0 | H84: =+C84*4 -> 16 | I84: =SUM(E84:H84) -> 16
A85: Alambrado | B85: =+E73 -> 8 | C85: 0 | D85: 0 | E85: =+B85*2*2.2 -> 35.2 | F85: 0 | G85: 0 | H85: 0 | I85: =SUM(E85:H85) -> 35.2
A87: ETAPA 3 | B87: =+'Ficha EC'!A11 -> EC3 - CS21a | D87: Extensão: | E87: =+'Ficha EC'!B11 -> 8 | F87: metros
B88: Extensão | C88: Base | D88: Altura | E88: Área | F88: Volume | G88: Peso | H88: Comprimento | I88: Quantitativo
A89: Desmatamento | B89: =+E87 -> 8 | C89: =+'Ficha EC'!C11 -> 3.3 | D89: =+'Ficha EC'!F11 -> 1.72 | E89: =+B89*(C89+20) -> 186.4 | F89: 0 | G89: 0 | H89: 0 | I89: =SUM(E89:H89) -> 186.4
A90: Escavavação | B90: =+E87 -> 8 | C90: =+C89 -> 3.3 | D90: =+D89 -> 1.72 | E90: 0 | F90: =+B90*(C90+5)*D90 -> 114.208 | G90: 0 | H90: 0 | I90: =SUM(E90:H90) -> 114.208
A91: Aterro | B91: =+E87 -> 8 | C91: =+C90 -> 3.3 | D91: =+D90 -> 1.72 | E91: 0 | F91: =+B91*C91*D91 -> 45.408 | G91: 0 | H91: 0 | I91: =SUM(E91:H91) -> 45.408
A92: Transporte | B92: 0 | C92: 0 | D92: 0 | E92: 0 | F92: =(F90-F91)*1.4*5 -> 481.6 | G92: 0 | H92: 0 | I92: =SUM(E92:H92) -> 481.6
A93: Magro | B93: =+E87 -> 8 | C93: =+C90 -> 3.3 | D93: 0.1 | E93: 0 | F93: =B93*(3*D93+C93)*0.3 -> 8.64 | G93: 0 | H93: 0 | I93: =SUM(E93:H93) -> 8.64
A94: Concreto | B94: =+E87 -> 8 | C94: =+C91 -> 3.3 | D94: =+D91 -> 1.72 | E94: 0 | F94: =B94*(3*D94+C94)*0.3 -> 20.304 | G94: 0 | H94: 0 | I94: =SUM(E94:H94) -> 20.304
A95: Lançamento | B95: 0 | C95: 0 | D95: 0 | E95: 0 | F95: =+F94 -> 20.304 | G95: 0 | H95: 0 | I95: =SUM(E95:H95) -> 20.304
A96: Formas | B96: =+E87 -> 8 | C96: =+C94 -> 3.3 | D96: =+D94 -> 1.72 | E96: =B96*(3*D96+C96)*2 -> 135.36 | F96: 0 | G96: 0 | H96: 0 | I96: =SUM(E96:H96) -> 135.36
A97: Armação | B97: 0 | C97: 0 | D97: 0 | E97: 0 | F97: 0 | G97: =+F94*120 -> 2436.48 | H97: 0 | I97: =SUM(E97:H97) -> 2436.48
A98: Guarda-corpo | B98: 0 | C98: =+C96 -> 3.3 | D98: 0 | E98: 0 | F98: 0 | G98: 0 | H98: =+C98*4 -> 13.2 | I98: =SUM(E98:H98) -> 13.2
A99: Alambrado | B99: =+E87 -> 8 | C99: 0 | D99: 0 | E99: =+B99*2*2.2 -> 35.2 | F99: 0 | G99: 0 | H99: 0 | I99: =SUM(E99:H99) -> 35.2
A101: ETAPA 3 | B101: =+'Ficha EC'!A12 -> EC4 - CS21a | D101: Extensão: | E101: =+'Ficha EC'!B12 -> 8 | F101: metros
B102: Extensão | C102: Base | D102: Altura | E102: Área | F102: Volume | G102: Peso | H102: Comprimento | I102: Quantitativo
A103: Desmatamento | B103: =+E101 -> 8 | C103: =+'Ficha EC'!C12 -> 3.1 | D103: =+'Ficha EC'!F12 -> 1.56 | E103: =+B103*(C103+20) -> 184.8 | F103: 0 | G103: 0 | H103: 0 | I103: =SUM(E103:H103) -> 184.8
A104: Escavavação | B104: =+E101 -> 8 | C104: =+C103 -> 3.1 | D104: =+D103 -> 1.56 | E104: 0 | F104: =+B104*(C104+5)*D104 -> 101.088 | G104: 0 | H104: 0 | I104: =SUM(E104:H104) -> 101.088
A105: Aterro | B105: =+E101 -> 8 | C105: =+C104 -> 3.1 | D105: =+D104 -> 1.56 | E105: 0 | F105: =+B105*C105*D105 -> 38.688 | G105: 0 | H105: 0 | I105: =SUM(E105:H105) -> 38.688
A106: Transporte | B106: 0 | C106: 0 | D106: 0 | E106: 0 | F106: =(F104-F105)*1.4*5 -> 436.8 | G106: 0 | H106: 0 | I106: =SUM(E106:H106) -> 436.8
A107: Magro | B107: =+E101 -> 8 | C107: =+C104 -> 3.1 | D107: 0.1 | E107: 0 | F107: =B107*(3*D107+C107)*0.3 -> 8.16 | G107: 0 | H107: 0 | I107: =SUM(E107:H107) -> 8.16
A108: Concreto | B108: =+E101 -> 8 | C108: =+C105 -> 3.1 | D108: =+D105 -> 1.56 | E108: 0 | F108: =B108*(3*D108+C108)*0.3 -> 18.672 | G108: 0 | H108: 0 | I108: =SUM(E108:H108) -> 18.672
...

Sheet MC OBRAS
A1: MEMÓRIA DE CÁLCULO - QUANTITATIVOS DAS OBRAS
A3: ETAPA 3 - ESCADA HIDRÁULICA CS21a
A5: Escavação: 7,00 x 5,00 x 250,00 = | E5: =7*5*250 -> 8750 | F5: m³
A6: Botafora: 4,00 x 4,00 x 250,00 = | E6: =4*4*250 -> 4000 | F6: m³
A7: Reaterro: | E7: =+E5-E6 -> 4750 | F7: m³
A8: Concreto: (3,00 + 2,00 + 2,00) x 0,30 x 250,00 = | E8: =7*0.3*250 -> 525 | F8: m³
A9: Formas: (3,00 + 2,00 + 2,00) x 2 x 250,00 = | E9: =7*2*250 -> 3500 | F9: m²
A10: Aço CA-50: 120 kg/m³ x | E10: =120*E8 -> 63000 | F10: kg
A16: ETAPA 4 - SIFÃO CS25
A18: Extensão: Poços (Entrada e Saída) = 4,50 m cada
A19: Galeria: 40,00 m
A20: Extensão Total = 49,00 metros
A22: Escavação: 5,00 x 2,00 x 49,00 = | E22: =5*2*49 -> 490 | F22: m³
A23: Botafora: | E23: =+E22 -> 490 | F23: m³
A24: Concreto: (2,10 x 3 + 3,60 x 2) x 0,30 x 49,00 = | E24: 198.45 | F24: m³
A25: Formas: (2,10 x 3 + 3,60 x 2) x 2 x 49,00 = | E25: =+E24/0.3*2 -> 1323 | F25: m²
A26: Aço CA-50: 120 kg/m³ x | E26: =120*E24 -> 23814 | F26: kg

Sheet MC GALERIAS
A1: MEMÓRIA DE CÁLCULO - QUANTITATIVOS DAS OBRAS | N1: Resumo das Quantidades
A2: Galerias de Transposição Simples
O3: ETAPA 3
O4: =+A15 -> GT1 - CS19-Trecho 5 | P4: =+A38 -> GT2 - CT1-S19-Trecho 1 | Q4: =+A61 -> GT3 - CT1-S19-Trecho 2 | R4: =+A84 -> GT1 - CS21a-Trecho 5 | S4: =+A107 -> GT1 - CS21a-Trecho 6 | T4: =+A169 -> GTD1 - CS19-Trecho 1 | U4: =+A192 -> GTD1 - CS21 | V4: =+A215 -> GTD2 - CS21a - Trecho 1 | W4: =+A238 -> GTD3 - CS21a - Trecho 3.1
N5: Escavação | O5: =+H17 -> 63.276 | P5: =+H40 -> 0 | Q5: =+H63 -> 0 | R5: =+H86 -> 87.312 | S5: =+H109 -> 0 | T5: =+H171 -> 210.5272 | U5: 210.5272 | V5: 210.5272 | W5: =+H240 -> 151.104
N6: Reaterro | O6: =+H25 -> 23.73 | P6: =+H48 -> 0 | Q6: =+H71 -> 0 | R6: =+H94 -> 41.58 | S6: =+H117 -> 0 | T6: =+H179 -> 51.52 | U6: 51.52 | V6: 51.52 | W6: =+H248 -> 41.16
N7: Transporte | O7: =+H21 -> 276.822 | P7: =+H44 -> 0 | Q7: =+H67 -> 0 | R7: =+H90 -> 320.124 | S7: =+H113 -> 0 | T7: =+H175 -> 1113.0504 | U7: 1113.0504 | V7: 1113.0504 | W7: =+H244 -> 769.608
N8: Concreto | O8: =+H27 -> 22.02 | P8: =+H50 -> 0 | Q8: =+H73 -> 0 | R8: =+H96 -> 21.624 | S8: =+H119 -> 0 | T8: =+H181 -> 60.72 | U8: 60.72 | V8: 60.72 | W8: =+H250 -> 47.52
L9: EXCLUÍDOS | N9: Lançamento | O9: =+O8 -> 22.02 | P9: =+P8 -> 0 | Q9: =+Q8 -> 0 | R9: =+R8 -> 21.624 | S9: =+S8 -> 0 | T9: =+T8 -> 60.72 | U9: 60.72 | V9: 60.72 | W9: =+H254 -> 88.2
N10: Formas | O10: =+H31 -> 76.3 | P10: =+H54 -> 0 | Q10: =+H77 -> 0 | R10: =+H100 -> 65.8 | S10: =+H123 -> 0 | T10: =+H185 -> 117.6 | U10: 117.6 | V10: 117.6 | W10: =+W9 -> 88.2
N11: Aço | O11: =+H33 -> 2642.4 | P11: =+H56 -> 0 | Q11: =+H79 -> 0 | R11: =+H102 -> 2594.88 | S11: =+H125 -> 0 | T11: =+H187 -> 7286.4 | U11: 7286.4 | V11: 7286.4 | W11: =+H256 -> 5702.4
N12: Junta | O12: =+H35 -> 14.8 | P12: =+H58 -> 0 | Q12: =+H81 -> 0 | R12: =+H104 -> 16 | S12: =+H127 -> 0 | T12: =+H189 -> 26.4 | U12: 26.4 | V12: 26.4 | W12: =+H258 -> 21.6
A14: ETAPA 3 | O14: ETAPA 4
A15: GT1 - CS19-Trecho 5 | D15: L1 Encontros = | F15: =2.4/1.5 -> 1.6 | H15: Bases Montante e Jusante = | K15: =2*1.3 -> 2.6 | O15: =+A130 -> GT1 - CS27 | P15: =+A261 -> GTD1 - CP3 - Trecho 2 | Q15: =+A284 -> GTD2 - CP3a - Trecho 2 | R15: =+A307 -> GTD3 - CS25 - Trecho 1
N16: Escavação | O16: =+H132 -> 37.71625 | P16: =+H263 -> 184.352 | Q16: =+H286 -> 164.76148 | R16: 210.5272
A17: Escavações: | H17: =SUM(H18:H19) -> 63.276 | N17: Reaterro | O17: =+H140 -> 19.565 | P17: =+H271 -> 49 | Q17: =+H294 -> 114.296 | R17: 51.52
B18: Encontros: | D18: 2 X (2,60 + 1,30) ÷ 2 X 1,60 X 2,40 = | H18: =2*(2.6+1.3)/2*1.6*2.4 -> 14.976 | N18: Transporte | O18: =+H136 -> 127.05875 | P18: =+H267 -> 947.464 | Q18: =+H290 -> 353.25836 | R18: 1113.0504
B19: Galeria: | D19: 2,30 X 3,00 X 7,00 = | H19: =2.3*3*7 -> 48.3 | N19: Concreto | O19: =+H142 -> 12.91365 | P19: =+H273 -> 31.08 | Q19: =+H296 -> 20.57448 | R19: 60.72
N20: Lançamento | O20: =+O19 -> 12.91365 | P20: =+P19 -> 31.08 | Q20: =+Q19 -> 20.57448 | R20: 60.72
A21: Botafora: | H21: =SUM(H22:H23) -> 276.822 | I21: =SUM(I22:I23) -> 39.546 | N21: Formas | O21: =+H146 -> 44.1 | P21: =+H277 -> 105 | Q21: =+H300 -> 68.74 | R21: 117.6
B22: Encontros: | H22: =+H18*1.4*5 -> 104.832 | I22: =+H18 -> 14.976 | N22: Aço | O22: =+H148 -> 1549.638 | P22: =+H279 -> 3729.6 | Q22: =+H302 -> 2468.9376 | R22: 7286.4
B23: Galeria: | D23: 1,30 X 2,70 X 7,00 = | H23: =1.3*2.7*7*1.4*5 -> 171.99 | I23: =1.3*2.7*7 -> 24.57 | N23: Junta | O23: =+H150 -> 10.2 | P23: =+H281 -> 18.4 | Q23: =+H304 -> 10.88 | R23: 26.4
A25: Reaterro: | H25: =+H17-I21 -> 23.73
A27: Concreto: | H27: =SUM(H28:H29) -> 22.02
B28: Encontros: | D28: 2 X (2,60 + 1,30) ÷ 2 + (2,40 X 2) X 1,60 X 0,30 = | H28: =((2.6+1.3)/2+(2.4*2))*1.6*0.3*2 -> 6.48
B29: Galeria: | D29: (1,30 + 2,40) X 2 X 0,30 X 7,00 = | H29: =(1.3+2.4)*2*0.3*7 -> 15.54
A31: Formas: | B31: Galeria: | D31: 1,30 + (2,40 X 4) X 7,00 = | H31: =(2.4*4+1.3)*7 -> 76.3
A33: Aço: | H33: =+H27*120 -> 2642.4
A35: Juntas: | H35: =2*(K15+2.4+2.4) -> 14.8
A37: ETAPA 3 | B37: ELIMINADO
A38: GT2 - CT1-S19-Trecho 1 | D38: L1 Encontros = | F38: 0 | H38: Bases Montante e Jusante = | K38: 0
A40: Escavações: | H40: =SUM(H41:H42) -> 0
B41: Encontros:
B42: Galeria:
A44: Botafora: | H44: =SUM(H45:H46) -> 0 | I44: =SUM(I45:I46) -> 0
B45: Encontros: | H45: =+H41*1.4*5 -> 0 | I45: =+H41 -> 0
B46: Galeria:
A48: Reaterro: | H48: =+H40-I44 -> 0
A50: Concreto: | H50: =SUM(H51:H52) -> 0
B51: Encontros:
B52: Galeria:
A54: Formas: | B54: Galeria:
A56: Aço: | H56: =+H50*120 -> 0
A58: Juntas:
A60: ETAPA 3 | B60: ELIMINADO
A61: GT3 - CT1-S19-Trecho 2 | D61: L1 Encontros = | F61: 0 | H61: Bases Montante e Jusante = | K61: 0
A63: Escavações: | H63: =SUM(H64:H65) -> 0
B64: Encontros:
B65: Galeria:
A67: Botafora: | H67: =SUM(H68:H69) -> 0 | I67: =SUM(I68:I69) -> 0
B68: Encontros: | H68: =+H64*1.4*5 -> 0 | I68: =+H64 -> 0
B69: Galeria:
A71: Reaterro: | H71: =+H63-I67 -> 0
A73: Concreto: | H73: =SUM(H74:H75) -> 0
B74: Encontros:
B75: Galeria:
A77: Formas: | B77: Galeria:
A79: Aço: | H79: =+H73*120 -> 0
A81: Juntas:
A83: ETAPA 3
A84: GT1 - CS21a-Trecho 5 | D84: L1 Encontros = | F84: =1.8/1.5 -> 1.2 | H84: Bases Montante e Jusante = | K84: =2*2.2 -> 4.4
A86: Escavações: | H86: =SUM(H87:H88) -> 87.312
B87: Encontros: | D87: 2 X (4,40 + 1,80) ÷ 2 X 1,20 X 1,80 = | H87: =(4.4+1.8)/2*1.2*1.8*2 -> 13.392
B88: Galeria: | D88: 4,40 X 2,40 X 7,00 = | H88: =4.4*2.4*7 -> 73.92
A90: Botafora: | H90: =SUM(H91:H92) -> 320.124 | I90: =SUM(I91:I92) -> 45.732
B91: Encontros: | H91: =+H87*1.4*5 -> 93.744 | I91: =+H87 -> 13.392
B92: Galeria: | D92: 2,20 X 2,10 X 7,00 = | H92: =2.2*2.1*7*1.4*5 -> 226.38 | I92: =2.2*2.1*7 -> 32.34
A94: Reaterro: | H94: =+H86-I90 -> 41.58
A96: Concreto: | H96: =SUM(H97:H98) -> 21.624
B97: Encontros: | D97: 2 X (4,40 + 1,80) ÷ 2 + (1,80 X 2) X 1,20 X 0,30 = | H97: =((4.4+1.8)/2+(1.8*2))*1.2*0.3*2 -> 4.824
B98: Galeria: | D98: (2,20 + 1,80) X 2 X 0,30 X 7,00 = | H98: =(2.2+1.8)*2*0.3*7 -> 16.8
A100: Formas: | B100: Galeria: | D100: 1,80 + (1,80 X 4) X 7,00 = | H100: =(1.8*4+2.2)*7 -> 65.8
A102: Aço: | H102: =+H96*120 -> 2594.88
A104: Juntas: | H104: =2*(K84+1.8+1.8) -> 16
A106: ETAPA 3 | B106: ELIMINADO
A107: GT1 - CS21a-Trecho 6 | D107: L1 Encontros = | H107: Bases Montante e Jusante =
A109: Escavações: | H109: =SUM(H110:H111) -> 0
B110: Encontros:
B111: Galeria:
A113: Botafora: | H113: =SUM(H114:H115) -> 0 | I113: =SUM(I114:I115) -> 0
B114: Encontros: | H114: =+H110*1.4*5 -> 0 | I114: =+H110 -> 0
B115: Galeria:
A117: Reaterro: | H117: =+H109-I113 -> 0
A119: Concreto: | H119: =SUM(H120:H121) -> 0
B120: Encontros:
B121: Galeria:
A123: Formas: | B123: Galeria:
A125: Aço: | H125: =+H119*120 -> 0
A127: Juntas:
A129: ETAPA 4
A130: GT1 - CS27 | D130: L1 Encontros = | F130: =1.25/1.5 -> 0.83333333 | H130: Bases Montante e Jusante = | K130: =2*1.3 -> 2.6
A132: Escavações: | H132: =SUM(H133:H134) -> 37.71625
B133: Encontros: | D133: 2 X (2,60 + 1,30) ÷ 2 X 0,83 X 1,30 = | H133: =(2.6+1.3)/2*0.83*1.25*2 -> 4.04625
B134: Galeria: | D134: 2,60 X 1,85 X 7,00 = | H134: =2.6*1.85*7 -> 33.67
A136: Botafora: | H136: =SUM(H137:H138) -> 127.05875 | I136: =SUM(I137:I138) -> 18.15125
B137: Encontros: | H137: =+H133*1.4*5 -> 28.32375 | I137: =+H133 -> 4.04625
B138: Galeria: | D138: 1,30 X 1,55 X 7,00 = | H138: =1.3*1.55*7*1.4*5 -> 98.735 | I138: =1.3*1.55*7 -> 14.105
A140: Reaterro: | H140: =+H132-I136 -> 19.565
A142: Concreto: | H142: =SUM(H143:H144) -> 12.91365
B143: Encontros: | D143: 2 X (2,60 + 1,25) ÷ 2 + (1,25 X 2) X 0,83 X 0,30 = | H143: =((2.6+1.25)/2+(1.25*2))*0.83*0.3*2 -> 2.20365
...

Sheet MC TUBULAÇÕES
A1: MEMÓRIA DE CÁLCULO - QUANTITATIVOS DOS TRECHOS EM TUBULAÇÕES
A3: ETAPA 3
A4: TS1-S19 | B4: Eextensão 1.683 metros | E4: Tubos Aço 800 mm
A5: Escavação: 1,40 x 1,20 x 1.683 = | E5: =1.4*1.2*1683 -> 2827.44 | F5: m³
A6: Botafora: π x 0,8²/4 x 1.683 = | E6: =3.1416*0.8*0.8/4*1683*1.4*5 -> 5921.7903 | F6: txkm
A7: Reaterro: | E7: =E5-3.1416*0.8*0.8/4*1683 -> 1981.47 | F7: m³
A8: Escoramento: 1.683 x 1,20 x 2 = | E8: =1683*2*1.2 -> 4039.2 | F8: m²
A9: Brita: 1,20 x 1.683 x 0,30 = | E9: =1.2*1683*0.3 -> 605.88
A10: Lastro: 1,20 x 1.683 x 0,10 = | E10: =1.2*1683*0.1 -> 201.96 | F10: m³
A11: Tubulação de aço = | E11: 1683 | F11: m
A13: ETAPA 4 - 1000 mm
A14: TP3 | B14: Eextensão 2.100 metros | E14: Tubos Aço 1.000 mm
A15: Escavação: 1,60 x 1,40 x 2.100 = | E15: =1.6*1.4*2100 -> 4704 | F15: m³
A16: Botafora: π x 1,0²/4 x 2.100 = | E16: =3.1416*1*1/4*2100*1.4*5 -> 11545.38 | F16: txkm
A17: Reaterro: | E17: =E15-3.1416*0.8*0.8/4*1683 -> 3858.03 | F17: m³
A18: Escoramento: 2.100 x 1,20 x 2 = | E18: =2100*2*1.4 -> 5880 | F18: m²
A19: Brita: 1,40 x 2,100 x 0,30 = | E19: =1.4*2100*0.3 -> 882
A20: Lastro: 1,40 x 2.100 x 0,10 = | E20: =1.4*2100*0.1 -> 294 | F20: m³
A21: Tubulação de aço = | E21: 2100 | F21: m
A23: ETAPA 4 - 600 mm
A24: TP3 | B24: Eextensão 665 metros | E24: Tubos Aço 600 mm
A25: Escavação: 1,20 x 1,00 x 665 = | E25: =1.2*1*665 -> 798 | F25: m³
A26: Botafora: π x 0,6²/4 x 665 = | E26: =3.1416*0.6*0.6/4*665*1.4*5 -> 1316.1733 | F26: txkm
A27: Reaterro: | E27: =E25-3.1416*0.6*0.6/4*665 -> 609.97524 | F27: m³
A28: Escoramento: 665 x 1,00 x 2 = | E28: =665*2*1 -> 1330 | F28: m²
A29: Brita: 1,00 x 665 x 0,30 = | E29: =1*665*0.3 -> 199.5
A30: Lastro: 1,00 x 665 x 0,10 = | E30: =1*665*0.1 -> 66.5 | F30: m³
A31: Tubulação de aço = | E31: 665 | F31: m
A33: ETAPA 4 - 500 mm
A34: TP3 | B34: Eextensão 1.377 metros | E34: Tubos Aço 500 mm
A35: Escavação: 1,10 x 0,90 x 1.377 = | E35: =1.1*1*1377 -> 1514.7 | F35: m³
A36: Botafora: π x 0,5²/4 x 1.377 = | E36: =3.1416*0.5*0.5/4*1377*1.4*5 -> 1892.6176 | F36: txkm
A37: Reaterro: | E37: =E35-3.1416*0.5*0.5/4*1377 -> 1244.3261 | F37: m³
A38: Escoramento: 1.377 x 1,10 x 2 = | E38: =1377*2*1.1 -> 3029.4 | F38: m²
A39: Brita: 0,90 x 1.377 x 0,30 = | E39: =0.9*1377*0.3 -> 371.79
A40: Lastro: 0,90 x 1.377 x 0,10 = | E40: =0.9*1377*0.1 -> 123.93 | F40: m³
A41: Tubulação de aço = | E41: 1377 | F41: m
A43: ETAPA 4 - 500 mm
A44: TS29 | B44: Eextensão 1.537 metros | E44: Tubos Aço 500 mm
A45: Escavação: 1,10 x 0,90 x 1.537 = | E45: =1.4*1.2*1537 -> 2582.16 | F45: m³
A46: Botafora: π x 0,5²/4 x 1.537 = | E46: =3.1416*0.5*0.5/4*1537*1.4*5 -> 2112.5296 | F46: txkm
A47: Reaterro: | E47: =E45-3.1416*0.5*0.5/4*1537 -> 2280.37 | F47: m³
A48: Escoramento: 1.537 x 1,10 x 2 = | E48: =1537*2*1.2 -> 3688.8 | F48: m²
A49: Brita: 0,90 x 1.537 x 0,30 = | E49: =0.9*1537*0.3 -> 414.99
A50: Lastro: 0,90 x 1.537 x 0,10 = | E50: =0.9*1537*0.1 -> 138.33 | F50: m³
A51: Tubulação de aço = | E51: 1537 | F51: m

Sheet MC ERs
A1: MEMÓRIA DE CÁLCULO - QUANTITATIVOS DAS ESTAÇÕES DE RECALQUE
A3: ETAPA 3 - ER1
A5: Desmatamento: 42,00 x 18,10 = | D5: =42*18.1 -> 760.2
A6: Escavação: 32,00 x 8,10 x 3,00 = | D6: =32*8.1*3 -> 777.6
A7: Botafora: | D7: =+D6*1.4*5 -> 5443.2
A8: Concreto: | H8: =SUM(H9:H14) -> 297.863
B9: Lajes de fundo: 23,30 x 7,80 x 0,30 = | H9: =23.3*7.8*0.3 -> 54.522
B10: Paredes Laterais: 23,30 x 2 x 2,70 x 0,30 = | H10: =23.3*2*2.7*0.3 -> 37.746
B11: Paredes Bombas : (11,30 x 4 + 8,10 x 2) x 9,75 x 0,30 = | H11: =61.4*9.75*0.3 -> 179.595
B12: Paredes Cãmara de Manobras : (9,00 x 2 + 2,00 x 2) x 3,00 x 0,30 = | H12: =22*3*0.3 -> 19.8
B13: Laje: 7,70 x 7,00 x 0,10 = | H13: =7.7*7*0.1 -> 5.39
B14: Vigas: 8,10 x 2 x 1,00 x 0,10 = | H14: =8.1*0.1 -> 0.81
A15: Formas: | H15: =+H8*6 -> 1787.178
A16: Cimbramento: | C16: Laje: 7,70 x 7,00 x 2,80 = | H16: =7*7*2.8 -> 137.2
A17: Aço CA-50: 120 kg/m³ x | H17: =+H8*120 -> 35743.56
A18: Cobertura: 10,00 x 10,00 = | H18: =10*10 -> 100
A19: TUBO DE AÇO CARBONO ø 1250 MM | E19: 42 | F19: metros
A20: TUBO DE AÇO CARBONO ø 900 MM | E20: 15 | F20: metros
A22: ETAPA 4 - ER1
A24: Desmatamento: 36,60 x 18,45 = | D24: =36.6*18.45 -> 675.27
A25: Escavação: 26,60 x 8,45 | D25: =26.6*8.45 -> 224.77
A26: Botafora: | D26: =+D25*1.4*5 -> 1573.39
A27: Concreto: | H27: =SUM(H28:H33) -> 228.276
B28: Lajes de fundo: 8,10 x 22,00 x 0,30 = | H28: =8.1*22*0.3 -> 53.46
B29: Paredes Laterais: 8,10 x 2 x 2,70 x 0,30 = | H29: =8.1*2*2.7*0.3 -> 13.122
B30: Paredes Bombas : (7,70 x 4 + 8,10 x 2) x 9,50 x 0,30 | H30: =47*9.5*0.3 -> 133.95
B31: Paredes Cãmara de Manobras : (8,70 x 2 + 2,00 x 2) x 2,80 x 0,30 = | H31: =21.4*2.8*0.3 -> 17.976
B32: Laje: 9,70 x 8,40 x 0,10 | H32: =9.7*8.4*0.1 -> 8.148
B33: Vigas: 8,10 x 2 x 1,00 x 0,10 = | H33: =8.1*2*0.1 -> 1.62
A34: Formas: | H34: =+H27*6 -> 1369.656
A35: Cimbramento: | C35: Laje: 9,70 x 8,40 x 2,80 = | H35: =9.7*8.4*2.8 -> 228.144
A36: Aço CA-50: 120 kg/m³ x | H36: =+H27*120 -> 27393.12
A37: Cobertura: 10,00 x 10,00 = | H37: =10*10 -> 100
A38: TUBO DE AÇO CARBONO ø 1050 MM | E38: 19.2 | F38: metros
A39: TUBO DE AÇO CARBONO ø 600 MM | E39: 13.15 | F39: metros
A41: ETAPA 4 - ER2
A43: Desmatamento: 34,00 x 12,00 = | D43: =34*12 -> 408
A44: Escavação: 24,00 x 8,00 x 2,50 = | D44: =24*8*2.5 -> 480
A45: Botafora: | D45: =+D44*1.4*5 -> 3360
A46: Concreto: | H46: =SUM(H47:H52) -> 176.285
B47: Lajes de fundo: 19,00 x 2,00 0,30 = | H47: =19*2*3 -> 114
B48: Paredes Laterais: 7,00 x 2 x 2,20 x 0,3 = | H48: =7*2*2.2*0.3 -> 9.24
B49: Paredes Bombas: 3,50 x 4 x 10,00 x 0,3 = | H49: =3.5*4*10*0.3 -> 42
B50: Paredes Cãmara de Manobras : 5,50 x 2 x 2,80 x 0,3 | H50: =5.5*2*2.8*0.3 -> 9.24
B51: Laje: 4,50 x 2,50 x 0,10 = | H51: =4.5*2.5*0.1 -> 1.125
B52: Vigas: 3,40 x 2 x 1,00 x 0,10 = | H52: =3.4*2*0.1 -> 0.68
A53: Formas: | H53: =+H46*6 -> 1057.71
A54: Cimbramento: | C54: Laje: 4,50 x 2,50 x 2,80 = | H54: =4.5*2.5*2.8 -> 31.5
A55: Aço CA-50: 120 kg/m³ x | H55: =+H46*120 -> 21154.2
A56: Cobertura: 10,00 x 5,00 = | H56: 50
A57: TUBO DE AÇO CARBONO ø 1000 MM | E57: 13 | F57: metros
A59: ETAPA 4 - ER3
A61: Desmatamento: 32,20 x 14,00 = | D61: =32.2*14 -> 450.8
A62: Escavação: 22,20 x 4,00 x 1,80 = | D62: =22.2*4*1.8 -> 159.84
A63: Botafora: | D63: =+D62*1.4*5 -> 1118.88
A64: Concreto: | H64: =SUM(H65:H70) -> 159.003
B65: Lajes de fundo: 18,00 x 4,40 x 0,30 = | H65: =18*4.4*0.3 -> 23.76
B66: Paredes Laterais: 5,25 x 2 x 0,30 = | H66: =5.25*2*0.3 -> 3.15
B67: Paredes Bombas : (11,30 x 3 + 4,52 x 2) x 9,00 x 0,30 = | H67: =42.94*9*0.3 -> 115.938
B68: Paredes Cãmara de Manobras : (5,05 + 2,00) x 2 x 2,80 x 0,30 = | H68: =7.05*2*2.8*0.3 -> 11.844
B69: Laje: 7,70 x 4,30 x 0,10 = | H69: =7.7*4.3*0.1 -> 3.311
B70: Vigas: 5,00 x 2 x 1,00 x 0,10 = | H70: =5*2*1*0.1 -> 1
A71: Formas: | H71: =+H64*6 -> 954.018
A72: Cimbramento: | C72: Laje: 7,70 x 4,30 x 2,80 = | H72: =7.7*4.3*2.8 -> 92.708
A73: Aço CA-50: 120 kg/m³ x | H73: =+H64*120 -> 19080.36
A74: Cobertura: 10,00 x 6,00 = | H74: =10*6 -> 60
A75: TUBO DE AÇO CARBONO ø 800 MM | E75: 6.5 | F75: metros
A76: TUBO DE AÇO CARBONO ø 300 MM | E76: 8.5 | F76: metros
A78: ETAPA 4 - ER4
A80: Desmatamento: 26,55 x 14,30 = | D80: =26.55*14.3 -> 379.665
A81: Escavação: 16,55 x 4,30 x 2,30 = | D81: =16.55*4.3*2.3 -> 163.6795
A82: Botafora: | D82: =+D81*1.4*5 -> 1145.7565
A83: Concreto: | H83: =SUM(H84:H89) -> 148.5985
B84: Lajes de fundo: 4,30 x 16,55 * 0,30 = | H84: =4.3*16.55*0.3 -> 21.3495
B85: Paredes Laterais: 5,25 x 2 x 2,00 = | H85: =5.25*2*2 -> 21
B86: Paredes Laterais: (7,50 x 3 + 3,50 x 3 + 5,10 x 2) x 6,80 x 0,30 = | H86: =43.2*6.8*0.3 -> 88.128
B87: Paredes Cãmara de Manobras : (6,70 + 2,00) x 2 x 2,80 x 0,30 | H87: =8.7*2*2.8*0.3 -> 14.616
B88: Laje: (4,20 x 3,60 + 3,50 x 2,55) x 0,10 = | H88: =24.05*0.1 -> 2.405
B89: Vigas: 5,50 x 2 x 1,00 x 0,10 = | H89: =5.5*2*0.1 -> 1.1
A90: Formas: | H90: =+H83*6 -> 891.591
A91: Cimbramento: | C91: Laje: (4,20 x 3,60 + 3,50 x 2,55) x 2,80 = | H91: =24.05*2.8 -> 67.34
A92: Aço CA-50: 120 kg/m³ x | H92: =+H83*120 -> 17831.82
A93: Cobertura: 10,00 x 6,50 = | H93: =10*6.5 -> 65
A94: TUBO DE AÇO CARBONO ø 900 MM | E94: 19.4 | F94: metros

Sheet Equipamentos Elétricos
A2: AREA | B2: QUANTIDADE | C2: EQUIPAMENTO/MATERIAL | D2: PROPÓSITO | E2: PESO[kg] OU COMPRIMENJTO [m] TOTAL | F2: R$ MONTAGEM | G2: VALOR AQUISIÇÃO | H2: CUSTO TOTAL
A3: EB1 | B3: 1 | C3: TRANSFORMADOR A ÓLEO 138-6,6 kV, 10/12 MVA | D3: RESERVA | E3: 17000 | F3: 34000 | G3: N/A | H3: 34000
A4: EB1 | B4: 1 | C4: PAINEL DE PROTEÇÃO DO TRANSFORMADOR | D4: NOVO | E4: 300 | F4: 600 | G4: 150000 | H4: 150600
A5: EB1 | B5: 900 | C5: CABOS HEPR 105º, 6/10 kV, 240 mm2 | D5: NOVO | E5: 900 | F5: 72900 | G5: 225000 | H5: 297900
A6: EB2 | B6: 1 | C6: TRANSFORMADOR A ÓLEO 138-6,6 kV, 15 MVA | D6: NOVO | E6: 30000 | F6: 50000 | G6: 4200000 | H6: 4580000
A7: EB2 | B7: 6 | C7: CUBÍCULOS DE MÉDIA TENSÃO CLASSE 7,2 kV | D7: NOVO | E7: 3600 | F7: 7200 | G7: 3000000 | H7: 3007200
A8: EB2 | B8: 150 | C8: CABOS HEPR 105º, 6/10 kV, 70 mm2 | D8: NOVO | E8: 150 | F8: 5025 | G8: 18000 | H8: 23025
A9: EB2 | B9: 300 | C9: CABOS HEPR 105º, 6/10 kV, 25 mm2 | D9: NOVO | E9: 300 | F9: 5700 | G9: 24900 | H9: 30600
A10: EB2 | B10: 1 | C10: SISTEMA DE CORRENTE CONTÍNUA | D10: NOVO | E10: 3000 | F10: 15000 | G10: 400000 | H10: 415000
A11: EB3 | B11: 1 | C11: TRANSFORMADOR A ÓLEO 138-6,6 kV, 5/6,5 MVA | D11: NOVO | E11: 10000 | F11: 20000 | G11: 2400000 | H11: 2420000
A12: EB3 | B12: 2 | C12: PAINEL DE PROTEÇÃO DO TRANSFORMADOR | D12: NOVO | E12: 600 | F12: 1200 | G12: 300000 | H12: 301200
A13: EB3 | B13: 4 | C13: CUBÍCULOS DE MÉDIA TENSÃO CLASSE 7,2 kV | D13: NOVO | E13: 2400 | F13: 4800 | G13: 2000000 | H13: 2004800
A14: EB3 | B14: 300 | C14: CABOS HEPR 105º, 6/10 kV, 25 mm2 | D14: NOVO | E14: 300 | F14: 5700 | G14: 24900 | H14: 30600
A15: EB3 | B15: 1 | C15: SISTEMA DE CORRENTE CONTÍNUA | D15: NOVO | E15: 3000 | F15: 15000 | G15: 400000 | H15: 415000
... A39: ECs | B39: 15 | C39: ALIMENTAÇÃO DE COMPORTA | D39: NOVO | E39: 15 | F39: 60000 | G39: 225000 | H39: 285000
A40: GERAL | B40: 3000 | C40: REDE AÉREA 13,8 kV | D40: NOVO | E40: 3000 | F40: 330000 | G40: =100000+17.5*9000 -> 257500 | H40: =SUM(F40:G40) -> 587500
A41: GERAL | B41: 19 | C41: SISTEMA DE COMUNICAÇÃO | D41: NOVO | E41: 19 | F41: 38000 | G41: 190000 | H41: 228000
G42: TOTAL | H42: =SUM(H3:H41) -> 17354775
C47: PREMISSAS
C48: NÃO ESTÁ INCLUSO OS ORÇAMENTOS REFERENTES AO SISTEMA DE ALTA TENSÃO EM 138 kV COM RELATÓRIOS JÁ ENVIADOS PELA CEMIG
C49: HAVERÁ UM SISTEMA DE 138 kV PARA ALIMENTAR A EB3 CONFORME ESTUDO DA CEMIG

Sheet Bombas
A1: Comjuntos Motobombas
H2: 0.2527
A3: Etapa 3 | E3: Preço Bomba | F3: Montagem | G3: Total | H3: BDI | I3: Final
A4: ER1 - BOMBA: CAPACIDADE = 2,37 m3/s | E4: =+E11*2.37/0.96 -> 1820883.3 | F4: =+E4*0.3 -> 546265 | G4: =+E4+F4 -> 2367148.3 | H4: =+G4*$H$2 -> 598178.39 | I4: =+G4+H4 -> 2965326.7
A5: ER1 - BOMBA: CAPACIDADE = 1,29 m3/s | E5: =+E11*1.29/0.96 -> 991113.72 | F5: =+E5*0.3 -> 297334.12 | G5: =+E5+F5 -> 1288447.8 | H5: =+G5*$H$2 -> 325590.77 | I5: =+G5+H5 -> 1614038.6
A7: Etapa 4
A8: ER1 - BOMBA: CAPACIDADE = 1,72 m3/s | E8: =+E11*1.72/0.96 -> 1321485 | F8: =+E8*0.3 -> 396445.49 | G8: =+E8+F8 -> 1717930.4 | H8: =+G8*$H$2 -> 434121.02 | I8: =+G8+H8 -> 2152051.5
A9: ER1 - BOMBA: CAPACIDADE = 0,52 m3/s | E9: 490335 | F9: =+E9*0.3 -> 147100.5 | G9: =+E9+F9 -> 637435.5 | H9: =+G9*$H$2 -> 161079.95 | I9: =+G9+H9 -> 798515.45
A10: ER2 - BOMBA: CAPACIDADE = 1,53 m3/s | E10: =+E11*1.53/0.96 -> 1175507 | F10: =+E10*0.3 -> 352652.09 | G10: =+E10+F10 -> 1528159.1 | H10: =+G10*$H$2 -> 386165.79 | I10: =+G10+H10 -> 1914324.9
A11: ER3 - BOMBA: CAPACIDADE = 0,96 m3/s | E11: 737573 | F11: =+E11*0.3 -> 221271.9 | G11: =+E11+F11 -> 958844.9 | H11: =+G11*$H$2 -> 242300.11 | I11: =+G11+H11 -> 1201145
A12: ER3 - BOMBA: CAPACIDADE = 0,133 m3/s | E12: 218530 | F12: =+E12*0.3 -> 65559 | G12: =+E12+F12 -> 284089 | H12: =+G12*$H$2 -> 71789.29 | I12: =+G12+H12 -> 355878.29
A13: ER4 - BOMBA: CAPACIDADE =1,28 m3/s | E13: =+E11*1.28/0.96 -> 983430.67 | F13: =+E13*0.3 -> 295029.2 | G13: =+E13+F13 -> 1278459.9 | H13: =+G13*$H$2 -> 323066.81 | I13: =+G13+H13 -> 1601526.7
D18: Etapa | E18: Obra | F18: Q (m³/s) | G18: Potência das bombas (kw) | H18: Valor
D19: Etapa 3 | E19: ER1 | F19: 2.37 | G19: 132.00541 | H19: =I4 -> 2965326.7
F20: 1.285 | G20: 71.708711 | H20: =I5 -> 1614038.6
D21: Etapa 4 | E21: ER1 | F21: 1.72 | G21: 125.41906 | H21: =I8 -> 2152051.5
F22: 0.52 | G22: 35.34939 | H22: =I9 -> 798515.45
E23: ER2 | F23: 1.529 | G23: 140.88546 | H23: =I10 -> 1914324.9
E24: ER3 | F24: 0.955 | G24: 47.592107 | H24: =I11 -> 1201145
F25: 0.133 | G25: 8.1814507 | H25: =I12 -> 355878.29
E26: ER4 | F26: 1.28 | G26: 47.139507 | H26: =I13 -> 1601526.7
D28: Etapa 1 | E28: EB2 | F28: 1.25 | G28: =450*0.73 -> 328.5 | H28: 1573894.9
D29: Etapa 1 | E29: EB2 | F29: 2.5 | G29: =884*0.73 -> 645.32 | H29: 3144818
D30: Etapa 1 | E30: EB2 | F30: 5.6 | G30: =1842*0.73 -> 1344.66 | H30: 5715490.6
D32: Etapa 2 | E32: EB3 | F32: 5.672 | G32: 699 | H32: 5784001.1

Sheet Tubulações ER
A1: Tubulações | F1: Preço Referencial: USD 2,50/kg = | J1: =2.5*5.3 -> 13.25 | K1: / kg
A3: Cálculo do peso por diâmetro:
A4: Adotada espessura 5/8" = 0,015875 m
A6: P (kg/m) = π x d (m) x 0,015875 (m) x 7800 kg/m³
A8: ETAPA 3 - CS21 - ER1 | F8: ETAPA 3 - CS21 - ER1 | K8: ETAPA 4 - CP3 -ER1 | P8: ETAPA 4 - CP3 -ER1
A9: Diâmetro da tubulação = | D9: 1.25 | F9: Diâmetro da tubulação = | I9: 0.9 | K9: Diâmetro da tubulação = | N9: 1.05 | P9: Diâmetro da tubulação = | S9: 0.6
A10: Comprimento total = | D10: 1 | F10: Comprimento total = | I10: 1 | K10: Comprimento total = | N10: 1 | P10: Comprimento total = | S10: 1
A11: Peso = | D11: =3.1416*D9*0.015875*7800*D10 -> 486.26078 | F11: Peso = | I11: =3.1416*I9*0.015875*7800*I10 -> 350.10776 | K11: Peso = | N11: =3.1416*N9*0.015875*7800*N10 -> 408.45905 | P11: Peso = | S11: =3.1416*S9*0.015875*7800*S10 -> 233.40517
A12: Preço = | D12: =+D11*$J$1 -> 6442.9553 | F12: Preço = | I12: =+I11*$J$1 -> 4638.9278 | K12: Preço = | N12: =+N11*$J$1 -> 5412.0824 | P12: Preço = | S12: =+S11*$J$1 -> 3092.6185
A13: Montagem = | D13: =+D12*0.3 -> 1932.8866 | F13: Montagem = | I13: =+I12*0.3 -> 1391.6783 | K13: Montagem = | N13: =+N12*0.3 -> 1623.6247 | P13: Montagem = | S13: =+S12*0.3 -> 927.78556
A14: Total = | D14: =+D12+D13 -> 8375.8418 | F14: Total = | I14: =+I12+I13 -> 6030.6061 | K14: Total = | N14: =+N12+N13 -> 7035.7072 | P14: Total = | S14: =+S12+S13 -> 4020.4041
A15: BDI = | B15: =+BDI!$C$16 -> 0.2527 | D15: =+D14*B15 -> 2116.5752 | F15: BDI = | G15: =+BDI!$C$16 -> 0.2527 | I15: =+I14*G15 -> 1523.9342 | K15: BDI = | L15: =+BDI!$C$16 -> 0.2527 | N15: =+N14*L15 -> 1777.9232 | P15: BDI = | Q15: =+BDI!$C$16 -> 0.2527 | S15: =+S14*Q15 -> 1015.9561
A16: Final = | D16: =+D14+D15 -> 10492.417 | F16: Final = | I16: =+I14+I15 -> 7554.5403 | K16: Final = | N16: =+N14+N15 -> 8813.6304 | P16: Final = | S16: =+S14+S15 -> 5036.3602
A18: ETAPA 4 - CP3a - ER2 | F18: ETAPA 4 - CP3b - ER3 | K18: ETAPA 4 - CP3b - ER3 | P18: ETAPA 4 - CP3 - ER4
A19: Diâmetro da tubulação = | D19: 1 | F19: Diâmetro da tubulação = | I19: 0.8 | K19: Diâmetro da tubulação = | N19: 0.3 | P19: Diâmetro da tubulação = | S19: 0.9
A20: Comprimento total = | D20: 1 | F20: Comprimento total = | I20: 1 | K20: Comprimento total = | N20: 1 | P20: Comprimento total = | S20: 1
A21: Peso = | D21: =3.1416*D19*0.015875*7800*D20 -> 389.00862 | F21: Peso = | I21: =3.1416*I19*0.015875*7800*I20 -> 311.2069 | K21: Peso = | N21: =3.1416*N19*0.015875*7800*N20 -> 116.70259 | P21: Peso = | S21: =3.1416*S19*0.015875*7800*S20 -> 350.10776
A22: Preço = | D22: =+D21*$J$1 -> 5154.3642 | F22: Preço = | I22: =+I21*$J$1 -> 4123.4914 | K22: Preço = | N22: =+N21*$J$1 -> 1546.3093 | P22: Preço = | S22: =+S21*$J$1 -> 4638.9278
A23: Montagem = | D23: =+D22*0.3 -> 1546.3093 | F23: Montagem = | I23: =+I22*0.3 -> 1237.0474 | K23: Montagem = | N23: =+N22*0.3 -> 463.89278 | P23: Montagem = | S23: =+S22*0.3 -> 1391.6783
A24: Total = | D24: =+D22+D23 -> 6700.6735 | F24: Total = | I24: =+I22+I23 -> 5360.5388 | K24: Total = | N24: =+N22+N23 -> 2010.202 | P24: Total = | S24: =+S22+S23 -> 6030.6061
A25: BDI = | B25: =+BDI!$C$16 -> 0.2527 | D25: =+D24*B25 -> 1693.2602 | F25: BDI = | G25: =+BDI!$C$16 -> 0.2527 | I25: =+I24*G25 -> 1354.6082 | K25: BDI = | L25: =+BDI!$C$16 -> 0.2527 | N25: =+N24*L25 -> 507.97806 | P25: BDI = | Q25: =+BDI!$C$16 -> 0.2527 | S25: =+S24*Q25 -> 1523.9342
A26: Final = | D26: =+D24+D25 -> 8393.9337 | F26: Final = | I26: =+I24+I25 -> 6715.1469 | K26: Final = | N26: =+N24+N25 -> 2518.1801 | P26: Final = | S26: =+S24+S25 -> 7554.5403
A28: ETAPA 4 - TS29
A29: Diâmetro da tubulação = | D29: 0.5
A30: Comprimento total = | D30: 1
A31: Peso = | D31: =3.1416*D29*0.015875*7800*D30 -> 194.50431
A32: Preço = | D32: =+D31*$J$1 -> 2577.1821
A33: Montagem = | D33: =+D32*0.3 -> 773.15463
A34: Total = | D34: =+D32+D33 -> 3350.3367
A35: BDI = | B35: =+BDI!$C$16 -> 0.2527 | D35: =+D34*B35 -> 846.63009
A36: Final = | D36: =+D34+D35 -> 4196.9668

Sheet Conexão - CEMIG
B2: EB3
B3: Instalação | C3: Atividade | D3: Custos com Participação Financeira do Cliente - Obras de Conexão (R$) | E3: Custos de Responsabilidade da Distribuidora - Obras de Conexão, Reforços e Melhorias (R$) | F3: Serviços e Fornecimentos Exclusivos CEMIG D (R$) | G3: Total (R$)
B4: SE Manga 5 | C4: Instalação de 1 seção de entrada de linha 138 kV para conexão do consumidor. | D4: 322672.76 | E4: 1799994.8 | F4: 204758.68 | G4: =SUM(D4:E4) -> 2122667.6
B5: LD 138 kV SE EB3 - Manga 5 | C5: Construção de aproximadamente 16,5 km de linha de distribuição 138 kV. Especificação: cabo Linnet (170,5 mm²), 25 MVA, estrutura metálica de circuito simples. | D5: 1724031.6 | E5: 11998321 | F5: 1218893.5 | G5: =SUM(D5:E5) -> 13722352
B6: CUSTO TOTAL DAS OBRAS | D6: =SUM(D4:D5) -> 2046704.4 | E6: =SUM(E4:E5) -> 13798315 | F6: =SUM(F4:F5) -> 1423652.2 | G6: =SUM(D6:E6) -> 15845020
B7: Custo de Perdas
B8: CUSTO TOTAL DA ALTERNATIVA | G8: =SUM(G4:G5) -> 15845020
B12: P1
B13: Instalação | C13: Atividade | D13: Obras de Conexão (Cliente) | E13: Obras de Conexão, Reforços e Melhorias (Distribuidora) | F13: Serviços e Fornecimentos Exclusivos CEMIG D | G13: Total (R$)
B14: SE Integração | C14: Construção de subestação de integração 138 kV próxima à linha com 3 disjuntores e casa de controle. | D14: 2868793.3 | E14: 6691436.3 | F14: 739798.62 | G14: =SUM(D14:E14) -> 9560229.6
B15: LD 138 kV Jaíba 1 - Manga 5 | C15: Seccionamento da LD e construção de aproximadamente 0,25 km de circuito duplo para interligação da SE de Integração; Especificação da LD: cabo Linnet 170,50 mm²; estrutura metálica de circuito duplo. | D15: 200549.62 | E15: 753744.57 | F15: 103945.61 | G15: =SUM(D15:E15) -> 954294.19
B16: LD 138 kV SE P1 - SE Integração | C16: Construção de aproximadamente 0,5 km de linha de distribuição 138 kV; Especificação: cabo Linnet (170,5 mm²), 125 MVA, estrutura metálica de circuito simples. | D16: 169839.79 | E16: 730799.33 | F16: 104740.55 | G16: =SUM(D16:E16) -> 900639.12
C17: CUSTO TOTAL DAS OBRAS | D17: =SUM(D14:D16) -> 3239182.7 | E17: =SUM(E14:E16) -> 8175980.2 | F17: =SUM(F14:F16) -> 948484.78 | G17: =SUM(D17:E17) -> 11415163
C18: Custo de Perdas
C19: CUSTO TOTAL DA ALTERNATIVA | G19: =SUM(G14:G16) -> 11415163
