Workbook
Name _ftn1: Benchmarking!$A$35
Name _ftn2: Benchmarking!$A$36
Name _ftnref1: Benchmarking!#REF!
Name _ftnref2: Benchmarking!#REF!

Sheet CAPA
B8: Fundo de Desenvolvimento da Infraestrutura Sustentável – FDIRS
B14: Serviços Técnicos relativos à Estruturação e o Desenvolvimento de Concessão do Perímetro Irrigado do Jaíba (Etapas III e IV) da Companhia de Desenvolvimento dos Vales do São Francisco e do Parnaíba - CODEVASF
B19: CONTRATO: 01/2025
B25: Estudo de Planejamento Agrícola - Jaíba Etapas 3 e 4
B31: Produto 7 - Estudo Mercado e Demanda - Planejamento Agrícola
K45: 46233
A51: CONSÓRCIO Nova Irrigação Jaíba/MG
B63: NOME DO ARQUIVO: JB_E3-4.PA.AGR.PL.001_R0-EST.PLANEJ.AGRICOLA

Sheet Lista de Abas
A1: Aba | B1: Descrição
A2: CAPA | B2: Informações referentes ao projeto e descrição do documento
A3: Premissas | B3: Descrição das principais premissas adotadas para a elaboração do estudo
A4: Planejamento Global | B4: Planilha consolidada com os resultados do Planejamento Global, por ano,da área em estudo, somando todos os cultivos. Na mesma aba contém o planejamento por cultura.
A5: Balanço custo - receita-modelos | B5: Planilha gerencial com os resumos dos balanços de receita/custo das culturas estudadas
A6: Área Plant-Colh e Produção | B6: Planilha Gerencial com o resultado dos principais indicados por ano (do 1 aou 35) por cultura: Ocupação de área, Produção ano, Valor de Venda e Custos de Implantação + Operacionais
A7: Resumos -> | B7: aba de identificação das abas à direita
A8: Resumo-Cult.Perma. | B8: Planilha resumo da rentabilidade das culturas permanentes por ha, considerando os gastos com a implantação, os custos operacionais e a receita anual do ano 1 ao ano 35.
A9: Resumo-Cult.Temp. | B9: Planilha resumo da rentabilidade das culturas temporárias por ha, considerando os gastos com a implantação, os custos operacionais e a receita anual do ano 1 ao ano 35.
A10: Custo diversos Manga.Limão | B10: Aba oculta - desconsiderar
A11: Custo diversos - Cult.anuais | B11: Aba oculta - desconsiderar
A12: Custo diversos - Cana | B12: Aba oculta - desconsiderar
... A41: Inflação | B41: Banco de dados com índices de inflação adotados

Sheet Premissas
C3: PREMISSAS
B4: 1 - | C4: Área bruta de 26.652 ha, área bruta das etapas 3 e 4
B5: 2 - | C5: Área irrigável conforme Projeto de 20.788 ha
B6: 3 - | C6: Área efetivamente irrigada conforme Projeto de 17.254 ha
B7: 4 - | C7: Adotou-se culturas que dominam 80% da área cultivada nas etapas 1 e 2
B8: 5 - | C8: Área de supressão vegetal conforme Projeto de 7.120, que representa 41,3% da área irrigada
B9: 6 - | C9: Os preços adotados de venda dos produtos foram em nível de propriedade, livres de impostos e fretes até o ponto de venda
B10: 7 - | C10: Os preços de venda refletem a media de 5 anos para Banana, Manga, limão
B11: 8 - | C11: O preço dos produtos milho, soja, feijão, reflete média de um periodo dos últimso 5 anos, dolarizado.
B12: 9 - | C12: O custo de produção refletem custos atuais praticados na região
B13: 10 - | C13: Admitiu-se um cronogra de liberção de área conforme cronograma de engenharia para as obras de infraestrutura de uso comum
B14: 11 - | C14: Admitiu-se que a área cultivada será realizada no ano posterior da liberação da obra
B15: 12 - | C15: Admitiu-se uma renovação da cultura da cana a cada 10 anos
... B19: 16 - | C19: Admitiu-se para as demais culturas irrigação tipo Pivô central

Sheet Planejamento Global
A1: Global | B1: 2 | D1: 4 | E1: 5 | F1: 6 | G1: 7 | H1: 8 | I1: 9 | J1: 10 | K1: 11 | L1: 12 | M1: 13 | N1: 14 | O1: 15 | P1: 16 | Q1: 17 | R1: 18 | S1: 19 | T1: 20 | U1: 21 | V1: 22 | W1: 23 | X1: 24 | Y1: 25 | Z1: 26 | AA1: 27 | AB1: 28 | AC1: 29 | AD1: 30 | AE1: 31 | AF1: 32 | AG1: 33 | AH1: 34 | AI1: 35 | AJ1: 36 | AK1: 37
A2: PLANEJAMENTO GLOBAL
A3: Planejamento total das culturas
A4: ITEM | B4: COMPONENTES | C4: ANOS DE IMPLANTAÇÃO DA CULTURA
C5: 1 | D5: =C5+1 -> 2 | E5: =D5+1 -> 3 | F5: =E5+1 -> 4 | G5: =F5+1 -> 5 | H5: =G5+1 -> 6 | I5: =H5+1 -> 7 | J5: =I5+1 -> 8 | K5: =J5+1 -> 9 | ... AK5: =AJ5+1 -> 35
A6: 1 | B6: INVESTIMENTOS | D6: =D16 -> 0 | E6: =E16 -> 0 | F6: =F16 -> 47330068 | G6: =G16 -> 48471840 | H6: =H16 -> 58006516 | I6: =I16 -> 1.1120001e+08 | J6: =J16 -> 1.0569294e+08 | K6: =K16 -> 1.0850775e+08 | ... AK6: =AK16 -> 0
A7: 1.1 | B7: Supressão vegetal | D7: =D48+D79+D110+D141+D172+D203+D234+D265+D296 -> 0 | E7: =E48+E79+E110+E141+E172+E203+E234+E265+E296 -> 0 | F7: =F48+F79+F110+F141+F172+F203+F234+F265+F296 -> 1628328.5 | G7: =G48+G79+G110+G141+G172+G203+G234+G265+G296 -> 1628328.5 | H7: =H48+H79+H110+H141+H172+H203+H234+H265+H296 -> 1956356.4 | I7: =I48+I79+I110+I141+I172+I203+I234+I265+I296 -> 3778495.2 | J7: =J48+J79+J110+J141+J172+J203+J234+J265+J296 -> 3545075 | K7: =K48+K79+K110+K141+K172+K203+K234+K265+K296 -> 3647546 | ... AK7: =AK48+AK79+AK110+AK141+AK172+AK203+AK234+AK265+AK296 -> 0
A8: 1.2 | B8: Sistema de irrigação localizada | C8: =C49+C80+C111+C142+C173+C204+C235+C266+C297 -> 0 | D8: =D49+D80+D111+D142+D173+D204+D235+D266+D297 -> 0 | E8: =E49+E80+E111+E142+E173+E204+E235+E266+E297 -> 0 | F8: =F49+F80+F111+F142+F173+F204+F235+F266+F297 -> 7363311.3 | G8: =G49+G80+G111+G142+G173+G204+G235+G266+G297 -> 7363311.3 | H8: =H49+H80+H111+H142+H173+H204+H235+H266+H297 -> 8846655.6 | I8: =I49+I80+I111+I142+I173+I204+I235+I266+I297 -> 17086378 | J8: =J49+J80+J111+J142+J173+J204+J235+J266+J297 -> 16030850 | ... AK8: =AK49+AK80+AK111+AK142+AK173+AK204+AK235+AK266+AK297 -> 0
A9: 1.3 | B9: Sistema de irrigação pivô central | C9: =C50+C81+C112+C143+C174+C205+C236+C267+C298 -> 0 | D9: =D50+D81+D112+D143+D174+D205+D236+D267+D298 -> 0 | E9: =E50+E81+E112+E143+E174+E205+E236+E267+E298 -> 0 | F9: =F50+F81+F112+F143+F174+F205+F236+F267+F298 -> 16998550 | G9: =G50+G81+G112+G143+G174+G205+G236+G267+G298 -> 16998550 | H9: =H50+H81+H112+H143+H174+H205+H236+H267+H298 -> 20422920 | I9: =I50+I81+I112+I143+I174+I205+I236+I267+I298 -> 39444707 | J9: =J50+J81+J112+J143+J174+J205+J236+J267+J298 -> 37007972 | ... AK9: =AK50+AK81+AK112+AK143+AK174+AK205+AK236+AK267+AK298 -> 0
A10: 1.4 | B10: Demais infraestrutura | C10: =C51+C82+C113+C144+C175+C206+C237+C268+C299 -> 0 | D10: =D51+D82+D113+D144+D175+D206+D237+D268+D299 -> 0 | E10: =E51+E82+E113+E144+E175+E206+E237+E268+E299 -> 0 | F10: =F51+F82+F113+F144+F175+F206+F237+F268+F299 -> 8300771.6 | G10: =G51+G82+G113+G144+G175+G206+G237+G268+G299 -> 8300771.6 | H10: =H51+H82+H113+H144+H175+H206+H237+H268+H299 -> 9972967.9 | I10: =I51+I82+I113+I144+I175+I206+I237+I268+I299 -> 19261731 | J10: =J51+J82+J113+J144+J175+J206+J237+J268+J299 -> 18071819 | ... AK10: =AK51+AK82+AK113+AK144+AK175+AK206+AK237+AK268+AK299 -> 0
B11: Ano de formação da cultura
A12: 1.5 | B12: Gasto com insumos | C12: =C53+C84+C115+C146+C177+C208+C239+C270+C301 -> 0 | D12: =D53+D84+D115+D146+D177+D208+D239+D270+D301 -> 0 | E12: =E53+E84+E115+E146+E177+E208+E239+E270+E301 -> 0 | F12: =F53+F84+F115+F146+F177+F208+F239+F270+F301 -> 6783097.9 | G12: =G53+G84+G115+G146+G177+G208+G239+G270+G301 -> 7252911.9 | H12: =H53+H84+H115+H146+H177+H208+H239+H270+H301 -> 8619371.8 | I12: =I53+I84+I115+I146+I177+I208+I239+I270+I301 -> 16304466 | J12: =J53+J84+J115+J146+J177+J208+J239+J270+J301 -> 15857845 | ... AK12: =AK53+AK84+AK115+AK146+AK177+AK208+AK239+AK270+AK301 -> 0
A13: 1.6 | B13: Gasto com mão de obra | C13: =C54+C85+C116+C147+C178+C209+C240+C271+C302 -> 0 | D13: =D54+D85+D116+D147+D178+D209+D240+D271+D302 -> 0 | E13: =E54+E85+E116+E147+E178+E209+E240+E271+E302 -> 0 | F13: =F54+F85+F116+F147+F178+F209+F240+F271+F302 -> 2248856 | G13: =G54+G85+G116+G147+G178+G209+G240+G271+G302 -> 2364403.3 | H13: =H54+H85+H116+H147+H178+H209+H240+H271+H302 -> 2817436.9 | I13: =I54+I85+I116+I147+I178+I209+I240+I271+I302 -> 5357238 | J13: =J54+J85+J116+J147+J178+J209+J240+J271+J302 -> 5164165.7 | ... AK13: =AK54+AK85+AK116+AK147+AK178+AK209+AK240+AK271+AK302 -> 0
A14: 1.7 | B14: Gasto com trator e equipamentos e avaição agrícola | C14: =C55+C86+C117+C148+C179+C210+C241+C272+C303 -> 0 | D14: =D55+D86+D117+D148+D179+D210+D241+D272+D303 -> 0 | E14: =E55+E86+E117+E148+E179+E210+E241+E272+E303 -> 0 | F14: =F55+F86+F117+F148+F179+F210+F241+F272+F303 -> 2580809.1 | G14: =G55+G86+G117+G148+G179+G210+G241+G272+G303 -> 2848279.9 | H14: =H55+H86+H117+H148+H179+H210+H241+H272+H303 -> 3368185.7 | I14: =I55+I86+I117+I148+I179+I210+I241+I272+I303 -> 6310055.4 | J14: =J55+J86+J117+J148+J179+J210+J241+J272+J303 -> 6239403.6 | ... AK14: =AK55+AK86+AK117+AK148+AK179+AK210+AK241+AK272+AK303 -> 0
A15: 1.8 | B15: Outros custos | C15: =C56+C87+C118+C149+C180+C211+C242+C273+C304 -> 0 | D15: =D56+D87+D118+D149+D180+D211+D242+D273+D304 -> 0 | E15: =E56+E87+E118+E149+E180+E211+E242+E273+E304 -> 0 | F15: =F56+F87+F118+F149+F180+F211+F242+F273+F304 -> 1426343.2 | G15: =G56+G87+G118+G149+G180+G211+G242+G273+G304 -> 1715283.5 | H15: =H56+H87+H118+H149+H180+H211+H242+H273+H304 -> 2002621.4 | I15: =I56+I87+I118+I149+I180+I211+I242+I273+I304 -> 3656941 | J15: =J56+J87+J118+J149+J180+J211+J242+J273+J304 -> 3775806.4 | ... AK15: =AK56+AK87+AK118+AK149+AK180+AK211+AK242+AK273+AK304 -> 0
B16: Sub-total - Investimentos | D16: =SUM(D7:D15) -> 0 | E16: =SUM(E7:E15) -> 0 | F16: =SUM(F7:F15) -> 47330068 | G16: =SUM(G7:G15) -> 48471840 | H16: =SUM(H7:H15) -> 58006516 | I16: =SUM(I7:I15) -> 1.1120001e+08 | J16: =SUM(J7:J15) -> 1.0569294e+08 | K16: =SUM(K7:K15) -> 1.0850775e+08 | ... AK16: =SUM(AK7:AK15) -> 0
A18: 2 | B18: CUSTOS OPERACIONAIS | D18: =D23 -> 0 | E18: =E23 -> 0 | F18: =F23 -> 14066016 | G18: =G23 -> 36860509 | H18: =H23 -> 65167661 | I18: =I23 -> 1.1157721e+08 | J18: =J23 -> 1.674746e+08 | K18: =K23 -> 2.264871e+08 | ... AK18: =AK23 -> 3.9093546e+08 | AM18: =AM23 -> 0 | AN18: =AN23 -> 0 | AO18: =AO23 -> 0 | AP18: =AP23 -> 0 | AQ18: =AQ23 -> 0 | AR18: =AR23 -> 0 | AS18: =AS23 -> 0 | AT18: =AT23 -> 0 | ... IS18: =IS23 -> 0
A19: 2.1 | B19: Gasto com insumos | D19: =D60+D91+D122+D153+D184+D215+D246+D277+D308 -> 0 | E19: =E60+E91+E122+E153+E184+E215+E246+E277+E308 -> 0 | F19: =F60+F91+F122+F153+F184+F215+F246+F277+F308 -> 6675345.2 | G19: =G60+G91+G122+G153+G184+G215+G246+G277+G308 -> 16493984 | H19: =H60+H91+H122+H153+H184+H215+H246+H277+H308 -> 28673773 | I19: =I60+I91+I122+I153+I184+I215+I246+I277+I308 -> 49465510 | J19: =J60+J91+J122+J153+J184+J215+J246+J277+J308 -> 73248307 | K19: =K60+K91+K122+K153+K184+K215+K246+K277+K308 -> 98580328 | ... AK19: =AK60+AK91+AK122+AK153+AK184+AK215+AK246+AK277+AK308 -> 1.6798231e+08 | AM19: =AM60+AM91+AM122+AM153+AM184+AM215+AM246+AM277+AM308 -> 0 | AN19: =AN60+AN91+AN122+AN153+AN184+AN215+AN246+AN277+AN308 -> 0 | AO19: =AO60+AO91+AO122+AO153+AO184+AO215+AO246+AO277+AO308 -> 0 | AP19: =AP60+AP91+AP122+AP153+AP184+AP215+AP246+AP277+AP308 -> 0 | AQ19: =AQ60+AQ91+AQ122+AQ153+AQ184+AQ215+AQ246+AQ277+AQ308 -> 0 | AR19: =AR60+AR91+AR122+AR153+AR184+AR215+AR246+AR277+AR308 -> 0 | AS19: =AS60+AS91+AS122+AS153+AS184+AS215+AS246+AS277+AS308 -> 0 | AT19: =AT60+AT91+AT122+AT153+AT184+AT215+AT246+AT277+AT308 -> 0 | ... IS19: =IS60+IS91+IS122+IS153+IS184+IS215+IS246+IS277+IS308 -> 0
A20: 2.2 | B20: Gasto com mão de obra | D20: =D61+D92+D123+D154+D185+D216+D247+D278+D309 -> 0 | E20: =E61+E92+E123+E154+E185+E216+E247+E278+E309 -> 0 | F20: =F61+F92+F123+F154+F185+F216+F247+F278+F309 -> 1425933.6 | G20: =G61+G92+G123+G154+G185+G216+G247+G278+G309 -> 6204525.1 | H20: =H61+H92+H123+H154+H185+H216+H247+H278+H309 -> 11732605 | I20: =I61+I92+I123+I154+I185+I216+I247+I278+I309 -> 19454736 | J20: =J61+J92+J123+J154+J185+J216+J247+J278+J309 -> 31189920 | K20: =K61+K92+K123+K154+K185+K216+K247+K278+K309 -> 42959387 | ... AK20: =AK61+AK92+AK123+AK154+AK185+AK216+AK247+AK278+AK309 -> 73576697 | AM20: =AM61+AM92+AM123+AM154+AM185+AM216+AM247+AM278+AM309 -> 0 | AN20: =AN61+AN92+AN123+AN154+AN185+AN216+AN247+AN278+AN309 -> 0 | AO20: =AO61+AO92+AO123+AO154+AO185+AO216+AO247+AO278+AO309 -> 0 | AP20: =AP61+AP92+AP123+AP154+AP185+AP216+AP247+AP278+AP309 -> 0 | AQ20: =AQ61+AQ92+AQ123+AQ154+AQ185+AQ216+AQ247+AQ278+AQ309 -> 0 | AR20: =AR61+AR92+AR123+AR154+AR185+AR216+AR247+AR278+AR309 -> 0 | AS20: =AS61+AS92+AS123+AS154+AS185+AS216+AS247+AS278+AS309 -> 0 | AT20: =AT61+AT92+AT123+AT154+AT185+AT216+AT247+AT278+AT309 -> 0 | ... IS20: =IS61+IS92+IS123+IS154+IS185+IS216+IS247+IS278+IS309 -> 0
A21: 2.3 | B21: Gasto com trator e equipamentos e avaição agrícola | D21: =D62+D93+D124+D155+D186+D217+D248+D279+D310 -> 0 | E21: =E62+E93+E124+E155+E186+E217+E248+E279+E310 -> 0 | F21: =F62+F93+F124+F155+F186+F217+F248+F279+F310 -> 3295711.1 | G21: =G62+G93+G124+G155+G186+G217+G248+G279+G310 -> 7622915.2 | H21: =H62+H93+H124+H155+H186+H217+H248+H279+H310 -> 13021699 | I21: =I62+I93+I124+I155+I186+I217+I248+I279+I310 -> 22368652 | J21: =J62+J93+J124+J155+J186+J217+J248+J279+J310 -> 32574426 | K21: =K62+K93+K124+K155+K186+K217+K248+K279+K310 -> 43285229 | ... AK21: =AK62+AK93+AK124+AK155+AK186+AK217+AK248+AK279+AK310 -> 69212206 | AM21: =AM62+AM93+AM124+AM155+AM186+AM217+AM248+AM279+AM310 -> 0 | AN21: =AN62+AN93+AN124+AN155+AN186+AN217+AN248+AN279+AN310 -> 0 | AO21: =AO62+AO93+AO124+AO155+AO186+AO217+AO248+AO279+AO310 -> 0 | AP21: =AP62+AP93+AP124+AP155+AP186+AP217+AP248+AP279+AP310 -> 0 | AQ21: =AQ62+AQ93+AQ124+AQ155+AQ186+AQ217+AQ248+AQ279+AQ310 -> 0 | AR21: =AR62+AR93+AR124+AR155+AR186+AR217+AR248+AR279+AR310 -> 0 | AS21: =AS62+AS93+AS124+AS155+AS186+AS217+AS248+AS279+AS310 -> 0 | AT21: =AT62+AT93+AT124+AT155+AT186+AT217+AT248+AT279+AT310 -> 0 | ... IS21: =IS62+IS93+IS124+IS155+IS186+IS217+IS248+IS279+IS310 -> 0
A22: 2.4 | B22: Outros custos | D22: =D63+D94+D125+D156+D187+D218+D249+D280+D311 -> 0 | E22: =E63+E94+E125+E156+E187+E218+E249+E280+E311 -> 0 | F22: =F63+F94+F125+F156+F187+F218+F249+F280+F311 -> 2669025.7 | G22: =G63+G94+G125+G156+G187+G218+G249+G280+G311 -> 6539084.9 | H22: =H63+H94+H125+H156+H187+H218+H249+H280+H311 -> 11739584 | I22: =I63+I94+I125+I156+I187+I218+I249+I280+I311 -> 20288311 | J22: =J63+J94+J125+J156+J187+J218+J249+J280+J311 -> 30461944 | K22: =K63+K94+K125+K156+K187+K218+K249+K280+K311 -> 41662157 | ... AK22: =AK63+AK94+AK125+AK156+AK187+AK218+AK249+AK280+AK311 -> 80164245 | AM22: =AM63+AM94+AM125+AM156+AM187+AM218+AM249+AM280+AM311 -> 0 | AN22: =AN63+AN94+AN125+AN156+AN187+AN218+AN249+AN280+AN311 -> 0 | AO22: =AO63+AO94+AO125+AO156+AO187+AO218+AO249+AO280+AO311 -> 0 | AP22: =AP63+AP94+AP125+AP156+AP187+AP218+AP249+AP280+AP311 -> 0 | AQ22: =AQ63+AQ94+AQ125+AQ156+AQ187+AQ218+AQ249+AQ280+AQ311 -> 0 | AR22: =AR63+AR94+AR125+AR156+AR187+AR218+AR249+AR280+AR311 -> 0 | AS22: =AS63+AS94+AS125+AS156+AS187+AS218+AS249+AS280+AS311 -> 0 | AT22: =AT63+AT94+AT125+AT156+AT187+AT218+AT249+AT280+AT311 -> 0 | ... IS22: =IS63+IS94+IS125+IS156+IS187+IS218+IS249+IS280+IS311 -> 0
B23: Sub-total - custos operacionais | D23: =SUM(D19:D22) -> 0 | E23: =SUM(E19:E22) -> 0 | F23: =SUM(F19:F22) -> 14066016 | G23: =SUM(G19:G22) -> 36860509 | H23: =SUM(H19:H22) -> 65167661 | I23: =SUM(I19:I22) -> 1.1157721e+08 | J23: =SUM(J19:J22) -> 1.674746e+08 | K23: =SUM(K19:K22) -> 2.264871e+08 | ... AK23: =SUM(AK19:AK22) -> 3.9093546e+08
A25: 3 | B25: ENTRADA - VALOR DA PRODUÇÃO | D25: =D35 -> 0 | E25: =E35 -> 0 | F25: =F35 -> 27876817 | G25: =G35 -> 72672258 | H25: =H35 -> 1.2688813e+08 | I25: =I35 -> 2.1675471e+08 | J25: =J35 -> 3.2944018e+08 | K25: =K35 -> 4.4506236e+08 | ... AK25: =AK35 -> 7.5819938e+08 | AM25: =AM35 -> 0 | AN25: =AN35 -> 0 | AO25: =AO35 -> 0 | AP25: =AP35 -> 0 | AQ25: =AQ35 -> 0 | AR25: =AR35 -> 0 | AS25: =AS35 -> 0 | AT25: =AT35 -> 0 | ... IS25: =IS35 -> 0
A26: 3.1 | B26: =VLOOKUP($A26,$A$44:$AK$321,B$1,0) -> Valor da produção Banana Nanica | D26: =VLOOKUP($A26,$A$44:$AK$321,D$1,0) -> 0 | E26: =VLOOKUP($A26,$A$44:$AK$321,E$1,0) -> 0 | F26: =VLOOKUP($A26,$A$44:$AK$321,F$1,0) -> 0 | G26: =VLOOKUP($A26,$A$44:$AK$321,G$1,0) -> 11074420 | H26: =VLOOKUP($A26,$A$44:$AK$321,H$1,0) -> 21456689 | I26: =VLOOKUP($A26,$A$44:$AK$321,I$1,0) -> 33377757 | J26: =VLOOKUP($A26,$A$44:$AK$321,J$1,0) -> 57551932 | K26: =VLOOKUP($A26,$A$44:$AK$321,K$1,0) -> 79224626 | ... AK26: =VLOOKUP($A26,$A$44:$AK$321,AK$1,0) -> 1.2028766e+08
A27: 3.2 | B27: =VLOOKUP($A27,$A$44:$AK$321,B$1,0) -> Valor da produção Banana Prata | D27: =VLOOKUP($A27,$A$44:$AK$321,D$1,0) -> 0 | E27: =VLOOKUP($A27,$A$44:$AK$321,E$1,0) -> 0 | F27: =VLOOKUP($A27,$A$44:$AK$321,F$1,0) -> 0 | G27: =VLOOKUP($A27,$A$44:$AK$321,G$1,0) -> 5167534.1 | H27: =VLOOKUP($A27,$A$44:$AK$321,H$1,0) -> 9929771.4 | I27: =VLOOKUP($A27,$A$44:$AK$321,I$1,0) -> 15327715 | J27: =VLOOKUP($A27,$A$44:$AK$321,J$1,0) -> 26151584 | K27: =VLOOKUP($A27,$A$44:$AK$321,K$1,0) -> 35424482 | ... AK27: =VLOOKUP($A27,$A$44:$AK$321,AK$1,0) -> 53872476
A28: 3.3 | B28: =VLOOKUP($A28,$A$44:$AK$321,B$1,0) -> Valor da produção Manga | D28: =VLOOKUP($A28,$A$44:$AK$321,D$1,0) -> 0 | E28: =VLOOKUP($A28,$A$44:$AK$321,E$1,0) -> 0 | F28: =VLOOKUP($A28,$A$44:$AK$321,F$1,0) -> 0 | G28: =VLOOKUP($A28,$A$44:$AK$321,G$1,0) -> 0 | H28: =VLOOKUP($A28,$A$44:$AK$321,H$1,0) -> 2171232.8 | I28: =VLOOKUP($A28,$A$44:$AK$321,I$1,0) -> 4892511.3 | J28: =VLOOKUP($A28,$A$44:$AK$321,J$1,0) -> 10222419 | K28: =VLOOKUP($A28,$A$44:$AK$321,K$1,0) -> 18642841 | ... AK28: =VLOOKUP($A28,$A$44:$AK$321,AK$1,0) -> 1.0183927e+08
A29: 3.4 | B29: =VLOOKUP($A29,$A$44:$AK$321,B$1,0) -> Valor da produção Limão | D29: =VLOOKUP($A29,$A$44:$AK$321,D$1,0) -> 0 | E29: =VLOOKUP($A29,$A$44:$AK$321,E$1,0) -> 0 | F29: =VLOOKUP($A29,$A$44:$AK$321,F$1,0) -> 0 | G29: =VLOOKUP($A29,$A$44:$AK$321,G$1,0) -> 676669.43 | H29: =VLOOKUP($A29,$A$44:$AK$321,H$1,0) -> 4084183.3 | I29: =VLOOKUP($A29,$A$44:$AK$321,I$1,0) -> 9223019.3 | J29: =VLOOKUP($A29,$A$44:$AK$321,J$1,0) -> 20889216 | K29: =VLOOKUP($A29,$A$44:$AK$321,K$1,0) -> 34699771 | ... AK29: =VLOOKUP($A29,$A$44:$AK$321,AK$1,0) -> 1.0006598e+08
A30: 3.5 | B30: =VLOOKUP($A30,$A$44:$AK$321,B$1,0) -> Valor da produção Cana | D30: =VLOOKUP($A30,$A$44:$AK$321,D$1,0) -> 0 | E30: =VLOOKUP($A30,$A$44:$AK$321,E$1,0) -> 0 | F30: =VLOOKUP($A30,$A$44:$AK$321,F$1,0) -> 0 | G30: =VLOOKUP($A30,$A$44:$AK$321,G$1,0) -> 0 | H30: =VLOOKUP($A30,$A$44:$AK$321,H$1,0) -> 0 | I30: =VLOOKUP($A30,$A$44:$AK$321,I$1,0) -> 0 | J30: =VLOOKUP($A30,$A$44:$AK$321,J$1,0) -> 0 | K30: =VLOOKUP($A30,$A$44:$AK$321,K$1,0) -> 0 | ... AK30: =VLOOKUP($A30,$A$44:$AK$321,AK$1,0) -> 0
A31: 3.6 | B31: =VLOOKUP($A31,$A$44:$AK$321,B$1,0) -> Valor da produção Soja | D31: =VLOOKUP($A31,$A$44:$AK$321,D$1,0) -> 0 | E31: =VLOOKUP($A31,$A$44:$AK$321,E$1,0) -> 0 | F31: =VLOOKUP($A31,$A$44:$AK$321,F$1,0) -> 8725410.6 | G31: =VLOOKUP($A31,$A$44:$AK$321,G$1,0) -> 17450821 | H31: =VLOOKUP($A31,$A$44:$AK$321,H$1,0) -> 27933972 | I31: =VLOOKUP($A31,$A$44:$AK$321,I$1,0) -> 48181067 | J31: =VLOOKUP($A31,$A$44:$AK$321,J$1,0) -> 67177378 | K31: =VLOOKUP($A31,$A$44:$AK$321,K$1,0) -> 86722781 | ... AK31: =VLOOKUP($A31,$A$44:$AK$321,AK$1,0) -> 1.1960749e+08
A32: 3.7 | B32: =VLOOKUP($A32,$A$44:$AK$321,B$1,0) -> Valor da produção Feijão | D32: =VLOOKUP($A32,$A$44:$AK$321,D$1,0) -> 0 | E32: =VLOOKUP($A32,$A$44:$AK$321,E$1,0) -> 0 | F32: =VLOOKUP($A32,$A$44:$AK$321,F$1,0) -> 5146765.8 | G32: =VLOOKUP($A32,$A$44:$AK$321,G$1,0) -> 10293532 | H32: =VLOOKUP($A32,$A$44:$AK$321,H$1,0) -> 16477117 | I32: =VLOOKUP($A32,$A$44:$AK$321,I$1,0) -> 28420057 | J32: =VLOOKUP($A32,$A$44:$AK$321,J$1,0) -> 39625211 | K32: =VLOOKUP($A32,$A$44:$AK$321,K$1,0) -> 51154251 | ... AK32: =VLOOKUP($A32,$A$44:$AK$321,AK$1,0) -> 70551606
A33: 3.8 | B33: =VLOOKUP($A33,$A$44:$AK$321,B$1,0) -> Valor da produção Milho 1 | D33: =VLOOKUP($A33,$A$44:$AK$321,D$1,0) -> 0 | E33: =VLOOKUP($A33,$A$44:$AK$321,E$1,0) -> 0 | F33: =VLOOKUP($A33,$A$44:$AK$321,F$1,0) -> 5059916.5 | G33: =VLOOKUP($A33,$A$44:$AK$321,G$1,0) -> 10119833 | H33: =VLOOKUP($A33,$A$44:$AK$321,H$1,0) -> 16199073 | I33: =VLOOKUP($A33,$A$44:$AK$321,I$1,0) -> 27940482 | J33: =VLOOKUP($A33,$A$44:$AK$321,J$1,0) -> 38956553 | K33: =VLOOKUP($A33,$A$44:$AK$321,K$1,0) -> 50291046 | ... AK33: =VLOOKUP($A33,$A$44:$AK$321,AK$1,0) -> 69361080
A34: 3.9 | B34: =VLOOKUP($A34,$A$44:$AK$321,B$1,0) -> Valor da produção Milho 2 | D34: =VLOOKUP($A34,$A$44:$AK$321,D$1,0) -> 0 | E34: =VLOOKUP($A34,$A$44:$AK$321,E$1,0) -> 0 | F34: =VLOOKUP($A34,$A$44:$AK$321,F$1,0) -> 8944724 | G34: =VLOOKUP($A34,$A$44:$AK$321,G$1,0) -> 17889448 | H34: =VLOOKUP($A34,$A$44:$AK$321,H$1,0) -> 28636093 | I34: =VLOOKUP($A34,$A$44:$AK$321,I$1,0) -> 49392099 | J34: =VLOOKUP($A34,$A$44:$AK$321,J$1,0) -> 68865883 | K34: =VLOOKUP($A34,$A$44:$AK$321,K$1,0) -> 88902560 | ... AK34: =VLOOKUP($A34,$A$44:$AK$321,AK$1,0) -> 1.2261383e+08
B35: Sub-total - valor da produção | D35: =SUM(D26:D34) -> 0 | E35: =SUM(E26:E34) -> 0 | F35: =SUM(F26:F34) -> 27876817 | G35: =SUM(G26:G34) -> 72672258 | H35: =SUM(H26:H34) -> 1.2688813e+08 | I35: =SUM(I26:I34) -> 2.1675471e+08 | J35: =SUM(J26:J34) -> 3.2944018e+08 | K35: =SUM(K26:K34) -> 4.4506236e+08 | ... AK35: =SUM(AK26:AK34) -> 7.5819938e+08
A37: 4 | B37: BALANÇO Anual (Item 3 - item 1 - item 2) | D37: =D35-D23-D16 -> 0 | E37: =E35-E23-E16 -> 0 | F37: =F35-F23-F16 -> -33519267 | G37: =G35-G23-G16 -> -12660092 | H37: =H35-H23-H16 -> 3713954.7 | I37: =I35-I23-I16 -> -6022512.6 | J37: =J35-J23-J16 -> 56272644 | K37: =K35-K23-K16 -> 1.1006751e+08 | ... AK37: =AK35-AK23-AK16 -> 3.6726393e+08
A39: 5 | B39: BALANÇO ACUMULADO | D39: =D37 -> 0 | E39: =D39+E37 -> 0 | F39: =E39+F37 -> -33519267 | G39: =F39+G37 -> -46179359 | H39: =G39+H37 -> -42465404 | I39: =H39+I37 -> -48487916 | J39: =I39+J37 -> 7784727.1 | K39: =J39+K37 -> 1.1785223e+08 | L39: =K39+L37 -> 2.9924036e+08 | ... AK39: =AJ39+AK37 -> 8.3318127e+09
A42: PLANEJAMENTO POR CULTURA
A43: Banana Nanica
A44: Planejamento Banana Nanica
A45: ITEM | B45: COMPONENTES | C45: ANO DE IMPLANTAÇÃO DA CULTURA
C46: 1 | D46: =C46+1 -> 2 | E46: =D46+1 -> 3 | F46: =E46+1 -> 4 | G46: =F46+1 -> 5 | H46: =G46+1 -> 6 | I46: =H46+1 -> 7 | J46: =I46+1 -> 8 | K46: =J46+1 -> 9 | ... AK46: =AJ46+1 -> 35
A47: 1 | B47: INVESTIMENTOS
A48: 1.1 | B48: Supressão vegetal | D48: ='Critérios de Implantação'!D$31*'Resumo-Cult.Perma.'!$C9 -> 0 | E48: ='Critérios de Implantação'!E$31*'Resumo-Cult.Perma.'!$C9 -> 0 | F48: ='Critérios de Implantação'!F$31*'Resumo-Cult.Perma.'!$C9 -> 146549.57 | G48: ='Critérios de Implantação'!G$31*'Resumo-Cult.Perma.'!$C9 -> 146549.57 | H48: ='Critérios de Implantação'!H$31*'Resumo-Cult.Perma.'!$C9 -> 176072.08 | I48: ='Critérios de Implantação'!I$31*'Resumo-Cult.Perma.'!$C9 -> 340064.57 | J48: ='Critérios de Implantação'!J$31*'Resumo-Cult.Perma.'!$C9 -> 319056.75 | K48: ='Critérios de Implantação'!K$31*'Resumo-Cult.Perma.'!$C9 -> 328279.14 | ... AK48: ='Critérios de Implantação'!AK$31*'Resumo-Cult.Perma.'!$C9 -> 0
A49: 1.2 | B49: Sistema de irrigação localizada | D49: ='Critérios de Implantação'!D$31*'Resumo-Cult.Perma.'!$C10 -> 0 | E49: ='Critérios de Implantação'!E$31*'Resumo-Cult.Perma.'!$C10 -> 0 | F49: ='Critérios de Implantação'!F$31*'Resumo-Cult.Perma.'!$C10 -> 2548838.5 | G49: ='Critérios de Implantação'!G$31*'Resumo-Cult.Perma.'!$C10 -> 2548838.5 | H49: ='Critérios de Implantação'!H$31*'Resumo-Cult.Perma.'!$C10 -> 3062303.9 | I49: ='Critérios de Implantação'!I$31*'Resumo-Cult.Perma.'!$C10 -> 5914515.5 | J49: ='Critérios de Implantação'!J$31*'Resumo-Cult.Perma.'!$C10 -> 5549140.6 | K49: ='Critérios de Implantação'!K$31*'Resumo-Cult.Perma.'!$C10 -> 5709539.4 | ... AK49: ='Critérios de Implantação'!AK$31*'Resumo-Cult.Perma.'!$C10 -> 0
A50: 1.3 | B50: Sistema de irrigação pivô central | D50: ='Critérios de Implantação'!D$31*'Resumo-Cult.Perma.'!$C11 -> 0 | E50: ='Critérios de Implantação'!E$31*'Resumo-Cult.Perma.'!$C11 -> 0 | F50: ='Critérios de Implantação'!F$31*'Resumo-Cult.Perma.'!$C11 -> 0 | G50: ='Critérios de Implantação'!G$31*'Resumo-Cult.Perma.'!$C11 -> 0 | H50: ='Critérios de Implantação'!H$31*'Resumo-Cult.Perma.'!$C11 -> 0 | I50: ='Critérios de Implantação'!I$31*'Resumo-Cult.Perma.'!$C11 -> 0 | J50: ='Critérios de Implantação'!J$31*'Resumo-Cult.Perma.'!$C11 -> 0 | K50: ='Critérios de Implantação'!K$31*'Resumo-Cult.Perma.'!$C11 -> 0 | ... AK50: ='Critérios de Implantação'!AK$31*'Resumo-Cult.Perma.'!$C11 -> 0
A51: 1.4 | B51: Demais infraestrutura | D51: ='Critérios de Implantação'!D$31*'Resumo-Cult.Perma.'!$C12 -> 0 | E51: ='Critérios de Implantação'!E$31*'Resumo-Cult.Perma.'!$C12 -> 0 | F51: ='Critérios de Implantação'!F$31*'Resumo-Cult.Perma.'!$C12 -> 2655142.1 | G51: ='Critérios de Implantação'!G$31*'Resumo-Cult.Perma.'!$C12 -> 2655142.1 | H51: ='Critérios de Implantação'!H$31*'Resumo-Cult.Perma.'!$C12 -> 3190022.3 | I51: ='Critérios de Implantação'!I$31*'Resumo-Cult.Perma.'!$C12 -> 6161190.2 | J51: ='Critérios de Implantação'!J$31*'Resumo-Cult.Perma.'!$C12 -> 5780576.7 | K51: ='Critérios de Implantação'!K$31*'Resumo-Cult.Perma.'!$C12 -> 5947665.2 | ... AK51: ='Critérios de Implantação'!AK$31*'Resumo-Cult.Perma.'!$C12 -> 0
B52: Ano de formação da cultura | D52: ='Critérios de Implantação'!D$31*'Resumo-Cult.Perma.'!$C13 -> 0 | E52: ='Critérios de Implantação'!E$31*'Resumo-Cult.Perma.'!$C13 -> 0 | F52: ='Critérios de Implantação'!F$31*'Resumo-Cult.Perma.'!$C13 -> 0 | G52: ='Critérios de Implantação'!G$31*'Resumo-Cult.Perma.'!$C13 -> 0 | H52: ='Critérios de Implantação'!H$31*'Resumo-Cult.Perma.'!$C13 -> 0 | I52: ='Critérios de Implantação'!I$31*'Resumo-Cult.Perma.'!$C13 -> 0 | J52: ='Critérios de Implantação'!J$31*'Resumo-Cult.Perma.'!$C13 -> 0 | K52: ='Critérios de Implantação'!K$31*'Resumo-Cult.Perma.'!$C13 -> 0 | ... AK52: ='Critérios de Implantação'!AK$31*'Resumo-Cult.Perma.'!$C13 -> 0
A53: 1.5 | B53: Gasto com insumos | D53: ='Critérios de Implantação'!D$31*'Resumo-Cult.Perma.'!$C14 -> 0 | E53: ='Critérios de Implantação'!E$31*'Resumo-Cult.Perma.'!$C14 -> 0 | F53: ='Critérios de Implantação'!F$31*'Resumo-Cult.Perma.'!$C14 -> 3201639.2 | G53: ='Critérios de Implantação'!G$31*'Resumo-Cult.Perma.'!$C14 -> 3201639.2 | H53: ='Critérios de Implantação'!H$31*'Resumo-Cult.Perma.'!$C14 -> 3846611.6 | I53: ='Critérios de Implantação'!I$31*'Resumo-Cult.Perma.'!$C14 -> 7429322.9 | J53: ='Critérios de Implantação'!J$31*'Resumo-Cult.Perma.'!$C14 -> 6970369.3 | K53: ='Critérios de Implantação'!K$31*'Resumo-Cult.Perma.'!$C14 -> 7171848.9 | ... AK53: ='Critérios de Implantação'!AK$31*'Resumo-Cult.Perma.'!$C14 -> 0
A54: 1.6 | B54: Gasto com mão de obra | D54: ='Critérios de Implantação'!D$31*'Resumo-Cult.Perma.'!$C15 -> 0 | E54: ='Critérios de Implantação'!E$31*'Resumo-Cult.Perma.'!$C15 -> 0 | F54: ='Critérios de Implantação'!F$31*'Resumo-Cult.Perma.'!$C15 -> 995406.41 | G54: ='Critérios de Implantação'!G$31*'Resumo-Cult.Perma.'!$C15 -> 995406.41 | H54: ='Critérios de Implantação'!H$31*'Resumo-Cult.Perma.'!$C15 -> 1195931.7 | I54: ='Critérios de Implantação'!I$31*'Resumo-Cult.Perma.'!$C15 -> 2309815.5 | J54: ='Critérios de Implantação'!J$31*'Resumo-Cult.Perma.'!$C15 -> 2167124.4 | K54: ='Critérios de Implantação'!K$31*'Resumo-Cult.Perma.'!$C15 -> 2229765.4 | ... AK54: ='Critérios de Implantação'!AK$31*'Resumo-Cult.Perma.'!$C15 -> 0
A55: 1.7 | B55: Gasto com trator e equipamentos e avaição agrícola | D55: ='Critérios de Implantação'!D$31*'Resumo-Cult.Perma.'!$C16 -> 0 | E55: ='Critérios de Implantação'!E$31*'Resumo-Cult.Perma.'!$C16 -> 0 | F55: ='Critérios de Implantação'!F$31*'Resumo-Cult.Perma.'!$C16 -> 864905.87 | G55: ='Critérios de Implantação'!G$31*'Resumo-Cult.Perma.'!$C16 -> 864905.87 | H55: ='Critérios de Implantação'!H$31*'Resumo-Cult.Perma.'!$C16 -> 1039141.8 | I55: ='Critérios de Implantação'!I$31*'Resumo-Cult.Perma.'!$C16 -> 2006992.3 | J55: ='Critérios de Implantação'!J$31*'Resumo-Cult.Perma.'!$C16 -> 1883008.4 | K55: ='Critérios de Implantação'!K$31*'Resumo-Cult.Perma.'!$C16 -> 1937437 | ... AK55: ='Critérios de Implantação'!AK$31*'Resumo-Cult.Perma.'!$C16 -> 0
A56: 1.8 | B56: Outros custos | D56: ='Critérios de Implantação'!D$31*'Resumo-Cult.Perma.'!$C17 -> 0 | E56: ='Critérios de Implantação'!E$31*'Resumo-Cult.Perma.'!$C17 -> 0 | F56: ='Critérios de Implantação'!F$31*'Resumo-Cult.Perma.'!$C17 -> 452696.47 | G56: ='Critérios de Implantação'!G$31*'Resumo-Cult.Perma.'!$C17 -> 452696.47 | H56: ='Critérios de Implantação'!H$31*'Resumo-Cult.Perma.'!$C17 -> 543892.5 | I56: ='Critérios de Implantação'!I$31*'Resumo-Cult.Perma.'!$C17 -> 1050470.7 | J56: ='Critérios de Implantação'!J$31*'Resumo-Cult.Perma.'!$C17 -> 985576.89 | K56: ='Critérios de Implantação'!K$31*'Resumo-Cult.Perma.'!$C17 -> 1014065.2 | ... AK56: ='Critérios de Implantação'!AK$31*'Resumo-Cult.Perma.'!$C17 -> 0
B57: Sub-total - Investimentos | D57: =SUM(D48:D56) -> 0 | E57: =SUM(E48:E56) -> 0 | F57: =SUM(F48:F56) -> 10865178 | G57: =SUM(G48:G56) -> 10865178 | H57: =SUM(H48:H56) -> 13053976 | I57: =SUM(I48:I56) -> 25212372 | J57: =SUM(J48:J56) -> 23654853 | K57: =SUM(K48:K56) -> 24338600 | ... AK57: =SUM(AK48:AK56) -> 0
A59: 2 | B59: CUSTOS OPERACIONAIS
A60: 2.1 | B60: Gasto com insumos | D60: =IFERROR(('Resumo-Cult.Perma.'!C21*('Critérios de Implantação'!D$52)),0)+IFERROR(('Resumo-Cult.Perma.'!B21*('Critérios de Implantação'!D$53)),0)+IFERROR(('Resumo-Cult.Perma.'!A21*('Critérios de Implantação'!D$60)),0) -> 0 | E60: =IFERROR(('Resumo-Cult.Perma.'!D21*('Critérios de Implantação'!E$52)),0)+IFERROR(('Resumo-Cult.Perma.'!C21*('Critérios de Implantação'!E$53)),0)+IFERROR(('Resumo-Cult.Perma.'!B21*('Critérios de Implantação'!E$60)),0) -> 0 | F60: =IFERROR(('Resumo-Cult.Perma.'!C21*('Critérios de Implantação'!F$52)),0)+IFERROR(('Resumo-Cult.Perma.'!B21*('Critérios de Implantação'!F$53)),0)+IFERROR(('Resumo-Cult.Perma.'!A21*('Critérios de Implantação'!F$54)),0)+IFERROR(('Resumo-Cult.Perma.'!#REF!*('Critérios de Implantação'!F$55)),0)+IFERROR(('Resumo-Cult.Perma.'!#REF!*('Critérios de Implantação'!F$56)),0)+IFERROR(('Resumo-Cult.Perma.'!#REF!*('Critérios de Implantação'!F$57)),0)+IFERROR(('Resumo-Cult.Perma.'!#REF!*('Critérios de Implantação'!F$58)),0)+IFERROR(('Resumo-Cult.Perma.'!#REF!*('Critérios de Implantação'!F$59)),0)+IFERROR(('Resumo-Cult.Perma.'!#REF!*('Critérios de Implantação'!F$60)),0) -> 0 | G60: =IFERROR('Resumo-Cult.Perma.'!D21*'Critérios de Implantação'!G$52,0)+IFERROR('Resumo-Cult.Perma.'!C21*'Critérios de Implantação'!G$53,0)+IFERROR('Resumo-Cult.Perma.'!B21*'Critérios de Implantação'!$Q$54,0)+IFERROR('Resumo-Cult.Perma.'!A21*'Critérios de Implantação'!$Q$55,0)+IFERROR('Resumo-Cult.Perma.'!#REF!*'Critérios de Implantação'!$Q$56,0)+IFERROR('Resumo-Cult.Perma.'!#REF!*'Critérios de Implantação'!$Q$57,0)+IFERROR('Resumo-Cult.Perma.'!#REF!*'Critérios de Implantação'!$Q$58,0)+IFERROR('Resumo-Cult.Perma.'!#REF!*'Critérios de Implantação'!$Q$59,0)+IFERROR('Resumo-Cult.Perma.'!#REF!*'Critérios de Implantação'!$Q$60,0) -> 1856488.2 | H60: =IFERROR('Resumo-Cult.Perma.'!E21*'Critérios de Implantação'!H$52,0)+IFERROR('Resumo-Cult.Perma.'!D21*'Critérios de Implantação'!H$53,0)+IFERROR('Resumo-Cult.Perma.'!C21*'Critérios de Implantação'!$Q$54,0)+IFERROR('Resumo-Cult.Perma.'!B21*'Critérios de Implantação'!$Q$55,0)+IFERROR('Resumo-Cult.Perma.'!A21*'Critérios de Implantação'!$Q$56,0)+IFERROR('Resumo-Cult.Perma.'!#REF!*'Critérios de Implantação'!$Q$57,0)+IFERROR('Resumo-Cult.Perma.'!#REF!*'Critérios de Implantação'!$Q$58,0)+IFERROR('Resumo-Cult.Perma.'!#REF!*'Critérios de Implantação'!$Q$59,0)+IFERROR('Resumo-Cult.Perma.'!#REF!*'Critérios de Implantação'!$Q$60,0) -> 3711871.8 | I60: =IFERROR('Resumo-Cult.Perma.'!F21*'Critérios de Implantação'!I$52,0)+IFERROR('Resumo-Cult.Perma.'!E21*'Critérios de Implantação'!I$53,0)+IFERROR('Resumo-Cult.Perma.'!D21*'Critérios de Implantação'!$Q$54,0)+IFERROR('Resumo-Cult.Perma.'!C21*'Critérios de Implantação'!$Q$55,0)+IFERROR('Resumo-Cult.Perma.'!B21*'Critérios de Implantação'!$Q$56,0)+IFERROR('Resumo-Cult.Perma.'!A21*'Critérios de Implantação'!$Q$57,0)+IFERROR('Resumo-Cult.Perma.'!#REF!*'Critérios de Implantação'!$Q$58,0)+IFERROR('Resumo-Cult.Perma.'!#REF!*'Critérios de Implantação'!$Q$59,0)+IFERROR('Resumo-Cult.Perma.'!#REF!*'Critérios de Implantação'!$Q$60,0) -> 5941246.3 | J60: =IFERROR('Resumo-Cult.Perma.'!G21*'Critérios de Implantação'!J$52,0)+IFERROR('Resumo-Cult.Perma.'!F21*'Critérios de Implantação'!J$53,0)+IFERROR('Resumo-Cult.Perma.'!E21*'Critérios de Implantação'!$Q$54,0)+IFERROR('Resumo-Cult.Perma.'!D21*'Critérios de Implantação'!$Q$55,0)+IFERROR('Resumo-Cult.Perma.'!C21*'Critérios de Implantação'!$Q$56,0)+IFERROR('Resumo-Cult.Perma.'!B21*'Critérios de Implantação'!$Q$57,0)+IFERROR('Resumo-Cult.Perma.'!A21*'Critérios de Implantação'!$Q$58,0)+IFERROR('Resumo-Cult.Perma.'!#REF!*'Critérios de Implantação'!$Q$59,0)+IFERROR('Resumo-Cult.Perma.'!#REF!*'Critérios de Implantação'!$Q$60,0) -> 10086218 | K60: =IFERROR('Resumo-Cult.Perma.'!H21*'Critérios de Implantação'!K$52,0)+IFERROR('Resumo-Cult.Perma.'!G21*'Critérios de Implantação'!K$53,0)+IFERROR('Resumo-Cult.Perma.'!F21*'Critérios de Implantação'!$Q$54,0)+IFERROR('Resumo-Cult.Perma.'!E21*'Critérios de Implantação'!$Q$55,0)+IFERROR('Resumo-Cult.Perma.'!D21*'Critérios de Implantação'!$Q$56,0)+IFERROR('Resumo-Cult.Perma.'!C21*'Critérios de Implantação'!$Q$57,0)+IFERROR('Resumo-Cult.Perma.'!B21*'Critérios de Implantação'!$Q$58,0)+IFERROR('Resumo-Cult.Perma.'!A21*'Critérios de Implantação'!$Q$59,0)+IFERROR('Resumo-Cult.Perma.'!#REF!*'Critérios de Implantação'!$Q$60,0) -> 13963827 | L60: =IFERROR('Resumo-Cult.Perma.'!I21*'Critérios de Implantação'!L$52,0)+IFERROR('Resumo-Cult.Perma.'!H21*'Critérios de Implantação'!L$53,0)+IFERROR('Resumo-Cult.Perma.'!G21*'Critérios de Implantação'!$Q$54,0)+IFERROR('Resumo-Cult.Perma.'!F21*'Critérios de Implantação'!$Q$55,0)+IFERROR('Resumo-Cult.Perma.'!E21*'Critérios de Implantação'!$Q$56,0)+IFERROR('Resumo-Cult.Perma.'!D21*'Critérios de Implantação'!$Q$57,0)+IFERROR('Resumo-Cult.Perma.'!C21*'Critérios de Implantação'!$Q$58,0)+IFERROR('Resumo-Cult.Perma.'!B21*'Critérios de Implantação'!$Q$59,0)+IFERROR('Resumo-Cult.Perma.'!A21*'Critérios de Implantação'!$Q$60,0) -> 17925862 | M60: =IFERROR('Resumo-Cult.Perma.'!J21*'Critérios de Implantação'!M$52,0)+IFERROR('Resumo-Cult.Perma.'!I21*'Critérios de Implantação'!M$53,0)+IFERROR('Resumo-Cult.Perma.'!H21*'Critérios de Implantação'!$Q$54,0)+IFERROR('Resumo-Cult.Perma.'!G21*'Critérios de Implantação'!$Q$55,0)+IFERROR('Resumo-Cult.Perma.'!F21*'Critérios de Implantação'!$Q$56,0)+IFERROR('Resumo-Cult.Perma.'!E21*'Critérios de Implantação'!$Q$57,0)+IFERROR('Resumo-Cult.Perma.'!D21*'Critérios de Implantação'!$Q$58,0)+IFERROR('Resumo-Cult.Perma.'!C21*'Critérios de Implantação'!$Q$59,0)+IFERROR('Resumo-Cult.Perma.'!B21*'Critérios de Implantação'!$Q$60,0) -> 20935801 | N60: =IFERROR('Resumo-Cult.Perma.'!K21*'Critérios de Implantação'!N$52,0)+IFERROR('Resumo-Cult.Perma.'!J21*'Critérios de Implantação'!N$53,0)+IFERROR('Resumo-Cult.Perma.'!I21*'Critérios de Implantação'!$Q$54,0)+IFERROR('Resumo-Cult.Perma.'!H21*'Critérios de Implantação'!$Q$55,0)+IFERROR('Resumo-Cult.Perma.'!G21*'Critérios de Implantação'!$Q$56,0)+IFERROR('Resumo-Cult.Perma.'!F21*'Critérios de Implantação'!$Q$57,0)+IFERROR('Resumo-Cult.Perma.'!E21*'Critérios de Implantação'!$Q$58,0)+IFERROR('Resumo-Cult.Perma.'!D21*'Critérios de Implantação'!$Q$59,0)+IFERROR('Resumo-Cult.Perma.'!C21*'Critérios de Implantação'!$Q$60,0) -> 22983150 | O60: =IFERROR('Resumo-Cult.Perma.'!L21*'Critérios de Implantação'!O$52,0)+IFERROR('Resumo-Cult.Perma.'!K21*'Critérios de Implantação'!O$53,0)+IFERROR('Resumo-Cult.Perma.'!J21*'Critérios de Implantação'!$Q$54,0)+IFERROR('Resumo-Cult.Perma.'!I21*'Critérios de Implantação'!$Q$55,0)+IFERROR('Resumo-Cult.Perma.'!H21*'Critérios de Implantação'!$Q$56,0)+IFERROR('Resumo-Cult.Perma.'!G21*'Critérios de Implantação'!$Q$57,0)+IFERROR('Resumo-Cult.Perma.'!F21*'Critérios de Implantação'!$Q$58,0)+IFERROR('Resumo-Cult.Perma.'!E21*'Critérios de Implantação'!$Q$59,0)+IFERROR('Resumo-Cult.Perma.'!D21*'Critérios de Implantação'!$Q$60,0) -> 23827715 | P60: =IFERROR('Resumo-Cult.Perma.'!M21*'Critérios de Implantação'!P$52,0)+IFERROR('Resumo-Cult.Perma.'!L21*'Critérios de Implantação'!P$53,0)+IFERROR('Resumo-Cult.Perma.'!K21*'Critérios de Implantação'!$Q$54,0)+IFERROR('Resumo-Cult.Perma.'!J21*'Critérios de Implantação'!$Q$55,0)+IFERROR('Resumo-Cult.Perma.'!I21*'Critérios de Implantação'!$Q$56,0)+IFERROR('Resumo-Cult.Perma.'!H21*'Critérios de Implantação'!$Q$57,0)+IFERROR('Resumo-Cult.Perma.'!G21*'Critérios de Implantação'!$Q$58,0)+IFERROR('Resumo-Cult.Perma.'!F21*'Critérios de Implantação'!$Q$59,0)+IFERROR('Resumo-Cult.Perma.'!E21*'Critérios de Implantação'!$Q$60,0) -> 23532064 | Q60: =IFERROR('Resumo-Cult.Perma.'!N21*'Critérios de Implantação'!Q$52,0)+IFERROR('Resumo-Cult.Perma.'!M21*'Critérios de Implantação'!Q$53,0)+IFERROR('Resumo-Cult.Perma.'!L21*'Critérios de Implantação'!$Q$54,0)+IFERROR('Resumo-Cult.Perma.'!K21*'Critérios de Implantação'!$Q$55,0)+IFERROR('Resumo-Cult.Perma.'!J21*'Critérios de Implantação'!$Q$56,0)+IFERROR('Resumo-Cult.Perma.'!I21*'Critérios de Implantação'!$Q$57,0)+IFERROR('Resumo-Cult.Perma.'!H21*'Critérios de Implantação'!$Q$58,0)+IFERROR('Resumo-Cult.Perma.'!G21*'Critérios de Implantação'!$Q$59,0)+IFERROR('Resumo-Cult.Perma.'!F21*'Critérios de Implantação'!$Q$60,0) -> 23322998 | R60: =IFERROR('Resumo-Cult.Perma.'!O21*'Critérios de Implantação'!R$52,0)+IFERROR('Resumo-Cult.Perma.'!N21*'Critérios de Implantação'!R$53,0)+IFERROR('Resumo-Cult.Perma.'!M21*'Critérios de Implantação'!$Q$54,0)+IFERROR('Resumo-Cult.Perma.'!L21*'Critérios de Implantação'!$Q$55,0)+IFERROR('Resumo-Cult.Perma.'!K21*'Critérios de Implantação'!$Q$56,0)+IFERROR('Resumo-Cult.Perma.'!J21*'Critérios de Implantação'!$Q$57,0)+IFERROR('Resumo-Cult.Perma.'!I21*'Critérios de Implantação'!$Q$58,0)+IFERROR('Resumo-Cult.Perma.'!H21*'Critérios de Implantação'!$Q$59,0)+IFERROR('Resumo-Cult.Perma.'!G21*'Critérios de Implantação'!$Q$60,0) -> 24725709 | S60: =IFERROR('Resumo-Cult.Perma.'!P21*'Critérios de Implantação'!S$52,0)+IFERROR('Resumo-Cult.Perma.'!O21*'Critérios de Implantação'!S$53,0)+IFERROR('Resumo-Cult.Perma.'!N21*'Critérios de Implantação'!$Q$54,0)+IFERROR('Resumo-Cult.Perma.'!M21*'Critérios de Implantação'!$Q$55,0)+IFERROR('Resumo-Cult.Perma.'!L21*'Critérios de Implantação'!$Q$56,0)+IFERROR('Resumo-Cult.Perma.'!K21*'Critérios de Implantação'!$Q$57,0)+IFERROR('Resumo-Cult.Perma.'!J21*'Critérios de Implantação'!$Q$58,0)+IFERROR('Resumo-Cult.Perma.'!I21*'Critérios de Implantação'!$Q$59,0)+IFERROR('Resumo-Cult.Perma.'!H21*'Critérios de Implantação'!$Q$60,0) -> 24888448 | ... AK60: =IFERROR('Resumo-Cult.Perma.'!AH21*'Critérios de Implantação'!AK$52,0)+IFERROR('Resumo-Cult.Perma.'!AG21*'Critérios de Implantação'!AK$53,0)+IFERROR('Resumo-Cult.Perma.'!AF21*'Critérios de Implantação'!$Q$54,0)+IFERROR('Resumo-Cult.Perma.'!AE21*'Critérios de Implantação'!$Q$55,0)+IFERROR('Resumo-Cult.Perma.'!AD21*'Critérios de Implantação'!$Q$56,0)+IFERROR('Resumo-Cult.Perma.'!AC21*'Critérios de Implantação'!$Q$57,0)+IFERROR('Resumo-Cult.Perma.'!AB21*'Critérios de Implantação'!$Q$58,0)+IFERROR('Resumo-Cult.Perma.'!AA21*'Critérios de Implantação'!$Q$59,0)+IFERROR('Resumo-Cult.Perma.'!Z21*'Critérios de Implantação'!$Q$60,0) -> 26179110
A61: 2.2 | B61: Gasto com mão de obra | D61: =IFERROR('Resumo-Cult.Perma.'!A22*'Critérios de Implantação'!D52,0)+IFERROR('Resumo-Cult.Perma.'!#REF!*'Critérios de Implantação'!D53,0)+IFERROR('Resumo-Cult.Perma.'!#REF!*'Critérios de Implantação'!D54,0)+IFERROR('Resumo-Cult.Perma.'!#REF!*'Critérios de Implantação'!D55,0)+IFERROR('Resumo-Cult.Perma.'!#REF!*'Critérios de Implantação'!D56,0)+IFERROR('Resumo-Cult.Perma.'!#REF!*'Critérios de Implantação'!D57,0)+IFERROR('Resumo-Cult.Perma.'!#REF!*'Critérios de Implantação'!D58,0)+IFERROR('Resumo-Cult.Perma.'!#REF!*'Critérios de Implantação'!D59,0)+IFERROR('Resumo-Cult.Perma.'!#REF!*'Critérios de Implantação'!D60,0) -> 0 | E61: =IFERROR('Resumo-Cult.Perma.'!B22*'Critérios de Implantação'!E52,0)+IFERROR('Resumo-Cult.Perma.'!A22*'Critérios de Implantação'!E53,0)+IFERROR('Resumo-Cult.Perma.'!#REF!*'Critérios de Implantação'!E54,0)+IFERROR('Resumo-Cult.Perma.'!#REF!*'Critérios de Implantação'!E55,0)+IFERROR('Resumo-Cult.Perma.'!#REF!*'Critérios de Implantação'!E56,0)+IFERROR('Resumo-Cult.Perma.'!#REF!*'Critérios de Implantação'!E57,0)+IFERROR('Resumo-Cult.Perma.'!#REF!*'Critérios de Implantação'!E58,0)+IFERROR('Resumo-Cult.Perma.'!#REF!*'Critérios de Implantação'!E59,0)+IFERROR('Resumo-Cult.Perma.'!#REF!*'Critérios de Implantação'!E60,0) -> 0 | F61: =IFERROR('Resumo-Cult.Perma.'!C22*'Critérios de Implantação'!F52,0)+IFERROR('Resumo-Cult.Perma.'!B22*'Critérios de Implantação'!F53,0)+IFERROR('Resumo-Cult.Perma.'!A22*'Critérios de Implantação'!F54,0)+IFERROR('Resumo-Cult.Perma.'!#REF!*'Critérios de Implantação'!F55,0)+IFERROR('Resumo-Cult.Perma.'!#REF!*'Critérios de Implantação'!F56,0)+IFERROR('Resumo-Cult.Perma.'!#REF!*'Critérios de Implantação'!F57,0)+IFERROR('Resumo-Cult.Perma.'!#REF!*'Critérios de Implantação'!F58,0)+IFERROR('Resumo-Cult.Perma.'!#REF!*'Critérios de Implantação'!F59,0)+IFERROR('Resumo-Cult.Perma.'!#REF!*'Critérios de Implantação'!F60,0) -> 0 | G61: =IFERROR('Resumo-Cult.Perma.'!D22*'Critérios de Implantação'!G$52,0)+IFERROR('Resumo-Cult.Perma.'!C22*'Critérios de Implantação'!G$53,0)+IFERROR('Resumo-Cult.Perma.'!B22*'Critérios de Implantação'!$Q$54,0)+IFERROR('Resumo-Cult.Perma.'!A22*'Critérios de Implantação'!$Q$55,0)+IFERROR('Resumo-Cult.Perma.'!#REF!*'Critérios de Implantação'!$Q$56,0)+IFERROR('Resumo-Cult.Perma.'!#REF!*'Critérios de Implantação'!$Q$57,0)+IFERROR('Resumo-Cult.Perma.'!#REF!*'Critérios de Implantação'!$Q$58,0)+IFERROR('Resumo-Cult.Perma.'!#REF!*'Critérios de Implantação'!$Q$59,0)+IFERROR('Resumo-Cult.Perma.'!#REF!*'Critérios de Implantação'!$Q$60,0) -> 2187243.3 | H61: =IFERROR('Resumo-Cult.Perma.'!E22*'Critérios de Implantação'!H$52,0)+IFERROR('Resumo-Cult.Perma.'!D22*'Critérios de Implantação'!H$53,0)+IFERROR('Resumo-Cult.Perma.'!C22*'Critérios de Implantação'!$Q$54,0)+IFERROR('Resumo-Cult.Perma.'!B22*'Critérios de Implantação'!$Q$55,0)+IFERROR('Resumo-Cult.Perma.'!A22*'Critérios de Implantação'!$Q$56,0)+IFERROR('Resumo-Cult.Perma.'!#REF!*'Critérios de Implantação'!$Q$57,0)+IFERROR('Resumo-Cult.Perma.'!#REF!*'Critérios de Implantação'!$Q$58,0)+IFERROR('Resumo-Cult.Perma.'!#REF!*'Critérios de Implantação'!$Q$59,0)+IFERROR('Resumo-Cult.Perma.'!#REF!*'Critérios de Implantação'!$Q$60,0) -> 4265091.9 | I61: =IFERROR('Resumo-Cult.Perma.'!F22*'Critérios de Implantação'!I$52,0)+IFERROR('Resumo-Cult.Perma.'!E22*'Critérios de Implantação'!I$53,0)+IFERROR('Resumo-Cult.Perma.'!D22*'Critérios de Implantação'!$Q$54,0)+IFERROR('Resumo-Cult.Perma.'!C22*'Critérios de Implantação'!$Q$55,0)+IFERROR('Resumo-Cult.Perma.'!B22*'Critérios de Implantação'!$Q$56,0)+IFERROR('Resumo-Cult.Perma.'!A22*'Critérios de Implantação'!$Q$57,0)+IFERROR('Resumo-Cult.Perma.'!#REF!*'Critérios de Implantação'!$Q$58,0)+IFERROR('Resumo-Cult.Perma.'!#REF!*'Critérios de Implantação'!$Q$59,0)+IFERROR('Resumo-Cult.Perma.'!#REF!*'Critérios de Implantação'!$Q$60,0) -> 6680737.8 | J61: =IFERROR('Resumo-Cult.Perma.'!G22*'Critérios de Implantação'!J$52,0)+IFERROR('Resumo-Cult.Perma.'!F22*'Critérios de Implantação'!J$53,0)+IFERROR('Resumo-Cult.Perma.'!E22*'Critérios de Implantação'!$Q$54,0)+IFERROR('Resumo-Cult.Perma.'!D22*'Critérios de Implantação'!$Q$55,0)+IFERROR('Resumo-Cult.Perma.'!C22*'Critérios de Implantação'!$Q$56,0)+IFERROR('Resumo-Cult.Perma.'!B22*'Critérios de Implantação'!$Q$57,0)+IFERROR('Resumo-Cult.Perma.'!A22*'Critérios de Implantação'!$Q$58,0)+IFERROR('Resumo-Cult.Perma.'!#REF!*'Critérios de Implantação'!$Q$59,0)+IFERROR('Resumo-Cult.Perma.'!#REF!*'Critérios de Implantação'!$Q$60,0) -> 11521924 | K61: =IFERROR('Resumo-Cult.Perma.'!H22*'Critérios de Implantação'!K$52,0)+IFERROR('Resumo-Cult.Perma.'!G22*'Critérios de Implantação'!K$53,0)+IFERROR('Resumo-Cult.Perma.'!F22*'Critérios de Implantação'!$Q$54,0)+IFERROR('Resumo-Cult.Perma.'!E22*'Critérios de Implantação'!$Q$55,0)+IFERROR('Resumo-Cult.Perma.'!D22*'Critérios de Implantação'!$Q$56,0)+IFERROR('Resumo-Cult.Perma.'!C22*'Critérios de Implantação'!$Q$57,0)+IFERROR('Resumo-Cult.Perma.'!B22*'Critérios de Implantação'!$Q$58,0)+IFERROR('Resumo-Cult.Perma.'!A22*'Critérios de Implantação'!$Q$59,0)+IFERROR('Resumo-Cult.Perma.'!#REF!*'Critérios de Implantação'!$Q$60,0) -> 15906440 | L61: =IFERROR('Resumo-Cult.Perma.'!I22*'Critérios de Implantação'!L$52,0)+IFERROR('Resumo-Cult.Perma.'!H22*'Critérios de Implantação'!L$53,0)+IFERROR('Resumo-Cult.Perma.'!G22*'Critérios de Implantação'!$Q$54,0)+IFERROR('Resumo-Cult.Perma.'!F22*'Critérios de Implantação'!$Q$55,0)+IFERROR('Resumo-Cult.Perma.'!E22*'Critérios de Implantação'!$Q$56,0)+IFERROR('Resumo-Cult.Perma.'!D22*'Critérios de Implantação'!$Q$57,0)+IFERROR('Resumo-Cult.Perma.'!C22*'Critérios de Implantação'!$Q$58,0)+IFERROR('Resumo-Cult.Perma.'!B22*'Critérios de Implantação'!$Q$59,0)+IFERROR('Resumo-Cult.Perma.'!A22*'Critérios de Implantação'!$Q$60,0) -> 20226394 | M61: =IFERROR('Resumo-Cult.Perma.'!J22*'Critérios de Implantação'!M$52,0)+IFERROR('Resumo-Cult.Perma.'!I22*'Critérios de Implantação'!M$53,0)+IFERROR('Resumo-Cult.Perma.'!H22*'Critérios de Implantação'!$Q$54,0)+IFERROR('Resumo-Cult.Perma.'!G22*'Critérios de Implantação'!$Q$55,0)+IFERROR('Resumo-Cult.Perma.'!F22*'Critérios de Implantação'!$Q$56,0)+IFERROR('Resumo-Cult.Perma.'!E22*'Critérios de Implantação'!$Q$57,0)+IFERROR('Resumo-Cult.Perma.'!D22*'Critérios de Implantação'!$Q$58,0)+IFERROR('Resumo-Cult.Perma.'!C22*'Critérios de Implantação'!$Q$59,0)+IFERROR('Resumo-Cult.Perma.'!B22*'Critérios de Implantação'!$Q$60,0) -> 23645662 | N61: =IFERROR('Resumo-Cult.Perma.'!K22*'Critérios de Implantação'!N$52,0)+IFERROR('Resumo-Cult.Perma.'!J22*'Critérios de Implantação'!N$53,0)+IFERROR('Resumo-Cult.Perma.'!I22*'Critérios de Implantação'!$Q$54,0)+IFERROR('Resumo-Cult.Perma.'!H22*'Critérios de Implantação'!$Q$55,0)+IFERROR('Resumo-Cult.Perma.'!G22*'Critérios de Implantação'!$Q$56,0)+IFERROR('Resumo-Cult.Perma.'!F22*'Critérios de Implantação'!$Q$57,0)+IFERROR('Resumo-Cult.Perma.'!E22*'Critérios de Implantação'!$Q$58,0)+IFERROR('Resumo-Cult.Perma.'!D22*'Critérios de Implantação'!$Q$59,0)+IFERROR('Resumo-Cult.Perma.'!C22*'Critérios de Implantação'!$Q$60,0) -> 25612787 | O61: =IFERROR('Resumo-Cult.Perma.'!L22*'Critérios de Implantação'!O$52,0)+IFERROR('Resumo-Cult.Perma.'!K22*'Critérios de Implantação'!O$53,0)+IFERROR('Resumo-Cult.Perma.'!J22*'Critérios de Implantação'!$Q$54,0)+IFERROR('Resumo-Cult.Perma.'!I22*'Critérios de Implantação'!$Q$55,0)+IFERROR('Resumo-Cult.Perma.'!H22*'Critérios de Implantação'!$Q$56,0)+IFERROR('Resumo-Cult.Perma.'!G22*'Critérios de Implantação'!$Q$57,0)+IFERROR('Resumo-Cult.Perma.'!F22*'Critérios de Implantação'!$Q$58,0)+IFERROR('Resumo-Cult.Perma.'!E22*'Critérios de Implantação'!$Q$59,0)+IFERROR('Resumo-Cult.Perma.'!D22*'Critérios de Implantação'!$Q$60,0) -> 26057066 | P61: =IFERROR('Resumo-Cult.Perma.'!M22*'Critérios de Implantação'!P$52,0)+IFERROR('Resumo-Cult.Perma.'!L22*'Critérios de Implantação'!P$53,0)+IFERROR('Resumo-Cult.Perma.'!K22*'Critérios de Implantação'!$Q$54,0)+IFERROR('Resumo-Cult.Perma.'!J22*'Critérios de Implantação'!$Q$55,0)+IFERROR('Resumo-Cult.Perma.'!I22*'Critérios de Implantação'!$Q$56,0)+IFERROR('Resumo-Cult.Perma.'!H22*'Critérios de Implantação'!$Q$57,0)+IFERROR('Resumo-Cult.Perma.'!G22*'Critérios de Implantação'!$Q$58,0)+IFERROR('Resumo-Cult.Perma.'!F22*'Critérios de Implantação'!$Q$59,0)+IFERROR('Resumo-Cult.Perma.'!E22*'Critérios de Implantação'!$Q$60,0) -> 25155582 | Q61: =IFERROR('Resumo-Cult.Perma.'!N22*'Critérios de Implantação'!Q$52,0)+IFERROR('Resumo-Cult.Perma.'!M22*'Critérios de Implantação'!Q$53,0)+IFERROR('Resumo-Cult.Perma.'!L22*'Critérios de Implantação'!$Q$54,0)+IFERROR('Resumo-Cult.Perma.'!K22*'Critérios de Implantação'!$Q$55,0)+IFERROR('Resumo-Cult.Perma.'!J22*'Critérios de Implantação'!$Q$56,0)+IFERROR('Resumo-Cult.Perma.'!I22*'Critérios de Implantação'!$Q$57,0)+IFERROR('Resumo-Cult.Perma.'!H22*'Critérios de Implantação'!$Q$58,0)+IFERROR('Resumo-Cult.Perma.'!G22*'Critérios de Implantação'!$Q$59,0)+IFERROR('Resumo-Cult.Perma.'!F22*'Critérios de Implantação'!$Q$60,0) -> 23916172 | R61: =IFERROR('Resumo-Cult.Perma.'!O22*'Critérios de Implantação'!R$52,0)+IFERROR('Resumo-Cult.Perma.'!N22*'Critérios de Implantação'!R$53,0)+IFERROR('Resumo-Cult.Perma.'!M22*'Critérios de Implantação'!$Q$54,0)+IFERROR('Resumo-Cult.Perma.'!L22*'Critérios de Implantação'!$Q$55,0)+IFERROR('Resumo-Cult.Perma.'!K22*'Critérios de Implantação'!$Q$56,0)+IFERROR('Resumo-Cult.Perma.'!J22*'Critérios de Implantação'!$Q$57,0)+IFERROR('Resumo-Cult.Perma.'!I22*'Critérios de Implantação'!$Q$58,0)+IFERROR('Resumo-Cult.Perma.'!H22*'Critérios de Implantação'!$Q$59,0)+IFERROR('Resumo-Cult.Perma.'!G22*'Critérios de Implantação'!$Q$60,0) -> 22352869 | S61: =IFERROR('Resumo-Cult.Perma.'!P22*'Critérios de Implantação'!S$52,0)+IFERROR('Resumo-Cult.Perma.'!O22*'Critérios de Implantação'!S$53,0)+IFERROR('Resumo-Cult.Perma.'!N22*'Critérios de Implantação'!$Q$54,0)+IFERROR('Resumo-Cult.Perma.'!M22*'Critérios de Implantação'!$Q$55,0)+IFERROR('Resumo-Cult.Perma.'!L22*'Critérios de Implantação'!$Q$56,0)+IFERROR('Resumo-Cult.Perma.'!K22*'Critérios de Implantação'!$Q$57,0)+IFERROR('Resumo-Cult.Perma.'!J22*'Critérios de Implantação'!$Q$58,0)+IFERROR('Resumo-Cult.Perma.'!I22*'Critérios de Implantação'!$Q$59,0)+IFERROR('Resumo-Cult.Perma.'!H22*'Critérios de Implantação'!$Q$60,0) -> 22010640 | ... AK61: =IFERROR('Resumo-Cult.Perma.'!AH22*'Critérios de Implantação'!AK$52,0)+IFERROR('Resumo-Cult.Perma.'!AG22*'Critérios de Implantação'!AK$53,0)+IFERROR('Resumo-Cult.Perma.'!AF22*'Critérios de Implantação'!$Q$54,0)+IFERROR('Resumo-Cult.Perma.'!AE22*'Critérios de Implantação'!$Q$55,0)+IFERROR('Resumo-Cult.Perma.'!AD22*'Critérios de Implantação'!$Q$56,0)+IFERROR('Resumo-Cult.Perma.'!AC22*'Critérios de Implantação'!$Q$57,0)+IFERROR('Resumo-Cult.Perma.'!AB22*'Critérios de Implantação'!$Q$58,0)+IFERROR('Resumo-Cult.Perma.'!AA22*'Critérios de Implantação'!$Q$59,0)+IFERROR('Resumo-Cult.Perma.'!Z22*'Critérios de Implantação'!$Q$60,0) -> 25816902
A62: 2.3 | B62: Gasto com trator e equipamentos e avaição agrícola | D62: =IFERROR(('Resumo-Cult.Perma.'!C23*('Critérios de Implantação'!D$52)),0)+IFERROR(('Resumo-Cult.Perma.'!B23*('Critérios de Implantação'!D$53)),0)+IFERROR(('Resumo-Cult.Perma.'!A23*('Critérios de Implantação'!D$60)),0) -> 0 | E62: =IFERROR(('Resumo-Cult.Perma.'!D23*('Critérios de Implantação'!E$52)),0)+IFERROR(('Resumo-Cult.Perma.'!C23*('Critérios de Implantação'!E$53)),0)+IFERROR(('Resumo-Cult.Perma.'!B23*('Critérios de Implantação'!E$60)),0) -> 0 | F62: =IFERROR(('Resumo-Cult.Perma.'!C23*('Critérios de Implantação'!F$52)),0)+IFERROR(('Resumo-Cult.Perma.'!B23*('Critérios de Implantação'!F$53)),0)+IFERROR(('Resumo-Cult.Perma.'!A23*('Critérios de Implantação'!F$54)),0)+IFERROR(('Resumo-Cult.Perma.'!#REF!*('Critérios de Implantação'!F$55)),0)+IFERROR(('Resumo-Cult.Perma.'!#REF!*('Critérios de Implantação'!F$56)),0)+IFERROR(('Resumo-Cult.Perma.'!#REF!*('Critérios de Implantação'!F$57)),0)+IFERROR(('Resumo-Cult.Perma.'!#REF!*('Critérios de Implantação'!F$58)),0)+IFERROR(('Resumo-Cult.Perma.'!#REF!*('Critérios de Implantação'!F$59)),0)+IFERROR(('Resumo-Cult.Perma.'!#REF!*('Critérios de Implantação'!F$60)),0) -> 0 | G62: =IFERROR('Resumo-Cult.Perma.'!D23*'Critérios de Implantação'!G$52,0)+IFERROR('Resumo-Cult.Perma.'!C23*'Critérios de Implantação'!G$53,0)+IFERROR('Resumo-Cult.Perma.'!B23*'Critérios de Implantação'!$Q$54,0)+IFERROR('Resumo-Cult.Perma.'!A23*'Critérios de Implantação'!$Q$55,0)+IFERROR('Resumo-Cult.Perma.'!#REF!*'Critérios de Implantação'!$Q$56,0)+IFERROR('Resumo-Cult.Perma.'!#REF!*'Critérios de Implantação'!$Q$57,0)+IFERROR('Resumo-Cult.Perma.'!#REF!*'Critérios de Implantação'!$Q$58,0)+IFERROR('Resumo-Cult.Perma.'!#REF!*'Critérios de Implantação'!$Q$59,0)+IFERROR('Resumo-Cult.Perma.'!#REF!*'Critérios de Implantação'!$Q$60,0) -> 387989.86 | H62: =IFERROR('Resumo-Cult.Perma.'!E23*'Critérios de Implantação'!H$52,0)+IFERROR('Resumo-Cult.Perma.'!D23*'Critérios de Implantação'!H$53,0)+IFERROR('Resumo-Cult.Perma.'!C23*'Critérios de Implantação'!$Q$54,0)+IFERROR('Resumo-Cult.Perma.'!B23*'Critérios de Implantação'!$Q$55,0)+IFERROR('Resumo-Cult.Perma.'!A23*'Critérios de Implantação'!$Q$56,0)+IFERROR('Resumo-Cult.Perma.'!#REF!*'Critérios de Implantação'!$Q$57,0)+IFERROR('Resumo-Cult.Perma.'!#REF!*'Critérios de Implantação'!$Q$58,0)+IFERROR('Resumo-Cult.Perma.'!#REF!*'Critérios de Implantação'!$Q$59,0)+IFERROR('Resumo-Cult.Perma.'!#REF!*'Critérios de Implantação'!$Q$60,0) -> 712258.77 | I62: =IFERROR('Resumo-Cult.Perma.'!F23*'Critérios de Implantação'!I$52,0)+IFERROR('Resumo-Cult.Perma.'!E23*'Critérios de Implantação'!I$53,0)+IFERROR('Resumo-Cult.Perma.'!D23*'Critérios de Implantação'!$Q$54,0)+IFERROR('Resumo-Cult.Perma.'!C23*'Critérios de Implantação'!$Q$55,0)+IFERROR('Resumo-Cult.Perma.'!B23*'Critérios de Implantação'!$Q$56,0)+IFERROR('Resumo-Cult.Perma.'!A23*'Critérios de Implantação'!$Q$57,0)+IFERROR('Resumo-Cult.Perma.'!#REF!*'Critérios de Implantação'!$Q$58,0)+IFERROR('Resumo-Cult.Perma.'!#REF!*'Critérios de Implantação'!$Q$59,0)+IFERROR('Resumo-Cult.Perma.'!#REF!*'Critérios de Implantação'!$Q$60,0) -> 1107608.4 | J62: =IFERROR('Resumo-Cult.Perma.'!G23*'Critérios de Implantação'!J$52,0)+IFERROR('Resumo-Cult.Perma.'!F23*'Critérios de Implantação'!J$53,0)+IFERROR('Resumo-Cult.Perma.'!E23*'Critérios de Implantação'!$Q$54,0)+IFERROR('Resumo-Cult.Perma.'!D23*'Critérios de Implantação'!$Q$55,0)+IFERROR('Resumo-Cult.Perma.'!C23*'Critérios de Implantação'!$Q$56,0)+IFERROR('Resumo-Cult.Perma.'!B23*'Critérios de Implantação'!$Q$57,0)+IFERROR('Resumo-Cult.Perma.'!A23*'Critérios de Implantação'!$Q$58,0)+IFERROR('Resumo-Cult.Perma.'!#REF!*'Critérios de Implantação'!$Q$59,0)+IFERROR('Resumo-Cult.Perma.'!#REF!*'Critérios de Implantação'!$Q$60,0) -> 1931371.5 | K62: =IFERROR('Resumo-Cult.Perma.'!H23*'Critérios de Implantação'!K$52,0)+IFERROR('Resumo-Cult.Perma.'!G23*'Critérios de Implantação'!K$53,0)+IFERROR('Resumo-Cult.Perma.'!F23*'Critérios de Implantação'!$Q$54,0)+IFERROR('Resumo-Cult.Perma.'!E23*'Critérios de Implantação'!$Q$55,0)+IFERROR('Resumo-Cult.Perma.'!D23*'Critérios de Implantação'!$Q$56,0)+IFERROR('Resumo-Cult.Perma.'!C23*'Critérios de Implantação'!$Q$57,0)+IFERROR('Resumo-Cult.Perma.'!B23*'Critérios de Implantação'!$Q$58,0)+IFERROR('Resumo-Cult.Perma.'!#REF!*'Critérios de Implantação'!$Q$59,0)+IFERROR('Resumo-Cult.Perma.'!#REF!*'Critérios de Implantação'!$Q$60,0) -> 2619704.7 | L62: =IFERROR('Resumo-Cult.Perma.'!I23*'Critérios de Implantação'!L$52,0)+IFERROR('Resumo-Cult.Perma.'!H23*'Critérios de Implantação'!L$53,0)+IFERROR('Resumo-Cult.Perma.'!G23*'Critérios de Implantação'!$Q$54,0)+IFERROR('Resumo-Cult.Perma.'!F23*'Critérios de Implantação'!$Q$55,0)+IFERROR('Resumo-Cult.Perma.'!E23*'Critérios de Implantação'!$Q$56,0)+IFERROR('Resumo-Cult.Perma.'!D23*'Critérios de Implantação'!$Q$57,0)+IFERROR('Resumo-Cult.Perma.'!C23*'Critérios de Implantação'!$Q$58,0)+IFERROR('Resumo-Cult.Perma.'!B23*'Critérios de Implantação'!$Q$59,0)+IFERROR('Resumo-Cult.Perma.'!A23*'Critérios de Implantação'!$Q$60,0) -> 3342172.2 | M62: =IFERROR('Resumo-Cult.Perma.'!J23*'Critérios de Implantação'!M$52,0)+IFERROR('Resumo-Cult.Perma.'!I23*'Critérios de Implantação'!M$53,0)+IFERROR('Resumo-Cult.Perma.'!H23*'Critérios de Implantação'!$Q$54,0)+IFERROR('Resumo-Cult.Perma.'!G23*'Critérios de Implantação'!$Q$55,0)+IFERROR('Resumo-Cult.Perma.'!F23*'Critérios de Implantação'!$Q$56,0)+IFERROR('Resumo-Cult.Perma.'!E23*'Critérios de Implantação'!$Q$57,0)+IFERROR('Resumo-Cult.Perma.'!D23*'Critérios de Implantação'!$Q$58,0)+IFERROR('Resumo-Cult.Perma.'!C23*'Critérios de Implantação'!$Q$59,0)+IFERROR('Resumo-Cult.Perma.'!B23*'Critérios de Implantação'!$Q$60,0) -> 3899896.9 | N62: =IFERROR('Resumo-Cult.Perma.'!K23*'Critérios de Implantação'!N$52,0)+IFERROR('Resumo-Cult.Perma.'!J23*'Critérios de Implantação'!N$53,0)+IFERROR('Resumo-Cult.Perma.'!I23*'Critérios de Implantação'!$Q$54,0)+IFERROR('Resumo-Cult.Perma.'!H23*'Critérios de Implantação'!$Q$55,0)+IFERROR('Resumo-Cult.Perma.'!G23*'Critérios de Implantação'!$Q$56,0)+IFERROR('Resumo-Cult.Perma.'!F23*'Critérios de Implantação'!$Q$57,0)+IFERROR('Resumo-Cult.Perma.'!E23*'Critérios de Implantação'!$Q$58,0)+IFERROR('Resumo-Cult.Perma.'!D23*'Critérios de Implantação'!$Q$59,0)+IFERROR('Resumo-Cult.Perma.'!C23*'Critérios de Implantação'!$Q$60,0) -> 4277102 | O62: =IFERROR('Resumo-Cult.Perma.'!L23*'Critérios de Implantação'!O$52,0)+IFERROR('Resumo-Cult.Perma.'!K23*'Critérios de Implantação'!O$53,0)+IFERROR('Resumo-Cult.Perma.'!J23*'Critérios de Implantação'!$Q$54,0)+IFERROR('Resumo-Cult.Perma.'!I23*'Critérios de Implantação'!$Q$55,0)+IFERROR('Resumo-Cult.Perma.'!H23*'Critérios de Implantação'!$Q$56,0)+IFERROR('Resumo-Cult.Perma.'!G23*'Critérios de Implantação'!$Q$57,0)+IFERROR('Resumo-Cult.Perma.'!F23*'Critérios de Implantação'!$Q$58,0)+IFERROR('Resumo-Cult.Perma.'!E23*'Critérios de Implantação'!$Q$59,0)+IFERROR('Resumo-Cult.Perma.'!D23*'Critérios de Implantação'!$Q$60,0) -> 4442607 | P62: =IFERROR('Resumo-Cult.Perma.'!M23*'Critérios de Implantação'!P$52,0)+IFERROR('Resumo-Cult.Perma.'!L23*'Critérios de Implantação'!P$53,0)+IFERROR('Resumo-Cult.Perma.'!K23*'Critérios de Implantação'!$Q$54,0)+IFERROR('Resumo-Cult.Perma.'!J23*'Critérios de Implantação'!$Q$55,0)+IFERROR('Resumo-Cult.Perma.'!I23*'Critérios de Implantação'!$Q$56,0)+IFERROR('Resumo-Cult.Perma.'!H23*'Critérios de Implantação'!$Q$57,0)+IFERROR('Resumo-Cult.Perma.'!G23*'Critérios de Implantação'!$Q$58,0)+IFERROR('Resumo-Cult.Perma.'!F23*'Critérios de Implantação'!$Q$59,0)+IFERROR('Resumo-Cult.Perma.'!E23*'Critérios de Implantação'!$Q$60,0) -> 4396534.9 | Q62: =IFERROR('Resumo-Cult.Perma.'!N23*'Critérios de Implantação'!Q$52,0)+IFERROR('Resumo-Cult.Perma.'!M23*'Critérios de Implantação'!Q$53,0)+IFERROR('Resumo-Cult.Perma.'!L23*'Critérios de Implantação'!$Q$54,0)+IFERROR('Resumo-Cult.Perma.'!K23*'Critérios de Implantação'!$Q$55,0)+IFERROR('Resumo-Cult.Perma.'!J23*'Critérios de Implantação'!$Q$56,0)+IFERROR('Resumo-Cult.Perma.'!I23*'Critérios de Implantação'!$Q$57,0)+IFERROR('Resumo-Cult.Perma.'!H23*'Critérios de Implantação'!$Q$58,0)+IFERROR('Resumo-Cult.Perma.'!G23*'Critérios de Implantação'!$Q$59,0)+IFERROR('Resumo-Cult.Perma.'!F23*'Critérios de Implantação'!$Q$60,0) -> 4396534.9 | R62: =IFERROR('Resumo-Cult.Perma.'!O23*'Critérios de Implantação'!R$52,0)+IFERROR('Resumo-Cult.Perma.'!N23*'Critérios de Implantação'!R$53,0)+IFERROR('Resumo-Cult.Perma.'!M23*'Critérios de Implantação'!$Q$54,0)+IFERROR('Resumo-Cult.Perma.'!L23*'Critérios de Implantação'!$Q$55,0)+IFERROR('Resumo-Cult.Perma.'!K23*'Critérios de Implantação'!$Q$56,0)+IFERROR('Resumo-Cult.Perma.'!J23*'Critérios de Implantação'!$Q$57,0)+IFERROR('Resumo-Cult.Perma.'!I23*'Critérios de Implantação'!$Q$58,0)+IFERROR('Resumo-Cult.Perma.'!H23*'Critérios de Implantação'!$Q$59,0)+IFERROR('Resumo-Cult.Perma.'!G23*'Critérios de Implantação'!$Q$60,0) -> 5506299.2 | S62: =IFERROR('Resumo-Cult.Perma.'!P23*'Critérios de Implantação'!S$52,0)+IFERROR('Resumo-Cult.Perma.'!O23*'Critérios de Implantação'!S$53,0)+IFERROR('Resumo-Cult.Perma.'!N23*'Critérios de Implantação'!$Q$54,0)+IFERROR('Resumo-Cult.Perma.'!M23*'Critérios de Implantação'!$Q$55,0)+IFERROR('Resumo-Cult.Perma.'!L23*'Critérios de Implantação'!$Q$56,0)+IFERROR('Resumo-Cult.Perma.'!K23*'Critérios de Implantação'!$Q$57,0)+IFERROR('Resumo-Cult.Perma.'!J23*'Critérios de Implantação'!$Q$58,0)+IFERROR('Resumo-Cult.Perma.'!I23*'Critérios de Implantação'!$Q$59,0)+IFERROR('Resumo-Cult.Perma.'!H23*'Critérios de Implantação'!$Q$60,0) -> 5577100.2 | ... AK62: =IFERROR('Resumo-Cult.Perma.'!AH23*'Critérios de Implantação'!AK$52,0)+IFERROR('Resumo-Cult.Perma.'!AG23*'Critérios de Implantação'!AK$53,0)+IFERROR('Resumo-Cult.Perma.'!AF23*'Critérios de Implantação'!$Q$54,0)+IFERROR('Resumo-Cult.Perma.'!AE23*'Critérios de Implantação'!$Q$55,0)+IFERROR('Resumo-Cult.Perma.'!AD23*'Critérios de Implantação'!$Q$56,0)+IFERROR('Resumo-Cult.Perma.'!AC23*'Critérios de Implantação'!$Q$57,0)+IFERROR('Resumo-Cult.Perma.'!AB23*'Critérios de Implantação'!$Q$58,0)+IFERROR('Resumo-Cult.Perma.'!AA23*'Critérios de Implantação'!$Q$59,0)+IFERROR('Resumo-Cult.Perma.'!Z23*'Critérios de Implantação'!$Q$60,0) -> 5961142.4
A63: 2.4 | B63: Outros custos | D63: =IFERROR(('Resumo-Cult.Perma.'!C24*('Critérios de Implantação'!D$52)),0)+IFERROR(('Resumo-Cult.Perma.'!B24*('Critérios de Implantação'!D$53)),0)+IFERROR(('Resumo-Cult.Perma.'!A24*('Critérios de Implantação'!D$60)),0) -> 0 | E63: =IFERROR(('Resumo-Cult.Perma.'!D24*('Critérios de Implantação'!E$52)),0)+IFERROR(('Resumo-Cult.Perma.'!C24*('Critérios de Implantação'!E$53)),0)+IFERROR(('Resumo-Cult.Perma.'!B24*('Critérios de Implantação'!E$60)),0) -> 0 | F63: =IFERROR(('Resumo-Cult.Perma.'!C24*('Critérios de Implantação'!F$52)),0)+IFERROR(('Resumo-Cult.Perma.'!B24*('Critérios de Implantação'!F$53)),0)+IFERROR(('Resumo-Cult.Perma.'!A24*('Critérios de Implantação'!F$54)),0)+IFERROR(('Resumo-Cult.Perma.'!#REF!*('Critérios de Implantação'!F$55)),0)+IFERROR(('Resumo-Cult.Perma.'!#REF!*('Critérios de Implantação'!F$56)),0)+IFERROR(('Resumo-Cult.Perma.'!#REF!*('Critérios de Implantação'!F$57)),0)+IFERROR(('Resumo-Cult.Perma.'!#REF!*('Critérios de Implantação'!F$58)),0)+IFERROR(('Resumo-Cult.Perma.'!#REF!*('Critérios de Implantação'!F$59)),0)+IFERROR(('Resumo-Cult.Perma.'!#REF!*('Critérios de Implantação'!F$60)),0) -> 0 | G63: =IFERROR('Resumo-Cult.Perma.'!D24*'Critérios de Implantação'!G$52,0)+IFERROR('Resumo-Cult.Perma.'!C24*'Critérios de Implantação'!G$53,0)+IFERROR('Resumo-Cult.Perma.'!B24*'Critérios de Implantação'!$Q$54,0)+IFERROR('Resumo-Cult.Perma.'!A24*'Critérios de Implantação'!$Q$55,0)+IFERROR('Resumo-Cult.Perma.'!#REF!*'Critérios de Implantação'!$Q$56,0)+IFERROR('Resumo-Cult.Perma.'!#REF!*'Critérios de Implantação'!$Q$57,0)+IFERROR('Resumo-Cult.Perma.'!#REF!*'Critérios de Implantação'!$Q$58,0)+IFERROR('Resumo-Cult.Perma.'!#REF!*'Critérios de Implantação'!$Q$59,0)+IFERROR('Resumo-Cult.Perma.'!#REF!*'Critérios de Implantação'!$Q$60,0) -> 478716.37 | H63: =IFERROR('Resumo-Cult.Perma.'!E24*'Critérios de Implantação'!H$52,0)+IFERROR('Resumo-Cult.Perma.'!D24*'Critérios de Implantação'!H$53,0)+IFERROR('Resumo-Cult.Perma.'!C24*'Critérios de Implantação'!$Q$54,0)+IFERROR('Resumo-Cult.Perma.'!B24*'Critérios de Implantação'!$Q$55,0)+IFERROR('Resumo-Cult.Perma.'!A24*'Critérios de Implantação'!$Q$56,0)+IFERROR('Resumo-Cult.Perma.'!#REF!*'Critérios de Implantação'!$Q$57,0)+IFERROR('Resumo-Cult.Perma.'!#REF!*'Critérios de Implantação'!$Q$58,0)+IFERROR('Resumo-Cult.Perma.'!#REF!*'Critérios de Implantação'!$Q$59,0)+IFERROR('Resumo-Cult.Perma.'!#REF!*'Critérios de Implantação'!$Q$60,0) -> 970442.7 | I63: =IFERROR('Resumo-Cult.Perma.'!F24*'Critérios de Implantação'!I$52,0)+IFERROR('Resumo-Cult.Perma.'!E24*'Critérios de Implantação'!I$53,0)+IFERROR('Resumo-Cult.Perma.'!D24*'Critérios de Implantação'!$Q$54,0)+IFERROR('Resumo-Cult.Perma.'!C24*'Critérios de Implantação'!$Q$55,0)+IFERROR('Resumo-Cult.Perma.'!B24*'Critérios de Implantação'!$Q$56,0)+IFERROR('Resumo-Cult.Perma.'!A24*'Critérios de Implantação'!$Q$57,0)+IFERROR('Resumo-Cult.Perma.'!#REF!*'Critérios de Implantação'!$Q$58,0)+IFERROR('Resumo-Cult.Perma.'!#REF!*'Critérios de Implantação'!$Q$59,0)+IFERROR('Resumo-Cult.Perma.'!#REF!*'Critérios de Implantação'!$Q$60,0) -> 1558606.8 | J63: =IFERROR('Resumo-Cult.Perma.'!G24*'Critérios de Implantação'!J$52,0)+IFERROR('Resumo-Cult.Perma.'!F24*'Critérios de Implantação'!J$53,0)+IFERROR('Resumo-Cult.Perma.'!E24*'Critérios de Implantação'!$Q$54,0)+IFERROR('Resumo-Cult.Perma.'!D24*'Critérios de Implantação'!$Q$55,0)+IFERROR('Resumo-Cult.Perma.'!C24*'Critérios de Implantação'!$Q$56,0)+IFERROR('Resumo-Cult.Perma.'!B24*'Critérios de Implantação'!$Q$57,0)+IFERROR('Resumo-Cult.Perma.'!A24*'Critérios de Implantação'!$Q$58,0)+IFERROR('Resumo-Cult.Perma.'!#REF!*'Critérios de Implantação'!$Q$59,0)+IFERROR('Resumo-Cult.Perma.'!#REF!*'Critérios de Implantação'!$Q$60,0) -> 2698096.8 | K63: =IFERROR('Resumo-Cult.Perma.'!H24*'Critérios de Implantação'!K$52,0)+IFERROR('Resumo-Cult.Perma.'!G24*'Critérios de Implantação'!K$53,0)+IFERROR('Resumo-Cult.Perma.'!F24*'Critérios de Implantação'!$Q$54,0)+IFERROR('Resumo-Cult.Perma.'!E24*'Critérios de Implantação'!$Q$55,0)+IFERROR('Resumo-Cult.Perma.'!D24*'Critérios de Implantação'!$Q$56,0)+IFERROR('Resumo-Cult.Perma.'!C24*'Critérios de Implantação'!$Q$57,0)+IFERROR('Resumo-Cult.Perma.'!B24*'Critérios de Implantação'!$Q$58,0)+IFERROR('Resumo-Cult.Perma.'!A24*'Critérios de Implantação'!$Q$59,0)+IFERROR('Resumo-Cult.Perma.'!#REF!*'Critérios de Implantação'!$Q$60,0) -> 3783521.5 | L63: =IFERROR('Resumo-Cult.Perma.'!I24*'Critérios de Implantação'!L$52,0)+IFERROR('Resumo-Cult.Perma.'!H24*'Critérios de Implantação'!L$53,0)+IFERROR('Resumo-Cult.Perma.'!G24*'Critérios de Implantação'!$Q$54,0)+IFERROR('Resumo-Cult.Perma.'!F24*'Critérios de Implantação'!$Q$55,0)+IFERROR('Resumo-Cult.Perma.'!E24*'Critérios de Implantação'!$Q$56,0)+IFERROR('Resumo-Cult.Perma.'!D24*'Critérios de Implantação'!$Q$57,0)+IFERROR('Resumo-Cult.Perma.'!C24*'Critérios de Implantação'!$Q$58,0)+IFERROR('Resumo-Cult.Perma.'!B24*'Critérios de Implantação'!$Q$59,0)+IFERROR('Resumo-Cult.Perma.'!A24*'Critérios de Implantação'!$Q$60,0) -> 4925847.7 | M63: =IFERROR('Resumo-Cult.Perma.'!J24*'Critérios de Implantação'!M$52,0)+IFERROR('Resumo-Cult.Perma.'!I24*'Critérios de Implantação'!M$53,0)+IFERROR('Resumo-Cult.Perma.'!H24*'Critérios de Implantação'!$Q$54,0)+IFERROR('Resumo-Cult.Perma.'!G24*'Critérios de Implantação'!$Q$55,0)+IFERROR('Resumo-Cult.Perma.'!F24*'Critérios de Implantação'!$Q$56,0)+IFERROR('Resumo-Cult.Perma.'!E24*'Critérios de Implantação'!$Q$57,0)+IFERROR('Resumo-Cult.Perma.'!D24*'Critérios de Implantação'!$Q$58,0)+IFERROR('Resumo-Cult.Perma.'!C24*'Critérios de Implantação'!$Q$59,0)+IFERROR('Resumo-Cult.Perma.'!B24*'Critérios de Implantação'!$Q$60,0) -> 5884700.8 | N63: =IFERROR('Resumo-Cult.Perma.'!K24*'Critérios de Implantação'!N$52,0)+IFERROR('Resumo-Cult.Perma.'!J24*'Critérios de Implantação'!N$53,0)+IFERROR('Resumo-Cult.Perma.'!I24*'Critérios de Implantação'!$Q$54,0)+IFERROR('Resumo-Cult.Perma.'!H24*'Critérios de Implantação'!$Q$55,0)+IFERROR('Resumo-Cult.Perma.'!G24*'Critérios de Implantação'!$Q$56,0)+IFERROR('Resumo-Cult.Perma.'!F24*'Critérios de Implantação'!$Q$57,0)+IFERROR('Resumo-Cult.Perma.'!E24*'Critérios de Implantação'!$Q$58,0)+IFERROR('Resumo-Cult.Perma.'!D24*'Critérios de Implantação'!$Q$59,0)+IFERROR('Resumo-Cult.Perma.'!C24*'Critérios de Implantação'!$Q$60,0) -> 6587218.8 | O63: =IFERROR('Resumo-Cult.Perma.'!L24*'Critérios de Implantação'!O$52,0)+IFERROR('Resumo-Cult.Perma.'!K24*'Critérios de Implantação'!O$53,0)+IFERROR('Resumo-Cult.Perma.'!J24*'Critérios de Implantação'!$Q$54,0)+IFERROR('Resumo-Cult.Perma.'!I24*'Critérios de Implantação'!$Q$55,0)+IFERROR('Resumo-Cult.Perma.'!H24*'Critérios de Implantação'!$Q$56,0)+IFERROR('Resumo-Cult.Perma.'!G24*'Critérios de Implantação'!$Q$57,0)+IFERROR('Resumo-Cult.Perma.'!F24*'Critérios de Implantação'!$Q$58,0)+IFERROR('Resumo-Cult.Perma.'!E24*'Critérios de Implantação'!$Q$59,0)+IFERROR('Resumo-Cult.Perma.'!D24*'Critérios de Implantação'!$Q$60,0) -> 7005081 | P63: =IFERROR('Resumo-Cult.Perma.'!M24*'Critérios de Implantação'!P$52,0)+IFERROR('Resumo-Cult.Perma.'!L24*'Critérios de Implantação'!P$53,0)+IFERROR('Resumo-Cult.Perma.'!K24*'Critérios de Implantação'!$Q$54,0)+IFERROR('Resumo-Cult.Perma.'!J24*'Critérios de Implantação'!$Q$55,0)+IFERROR('Resumo-Cult.Perma.'!I24*'Critérios de Implantação'!$Q$56,0)+IFERROR('Resumo-Cult.Perma.'!H24*'Critérios de Implantação'!$Q$57,0)+IFERROR('Resumo-Cult.Perma.'!G24*'Critérios de Implantação'!$Q$58,0)+IFERROR('Resumo-Cult.Perma.'!F24*'Critérios de Implantação'!$Q$59,0)+IFERROR('Resumo-Cult.Perma.'!E24*'Critérios de Implantação'!$Q$60,0) -> 7093934.4 | Q63: =IFERROR('Resumo-Cult.Perma.'!N24*'Critérios de Implantação'!Q$52,0)+IFERROR('Resumo-Cult.Perma.'!M24*'Critérios de Implantação'!Q$53,0)+IFERROR('Resumo-Cult.Perma.'!L24*'Critérios de Implantação'!$Q$54,0)+IFERROR('Resumo-Cult.Perma.'!K24*'Critérios de Implantação'!$Q$55,0)+IFERROR('Resumo-Cult.Perma.'!J24*'Critérios de Implantação'!$Q$56,0)+IFERROR('Resumo-Cult.Perma.'!I24*'Critérios de Implantação'!$Q$57,0)+IFERROR('Resumo-Cult.Perma.'!H24*'Critérios de Implantação'!$Q$58,0)+IFERROR('Resumo-Cult.Perma.'!G24*'Critérios de Implantação'!$Q$59,0)+IFERROR('Resumo-Cult.Perma.'!F24*'Critérios de Implantação'!$Q$60,0) -> 7169048.1 | R63: =IFERROR('Resumo-Cult.Perma.'!O24*'Critérios de Implantação'!R$52,0)+IFERROR('Resumo-Cult.Perma.'!N24*'Critérios de Implantação'!R$53,0)+IFERROR('Resumo-Cult.Perma.'!M24*'Critérios de Implantação'!$Q$54,0)+IFERROR('Resumo-Cult.Perma.'!L24*'Critérios de Implantação'!$Q$55,0)+IFERROR('Resumo-Cult.Perma.'!K24*'Critérios de Implantação'!$Q$56,0)+IFERROR('Resumo-Cult.Perma.'!J24*'Critérios de Implantação'!$Q$57,0)+IFERROR('Resumo-Cult.Perma.'!I24*'Critérios de Implantação'!$Q$58,0)+IFERROR('Resumo-Cult.Perma.'!H24*'Critérios de Implantação'!$Q$59,0)+IFERROR('Resumo-Cult.Perma.'!G24*'Critérios de Implantação'!$Q$60,0) -> 7146932.1 | S63: =IFERROR('Resumo-Cult.Perma.'!P24*'Critérios de Implantação'!S$52,0)+IFERROR('Resumo-Cult.Perma.'!O24*'Critérios de Implantação'!S$53,0)+IFERROR('Resumo-Cult.Perma.'!N24*'Critérios de Implantação'!$Q$54,0)+IFERROR('Resumo-Cult.Perma.'!M24*'Critérios de Implantação'!$Q$55,0)+IFERROR('Resumo-Cult.Perma.'!L24*'Critérios de Implantação'!$Q$56,0)+IFERROR('Resumo-Cult.Perma.'!K24*'Critérios de Implantação'!$Q$57,0)+IFERROR('Resumo-Cult.Perma.'!J24*'Critérios de Implantação'!$Q$58,0)+IFERROR('Resumo-Cult.Perma.'!I24*'Critérios de Implantação'!$Q$59,0)+IFERROR('Resumo-Cult.Perma.'!H24*'Critérios de Implantação'!$Q$60,0) -> 7128547.6 | ... AK63: =IFERROR('Resumo-Cult.Perma.'!AH24*'Critérios de Implantação'!AK$52,0)+IFERROR('Resumo-Cult.Perma.'!AG24*'Critérios de Implantação'!AK$53,0)+IFERROR('Resumo-Cult.Perma.'!AF24*'Critérios de Implantação'!$Q$54,0)+IFERROR('Resumo-Cult.Perma.'!AE24*'Critérios de Implantação'!$Q$55,0)+IFERROR('Resumo-Cult.Perma.'!AD24*'Critérios de Implantação'!$Q$56,0)+IFERROR('Resumo-Cult.Perma.'!AC24*'Critérios de Implantação'!$Q$57,0)+IFERROR('Resumo-Cult.Perma.'!AB24*'Critérios de Implantação'!$Q$58,0)+IFERROR('Resumo-Cult.Perma.'!AA24*'Critérios de Implantação'!$Q$59,0)+IFERROR('Resumo-Cult.Perma.'!Z24*'Critérios de Implantação'!$Q$60,0) -> 6815615.3
B64: Sub-total - custos operacionais | D64: =SUM(D60:D63) -> 0 | E64: =SUM(E60:E63) -> 0 | F64: =SUM(F60:F63) -> 0 | G64: =SUM(G60:G63) -> 4910437.7 | H64: =SUM(H60:H63) -> 9659665.2 | I64: =SUM(I60:I63) -> 15288199 | J64: =SUM(J60:J63) -> 26237610 | K64: =SUM(K60:K63) -> 36273493 | ... AK64: =SUM(AK60:AK63) -> 64772769
A66: 3 | B66: ENTRADA - VALOR DA PRODUÇÃO
A67: 3.1 | B67: ="Valor da produção "&A43 -> Valor da produção Banana Nanica | D67: =IFERROR(('Resumo-Cult.Perma.'!A28*('Critérios de Implantação'!D$52)),0)+IFERROR(('Resumo-Cult.Perma.'!#REF!*('Critérios de Implantação'!D$53)),0)+IFERROR(('Resumo-Cult.Perma.'!#REF!*('Critérios de Implantação'!D$54)),0)+IFERROR(('Resumo-Cult.Perma.'!#REF!*('Critérios de Implantação'!D$55)),0)+IFERROR(('Resumo-Cult.Perma.'!#REF!*('Critérios de Implantação'!D$56)),0)+IFERROR(('Resumo-Cult.Perma.'!#REF!*('Critérios de Implantação'!D$57)),0)+IFERROR(('Resumo-Cult.Perma.'!#REF!*('Critérios de Implantação'!D$58)),0)+IFERROR(('Resumo-Cult.Perma.'!#REF!*('Critérios de Implantação'!D$59)),0)+IFERROR(('Resumo-Cult.Perma.'!#REF!*('Critérios de Implantação'!D$60)),0) -> 0 | E67: =IFERROR(('Resumo-Cult.Perma.'!B28*('Critérios de Implantação'!E$52)),0)+IFERROR(('Resumo-Cult.Perma.'!A28*('Critérios de Implantação'!E$53)),0)+IFERROR(('Resumo-Cult.Perma.'!#REF!*('Critérios de Implantação'!E$54)),0)+IFERROR(('Resumo-Cult.Perma.'!#REF!*('Critérios de Implantação'!E$55)),0)+IFERROR(('Resumo-Cult.Perma.'!#REF!*('Critérios de Implantação'!E$56)),0)+IFERROR(('Resumo-Cult.Perma.'!#REF!*('Critérios de Implantação'!E$57)),0)+IFERROR(('Resumo-Cult.Perma.'!#REF!*('Critérios de Implantação'!E$58)),0)+IFERROR(('Resumo-Cult.Perma.'!#REF!*('Critérios de Implantação'!E$59)),0)+IFERROR(('Resumo-Cult.Perma.'!#REF!*('Critérios de Implantação'!E$60)),0) -> 0 | F67: =IFERROR(('Resumo-Cult.Perma.'!C28*('Critérios de Implantação'!F$52)),0)+IFERROR(('Resumo-Cult.Perma.'!B28*('Critérios de Implantação'!F$53)),0)+IFERROR(('Resumo-Cult.Perma.'!A28*('Critérios de Implantação'!F$54)),0)+IFERROR(('Resumo-Cult.Perma.'!#REF!*('Critérios de Implantação'!F$55)),0)+IFERROR(('Resumo-Cult.Perma.'!#REF!*('Critérios de Implantação'!F$56)),0)+IFERROR(('Resumo-Cult.Perma.'!#REF!*('Critérios de Implantação'!F$57)),0)+IFERROR(('Resumo-Cult.Perma.'!#REF!*('Critérios de Implantação'!F$58)),0)+IFERROR(('Resumo-Cult.Perma.'!#REF!*('Critérios de Implantação'!F$59)),0)+IFERROR(('Resumo-Cult.Perma.'!#REF!*('Critérios de Implantação'!F$60)),0) -> 0 | G67: =IFERROR(('Resumo-Cult.Perma.'!D28*('Critérios de Implantação'!G$52)),0)+IFERROR(('Resumo-Cult.Perma.'!C28*('Critérios de Implantação'!G$53)),0)+IFERROR(('Resumo-Cult.Perma.'!B28*('Critérios de Implantação'!G$54)),0)+IFERROR(('Resumo-Cult.Perma.'!A28*('Critérios de Implantação'!G$55)),0)+IFERROR(('Resumo-Cult.Perma.'!#REF!*('Critérios de Implantação'!G$56)),0)+IFERROR(('Resumo-Cult.Perma.'!#REF!*('Critérios de Implantação'!G$57)),0)+IFERROR(('Resumo-Cult.Perma.'!#REF!*('Critérios de Implantação'!G$58)),0)+IFERROR(('Resumo-Cult.Perma.'!#REF!*('Critérios de Implantação'!G$59)),0)+IFERROR(('Resumo-Cult.Perma.'!#REF!*('Critérios de Implantação'!G$60)),0) -> 11074420 | H67: =IFERROR(('Resumo-Cult.Perma.'!E28*('Critérios de Implantação'!H$52)),0)+IFERROR(('Resumo-Cult.Perma.'!D28*('Critérios de Implantação'!H$53)),0)+IFERROR(('Resumo-Cult.Perma.'!C28*('Critérios de Implantação'!H$54)),0)+IFERROR(('Resumo-Cult.Perma.'!B28*('Critérios de Implantação'!H$55)),0)+IFERROR(('Resumo-Cult.Perma.'!A28*('Critérios de Implantação'!H$56)),0)+IFERROR(('Resumo-Cult.Perma.'!#REF!*('Critérios de Implantação'!H$57)),0)+IFERROR(('Resumo-Cult.Perma.'!#REF!*('Critérios de Implantação'!H$58)),0)+IFERROR(('Resumo-Cult.Perma.'!#REF!*('Critérios de Implantação'!H$59)),0)+IFERROR(('Resumo-Cult.Perma.'!#REF!*('Critérios de Implantação'!H$60)),0) -> 21456689 | I67: =IFERROR(('Resumo-Cult.Perma.'!F28*('Critérios de Implantação'!I$52)),0)+IFERROR(('Resumo-Cult.Perma.'!E28*('Critérios de Implantação'!I$53)),0)+IFERROR(('Resumo-Cult.Perma.'!D28*('Critérios de Implantação'!I$54)),0)+IFERROR(('Resumo-Cult.Perma.'!C28*('Critérios de Implantação'!I$55)),0)+IFERROR(('Resumo-Cult.Perma.'!B28*('Critérios de Implantação'!I$56)),0)+IFERROR(('Resumo-Cult.Perma.'!A28*('Critérios de Implantação'!I$57)),0)+IFERROR(('Resumo-Cult.Perma.'!#REF!*('Critérios de Implantação'!I$58)),0)+IFERROR(('Resumo-Cult.Perma.'!#REF!*('Critérios de Implantação'!I$59)),0)+IFERROR(('Resumo-Cult.Perma.'!#REF!*('Critérios de Implantação'!I$60)),0) -> 33377757 | J67: =IFERROR(('Resumo-Cult.Perma.'!G28*('Critérios de Implantação'!J$52)),0)+IFERROR(('Resumo-Cult.Perma.'!F28*('Critérios de Implantação'!J$53)),0)+IFERROR(('Resumo-Cult.Perma.'!E28*('Critérios de Implantação'!J$54)),0)+IFERROR(('Resumo-Cult.Perma.'!D28*('Critérios de Implantação'!J$55)),0)+IFERROR(('Resumo-Cult.Perma.'!C28*('Critérios de Implantação'!J$56)),0)+IFERROR(('Resumo-Cult.Perma.'!B28*('Critérios de Implantação'!J$57)),0)+IFERROR(('Resumo-Cult.Perma.'!A28*('Critérios de Implantação'!J$58)),0)+IFERROR(('Resumo-Cult.Perma.'!#REF!*('Critérios de Implantação'!J$59)),0)+IFERROR(('Resumo-Cult.Perma.'!#REF!*('Critérios de Implantação'!J$60)),0) -> 57551932 | K67: =IFERROR(('Resumo-Cult.Perma.'!H28*('Critérios de Implantação'!K$52)),0)+IFERROR(('Resumo-Cult.Perma.'!G28*('Critérios de Implantação'!K$53)),0)+IFERROR(('Resumo-Cult.Perma.'!F28*('Critérios de Implantação'!K$54)),0)+IFERROR(('Resumo-Cult.Perma.'!E28*('Critérios de Implantação'!K$55)),0)+IFERROR(('Resumo-Cult.Perma.'!D28*('Critérios de Implantação'!K$56)),0)+IFERROR(('Resumo-Cult.Perma.'!C28*('Critérios de Implantação'!K$57)),0)+IFERROR(('Resumo-Cult.Perma.'!B28*('Critérios de Implantação'!K$58)),0)+IFERROR(('Resumo-Cult.Perma.'!A28*('Critérios de Implantação'!K$59)),0)+IFERROR(('Resumo-Cult.Perma.'!#REF!*('Critérios de Implantação'!K$60)),0) -> 79224626 | L67: =IFERROR(('Resumo-Cult.Perma.'!I28*('Critérios de Implantação'!L$52)),0)+IFERROR(('Resumo-Cult.Perma.'!H28*('Critérios de Implantação'!L$53)),0)+IFERROR(('Resumo-Cult.Perma.'!G28*('Critérios de Implantação'!L$54)),0)+IFERROR(('Resumo-Cult.Perma.'!F28*('Critérios de Implantação'!L$55)),0)+IFERROR(('Resumo-Cult.Perma.'!E28*('Critérios de Implantação'!L$56)),0)+IFERROR(('Resumo-Cult.Perma.'!D28*('Critérios de Implantação'!L$57)),0)+IFERROR(('Resumo-Cult.Perma.'!C28*('Critérios de Implantação'!L$58)),0)+IFERROR(('Resumo-Cult.Perma.'!B28*('Critérios de Implantação'!L$59)),0)+IFERROR(('Resumo-Cult.Perma.'!A28*('Critérios de Implantação'!L$60)),0) -> 1.0022677e+08 | M67: =IFERROR(('Resumo-Cult.Perma.'!J28*('Critérios de Implantação'!M$52)),0)+IFERROR(('Resumo-Cult.Perma.'!I28*('Critérios de Implantação'!M$53)),0)+IFERROR(('Resumo-Cult.Perma.'!H28*('Critérios de Implantação'!M$54)),0)+IFERROR(('Resumo-Cult.Perma.'!G28*('Critérios de Implantação'!M$55)),0)+IFERROR(('Resumo-Cult.Perma.'!F28*('Critérios de Implantação'!M$56)),0)+IFERROR(('Resumo-Cult.Perma.'!E28*('Critérios de Implantação'!M$57)),0)+IFERROR(('Resumo-Cult.Perma.'!D28*('Critérios de Implantação'!M$58)),0)+IFERROR(('Resumo-Cult.Perma.'!C28*('Critérios de Implantação'!M$59)),0)+IFERROR(('Resumo-Cult.Perma.'!B28*('Critérios de Implantação'!M$60)),0) -> 1.1668446e+08 | N67: =IFERROR(('Resumo-Cult.Perma.'!K28*('Critérios de Implantação'!N$52)),0)+IFERROR(('Resumo-Cult.Perma.'!J28*('Critérios de Implantação'!N$53)),0)+IFERROR(('Resumo-Cult.Perma.'!I28*('Critérios de Implantação'!N$54)),0)+IFERROR(('Resumo-Cult.Perma.'!H28*('Critérios de Implantação'!N$55)),0)+IFERROR(('Resumo-Cult.Perma.'!G28*('Critérios de Implantação'!N$56)),0)+IFERROR(('Resumo-Cult.Perma.'!F28*('Critérios de Implantação'!N$57)),0)+IFERROR(('Resumo-Cult.Perma.'!E28*('Critérios de Implantação'!N$58)),0)+IFERROR(('Resumo-Cult.Perma.'!D28*('Critérios de Implantação'!N$59)),0)+IFERROR(('Resumo-Cult.Perma.'!C28*('Critérios de Implantação'!N$60)),0) -> 1.2528716e+08 | O67: =IFERROR(('Resumo-Cult.Perma.'!L28*('Critérios de Implantação'!O$52)),0)+IFERROR(('Resumo-Cult.Perma.'!K28*('Critérios de Implantação'!O$53)),0)+IFERROR(('Resumo-Cult.Perma.'!J28*('Critérios de Implantação'!O$54)),0)+IFERROR(('Resumo-Cult.Perma.'!I28*('Critérios de Implantação'!O$55)),0)+IFERROR(('Resumo-Cult.Perma.'!H28*('Critérios de Implantação'!O$56)),0)+IFERROR(('Resumo-Cult.Perma.'!G28*('Critérios de Implantação'!O$57)),0)+IFERROR(('Resumo-Cult.Perma.'!F28*('Critérios de Implantação'!O$58)),0)+IFERROR(('Resumo-Cult.Perma.'!E28*('Critérios de Implantação'!O$59)),0)+IFERROR(('Resumo-Cult.Perma.'!D28*('Critérios de Implantação'!O$60)),0) -> 1.2596064e+08 | P67: =IFERROR(('Resumo-Cult.Perma.'!M28*('Critérios de Implantação'!P$52)),0)+IFERROR(('Resumo-Cult.Perma.'!L28*('Critérios de Implantação'!P$53)),0)+IFERROR(('Resumo-Cult.Perma.'!K28*('Critérios de Implantação'!P$54)),0)+IFERROR(('Resumo-Cult.Perma.'!J28*('Critérios de Implantação'!P$55)),0)+IFERROR(('Resumo-Cult.Perma.'!I28*('Critérios de Implantação'!P$56)),0)+IFERROR(('Resumo-Cult.Perma.'!H28*('Critérios de Implantação'!P$57)),0)+IFERROR(('Resumo-Cult.Perma.'!G28*('Critérios de Implantação'!P$58)),0)+IFERROR(('Resumo-Cult.Perma.'!F28*('Critérios de Implantação'!P$59)),0)+IFERROR(('Resumo-Cult.Perma.'!E28*('Critérios de Implantação'!P$60)),0) -> 1.1992117e+08 | Q67: =IFERROR(('Resumo-Cult.Perma.'!N28*('Critérios de Implantação'!Q$52)),0)+IFERROR(('Resumo-Cult.Perma.'!M28*('Critérios de Implantação'!Q$53)),0)+IFERROR(('Resumo-Cult.Perma.'!L28*('Critérios de Implantação'!Q$54)),0)+IFERROR(('Resumo-Cult.Perma.'!K28*('Critérios de Implantação'!Q$55)),0)+IFERROR(('Resumo-Cult.Perma.'!J28*('Critérios de Implantação'!Q$56)),0)+IFERROR(('Resumo-Cult.Perma.'!I28*('Critérios de Implantação'!Q$57)),0)+IFERROR(('Resumo-Cult.Perma.'!H28*('Critérios de Implantação'!Q$58)),0)+IFERROR(('Resumo-Cult.Perma.'!G28*('Critérios de Implantação'!Q$59)),0)+IFERROR(('Resumo-Cult.Perma.'!F28*('Critérios de Implantação'!Q$60)),0) -> 1.1157822e+08 | R67: =IFERROR(('Resumo-Cult.Perma.'!O28*('Critérios de Implantação'!R$52)),0)+IFERROR(('Resumo-Cult.Perma.'!N28*('Critérios de Implantação'!R$53)),0)+IFERROR(('Resumo-Cult.Perma.'!M28*('Critérios de Implantação'!R$54)),0)+IFERROR(('Resumo-Cult.Perma.'!L28*('Critérios de Implantação'!R$55)),0)+IFERROR(('Resumo-Cult.Perma.'!K28*('Critérios de Implantação'!R$56)),0)+IFERROR(('Resumo-Cult.Perma.'!J28*('Critérios de Implantação'!R$57)),0)+IFERROR(('Resumo-Cult.Perma.'!I28*('Critérios de Implantação'!R$58)),0)+IFERROR(('Resumo-Cult.Perma.'!H28*('Critérios de Implantação'!R$59)),0)+IFERROR(('Resumo-Cult.Perma.'!G28*('Critérios de Implantação'!R$60)),0) -> 97959087 | S67: =IFERROR(('Resumo-Cult.Perma.'!P28*('Critérios de Implantação'!S$52)),0)+IFERROR(('Resumo-Cult.Perma.'!O28*('Critérios de Implantação'!S$53)),0)+IFERROR(('Resumo-Cult.Perma.'!N28*('Critérios de Implantação'!S$54)),0)+IFERROR(('Resumo-Cult.Perma.'!M28*('Critérios de Implantação'!S$55)),0)+IFERROR(('Resumo-Cult.Perma.'!L28*('Critérios de Implantação'!S$56)),0)+IFERROR(('Resumo-Cult.Perma.'!K28*('Critérios de Implantação'!S$57)),0)+IFERROR(('Resumo-Cult.Perma.'!J28*('Critérios de Implantação'!S$58)),0)+IFERROR(('Resumo-Cult.Perma.'!I28*('Critérios de Implantação'!S$59)),0)+IFERROR(('Resumo-Cult.Perma.'!H28*('Critérios de Implantação'!S$60)),0) -> 95611180 | ... AK67: =IFERROR(('Resumo-Cult.Perma.'!AH28*('Critérios de Implantação'!AK$52)),0)+IFERROR(('Resumo-Cult.Perma.'!AG28*('Critérios de Implantação'!AK$53)),0)+IFERROR(('Resumo-Cult.Perma.'!AF28*('Critérios de Implantação'!AK$54)),0)+IFERROR(('Resumo-Cult.Perma.'!AE28*('Critérios de Implantação'!AK$55)),0)+IFERROR(('Resumo-Cult.Perma.'!AD28*('Critérios de Implantação'!AK$56)),0)+IFERROR(('Resumo-Cult.Perma.'!AC28*('Critérios de Implantação'!AK$57)),0)+IFERROR(('Resumo-Cult.Perma.'!AB28*('Critérios de Implantação'!AK$58)),0)+IFERROR(('Resumo-Cult.Perma.'!AA28*('Critérios de Implantação'!AK$59)),0)+IFERROR(('Resumo-Cult.Perma.'!Z28*('Critérios de Implantação'!AK$60)),0) -> 1.2028766e+08
B68: Sub-total - valor da produção | D68: =SUM(D67:D67) -> 0 | E68: =SUM(E67:E67) -> 0 | F68: =SUM(F67:F67) -> 0 | G68: =SUM(G67:G67) -> 11074420 | H68: =SUM(H67:H67) -> 21456689 | I68: =SUM(I67:I67) -> 33377757 | J68: =SUM(J67:J67) -> 57551932 | K68: =SUM(K67:K67) -> 79224626 | ... AK68: =SUM(AK67:AK67) -> 1.2028766e+08
A70: 4 | B70: BALANÇO Anual (Item 3 - item 1 - item 2) | D70: =D68-D64-D57 -> 0 | E70: =E68-E64-E57 -> 0 | F70: =F68-F64-F57 -> -10865178 | G70: =G68-G64-G57 -> -4701195.6 | H70: =H68-H64-H57 -> -1256952 | I70: =I68-I64-I57 -> -7122814.4 | J70: =J68-J64-J57 -> 7659469.3 | K70: =K68-K64-K57 -> 18612533 | ... AK70: =AK68-AK64-AK57 -> 55514894
A72: 5 | B72: BALANÇO ACUMULADO | D72: =D70 -> 0 | E72: =D72+E70 -> 0 | F72: =E72+F70 -> -10865178 | G72: =F72+G70 -> -15566374 | H72: =G72+H70 -> -16823326 | I72: =H72+I70 -> -23946140 | J72: =I72+J70 -> -16286671 | K72: =J72+K70 -> 2325861.9 | L72: =K72+L70 -> 36306957 | ... AK72: =AJ72+AK70 -> 1.1564316e+09
A74: Banana Prata
A75: Planejamento Banana Prata
A76: ITEM | B76: COMPONENTES | C76: ANO DE IMPLANTAÇÃO DA CULTURA
C77: 1 | D77: =C77+1 -> 2 | E77: =D77+1 -> 3 | F77: =E77+1 -> 4 | G77: =F77+1 -> 5 | H77: =G77+1 -> 6 | I77: =H77+1 -> 7 | J77: =I77+1 -> 8 | K77: =J77+1 -> 9 | ... AK77: =AJ77+1 -> 35
A78: 1 | B78: INVESTIMENTOS
A79: 1.1 | B79: Supressão vegetal | D79: ='Critérios de Implantação'!D$32*'Resumo-Cult.Perma.'!$C42 -> 0 | E79: ='Critérios de Implantação'!E$32*'Resumo-Cult.Perma.'!$C42 -> 0 | F79: ='Critérios de Implantação'!F$32*'Resumo-Cult.Perma.'!$C42 -> 81416.426 | G79: ='Critérios de Implantação'!G$32*'Resumo-Cult.Perma.'!$C42 -> 81416.426 | H79: ='Critérios de Implantação'!H$32*'Resumo-Cult.Perma.'!$C42 -> 97817.822 | I79: ='Critérios de Implantação'!I$32*'Resumo-Cult.Perma.'!$C42 -> 188924.76 | J79: ='Critérios de Implantação'!J$32*'Resumo-Cult.Perma.'!$C42 -> 177253.75 | K79: ='Critérios de Implantação'!K$32*'Resumo-Cult.Perma.'!$C42 -> 182377.3 | ... AK79: ='Critérios de Implantação'!AK$32*'Resumo-Cult.Perma.'!$C42 -> 0
A80: 1.2 | B80: Sistema de irrigação localizada | D80: ='Critérios de Implantação'!D$32*'Resumo-Cult.Perma.'!$C43 -> 0 | E80: ='Critérios de Implantação'!E$32*'Resumo-Cult.Perma.'!$C43 -> 0 | F80: ='Critérios de Implantação'!F$32*'Resumo-Cult.Perma.'!$C43 -> 1416021.4 | G80: ='Critérios de Implantação'!G$32*'Resumo-Cult.Perma.'!$C43 -> 1416021.4 | H80: ='Critérios de Implantação'!H$32*'Resumo-Cult.Perma.'!$C43 -> 1701279.9 | I80: ='Critérios de Implantação'!I$32*'Resumo-Cult.Perma.'!$C43 -> 3285842 | J80: ='Critérios de Implantação'!J$32*'Resumo-Cult.Perma.'!$C43 -> 3082855.9 | K80: ='Critérios de Implantação'!K$32*'Resumo-Cult.Perma.'!$C43 -> 3171966.3 | ... AK80: ='Critérios de Implantação'!AK$32*'Resumo-Cult.Perma.'!$C43 -> 0
A81: 1.3 | B81: Sistema de irrigação pivô central | D81: ='Critérios de Implantação'!D$32*'Resumo-Cult.Perma.'!$C44 -> 0 | E81: ='Critérios de Implantação'!E$32*'Resumo-Cult.Perma.'!$C44 -> 0 | F81: ='Critérios de Implantação'!F$32*'Resumo-Cult.Perma.'!$C44 -> 0 | G81: ='Critérios de Implantação'!G$32*'Resumo-Cult.Perma.'!$C44 -> 0 | H81: ='Critérios de Implantação'!H$32*'Resumo-Cult.Perma.'!$C44 -> 0 | I81: ='Critérios de Implantação'!I$32*'Resumo-Cult.Perma.'!$C44 -> 0 | J81: ='Critérios de Implantação'!J$32*'Resumo-Cult.Perma.'!$C44 -> 0 | K81: ='Critérios de Implantação'!K$32*'Resumo-Cult.Perma.'!$C44 -> 0 | ... AK81: ='Critérios de Implantação'!AK$32*'Resumo-Cult.Perma.'!$C44 -> 0
A82: 1.4 | B82: Demais infraestrutura | D82: ='Critérios de Implantação'!D$32*'Resumo-Cult.Perma.'!$C45 -> 0 | E82: ='Critérios de Implantação'!E$32*'Resumo-Cult.Perma.'!$C45 -> 0 | F82: ='Critérios de Implantação'!F$32*'Resumo-Cult.Perma.'!$C45 -> 1475078.9 | G82: ='Critérios de Implantação'!G$32*'Resumo-Cult.Perma.'!$C45 -> 1475078.9 | H82: ='Critérios de Implantação'!H$32*'Resumo-Cult.Perma.'!$C45 -> 1772234.6 | I82: ='Critérios de Implantação'!I$32*'Resumo-Cult.Perma.'!$C45 -> 3422883.5 | J82: ='Critérios de Implantação'!J$32*'Resumo-Cult.Perma.'!$C45 -> 3211431.5 | K82: ='Critérios de Implantação'!K$32*'Resumo-Cult.Perma.'!$C45 -> 3304258.5 | ... AK82: ='Critérios de Implantação'!AK$32*'Resumo-Cult.Perma.'!$C45 -> 0
B83: Ano de formação da cultura | D83: ='Critérios de Implantação'!D$32*'Resumo-Cult.Perma.'!$C46 -> 0 | E83: ='Critérios de Implantação'!E$32*'Resumo-Cult.Perma.'!$C46 -> 0 | F83: ='Critérios de Implantação'!F$32*'Resumo-Cult.Perma.'!$C46 -> 0 | G83: ='Critérios de Implantação'!G$32*'Resumo-Cult.Perma.'!$C46 -> 0 | H83: ='Critérios de Implantação'!H$32*'Resumo-Cult.Perma.'!$C46 -> 0 | I83: ='Critérios de Implantação'!I$32*'Resumo-Cult.Perma.'!$C46 -> 0 | J83: ='Critérios de Implantação'!J$32*'Resumo-Cult.Perma.'!$C46 -> 0 | K83: ='Critérios de Implantação'!K$32*'Resumo-Cult.Perma.'!$C46 -> 0 | ... AK83: ='Critérios de Implantação'!AK$32*'Resumo-Cult.Perma.'!$C46 -> 0
A84: 1.5 | B84: Gasto com insumos | D84: ='Critérios de Implantação'!D$32*'Resumo-Cult.Perma.'!$C47 -> 0 | E84: ='Critérios de Implantação'!E$32*'Resumo-Cult.Perma.'!$C47 -> 0 | F84: ='Critérios de Implantação'!F$32*'Resumo-Cult.Perma.'!$C47 -> 998474.58 | G84: ='Critérios de Implantação'!G$32*'Resumo-Cult.Perma.'!$C47 -> 998474.58 | H84: ='Critérios de Implantação'!H$32*'Resumo-Cult.Perma.'!$C47 -> 1199618 | I84: ='Critérios de Implantação'!I$32*'Resumo-Cult.Perma.'!$C47 -> 2316935.1 | J84: ='Critérios de Implantação'!J$32*'Resumo-Cult.Perma.'!$C47 -> 2173804.2 | K84: ='Critérios de Implantação'!K$32*'Resumo-Cult.Perma.'!$C47 -> 2236638.3 | ... AK84: ='Critérios de Implantação'!AK$32*'Resumo-Cult.Perma.'!$C47 -> 0
A85: 1.6 | B85: Gasto com mão de obra | D85: ='Critérios de Implantação'!D$32*'Resumo-Cult.Perma.'!$C48 -> 0 | E85: ='Critérios de Implantação'!E$32*'Resumo-Cult.Perma.'!$C48 -> 0 | F85: ='Critérios de Implantação'!F$32*'Resumo-Cult.Perma.'!$C48 -> 489125.26 | G85: ='Critérios de Implantação'!G$32*'Resumo-Cult.Perma.'!$C48 -> 489125.26 | H85: ='Critérios de Implantação'!H$32*'Resumo-Cult.Perma.'!$C48 -> 587659.89 | I85: ='Critérios de Implantação'!I$32*'Resumo-Cult.Perma.'!$C48 -> 1135002.8 | J85: ='Critérios de Implantação'!J$32*'Resumo-Cult.Perma.'!$C48 -> 1064886.9 | K85: ='Critérios de Implantação'!K$32*'Resumo-Cult.Perma.'!$C48 -> 1095667.7 | ... AK85: ='Critérios de Implantação'!AK$32*'Resumo-Cult.Perma.'!$C48 -> 0
A86: 1.7 | B86: Gasto com trator e equipamentos e avaição agrícola | D86: ='Critérios de Implantação'!D$32*'Resumo-Cult.Perma.'!$C49 -> 0 | E86: ='Critérios de Implantação'!E$32*'Resumo-Cult.Perma.'!$C49 -> 0 | F86: ='Critérios de Implantação'!F$32*'Resumo-Cult.Perma.'!$C49 -> 480503.26 | G86: ='Critérios de Implantação'!G$32*'Resumo-Cult.Perma.'!$C49 -> 480503.26 | H86: ='Critérios de Implantação'!H$32*'Resumo-Cult.Perma.'!$C49 -> 577300.99 | I86: ='Critérios de Implantação'!I$32*'Resumo-Cult.Perma.'!$C49 -> 1114995.7 | J86: ='Critérios de Implantação'!J$32*'Resumo-Cult.Perma.'!$C49 -> 1046115.8 | K86: ='Critérios de Implantação'!K$32*'Resumo-Cult.Perma.'!$C49 -> 1076353.9 | ... AK86: ='Critérios de Implantação'!AK$32*'Resumo-Cult.Perma.'!$C49 -> 0
A87: 1.8 | B87: Outros custos | D87: ='Critérios de Implantação'!D$32*'Resumo-Cult.Perma.'!$C50 -> 0 | E87: ='Critérios de Implantação'!E$32*'Resumo-Cult.Perma.'!$C50 -> 0 | F87: ='Critérios de Implantação'!F$32*'Resumo-Cult.Perma.'!$C50 -> 251498.04 | G87: ='Critérios de Implantação'!G$32*'Resumo-Cult.Perma.'!$C50 -> 251498.04 | H87: ='Critérios de Implantação'!H$32*'Resumo-Cult.Perma.'!$C50 -> 302162.5 | I87: ='Critérios de Implantação'!I$32*'Resumo-Cult.Perma.'!$C50 -> 583594.86 | J87: ='Critérios de Implantação'!J$32*'Resumo-Cult.Perma.'!$C50 -> 547542.72 | K87: ='Critérios de Implantação'!K$32*'Resumo-Cult.Perma.'!$C50 -> 563369.53 | ... AK87: ='Critérios de Implantação'!AK$32*'Resumo-Cult.Perma.'!$C50 -> 0
B88: Sub-total - Investimentos | D88: =SUM(D79:D87) -> 0 | E88: =SUM(E79:E87) -> 0 | F88: =SUM(F79:F87) -> 5192117.9 | G88: =SUM(G79:G87) -> 5192117.9 | H88: =SUM(H79:H87) -> 6238073.7 | I88: =SUM(I79:I87) -> 12048179 | J88: =SUM(J79:J87) -> 11303891 | K88: =SUM(K79:K87) -> 11630631 | ... AK88: =SUM(AK79:AK87) -> 0
A90: 2 | B90: CUSTOS OPERACIONAIS
A91: 2.1 | B91: Gasto com insumos | D91: =IFERROR('Resumo-Cult.Perma.'!A54*'Critérios de Implantação'!D$61,0)+IFERROR('Resumo-Cult.Perma.'!#REF!*'Critérios de Implantação'!D$62,0)+IFERROR('Resumo-Cult.Perma.'!#REF!*'Critérios de Implantação'!$Q$63,0)+IFERROR('Resumo-Cult.Perma.'!#REF!*'Critérios de Implantação'!$Q$64,0)+IFERROR('Resumo-Cult.Perma.'!#REF!*'Critérios de Implantação'!$Q$65,0)+IFERROR('Resumo-Cult.Perma.'!#REF!*'Critérios de Implantação'!$Q$66,0)+IFERROR('Resumo-Cult.Perma.'!#REF!*'Critérios de Implantação'!$Q$67,0)+IFERROR('Resumo-Cult.Perma.'!#REF!*'Critérios de Implantação'!$Q$68,0)+IFERROR('Resumo-Cult.Perma.'!#REF!*'Critérios de Implantação'!$Q$69,0) -> 0 | E91: =IFERROR('Resumo-Cult.Perma.'!B54*'Critérios de Implantação'!E$61,0)+IFERROR('Resumo-Cult.Perma.'!A54*'Critérios de Implantação'!E$62,0)+IFERROR('Resumo-Cult.Perma.'!#REF!*'Critérios de Implantação'!$Q$63,0)+IFERROR('Resumo-Cult.Perma.'!#REF!*'Critérios de Implantação'!$Q$64,0)+IFERROR('Resumo-Cult.Perma.'!#REF!*'Critérios de Implantação'!$Q$65,0)+IFERROR('Resumo-Cult.Perma.'!#REF!*'Critérios de Implantação'!$Q$66,0)+IFERROR('Resumo-Cult.Perma.'!#REF!*'Critérios de Implantação'!$Q$67,0)+IFERROR('Resumo-Cult.Perma.'!#REF!*'Critérios de Implantação'!$Q$68,0)+IFERROR('Resumo-Cult.Perma.'!#REF!*'Critérios de Implantação'!$Q$69,0) -> 0 | F91: =IFERROR('Resumo-Cult.Perma.'!C54*'Critérios de Implantação'!F$61,0)+IFERROR('Resumo-Cult.Perma.'!B54*'Critérios de Implantação'!F$62,0)+IFERROR('Resumo-Cult.Perma.'!A54*'Critérios de Implantação'!$Q$63,0)+IFERROR('Resumo-Cult.Perma.'!#REF!*'Critérios de Implantação'!$Q$64,0)+IFERROR('Resumo-Cult.Perma.'!#REF!*'Critérios de Implantação'!$Q$65,0)+IFERROR('Resumo-Cult.Perma.'!#REF!*'Critérios de Implantação'!$Q$66,0)+IFERROR('Resumo-Cult.Perma.'!#REF!*'Critérios de Implantação'!$Q$67,0)+IFERROR('Resumo-Cult.Perma.'!#REF!*'Critérios de Implantação'!$Q$68,0)+IFERROR('Resumo-Cult.Perma.'!#REF!*'Critérios de Implantação'!$Q$69,0) -> 0 | G91: =IFERROR('Resumo-Cult.Perma.'!D54*'Critérios de Implantação'!G$61,0)+IFERROR('Resumo-Cult.Perma.'!C54*'Critérios de Implantação'!G$62,0)+IFERROR('Resumo-Cult.Perma.'!B54*'Critérios de Implantação'!$Q$63,0)+IFERROR('Resumo-Cult.Perma.'!A54*'Critérios de Implantação'!$Q$64,0)+IFERROR('Resumo-Cult.Perma.'!#REF!*'Critérios de Implantação'!$Q$65,0)+IFERROR('Resumo-Cult.Perma.'!#REF!*'Critérios de Implantação'!$Q$66,0)+IFERROR('Resumo-Cult.Perma.'!#REF!*'Critérios de Implantação'!$Q$67,0)+IFERROR('Resumo-Cult.Perma.'!#REF!*'Critérios de Implantação'!$Q$68,0)+IFERROR('Resumo-Cult.Perma.'!#REF!*'Critérios de Implantação'!$Q$69,0) -> 633144.83 | H91: =IFERROR('Resumo-Cult.Perma.'!E54*'Critérios de Implantação'!H$61,0)+IFERROR('Resumo-Cult.Perma.'!D54*'Critérios de Implantação'!H$62,0)+IFERROR('Resumo-Cult.Perma.'!C54*'Critérios de Implantação'!$Q$63,0)+IFERROR('Resumo-Cult.Perma.'!B54*'Critérios de Implantação'!$Q$64,0)+IFERROR('Resumo-Cult.Perma.'!A54*'Critérios de Implantação'!$Q$65,0)+IFERROR('Resumo-Cult.Perma.'!#REF!*'Critérios de Implantação'!$Q$66,0)+IFERROR('Resumo-Cult.Perma.'!#REF!*'Critérios de Implantação'!$Q$67,0)+IFERROR('Resumo-Cult.Perma.'!#REF!*'Critérios de Implantação'!$Q$68,0)+IFERROR('Resumo-Cult.Perma.'!#REF!*'Critérios de Implantação'!$Q$69,0) -> 1265676.1 | I91: =IFERROR('Resumo-Cult.Perma.'!F54*'Critérios de Implantação'!I$61,0)+IFERROR('Resumo-Cult.Perma.'!E54*'Critérios de Implantação'!I$62,0)+IFERROR('Resumo-Cult.Perma.'!D54*'Critérios de Implantação'!$Q$63,0)+IFERROR('Resumo-Cult.Perma.'!C54*'Critérios de Implantação'!$Q$64,0)+IFERROR('Resumo-Cult.Perma.'!B54*'Critérios de Implantação'!$Q$65,0)+IFERROR('Resumo-Cult.Perma.'!A54*'Critérios de Implantação'!$Q$66,0)+IFERROR('Resumo-Cult.Perma.'!#REF!*'Critérios de Implantação'!$Q$67,0)+IFERROR('Resumo-Cult.Perma.'!#REF!*'Critérios de Implantação'!$Q$68,0)+IFERROR('Resumo-Cult.Perma.'!#REF!*'Critérios de Implantação'!$Q$69,0) -> 2025754.8 | J91: =IFERROR('Resumo-Cult.Perma.'!G54*'Critérios de Implantação'!J$61,0)+IFERROR('Resumo-Cult.Perma.'!F54*'Critérios de Implantação'!J$62,0)+IFERROR('Resumo-Cult.Perma.'!E54*'Critérios de Implantação'!$Q$63,0)+IFERROR('Resumo-Cult.Perma.'!D54*'Critérios de Implantação'!$Q$64,0)+IFERROR('Resumo-Cult.Perma.'!C54*'Critérios de Implantação'!$Q$65,0)+IFERROR('Resumo-Cult.Perma.'!B54*'Critérios de Implantação'!$Q$66,0)+IFERROR('Resumo-Cult.Perma.'!A54*'Critérios de Implantação'!$Q$67,0)+IFERROR('Resumo-Cult.Perma.'!#REF!*'Critérios de Implantação'!$Q$68,0)+IFERROR('Resumo-Cult.Perma.'!#REF!*'Critérios de Implantação'!$Q$69,0) -> 3449416.5 | K91: =IFERROR('Resumo-Cult.Perma.'!H54*'Critérios de Implantação'!K$61,0)+IFERROR('Resumo-Cult.Perma.'!G54*'Critérios de Implantação'!K$62,0)+IFERROR('Resumo-Cult.Perma.'!F54*'Critérios de Implantação'!$Q$63,0)+IFERROR('Resumo-Cult.Perma.'!E54*'Critérios de Implantação'!$Q$64,0)+IFERROR('Resumo-Cult.Perma.'!D54*'Critérios de Implantação'!$Q$65,0)+IFERROR('Resumo-Cult.Perma.'!C54*'Critérios de Implantação'!$Q$66,0)+IFERROR('Resumo-Cult.Perma.'!B54*'Critérios de Implantação'!$Q$67,0)+IFERROR('Resumo-Cult.Perma.'!A54*'Critérios de Implantação'!$Q$68,0)+IFERROR('Resumo-Cult.Perma.'!#REF!*'Critérios de Implantação'!$Q$69,0) -> 4781630.6 | L91: =IFERROR('Resumo-Cult.Perma.'!I54*'Critérios de Implantação'!L$61,0)+IFERROR('Resumo-Cult.Perma.'!H54*'Critérios de Implantação'!L$62,0)+IFERROR('Resumo-Cult.Perma.'!G54*'Critérios de Implantação'!$Q$63,0)+IFERROR('Resumo-Cult.Perma.'!F54*'Critérios de Implantação'!$Q$64,0)+IFERROR('Resumo-Cult.Perma.'!E54*'Critérios de Implantação'!$Q$65,0)+IFERROR('Resumo-Cult.Perma.'!D54*'Critérios de Implantação'!$Q$66,0)+IFERROR('Resumo-Cult.Perma.'!C54*'Critérios de Implantação'!$Q$67,0)+IFERROR('Resumo-Cult.Perma.'!B54*'Critérios de Implantação'!$Q$68,0)+IFERROR('Resumo-Cult.Perma.'!A54*'Critérios de Implantação'!$Q$69,0) -> 6144752 | M91: =IFERROR('Resumo-Cult.Perma.'!J54*'Critérios de Implantação'!M$61,0)+IFERROR('Resumo-Cult.Perma.'!I54*'Critérios de Implantação'!M$62,0)+IFERROR('Resumo-Cult.Perma.'!H54*'Critérios de Implantação'!$Q$63,0)+IFERROR('Resumo-Cult.Perma.'!G54*'Critérios de Implantação'!$Q$64,0)+IFERROR('Resumo-Cult.Perma.'!F54*'Critérios de Implantação'!$Q$65,0)+IFERROR('Resumo-Cult.Perma.'!E54*'Critérios de Implantação'!$Q$66,0)+IFERROR('Resumo-Cult.Perma.'!D54*'Critérios de Implantação'!$Q$67,0)+IFERROR('Resumo-Cult.Perma.'!C54*'Critérios de Implantação'!$Q$68,0)+IFERROR('Resumo-Cult.Perma.'!B54*'Critérios de Implantação'!$Q$69,0) -> 7194708.1 | N91: =IFERROR('Resumo-Cult.Perma.'!K54*'Critérios de Implantação'!N$61,0)+IFERROR('Resumo-Cult.Perma.'!J54*'Critérios de Implantação'!N$62,0)+IFERROR('Resumo-Cult.Perma.'!I54*'Critérios de Implantação'!$Q$63,0)+IFERROR('Resumo-Cult.Perma.'!H54*'Critérios de Implantação'!$Q$64,0)+IFERROR('Resumo-Cult.Perma.'!G54*'Critérios de Implantação'!$Q$65,0)+IFERROR('Resumo-Cult.Perma.'!F54*'Critérios de Implantação'!$Q$66,0)+IFERROR('Resumo-Cult.Perma.'!E54*'Critérios de Implantação'!$Q$67,0)+IFERROR('Resumo-Cult.Perma.'!D54*'Critérios de Implantação'!$Q$68,0)+IFERROR('Resumo-Cult.Perma.'!C54*'Critérios de Implantação'!$Q$69,0) -> 7914996.2 | O91: =IFERROR('Resumo-Cult.Perma.'!L54*'Critérios de Implantação'!O$61,0)+IFERROR('Resumo-Cult.Perma.'!K54*'Critérios de Implantação'!O$62,0)+IFERROR('Resumo-Cult.Perma.'!J54*'Critérios de Implantação'!$Q$63,0)+IFERROR('Resumo-Cult.Perma.'!I54*'Critérios de Implantação'!$Q$64,0)+IFERROR('Resumo-Cult.Perma.'!H54*'Critérios de Implantação'!$Q$65,0)+IFERROR('Resumo-Cult.Perma.'!G54*'Critérios de Implantação'!$Q$66,0)+IFERROR('Resumo-Cult.Perma.'!F54*'Critérios de Implantação'!$Q$67,0)+IFERROR('Resumo-Cult.Perma.'!E54*'Critérios de Implantação'!$Q$68,0)+IFERROR('Resumo-Cult.Perma.'!D54*'Critérios de Implantação'!$Q$69,0) -> 8225857 | P91: =IFERROR('Resumo-Cult.Perma.'!M54*'Critérios de Implantação'!P$61,0)+IFERROR('Resumo-Cult.Perma.'!L54*'Critérios de Implantação'!P$62,0)+IFERROR('Resumo-Cult.Perma.'!K54*'Critérios de Implantação'!$Q$63,0)+IFERROR('Resumo-Cult.Perma.'!J54*'Critérios de Implantação'!$Q$64,0)+IFERROR('Resumo-Cult.Perma.'!I54*'Critérios de Implantação'!$Q$65,0)+IFERROR('Resumo-Cult.Perma.'!H54*'Critérios de Implantação'!$Q$66,0)+IFERROR('Resumo-Cult.Perma.'!G54*'Critérios de Implantação'!$Q$67,0)+IFERROR('Resumo-Cult.Perma.'!F54*'Critérios de Implantação'!$Q$68,0)+IFERROR('Resumo-Cult.Perma.'!E54*'Critérios de Implantação'!$Q$69,0) -> 8143716.7 | Q91: =IFERROR('Resumo-Cult.Perma.'!N54*'Critérios de Implantação'!Q$61,0)+IFERROR('Resumo-Cult.Perma.'!M54*'Critérios de Implantação'!Q$62,0)+IFERROR('Resumo-Cult.Perma.'!L54*'Critérios de Implantação'!$Q$63,0)+IFERROR('Resumo-Cult.Perma.'!K54*'Critérios de Implantação'!$Q$64,0)+IFERROR('Resumo-Cult.Perma.'!J54*'Critérios de Implantação'!$Q$65,0)+IFERROR('Resumo-Cult.Perma.'!I54*'Critérios de Implantação'!$Q$66,0)+IFERROR('Resumo-Cult.Perma.'!H54*'Critérios de Implantação'!$Q$67,0)+IFERROR('Resumo-Cult.Perma.'!G54*'Critérios de Implantação'!$Q$68,0)+IFERROR('Resumo-Cult.Perma.'!F54*'Critérios de Implantação'!$Q$69,0) -> 8085773.4 | R91: =IFERROR('Resumo-Cult.Perma.'!O54*'Critérios de Implantação'!R$61,0)+IFERROR('Resumo-Cult.Perma.'!N54*'Critérios de Implantação'!R$62,0)+IFERROR('Resumo-Cult.Perma.'!M54*'Critérios de Implantação'!$Q$63,0)+IFERROR('Resumo-Cult.Perma.'!L54*'Critérios de Implantação'!$Q$64,0)+IFERROR('Resumo-Cult.Perma.'!K54*'Critérios de Implantação'!$Q$65,0)+IFERROR('Resumo-Cult.Perma.'!J54*'Critérios de Implantação'!$Q$66,0)+IFERROR('Resumo-Cult.Perma.'!I54*'Critérios de Implantação'!$Q$67,0)+IFERROR('Resumo-Cult.Perma.'!H54*'Critérios de Implantação'!$Q$68,0)+IFERROR('Resumo-Cult.Perma.'!G54*'Critérios de Implantação'!$Q$69,0) -> 8467363.4 | S91: =IFERROR('Resumo-Cult.Perma.'!P54*'Critérios de Implantação'!S$61,0)+IFERROR('Resumo-Cult.Perma.'!O54*'Critérios de Implantação'!S$62,0)+IFERROR('Resumo-Cult.Perma.'!N54*'Critérios de Implantação'!$Q$63,0)+IFERROR('Resumo-Cult.Perma.'!M54*'Critérios de Implantação'!$Q$64,0)+IFERROR('Resumo-Cult.Perma.'!L54*'Critérios de Implantação'!$Q$65,0)+IFERROR('Resumo-Cult.Perma.'!K54*'Critérios de Implantação'!$Q$66,0)+IFERROR('Resumo-Cult.Perma.'!J54*'Critérios de Implantação'!$Q$67,0)+IFERROR('Resumo-Cult.Perma.'!I54*'Critérios de Implantação'!$Q$68,0)+IFERROR('Resumo-Cult.Perma.'!H54*'Critérios de Implantação'!$Q$69,0) -> 8512774.7 | ... AK91: =IFERROR('Resumo-Cult.Perma.'!AH54*'Critérios de Implantação'!AK$61,0)+IFERROR('Resumo-Cult.Perma.'!AG54*'Critérios de Implantação'!AK$62,0)+IFERROR('Resumo-Cult.Perma.'!AF54*'Critérios de Implantação'!$Q$63,0)+IFERROR('Resumo-Cult.Perma.'!AE54*'Critérios de Implantação'!$Q$64,0)+IFERROR('Resumo-Cult.Perma.'!AD54*'Critérios de Implantação'!$Q$65,0)+IFERROR('Resumo-Cult.Perma.'!AC54*'Critérios de Implantação'!$Q$66,0)+IFERROR('Resumo-Cult.Perma.'!AB54*'Critérios de Implantação'!$Q$67,0)+IFERROR('Resumo-Cult.Perma.'!AA54*'Critérios de Implantação'!$Q$68,0)+IFERROR('Resumo-Cult.Perma.'!Z54*'Critérios de Implantação'!$Q$69,0) -> 8868633.1
A92: 2.2 | B92: Gasto com mão de obra | D92: =IFERROR('Resumo-Cult.Perma.'!A55*'Critérios de Implantação'!D$61,0)+IFERROR('Resumo-Cult.Perma.'!#REF!*'Critérios de Implantação'!D$62,0)+IFERROR('Resumo-Cult.Perma.'!#REF!*'Critérios de Implantação'!$Q$63,0)+IFERROR('Resumo-Cult.Perma.'!#REF!*'Critérios de Implantação'!$Q$64,0)+IFERROR('Resumo-Cult.Perma.'!#REF!*'Critérios de Implantação'!$Q$65,0)+IFERROR('Resumo-Cult.Perma.'!#REF!*'Critérios de Implantação'!$Q$66,0)+IFERROR('Resumo-Cult.Perma.'!#REF!*'Critérios de Implantação'!$Q$67,0)+IFERROR('Resumo-Cult.Perma.'!#REF!*'Critérios de Implantação'!$Q$68,0)+IFERROR('Resumo-Cult.Perma.'!#REF!*'Critérios de Implantação'!$Q$69,0) -> 0 | E92: =IFERROR('Resumo-Cult.Perma.'!B55*'Critérios de Implantação'!E$61,0)+IFERROR('Resumo-Cult.Perma.'!A55*'Critérios de Implantação'!E$62,0)+IFERROR('Resumo-Cult.Perma.'!#REF!*'Critérios de Implantação'!$Q$63,0)+IFERROR('Resumo-Cult.Perma.'!#REF!*'Critérios de Implantação'!$Q$64,0)+IFERROR('Resumo-Cult.Perma.'!#REF!*'Critérios de Implantação'!$Q$65,0)+IFERROR('Resumo-Cult.Perma.'!#REF!*'Critérios de Implantação'!$Q$66,0)+IFERROR('Resumo-Cult.Perma.'!#REF!*'Critérios de Implantação'!$Q$67,0)+IFERROR('Resumo-Cult.Perma.'!#REF!*'Critérios de Implantação'!$Q$68,0)+IFERROR('Resumo-Cult.Perma.'!#REF!*'Critérios de Implantação'!$Q$69,0) -> 0 | F92: =IFERROR('Resumo-Cult.Perma.'!C55*'Critérios de Implantação'!F$61,0)+IFERROR('Resumo-Cult.Perma.'!B55*'Critérios de Implantação'!F$62,0)+IFERROR('Resumo-Cult.Perma.'!A55*'Critérios de Implantação'!$Q$63,0)+IFERROR('Resumo-Cult.Perma.'!#REF!*'Critérios de Implantação'!$Q$64,0)+IFERROR('Resumo-Cult.Perma.'!#REF!*'Critérios de Implantação'!$Q$65,0)+IFERROR('Resumo-Cult.Perma.'!#REF!*'Critérios de Implantação'!$Q$66,0)+IFERROR('Resumo-Cult.Perma.'!#REF!*'Critérios de Implantação'!$Q$67,0)+IFERROR('Resumo-Cult.Perma.'!#REF!*'Critérios de Implantação'!$Q$68,0)+IFERROR('Resumo-Cult.Perma.'!#REF!*'Critérios de Implantação'!$Q$69,0) -> 0 | G92: =IFERROR('Resumo-Cult.Perma.'!D55*'Critérios de Implantação'!G$61,0)+IFERROR('Resumo-Cult.Perma.'!C55*'Critérios de Implantação'!G$62,0)+IFERROR('Resumo-Cult.Perma.'!B55*'Critérios de Implantação'!$Q$63,0)+IFERROR('Resumo-Cult.Perma.'!A55*'Critérios de Implantação'!$Q$64,0)+IFERROR('Resumo-Cult.Perma.'!#REF!*'Critérios de Implantação'!$Q$65,0)+IFERROR('Resumo-Cult.Perma.'!#REF!*'Critérios de Implantação'!$Q$66,0)+IFERROR('Resumo-Cult.Perma.'!#REF!*'Critérios de Implantação'!$Q$67,0)+IFERROR('Resumo-Cult.Perma.'!#REF!*'Critérios de Implantação'!$Q$68,0)+IFERROR('Resumo-Cult.Perma.'!#REF!*'Critérios de Implantação'!$Q$69,0) -> 735044.91 | H92: =IFERROR('Resumo-Cult.Perma.'!E55*'Critérios de Implantação'!H$61,0)+IFERROR('Resumo-Cult.Perma.'!D55*'Critérios de Implantação'!H$62,0)+IFERROR('Resumo-Cult.Perma.'!C55*'Critérios de Implantação'!$Q$63,0)+IFERROR('Resumo-Cult.Perma.'!B55*'Critérios de Implantação'!$Q$64,0)+IFERROR('Resumo-Cult.Perma.'!A55*'Critérios de Implantação'!$Q$65,0)+IFERROR('Resumo-Cult.Perma.'!#REF!*'Critérios de Implantação'!$Q$66,0)+IFERROR('Resumo-Cult.Perma.'!#REF!*'Critérios de Implantação'!$Q$67,0)+IFERROR('Resumo-Cult.Perma.'!#REF!*'Critérios de Implantação'!$Q$68,0)+IFERROR('Resumo-Cult.Perma.'!#REF!*'Critérios de Implantação'!$Q$69,0) -> 1432407.9 | I92: =IFERROR('Resumo-Cult.Perma.'!F55*'Critérios de Implantação'!I$61,0)+IFERROR('Resumo-Cult.Perma.'!E55*'Critérios de Implantação'!I$62,0)+IFERROR('Resumo-Cult.Perma.'!D55*'Critérios de Implantação'!$Q$63,0)+IFERROR('Resumo-Cult.Perma.'!C55*'Critérios de Implantação'!$Q$64,0)+IFERROR('Resumo-Cult.Perma.'!B55*'Critérios de Implantação'!$Q$65,0)+IFERROR('Resumo-Cult.Perma.'!A55*'Critérios de Implantação'!$Q$66,0)+IFERROR('Resumo-Cult.Perma.'!#REF!*'Critérios de Implantação'!$Q$67,0)+IFERROR('Resumo-Cult.Perma.'!#REF!*'Critérios de Implantação'!$Q$68,0)+IFERROR('Resumo-Cult.Perma.'!#REF!*'Critérios de Implantação'!$Q$69,0) -> 2243814.5 | J92: =IFERROR('Resumo-Cult.Perma.'!G55*'Critérios de Implantação'!J$61,0)+IFERROR('Resumo-Cult.Perma.'!F55*'Critérios de Implantação'!J$62,0)+IFERROR('Resumo-Cult.Perma.'!E55*'Critérios de Implantação'!$Q$63,0)+IFERROR('Resumo-Cult.Perma.'!D55*'Critérios de Implantação'!$Q$64,0)+IFERROR('Resumo-Cult.Perma.'!C55*'Critérios de Implantação'!$Q$65,0)+IFERROR('Resumo-Cult.Perma.'!B55*'Critérios de Implantação'!$Q$66,0)+IFERROR('Resumo-Cult.Perma.'!A55*'Critérios de Implantação'!$Q$67,0)+IFERROR('Resumo-Cult.Perma.'!#REF!*'Critérios de Implantação'!$Q$68,0)+IFERROR('Resumo-Cult.Perma.'!#REF!*'Critérios de Implantação'!$Q$69,0) -> 3847070.1 | K92: =IFERROR('Resumo-Cult.Perma.'!H55*'Critérios de Implantação'!K$61,0)+IFERROR('Resumo-Cult.Perma.'!G55*'Critérios de Implantação'!K$62,0)+IFERROR('Resumo-Cult.Perma.'!F55*'Critérios de Implantação'!$Q$63,0)+IFERROR('Resumo-Cult.Perma.'!E55*'Critérios de Implantação'!$Q$64,0)+IFERROR('Resumo-Cult.Perma.'!D55*'Critérios de Implantação'!$Q$65,0)+IFERROR('Resumo-Cult.Perma.'!C55*'Critérios de Implantação'!$Q$66,0)+IFERROR('Resumo-Cult.Perma.'!B55*'Critérios de Implantação'!$Q$67,0)+IFERROR('Resumo-Cult.Perma.'!A55*'Critérios de Implantação'!$Q$68,0)+IFERROR('Resumo-Cult.Perma.'!#REF!*'Critérios de Implantação'!$Q$69,0) -> 5272841.6 | L92: =IFERROR('Resumo-Cult.Perma.'!I55*'Critérios de Implantação'!L$61,0)+IFERROR('Resumo-Cult.Perma.'!H55*'Critérios de Implantação'!L$62,0)+IFERROR('Resumo-Cult.Perma.'!G55*'Critérios de Implantação'!$Q$63,0)+IFERROR('Resumo-Cult.Perma.'!F55*'Critérios de Implantação'!$Q$64,0)+IFERROR('Resumo-Cult.Perma.'!E55*'Critérios de Implantação'!$Q$65,0)+IFERROR('Resumo-Cult.Perma.'!D55*'Critérios de Implantação'!$Q$66,0)+IFERROR('Resumo-Cult.Perma.'!C55*'Critérios de Implantação'!$Q$67,0)+IFERROR('Resumo-Cult.Perma.'!B55*'Critérios de Implantação'!$Q$68,0)+IFERROR('Resumo-Cult.Perma.'!A55*'Critérios de Implantação'!$Q$69,0) -> 6673505.3 | M92: =IFERROR('Resumo-Cult.Perma.'!J55*'Critérios de Implantação'!M$61,0)+IFERROR('Resumo-Cult.Perma.'!I55*'Critérios de Implantação'!M$62,0)+IFERROR('Resumo-Cult.Perma.'!H55*'Critérios de Implantação'!$Q$63,0)+IFERROR('Resumo-Cult.Perma.'!G55*'Critérios de Implantação'!$Q$64,0)+IFERROR('Resumo-Cult.Perma.'!F55*'Critérios de Implantação'!$Q$65,0)+IFERROR('Resumo-Cult.Perma.'!E55*'Critérios de Implantação'!$Q$66,0)+IFERROR('Resumo-Cult.Perma.'!D55*'Critérios de Implantação'!$Q$67,0)+IFERROR('Resumo-Cult.Perma.'!C55*'Critérios de Implantação'!$Q$68,0)+IFERROR('Resumo-Cult.Perma.'!B55*'Critérios de Implantação'!$Q$69,0) -> 7740857.8 | N92: =IFERROR('Resumo-Cult.Perma.'!K55*'Critérios de Implantação'!N$61,0)+IFERROR('Resumo-Cult.Perma.'!J55*'Critérios de Implantação'!N$62,0)+IFERROR('Resumo-Cult.Perma.'!I55*'Critérios de Implantação'!$Q$63,0)+IFERROR('Resumo-Cult.Perma.'!H55*'Critérios de Implantação'!$Q$64,0)+IFERROR('Resumo-Cult.Perma.'!G55*'Critérios de Implantação'!$Q$65,0)+IFERROR('Resumo-Cult.Perma.'!F55*'Critérios de Implantação'!$Q$66,0)+IFERROR('Resumo-Cult.Perma.'!E55*'Critérios de Implantação'!$Q$67,0)+IFERROR('Resumo-Cult.Perma.'!D55*'Critérios de Implantação'!$Q$68,0)+IFERROR('Resumo-Cult.Perma.'!C55*'Critérios de Implantação'!$Q$69,0) -> 8401857.3 | O92: =IFERROR('Resumo-Cult.Perma.'!L55*'Critérios de Implantação'!O$61,0)+IFERROR('Resumo-Cult.Perma.'!K55*'Critérios de Implantação'!O$62,0)+IFERROR('Resumo-Cult.Perma.'!J55*'Critérios de Implantação'!$Q$63,0)+IFERROR('Resumo-Cult.Perma.'!I55*'Critérios de Implantação'!$Q$64,0)+IFERROR('Resumo-Cult.Perma.'!H55*'Critérios de Implantação'!$Q$65,0)+IFERROR('Resumo-Cult.Perma.'!G55*'Critérios de Implantação'!$Q$66,0)+IFERROR('Resumo-Cult.Perma.'!F55*'Critérios de Implantação'!$Q$67,0)+IFERROR('Resumo-Cult.Perma.'!E55*'Critérios de Implantação'!$Q$68,0)+IFERROR('Resumo-Cult.Perma.'!D55*'Critérios de Implantação'!$Q$69,0) -> 8588358.3 | P92: =IFERROR('Resumo-Cult.Perma.'!M55*'Critérios de Implantação'!P$61,0)+IFERROR('Resumo-Cult.Perma.'!L55*'Critérios de Implantação'!P$62,0)+IFERROR('Resumo-Cult.Perma.'!K55*'Critérios de Implantação'!$Q$63,0)+IFERROR('Resumo-Cult.Perma.'!J55*'Critérios de Implantação'!$Q$64,0)+IFERROR('Resumo-Cult.Perma.'!I55*'Critérios de Implantação'!$Q$65,0)+IFERROR('Resumo-Cult.Perma.'!H55*'Critérios de Implantação'!$Q$66,0)+IFERROR('Resumo-Cult.Perma.'!G55*'Critérios de Implantação'!$Q$67,0)+IFERROR('Resumo-Cult.Perma.'!F55*'Critérios de Implantação'!$Q$68,0)+IFERROR('Resumo-Cult.Perma.'!E55*'Critérios de Implantação'!$Q$69,0) -> 8294737.1 | Q92: =IFERROR('Resumo-Cult.Perma.'!N55*'Critérios de Implantação'!Q$61,0)+IFERROR('Resumo-Cult.Perma.'!M55*'Critérios de Implantação'!Q$62,0)+IFERROR('Resumo-Cult.Perma.'!L55*'Critérios de Implantação'!$Q$63,0)+IFERROR('Resumo-Cult.Perma.'!K55*'Critérios de Implantação'!$Q$64,0)+IFERROR('Resumo-Cult.Perma.'!J55*'Critérios de Implantação'!$Q$65,0)+IFERROR('Resumo-Cult.Perma.'!I55*'Critérios de Implantação'!$Q$66,0)+IFERROR('Resumo-Cult.Perma.'!H55*'Critérios de Implantação'!$Q$67,0)+IFERROR('Resumo-Cult.Perma.'!G55*'Critérios de Implantação'!$Q$68,0)+IFERROR('Resumo-Cult.Perma.'!F55*'Critérios de Implantação'!$Q$69,0) -> 8044134.7 | R92: =IFERROR('Resumo-Cult.Perma.'!O55*'Critérios de Implantação'!R$61,0)+IFERROR('Resumo-Cult.Perma.'!N55*'Critérios de Implantação'!R$62,0)+IFERROR('Resumo-Cult.Perma.'!M55*'Critérios de Implantação'!$Q$63,0)+IFERROR('Resumo-Cult.Perma.'!L55*'Critérios de Implantação'!$Q$64,0)+IFERROR('Resumo-Cult.Perma.'!K55*'Critérios de Implantação'!$Q$65,0)+IFERROR('Resumo-Cult.Perma.'!J55*'Critérios de Implantação'!$Q$66,0)+IFERROR('Resumo-Cult.Perma.'!I55*'Critérios de Implantação'!$Q$67,0)+IFERROR('Resumo-Cult.Perma.'!H55*'Critérios de Implantação'!$Q$68,0)+IFERROR('Resumo-Cult.Perma.'!G55*'Critérios de Implantação'!$Q$69,0) -> 7831645.1 | S92: =IFERROR('Resumo-Cult.Perma.'!P55*'Critérios de Implantação'!S$61,0)+IFERROR('Resumo-Cult.Perma.'!O55*'Critérios de Implantação'!S$62,0)+IFERROR('Resumo-Cult.Perma.'!N55*'Critérios de Implantação'!$Q$63,0)+IFERROR('Resumo-Cult.Perma.'!M55*'Critérios de Implantação'!$Q$64,0)+IFERROR('Resumo-Cult.Perma.'!L55*'Critérios de Implantação'!$Q$65,0)+IFERROR('Resumo-Cult.Perma.'!K55*'Critérios de Implantação'!$Q$66,0)+IFERROR('Resumo-Cult.Perma.'!J55*'Critérios de Implantação'!$Q$67,0)+IFERROR('Resumo-Cult.Perma.'!I55*'Critérios de Implantação'!$Q$68,0)+IFERROR('Resumo-Cult.Perma.'!H55*'Critérios de Implantação'!$Q$69,0) -> 7844447.2 | ... AK92: =IFERROR('Resumo-Cult.Perma.'!AH55*'Critérios de Implantação'!AK$61,0)+IFERROR('Resumo-Cult.Perma.'!AG55*'Critérios de Implantação'!AK$62,0)+IFERROR('Resumo-Cult.Perma.'!AF55*'Critérios de Implantação'!$Q$63,0)+IFERROR('Resumo-Cult.Perma.'!AE55*'Critérios de Implantação'!$Q$64,0)+IFERROR('Resumo-Cult.Perma.'!AD55*'Critérios de Implantação'!$Q$65,0)+IFERROR('Resumo-Cult.Perma.'!AC55*'Critérios de Implantação'!$Q$66,0)+IFERROR('Resumo-Cult.Perma.'!AB55*'Critérios de Implantação'!$Q$67,0)+IFERROR('Resumo-Cult.Perma.'!AA55*'Critérios de Implantação'!$Q$68,0)+IFERROR('Resumo-Cult.Perma.'!Z55*'Critérios de Implantação'!$Q$69,0) -> 8700761.6
A93: 2.3 | B93: Gasto com trator e equipamentos e avaição agrícola | D93: =IFERROR('Resumo-Cult.Perma.'!A56*'Critérios de Implantação'!D$61,0)+IFERROR('Resumo-Cult.Perma.'!#REF!*'Critérios de Implantação'!D$62,0)+IFERROR('Resumo-Cult.Perma.'!#REF!*'Critérios de Implantação'!$Q$63,0)+IFERROR('Resumo-Cult.Perma.'!#REF!*'Critérios de Implantação'!$Q$64,0)+IFERROR('Resumo-Cult.Perma.'!#REF!*'Critérios de Implantação'!$Q$65,0)+IFERROR('Resumo-Cult.Perma.'!#REF!*'Critérios de Implantação'!$Q$66,0)+IFERROR('Resumo-Cult.Perma.'!#REF!*'Critérios de Implantação'!$Q$67,0)+IFERROR('Resumo-Cult.Perma.'!#REF!*'Critérios de Implantação'!$Q$68,0)+IFERROR('Resumo-Cult.Perma.'!#REF!*'Critérios de Implantação'!$Q$69,0) -> 0 | E93: =IFERROR('Resumo-Cult.Perma.'!B56*'Critérios de Implantação'!E$61,0)+IFERROR('Resumo-Cult.Perma.'!A56*'Critérios de Implantação'!E$62,0)+IFERROR('Resumo-Cult.Perma.'!#REF!*'Critérios de Implantação'!$Q$63,0)+IFERROR('Resumo-Cult.Perma.'!#REF!*'Critérios de Implantação'!$Q$64,0)+IFERROR('Resumo-Cult.Perma.'!#REF!*'Critérios de Implantação'!$Q$65,0)+IFERROR('Resumo-Cult.Perma.'!#REF!*'Critérios de Implantação'!$Q$66,0)+IFERROR('Resumo-Cult.Perma.'!#REF!*'Critérios de Implantação'!$Q$67,0)+IFERROR('Resumo-Cult.Perma.'!#REF!*'Critérios de Implantação'!$Q$68,0)+IFERROR('Resumo-Cult.Perma.'!#REF!*'Critérios de Implantação'!$Q$69,0) -> 0 | F93: =IFERROR('Resumo-Cult.Perma.'!C56*'Critérios de Implantação'!F$61,0)+IFERROR('Resumo-Cult.Perma.'!B56*'Critérios de Implantação'!F$62,0)+IFERROR('Resumo-Cult.Perma.'!A56*'Critérios de Implantação'!$Q$63,0)+IFERROR('Resumo-Cult.Perma.'!#REF!*'Critérios de Implantação'!$Q$64,0)+IFERROR('Resumo-Cult.Perma.'!#REF!*'Critérios de Implantação'!$Q$65,0)+IFERROR('Resumo-Cult.Perma.'!#REF!*'Critérios de Implantação'!$Q$66,0)+IFERROR('Resumo-Cult.Perma.'!#REF!*'Critérios de Implantação'!$Q$67,0)+IFERROR('Resumo-Cult.Perma.'!#REF!*'Critérios de Implantação'!$Q$68,0)+IFERROR('Resumo-Cult.Perma.'!#REF!*'Critérios de Implantação'!$Q$69,0) -> 0 | G93: =IFERROR('Resumo-Cult.Perma.'!D56*'Critérios de Implantação'!G$61,0)+IFERROR('Resumo-Cult.Perma.'!C56*'Critérios de Implantação'!G$62,0)+IFERROR('Resumo-Cult.Perma.'!B56*'Critérios de Implantação'!$Q$63,0)+IFERROR('Resumo-Cult.Perma.'!A56*'Critérios de Implantação'!$Q$64,0)+IFERROR('Resumo-Cult.Perma.'!#REF!*'Critérios de Implantação'!$Q$65,0)+IFERROR('Resumo-Cult.Perma.'!#REF!*'Critérios de Implantação'!$Q$66,0)+IFERROR('Resumo-Cult.Perma.'!#REF!*'Critérios de Implantação'!$Q$67,0)+IFERROR('Resumo-Cult.Perma.'!#REF!*'Critérios de Implantação'!$Q$68,0)+IFERROR('Resumo-Cult.Perma.'!#REF!*'Critérios de Implantação'!$Q$69,0) -> 215549.92 | H93: =IFERROR('Resumo-Cult.Perma.'!E56*'Critérios de Implantação'!H$61,0)+IFERROR('Resumo-Cult.Perma.'!D56*'Critérios de Implantação'!H$62,0)+IFERROR('Resumo-Cult.Perma.'!C56*'Critérios de Implantação'!$Q$63,0)+IFERROR('Resumo-Cult.Perma.'!B56*'Critérios de Implantação'!$Q$64,0)+IFERROR('Resumo-Cult.Perma.'!A56*'Critérios de Implantação'!$Q$65,0)+IFERROR('Resumo-Cult.Perma.'!#REF!*'Critérios de Implantação'!$Q$66,0)+IFERROR('Resumo-Cult.Perma.'!#REF!*'Critérios de Implantação'!$Q$67,0)+IFERROR('Resumo-Cult.Perma.'!#REF!*'Critérios de Implantação'!$Q$68,0)+IFERROR('Resumo-Cult.Perma.'!#REF!*'Critérios de Implantação'!$Q$69,0) -> 395699.31 | I93: =IFERROR('Resumo-Cult.Perma.'!F56*'Critérios de Implantação'!I$61,0)+IFERROR('Resumo-Cult.Perma.'!E56*'Critérios de Implantação'!I$62,0)+IFERROR('Resumo-Cult.Perma.'!D56*'Critérios de Implantação'!$Q$63,0)+IFERROR('Resumo-Cult.Perma.'!C56*'Critérios de Implantação'!$Q$64,0)+IFERROR('Resumo-Cult.Perma.'!B56*'Critérios de Implantação'!$Q$65,0)+IFERROR('Resumo-Cult.Perma.'!A56*'Critérios de Implantação'!$Q$66,0)+IFERROR('Resumo-Cult.Perma.'!#REF!*'Critérios de Implantação'!$Q$67,0)+IFERROR('Resumo-Cult.Perma.'!#REF!*'Critérios de Implantação'!$Q$68,0)+IFERROR('Resumo-Cult.Perma.'!#REF!*'Critérios de Implantação'!$Q$69,0) -> 615338 | J93: =IFERROR('Resumo-Cult.Perma.'!G56*'Critérios de Implantação'!J$61,0)+IFERROR('Resumo-Cult.Perma.'!F56*'Critérios de Implantação'!J$62,0)+IFERROR('Resumo-Cult.Perma.'!E56*'Critérios de Implantação'!$Q$63,0)+IFERROR('Resumo-Cult.Perma.'!D56*'Critérios de Implantação'!$Q$64,0)+IFERROR('Resumo-Cult.Perma.'!C56*'Critérios de Implantação'!$Q$65,0)+IFERROR('Resumo-Cult.Perma.'!B56*'Critérios de Implantação'!$Q$66,0)+IFERROR('Resumo-Cult.Perma.'!A56*'Critérios de Implantação'!$Q$67,0)+IFERROR('Resumo-Cult.Perma.'!#REF!*'Critérios de Implantação'!$Q$68,0)+IFERROR('Resumo-Cult.Perma.'!#REF!*'Critérios de Implantação'!$Q$69,0) -> 1072984.2 | K93: =IFERROR('Resumo-Cult.Perma.'!H56*'Critérios de Implantação'!K$61,0)+IFERROR('Resumo-Cult.Perma.'!G56*'Critérios de Implantação'!K$62,0)+IFERROR('Resumo-Cult.Perma.'!F56*'Critérios de Implantação'!$Q$63,0)+IFERROR('Resumo-Cult.Perma.'!E56*'Critérios de Implantação'!$Q$64,0)+IFERROR('Resumo-Cult.Perma.'!D56*'Critérios de Implantação'!$Q$65,0)+IFERROR('Resumo-Cult.Perma.'!C56*'Critérios de Implantação'!$Q$66,0)+IFERROR('Resumo-Cult.Perma.'!B56*'Critérios de Implantação'!$Q$67,0)+IFERROR('Resumo-Cult.Perma.'!A56*'Critérios de Implantação'!$Q$68,0)+IFERROR('Resumo-Cult.Perma.'!#REF!*'Critérios de Implantação'!$Q$69,0) -> 1455391.5 | L93: =IFERROR('Resumo-Cult.Perma.'!I56*'Critérios de Implantação'!L$61,0)+IFERROR('Resumo-Cult.Perma.'!H56*'Critérios de Implantação'!L$62,0)+IFERROR('Resumo-Cult.Perma.'!G56*'Critérios de Implantação'!$Q$63,0)+IFERROR('Resumo-Cult.Perma.'!F56*'Critérios de Implantação'!$Q$64,0)+IFERROR('Resumo-Cult.Perma.'!E56*'Critérios de Implantação'!$Q$65,0)+IFERROR('Resumo-Cult.Perma.'!D56*'Critérios de Implantação'!$Q$66,0)+IFERROR('Resumo-Cult.Perma.'!C56*'Critérios de Implantação'!$Q$67,0)+IFERROR('Resumo-Cult.Perma.'!B56*'Critérios de Implantação'!$Q$68,0)+IFERROR('Resumo-Cult.Perma.'!A56*'Critérios de Implantação'!$Q$69,0) -> 1856762.3 | M93: =IFERROR('Resumo-Cult.Perma.'!J56*'Critérios de Implantação'!M$61,0)+IFERROR('Resumo-Cult.Perma.'!I56*'Critérios de Implantação'!M$62,0)+IFERROR('Resumo-Cult.Perma.'!H56*'Critérios de Implantação'!$Q$63,0)+IFERROR('Resumo-Cult.Perma.'!G56*'Critérios de Implantação'!$Q$64,0)+IFERROR('Resumo-Cult.Perma.'!F56*'Critérios de Implantação'!$Q$65,0)+IFERROR('Resumo-Cult.Perma.'!E56*'Critérios de Implantação'!$Q$66,0)+IFERROR('Resumo-Cult.Perma.'!D56*'Critérios de Implantação'!$Q$67,0)+IFERROR('Resumo-Cult.Perma.'!C56*'Critérios de Implantação'!$Q$68,0)+IFERROR('Resumo-Cult.Perma.'!B56*'Critérios de Implantação'!$Q$69,0) -> 2166609.4 | N93: =IFERROR('Resumo-Cult.Perma.'!K56*'Critérios de Implantação'!N$61,0)+IFERROR('Resumo-Cult.Perma.'!J56*'Critérios de Implantação'!N$62,0)+IFERROR('Resumo-Cult.Perma.'!I56*'Critérios de Implantação'!$Q$63,0)+IFERROR('Resumo-Cult.Perma.'!H56*'Critérios de Implantação'!$Q$64,0)+IFERROR('Resumo-Cult.Perma.'!G56*'Critérios de Implantação'!$Q$65,0)+IFERROR('Resumo-Cult.Perma.'!F56*'Critérios de Implantação'!$Q$66,0)+IFERROR('Resumo-Cult.Perma.'!E56*'Critérios de Implantação'!$Q$67,0)+IFERROR('Resumo-Cult.Perma.'!D56*'Critérios de Implantação'!$Q$68,0)+IFERROR('Resumo-Cult.Perma.'!C56*'Critérios de Implantação'!$Q$69,0) -> 2376167.8 | O93: =IFERROR('Resumo-Cult.Perma.'!L56*'Critérios de Implantação'!O$61,0)+IFERROR('Resumo-Cult.Perma.'!K56*'Critérios de Implantação'!O$62,0)+IFERROR('Resumo-Cult.Perma.'!J56*'Critérios de Implantação'!$Q$63,0)+IFERROR('Resumo-Cult.Perma.'!I56*'Critérios de Implantação'!$Q$64,0)+IFERROR('Resumo-Cult.Perma.'!H56*'Critérios de Implantação'!$Q$65,0)+IFERROR('Resumo-Cult.Perma.'!G56*'Critérios de Implantação'!$Q$66,0)+IFERROR('Resumo-Cult.Perma.'!F56*'Critérios de Implantação'!$Q$67,0)+IFERROR('Resumo-Cult.Perma.'!E56*'Critérios de Implantação'!$Q$68,0)+IFERROR('Resumo-Cult.Perma.'!D56*'Critérios de Implantação'!$Q$69,0) -> 2468115 | P93: =IFERROR('Resumo-Cult.Perma.'!M56*'Critérios de Implantação'!P$61,0)+IFERROR('Resumo-Cult.Perma.'!L56*'Critérios de Implantação'!P$62,0)+IFERROR('Resumo-Cult.Perma.'!K56*'Critérios de Implantação'!$Q$63,0)+IFERROR('Resumo-Cult.Perma.'!J56*'Critérios de Implantação'!$Q$64,0)+IFERROR('Resumo-Cult.Perma.'!I56*'Critérios de Implantação'!$Q$65,0)+IFERROR('Resumo-Cult.Perma.'!H56*'Critérios de Implantação'!$Q$66,0)+IFERROR('Resumo-Cult.Perma.'!G56*'Critérios de Implantação'!$Q$67,0)+IFERROR('Resumo-Cult.Perma.'!F56*'Critérios de Implantação'!$Q$68,0)+IFERROR('Resumo-Cult.Perma.'!E56*'Critérios de Implantação'!$Q$69,0) -> 2442519.4 | Q93: =IFERROR('Resumo-Cult.Perma.'!N56*'Critérios de Implantação'!Q$61,0)+IFERROR('Resumo-Cult.Perma.'!M56*'Critérios de Implantação'!Q$62,0)+IFERROR('Resumo-Cult.Perma.'!L56*'Critérios de Implantação'!$Q$63,0)+IFERROR('Resumo-Cult.Perma.'!K56*'Critérios de Implantação'!$Q$64,0)+IFERROR('Resumo-Cult.Perma.'!J56*'Critérios de Implantação'!$Q$65,0)+IFERROR('Resumo-Cult.Perma.'!I56*'Critérios de Implantação'!$Q$66,0)+IFERROR('Resumo-Cult.Perma.'!H56*'Critérios de Implantação'!$Q$67,0)+IFERROR('Resumo-Cult.Perma.'!G56*'Critérios de Implantação'!$Q$68,0)+IFERROR('Resumo-Cult.Perma.'!F56*'Critérios de Implantação'!$Q$69,0) -> 2442519.4 | R93: =IFERROR('Resumo-Cult.Perma.'!O56*'Critérios de Implantação'!R$61,0)+IFERROR('Resumo-Cult.Perma.'!N56*'Critérios de Implantação'!R$62,0)+IFERROR('Resumo-Cult.Perma.'!M56*'Critérios de Implantação'!$Q$63,0)+IFERROR('Resumo-Cult.Perma.'!L56*'Critérios de Implantação'!$Q$64,0)+IFERROR('Resumo-Cult.Perma.'!K56*'Critérios de Implantação'!$Q$65,0)+IFERROR('Resumo-Cult.Perma.'!J56*'Critérios de Implantação'!$Q$66,0)+IFERROR('Resumo-Cult.Perma.'!I56*'Critérios de Implantação'!$Q$67,0)+IFERROR('Resumo-Cult.Perma.'!H56*'Critérios de Implantação'!$Q$68,0)+IFERROR('Resumo-Cult.Perma.'!G56*'Critérios de Implantação'!$Q$69,0) -> 3059055.1 | S93: =IFERROR('Resumo-Cult.Perma.'!P56*'Critérios de Implantação'!S$61,0)+IFERROR('Resumo-Cult.Perma.'!O56*'Critérios de Implantação'!S$62,0)+IFERROR('Resumo-Cult.Perma.'!N56*'Critérios de Implantação'!$Q$63,0)+IFERROR('Resumo-Cult.Perma.'!M56*'Critérios de Implantação'!$Q$64,0)+IFERROR('Resumo-Cult.Perma.'!L56*'Critérios de Implantação'!$Q$65,0)+IFERROR('Resumo-Cult.Perma.'!K56*'Critérios de Implantação'!$Q$66,0)+IFERROR('Resumo-Cult.Perma.'!J56*'Critérios de Implantação'!$Q$67,0)+IFERROR('Resumo-Cult.Perma.'!I56*'Critérios de Implantação'!$Q$68,0)+IFERROR('Resumo-Cult.Perma.'!H56*'Critérios de Implantação'!$Q$69,0) -> 3098389 | ... AK93: =IFERROR('Resumo-Cult.Perma.'!AH56*'Critérios de Implantação'!AK$61,0)+IFERROR('Resumo-Cult.Perma.'!AG56*'Critérios de Implantação'!AK$62,0)+IFERROR('Resumo-Cult.Perma.'!AF56*'Critérios de Implantação'!$Q$63,0)+IFERROR('Resumo-Cult.Perma.'!AE56*'Critérios de Implantação'!$Q$64,0)+IFERROR('Resumo-Cult.Perma.'!AD56*'Critérios de Implantação'!$Q$65,0)+IFERROR('Resumo-Cult.Perma.'!AC56*'Critérios de Implantação'!$Q$66,0)+IFERROR('Resumo-Cult.Perma.'!AB56*'Critérios de Implantação'!$Q$67,0)+IFERROR('Resumo-Cult.Perma.'!AA56*'Critérios de Implantação'!$Q$68,0)+IFERROR('Resumo-Cult.Perma.'!Z56*'Critérios de Implantação'!$Q$69,0) -> 3311745.8
A94: 2.4 | B94: Outros custos | D94: =IFERROR('Resumo-Cult.Perma.'!A57*'Critérios de Implantação'!D$61,0)+IFERROR('Resumo-Cult.Perma.'!#REF!*'Critérios de Implantação'!D$62,0)+IFERROR('Resumo-Cult.Perma.'!#REF!*'Critérios de Implantação'!$Q$63,0)+IFERROR('Resumo-Cult.Perma.'!#REF!*'Critérios de Implantação'!$Q$64,0)+IFERROR('Resumo-Cult.Perma.'!#REF!*'Critérios de Implantação'!$Q$65,0)+IFERROR('Resumo-Cult.Perma.'!#REF!*'Critérios de Implantação'!$Q$66,0)+IFERROR('Resumo-Cult.Perma.'!#REF!*'Critérios de Implantação'!$Q$67,0)+IFERROR('Resumo-Cult.Perma.'!#REF!*'Critérios de Implantação'!$Q$68,0)+IFERROR('Resumo-Cult.Perma.'!#REF!*'Critérios de Implantação'!$Q$69,0) -> 0 | E94: =IFERROR('Resumo-Cult.Perma.'!B57*'Critérios de Implantação'!E$61,0)+IFERROR('Resumo-Cult.Perma.'!A57*'Critérios de Implantação'!E$62,0)+IFERROR('Resumo-Cult.Perma.'!#REF!*'Critérios de Implantação'!$Q$63,0)+IFERROR('Resumo-Cult.Perma.'!#REF!*'Critérios de Implantação'!$Q$64,0)+IFERROR('Resumo-Cult.Perma.'!#REF!*'Critérios de Implantação'!$Q$65,0)+IFERROR('Resumo-Cult.Perma.'!#REF!*'Critérios de Implantação'!$Q$66,0)+IFERROR('Resumo-Cult.Perma.'!#REF!*'Critérios de Implantação'!$Q$67,0)+IFERROR('Resumo-Cult.Perma.'!#REF!*'Critérios de Implantação'!$Q$68,0)+IFERROR('Resumo-Cult.Perma.'!#REF!*'Critérios de Implantação'!$Q$69,0) -> 0 | F94: =IFERROR('Resumo-Cult.Perma.'!C57*'Critérios de Implantação'!F$61,0)+IFERROR('Resumo-Cult.Perma.'!B57*'Critérios de Implantação'!F$62,0)+IFERROR('Resumo-Cult.Perma.'!A57*'Critérios de Implantação'!$Q$63,0)+IFERROR('Resumo-Cult.Perma.'!#REF!*'Critérios de Implantação'!$Q$64,0)+IFERROR('Resumo-Cult.Perma.'!#REF!*'Critérios de Implantação'!$Q$65,0)+IFERROR('Resumo-Cult.Perma.'!#REF!*'Critérios de Implantação'!$Q$66,0)+IFERROR('Resumo-Cult.Perma.'!#REF!*'Critérios de Implantação'!$Q$67,0)+IFERROR('Resumo-Cult.Perma.'!#REF!*'Critérios de Implantação'!$Q$68,0)+IFERROR('Resumo-Cult.Perma.'!#REF!*'Critérios de Implantação'!$Q$69,0) -> 0 | G94: =IFERROR('Resumo-Cult.Perma.'!D57*'Critérios de Implantação'!G$61,0)+IFERROR('Resumo-Cult.Perma.'!C57*'Critérios de Implantação'!G$62,0)+IFERROR('Resumo-Cult.Perma.'!B57*'Critérios de Implantação'!$Q$63,0)+IFERROR('Resumo-Cult.Perma.'!A57*'Critérios de Implantação'!$Q$64,0)+IFERROR('Resumo-Cult.Perma.'!#REF!*'Critérios de Implantação'!$Q$65,0)+IFERROR('Resumo-Cult.Perma.'!#REF!*'Critérios de Implantação'!$Q$66,0)+IFERROR('Resumo-Cult.Perma.'!#REF!*'Critérios de Implantação'!$Q$67,0)+IFERROR('Resumo-Cult.Perma.'!#REF!*'Critérios de Implantação'!$Q$68,0)+IFERROR('Resumo-Cult.Perma.'!#REF!*'Critérios de Implantação'!$Q$69,0) -> 265953.54 | H94: =IFERROR('Resumo-Cult.Perma.'!E57*'Critérios de Implantação'!H$61,0)+IFERROR('Resumo-Cult.Perma.'!D57*'Critérios de Implantação'!H$62,0)+IFERROR('Resumo-Cult.Perma.'!C57*'Critérios de Implantação'!$Q$63,0)+IFERROR('Resumo-Cult.Perma.'!B57*'Critérios de Implantação'!$Q$64,0)+IFERROR('Resumo-Cult.Perma.'!A57*'Critérios de Implantação'!$Q$65,0)+IFERROR('Resumo-Cult.Perma.'!#REF!*'Critérios de Implantação'!$Q$66,0)+IFERROR('Resumo-Cult.Perma.'!#REF!*'Critérios de Implantação'!$Q$67,0)+IFERROR('Resumo-Cult.Perma.'!#REF!*'Critérios de Implantação'!$Q$68,0)+IFERROR('Resumo-Cult.Perma.'!#REF!*'Critérios de Implantação'!$Q$69,0) -> 539134.83 | I94: =IFERROR('Resumo-Cult.Perma.'!F57*'Critérios de Implantação'!I$61,0)+IFERROR('Resumo-Cult.Perma.'!E57*'Critérios de Implantação'!I$62,0)+IFERROR('Resumo-Cult.Perma.'!D57*'Critérios de Implantação'!$Q$63,0)+IFERROR('Resumo-Cult.Perma.'!C57*'Critérios de Implantação'!$Q$64,0)+IFERROR('Resumo-Cult.Perma.'!B57*'Critérios de Implantação'!$Q$65,0)+IFERROR('Resumo-Cult.Perma.'!A57*'Critérios de Implantação'!$Q$66,0)+IFERROR('Resumo-Cult.Perma.'!#REF!*'Critérios de Implantação'!$Q$67,0)+IFERROR('Resumo-Cult.Perma.'!#REF!*'Critérios de Implantação'!$Q$68,0)+IFERROR('Resumo-Cult.Perma.'!#REF!*'Critérios de Implantação'!$Q$69,0) -> 865892.66 | J94: =IFERROR('Resumo-Cult.Perma.'!G57*'Critérios de Implantação'!J$61,0)+IFERROR('Resumo-Cult.Perma.'!F57*'Critérios de Implantação'!J$62,0)+IFERROR('Resumo-Cult.Perma.'!E57*'Critérios de Implantação'!$Q$63,0)+IFERROR('Resumo-Cult.Perma.'!D57*'Critérios de Implantação'!$Q$64,0)+IFERROR('Resumo-Cult.Perma.'!C57*'Critérios de Implantação'!$Q$65,0)+IFERROR('Resumo-Cult.Perma.'!B57*'Critérios de Implantação'!$Q$66,0)+IFERROR('Resumo-Cult.Perma.'!A57*'Critérios de Implantação'!$Q$67,0)+IFERROR('Resumo-Cult.Perma.'!#REF!*'Critérios de Implantação'!$Q$68,0)+IFERROR('Resumo-Cult.Perma.'!#REF!*'Critérios de Implantação'!$Q$69,0) -> 1498942.7 | K94: =IFERROR('Resumo-Cult.Perma.'!H57*'Critérios de Implantação'!K$61,0)+IFERROR('Resumo-Cult.Perma.'!G57*'Critérios de Implantação'!K$62,0)+IFERROR('Resumo-Cult.Perma.'!F57*'Critérios de Implantação'!$Q$63,0)+IFERROR('Resumo-Cult.Perma.'!E57*'Critérios de Implantação'!$Q$64,0)+IFERROR('Resumo-Cult.Perma.'!D57*'Critérios de Implantação'!$Q$65,0)+IFERROR('Resumo-Cult.Perma.'!C57*'Critérios de Implantação'!$Q$66,0)+IFERROR('Resumo-Cult.Perma.'!B57*'Critérios de Implantação'!$Q$67,0)+IFERROR('Resumo-Cult.Perma.'!A57*'Critérios de Implantação'!$Q$68,0)+IFERROR('Resumo-Cult.Perma.'!#REF!*'Critérios de Implantação'!$Q$69,0) -> 2101956.4 | L94: =IFERROR('Resumo-Cult.Perma.'!I57*'Critérios de Implantação'!L$61,0)+IFERROR('Resumo-Cult.Perma.'!H57*'Critérios de Implantação'!L$62,0)+IFERROR('Resumo-Cult.Perma.'!G57*'Critérios de Implantação'!$Q$63,0)+IFERROR('Resumo-Cult.Perma.'!F57*'Critérios de Implantação'!$Q$64,0)+IFERROR('Resumo-Cult.Perma.'!E57*'Critérios de Implantação'!$Q$65,0)+IFERROR('Resumo-Cult.Perma.'!D57*'Critérios de Implantação'!$Q$66,0)+IFERROR('Resumo-Cult.Perma.'!C57*'Critérios de Implantação'!$Q$67,0)+IFERROR('Resumo-Cult.Perma.'!B57*'Critérios de Implantação'!$Q$68,0)+IFERROR('Resumo-Cult.Perma.'!A57*'Critérios de Implantação'!$Q$69,0) -> 2736582.1 | M94: =IFERROR('Resumo-Cult.Perma.'!J57*'Critérios de Implantação'!M$61,0)+IFERROR('Resumo-Cult.Perma.'!I57*'Critérios de Implantação'!M$62,0)+IFERROR('Resumo-Cult.Perma.'!H57*'Critérios de Implantação'!$Q$63,0)+IFERROR('Resumo-Cult.Perma.'!G57*'Critérios de Implantação'!$Q$64,0)+IFERROR('Resumo-Cult.Perma.'!F57*'Critérios de Implantação'!$Q$65,0)+IFERROR('Resumo-Cult.Perma.'!E57*'Critérios de Implantação'!$Q$66,0)+IFERROR('Resumo-Cult.Perma.'!D57*'Critérios de Implantação'!$Q$67,0)+IFERROR('Resumo-Cult.Perma.'!C57*'Critérios de Implantação'!$Q$68,0)+IFERROR('Resumo-Cult.Perma.'!B57*'Critérios de Implantação'!$Q$69,0) -> 3269278.2 | N94: =IFERROR('Resumo-Cult.Perma.'!K57*'Critérios de Implantação'!N$61,0)+IFERROR('Resumo-Cult.Perma.'!J57*'Critérios de Implantação'!N$62,0)+IFERROR('Resumo-Cult.Perma.'!I57*'Critérios de Implantação'!$Q$63,0)+IFERROR('Resumo-Cult.Perma.'!H57*'Critérios de Implantação'!$Q$64,0)+IFERROR('Resumo-Cult.Perma.'!G57*'Critérios de Implantação'!$Q$65,0)+IFERROR('Resumo-Cult.Perma.'!F57*'Critérios de Implantação'!$Q$66,0)+IFERROR('Resumo-Cult.Perma.'!E57*'Critérios de Implantação'!$Q$67,0)+IFERROR('Resumo-Cult.Perma.'!D57*'Critérios de Implantação'!$Q$68,0)+IFERROR('Resumo-Cult.Perma.'!C57*'Critérios de Implantação'!$Q$69,0) -> 3659566 | O94: =IFERROR('Resumo-Cult.Perma.'!L57*'Critérios de Implantação'!O$61,0)+IFERROR('Resumo-Cult.Perma.'!K57*'Critérios de Implantação'!O$62,0)+IFERROR('Resumo-Cult.Perma.'!J57*'Critérios de Implantação'!$Q$63,0)+IFERROR('Resumo-Cult.Perma.'!I57*'Critérios de Implantação'!$Q$64,0)+IFERROR('Resumo-Cult.Perma.'!H57*'Critérios de Implantação'!$Q$65,0)+IFERROR('Resumo-Cult.Perma.'!G57*'Critérios de Implantação'!$Q$66,0)+IFERROR('Resumo-Cult.Perma.'!F57*'Critérios de Implantação'!$Q$67,0)+IFERROR('Resumo-Cult.Perma.'!E57*'Critérios de Implantação'!$Q$68,0)+IFERROR('Resumo-Cult.Perma.'!D57*'Critérios de Implantação'!$Q$69,0) -> 3891711.7 | P94: =IFERROR('Resumo-Cult.Perma.'!M57*'Critérios de Implantação'!P$61,0)+IFERROR('Resumo-Cult.Perma.'!L57*'Critérios de Implantação'!P$62,0)+IFERROR('Resumo-Cult.Perma.'!K57*'Critérios de Implantação'!$Q$63,0)+IFERROR('Resumo-Cult.Perma.'!J57*'Critérios de Implantação'!$Q$64,0)+IFERROR('Resumo-Cult.Perma.'!I57*'Critérios de Implantação'!$Q$65,0)+IFERROR('Resumo-Cult.Perma.'!H57*'Critérios de Implantação'!$Q$66,0)+IFERROR('Resumo-Cult.Perma.'!G57*'Critérios de Implantação'!$Q$67,0)+IFERROR('Resumo-Cult.Perma.'!F57*'Critérios de Implantação'!$Q$68,0)+IFERROR('Resumo-Cult.Perma.'!E57*'Critérios de Implantação'!$Q$69,0) -> 3941074.7 | Q94: =IFERROR('Resumo-Cult.Perma.'!N57*'Critérios de Implantação'!Q$61,0)+IFERROR('Resumo-Cult.Perma.'!M57*'Critérios de Implantação'!Q$62,0)+IFERROR('Resumo-Cult.Perma.'!L57*'Critérios de Implantação'!$Q$63,0)+IFERROR('Resumo-Cult.Perma.'!K57*'Critérios de Implantação'!$Q$64,0)+IFERROR('Resumo-Cult.Perma.'!J57*'Critérios de Implantação'!$Q$65,0)+IFERROR('Resumo-Cult.Perma.'!I57*'Critérios de Implantação'!$Q$66,0)+IFERROR('Resumo-Cult.Perma.'!H57*'Critérios de Implantação'!$Q$67,0)+IFERROR('Resumo-Cult.Perma.'!G57*'Critérios de Implantação'!$Q$68,0)+IFERROR('Resumo-Cult.Perma.'!F57*'Critérios de Implantação'!$Q$69,0) -> 3982804.5 | R94: =IFERROR('Resumo-Cult.Perma.'!O57*'Critérios de Implantação'!R$61,0)+IFERROR('Resumo-Cult.Perma.'!N57*'Critérios de Implantação'!R$62,0)+IFERROR('Resumo-Cult.Perma.'!M57*'Critérios de Implantação'!$Q$63,0)+IFERROR('Resumo-Cult.Perma.'!L57*'Critérios de Implantação'!$Q$64,0)+IFERROR('Resumo-Cult.Perma.'!K57*'Critérios de Implantação'!$Q$65,0)+IFERROR('Resumo-Cult.Perma.'!J57*'Critérios de Implantação'!$Q$66,0)+IFERROR('Resumo-Cult.Perma.'!I57*'Critérios de Implantação'!$Q$67,0)+IFERROR('Resumo-Cult.Perma.'!H57*'Critérios de Implantação'!$Q$68,0)+IFERROR('Resumo-Cult.Perma.'!G57*'Critérios de Implantação'!$Q$69,0) -> 3970517.9 | S94: =IFERROR('Resumo-Cult.Perma.'!P57*'Critérios de Implantação'!S$61,0)+IFERROR('Resumo-Cult.Perma.'!O57*'Critérios de Implantação'!S$62,0)+IFERROR('Resumo-Cult.Perma.'!N57*'Critérios de Implantação'!$Q$63,0)+IFERROR('Resumo-Cult.Perma.'!M57*'Critérios de Implantação'!$Q$64,0)+IFERROR('Resumo-Cult.Perma.'!L57*'Critérios de Implantação'!$Q$65,0)+IFERROR('Resumo-Cult.Perma.'!K57*'Critérios de Implantação'!$Q$66,0)+IFERROR('Resumo-Cult.Perma.'!J57*'Critérios de Implantação'!$Q$67,0)+IFERROR('Resumo-Cult.Perma.'!I57*'Critérios de Implantação'!$Q$68,0)+IFERROR('Resumo-Cult.Perma.'!H57*'Critérios de Implantação'!$Q$69,0) -> 3960304.2 | ... AK94: =IFERROR('Resumo-Cult.Perma.'!AH57*'Critérios de Implantação'!AK$61,0)+IFERROR('Resumo-Cult.Perma.'!AG57*'Critérios de Implantação'!AK$62,0)+IFERROR('Resumo-Cult.Perma.'!AF57*'Critérios de Implantação'!$Q$63,0)+IFERROR('Resumo-Cult.Perma.'!AE57*'Critérios de Implantação'!$Q$64,0)+IFERROR('Resumo-Cult.Perma.'!AD57*'Critérios de Implantação'!$Q$65,0)+IFERROR('Resumo-Cult.Perma.'!AC57*'Critérios de Implantação'!$Q$66,0)+IFERROR('Resumo-Cult.Perma.'!AB57*'Critérios de Implantação'!$Q$67,0)+IFERROR('Resumo-Cult.Perma.'!AA57*'Critérios de Implantação'!$Q$68,0)+IFERROR('Resumo-Cult.Perma.'!Z57*'Critérios de Implantação'!$Q$69,0) -> 3786453
B95: Sub-total - custos operacionais | D95: =SUM(D91:D94) -> 0 | E95: =SUM(E91:E94) -> 0 | F95: =SUM(F91:F94) -> 0 | G95: =SUM(G91:G94) -> 1849693.2 | H95: =SUM(H91:H94) -> 3632918.1 | I95: =SUM(I91:I94) -> 5750799.9 | J95: =SUM(J91:J94) -> 9868413.4 | K95: =SUM(K91:K94) -> 13611820 | ... AK95: =SUM(AK91:AK94) -> 24667593
A97: 3 | B97: ENTRADA - VALOR DA PRODUÇÃO
A98: 3.2 | B98: ="Valor da produção "&A74 -> Valor da produção Banana Prata | D98: =IFERROR(('Resumo-Cult.Perma.'!C58*('Critérios de Implantação'!D$61)),0)+IFERROR(('Resumo-Cult.Perma.'!B58*('Critérios de Implantação'!D$62)),0)+IFERROR(('Resumo-Cult.Perma.'!A58*('Critérios de Implantação'!D$69)),0) -> 0 | E98: =IFERROR(('Resumo-Cult.Perma.'!D61*('Critérios de Implantação'!E$61)),0)+IFERROR(('Resumo-Cult.Perma.'!C61*('Critérios de Implantação'!E$62)),0)+IFERROR(('Resumo-Cult.Perma.'!B61*('Critérios de Implantação'!E$69)),0) -> 0 | F98: =IFERROR(('Resumo-Cult.Perma.'!E61*('Critérios de Implantação'!F$61)),0)+IFERROR(('Resumo-Cult.Perma.'!D61*('Critérios de Implantação'!F$62)),0)+IFERROR(('Resumo-Cult.Perma.'!C61*('Critérios de Implantação'!F$69)),0) -> 0 | G98: =IFERROR(('Resumo-Cult.Perma.'!D61*('Critérios de Implantação'!G$61)),0)+IFERROR(('Resumo-Cult.Perma.'!C61*('Critérios de Implantação'!G$62)),0)+IFERROR(('Resumo-Cult.Perma.'!B61*('Critérios de Implantação'!G$63)),0)+IFERROR(('Resumo-Cult.Perma.'!A6128*('Critérios de Implantação'!G$64)),0)+IFERROR(('Resumo-Cult.Perma.'!#REF!*('Critérios de Implantação'!G$65)),0)+IFERROR(('Resumo-Cult.Perma.'!#REF!*('Critérios de Implantação'!G$66)),0)+IFERROR(('Resumo-Cult.Perma.'!#REF!*('Critérios de Implantação'!G$67)),0)+IFERROR(('Resumo-Cult.Perma.'!#REF!*('Critérios de Implantação'!G$68)),0)+IFERROR(('Resumo-Cult.Perma.'!#REF!*('Critérios de Implantação'!G$69)),0) -> 5167534.1 | H98: =IFERROR(('Resumo-Cult.Perma.'!E61*('Critérios de Implantação'!H$61)),0)+IFERROR(('Resumo-Cult.Perma.'!D61*('Critérios de Implantação'!H$62)),0)+IFERROR(('Resumo-Cult.Perma.'!C61*('Critérios de Implantação'!H$63)),0)+IFERROR(('Resumo-Cult.Perma.'!B6128*('Critérios de Implantação'!H$64)),0)+IFERROR(('Resumo-Cult.Perma.'!#REF!*('Critérios de Implantação'!H$65)),0)+IFERROR(('Resumo-Cult.Perma.'!#REF!*('Critérios de Implantação'!H$66)),0)+IFERROR(('Resumo-Cult.Perma.'!#REF!*('Critérios de Implantação'!H$67)),0)+IFERROR(('Resumo-Cult.Perma.'!#REF!*('Critérios de Implantação'!H$68)),0)+IFERROR(('Resumo-Cult.Perma.'!#REF!*('Critérios de Implantação'!H$69)),0) -> 9929771.4 | I98: =IFERROR(('Resumo-Cult.Perma.'!F61*('Critérios de Implantação'!I$61)),0)+IFERROR(('Resumo-Cult.Perma.'!E61*('Critérios de Implantação'!I$62)),0)+IFERROR(('Resumo-Cult.Perma.'!D61*('Critérios de Implantação'!I$63)),0)+IFERROR(('Resumo-Cult.Perma.'!C6128*('Critérios de Implantação'!I$64)),0)+IFERROR(('Resumo-Cult.Perma.'!#REF!*('Critérios de Implantação'!I$65)),0)+IFERROR(('Resumo-Cult.Perma.'!#REF!*('Critérios de Implantação'!I$66)),0)+IFERROR(('Resumo-Cult.Perma.'!#REF!*('Critérios de Implantação'!I$67)),0)+IFERROR(('Resumo-Cult.Perma.'!#REF!*('Critérios de Implantação'!I$68)),0)+IFERROR(('Resumo-Cult.Perma.'!#REF!*('Critérios de Implantação'!I$69)),0) -> 15327715 | J98: =IFERROR(('Resumo-Cult.Perma.'!G61*('Critérios de Implantação'!J$61)),0)+IFERROR(('Resumo-Cult.Perma.'!F61*('Critérios de Implantação'!J$62)),0)+IFERROR(('Resumo-Cult.Perma.'!E61*('Critérios de Implantação'!J$63)),0)+IFERROR(('Resumo-Cult.Perma.'!D61*('Critérios de Implantação'!J$64)),0)+IFERROR(('Resumo-Cult.Perma.'!#REF!*('Critérios de Implantação'!J$65)),0)+IFERROR(('Resumo-Cult.Perma.'!#REF!*('Critérios de Implantação'!J$66)),0)+IFERROR(('Resumo-Cult.Perma.'!#REF!*('Critérios de Implantação'!J$67)),0)+IFERROR(('Resumo-Cult.Perma.'!#REF!*('Critérios de Implantação'!J$68)),0)+IFERROR(('Resumo-Cult.Perma.'!#REF!*('Critérios de Implantação'!J$69)),0) -> 26151584 | K98: =IFERROR(('Resumo-Cult.Perma.'!H61*('Critérios de Implantação'!K$61)),0)+IFERROR(('Resumo-Cult.Perma.'!G61*('Critérios de Implantação'!K$62)),0)+IFERROR(('Resumo-Cult.Perma.'!F61*('Critérios de Implantação'!K$63)),0)+IFERROR(('Resumo-Cult.Perma.'!E61*('Critérios de Implantação'!K$64)),0)+IFERROR(('Resumo-Cult.Perma.'!D61*('Critérios de Implantação'!K$65)),0)+IFERROR(('Resumo-Cult.Perma.'!#REF!*('Critérios de Implantação'!K$66)),0)+IFERROR(('Resumo-Cult.Perma.'!#REF!*('Critérios de Implantação'!K$67)),0)+IFERROR(('Resumo-Cult.Perma.'!#REF!*('Critérios de Implantação'!K$68)),0)+IFERROR(('Resumo-Cult.Perma.'!#REF!*('Critérios de Implantação'!K$69)),0) -> 35424482 | L98: =IFERROR(('Resumo-Cult.Perma.'!I61*('Critérios de Implantação'!L$61)),0)+IFERROR(('Resumo-Cult.Perma.'!H61*('Critérios de Implantação'!L$62)),0)+IFERROR(('Resumo-Cult.Perma.'!G61*('Critérios de Implantação'!L$63)),0)+IFERROR(('Resumo-Cult.Perma.'!F61*('Critérios de Implantação'!L$64)),0)+IFERROR(('Resumo-Cult.Perma.'!E61*('Critérios de Implantação'!L$65)),0)+IFERROR(('Resumo-Cult.Perma.'!D61*('Critérios de Implantação'!L$66)),0)+IFERROR(('Resumo-Cult.Perma.'!#REF!*('Critérios de Implantação'!L$67)),0)+IFERROR(('Resumo-Cult.Perma.'!#REF!*('Critérios de Implantação'!L$68)),0)+IFERROR(('Resumo-Cult.Perma.'!#REF!*('Critérios de Implantação'!L$69)),0) -> 44166436 | M98: =IFERROR(('Resumo-Cult.Perma.'!J61*('Critérios de Implantação'!M$61)),0)+IFERROR(('Resumo-Cult.Perma.'!I61*('Critérios de Implantação'!M$62)),0)+IFERROR(('Resumo-Cult.Perma.'!H61*('Critérios de Implantação'!M$63)),0)+IFERROR(('Resumo-Cult.Perma.'!G61*('Critérios de Implantação'!M$64)),0)+IFERROR(('Resumo-Cult.Perma.'!F61*('Critérios de Implantação'!M$65)),0)+IFERROR(('Resumo-Cult.Perma.'!E61*('Critérios de Implantação'!M$66)),0)+IFERROR(('Resumo-Cult.Perma.'!D61*('Critérios de Implantação'!M$67)),0)+IFERROR(('Resumo-Cult.Perma.'!#REF!*('Critérios de Implantação'!M$68)),0)+IFERROR(('Resumo-Cult.Perma.'!#REF!*('Critérios de Implantação'!M$69)),0) -> 50431321 | N98: =IFERROR(('Resumo-Cult.Perma.'!K61*('Critérios de Implantação'!N$61)),0)+IFERROR(('Resumo-Cult.Perma.'!J61*('Critérios de Implantação'!N$62)),0)+IFERROR(('Resumo-Cult.Perma.'!I61*('Critérios de Implantação'!N$63)),0)+IFERROR(('Resumo-Cult.Perma.'!H61*('Critérios de Implantação'!N$64)),0)+IFERROR(('Resumo-Cult.Perma.'!G61*('Critérios de Implantação'!N$65)),0)+IFERROR(('Resumo-Cult.Perma.'!F61*('Critérios de Implantação'!N$66)),0)+IFERROR(('Resumo-Cult.Perma.'!E61*('Critérios de Implantação'!N$67)),0)+IFERROR(('Resumo-Cult.Perma.'!D61*('Critérios de Implantação'!N$68)),0)+IFERROR(('Resumo-Cult.Perma.'!#REF!*('Critérios de Implantação'!N$69)),0) -> 53743932 | O98: =IFERROR(('Resumo-Cult.Perma.'!L61*('Critérios de Implantação'!O$61)),0)+IFERROR(('Resumo-Cult.Perma.'!K61*('Critérios de Implantação'!O$62)),0)+IFERROR(('Resumo-Cult.Perma.'!J61*('Critérios de Implantação'!O$63)),0)+IFERROR(('Resumo-Cult.Perma.'!I61*('Critérios de Implantação'!O$64)),0)+IFERROR(('Resumo-Cult.Perma.'!H61*('Critérios de Implantação'!O$65)),0)+IFERROR(('Resumo-Cult.Perma.'!G61*('Critérios de Implantação'!O$66)),0)+IFERROR(('Resumo-Cult.Perma.'!F61*('Critérios de Implantação'!O$67)),0)+IFERROR(('Resumo-Cult.Perma.'!E61*('Critérios de Implantação'!O$68)),0)+IFERROR(('Resumo-Cult.Perma.'!D61*('Critérios de Implantação'!O$69)),0) -> 53687510 | P98: =IFERROR(('Resumo-Cult.Perma.'!M61*('Critérios de Implantação'!P$61)),0)+IFERROR(('Resumo-Cult.Perma.'!L61*('Critérios de Implantação'!P$62)),0)+IFERROR(('Resumo-Cult.Perma.'!K61*('Critérios de Implantação'!P$63)),0)+IFERROR(('Resumo-Cult.Perma.'!J61*('Critérios de Implantação'!P$64)),0)+IFERROR(('Resumo-Cult.Perma.'!I61*('Critérios de Implantação'!P$65)),0)+IFERROR(('Resumo-Cult.Perma.'!H61*('Critérios de Implantação'!P$66)),0)+IFERROR(('Resumo-Cult.Perma.'!G61*('Critérios de Implantação'!P$67)),0)+IFERROR(('Resumo-Cult.Perma.'!F61*('Critérios de Implantação'!P$68)),0)+IFERROR(('Resumo-Cult.Perma.'!E61*('Critérios de Implantação'!P$69)),0) -> 50218949 | Q98: =IFERROR(('Resumo-Cult.Perma.'!N61*('Critérios de Implantação'!Q$61)),0)+IFERROR(('Resumo-Cult.Perma.'!M61*('Critérios de Implantação'!Q$62)),0)+IFERROR(('Resumo-Cult.Perma.'!L61*('Critérios de Implantação'!Q$63)),0)+IFERROR(('Resumo-Cult.Perma.'!K61*('Critérios de Implantação'!Q$64)),0)+IFERROR(('Resumo-Cult.Perma.'!J61*('Critérios de Implantação'!Q$65)),0)+IFERROR(('Resumo-Cult.Perma.'!I61*('Critérios de Implantação'!Q$66)),0)+IFERROR(('Resumo-Cult.Perma.'!H61*('Critérios de Implantação'!Q$67)),0)+IFERROR(('Resumo-Cult.Perma.'!G61*('Critérios de Implantação'!Q$68)),0)+IFERROR(('Resumo-Cult.Perma.'!F61*('Critérios de Implantação'!Q$69)),0) -> 47234429 | R98: =IFERROR(('Resumo-Cult.Perma.'!O61*('Critérios de Implantação'!R$61)),0)+IFERROR(('Resumo-Cult.Perma.'!N61*('Critérios de Implantação'!R$62)),0)+IFERROR(('Resumo-Cult.Perma.'!M61*('Critérios de Implantação'!R$63)),0)+IFERROR(('Resumo-Cult.Perma.'!L61*('Critérios de Implantação'!R$64)),0)+IFERROR(('Resumo-Cult.Perma.'!K61*('Critérios de Implantação'!R$65)),0)+IFERROR(('Resumo-Cult.Perma.'!J61*('Critérios de Implantação'!R$66)),0)+IFERROR(('Resumo-Cult.Perma.'!I61*('Critérios de Implantação'!R$67)),0)+IFERROR(('Resumo-Cult.Perma.'!H61*('Critérios de Implantação'!R$68)),0)+IFERROR(('Resumo-Cult.Perma.'!G61*('Critérios de Implantação'!R$69)),0) -> 42421554 | S98: =IFERROR(('Resumo-Cult.Perma.'!P61*('Critérios de Implantação'!S$61)),0)+IFERROR(('Resumo-Cult.Perma.'!O61*('Critérios de Implantação'!S$62)),0)+IFERROR(('Resumo-Cult.Perma.'!N61*('Critérios de Implantação'!S$63)),0)+IFERROR(('Resumo-Cult.Perma.'!M61*('Critérios de Implantação'!S$64)),0)+IFERROR(('Resumo-Cult.Perma.'!L61*('Critérios de Implantação'!S$65)),0)+IFERROR(('Resumo-Cult.Perma.'!K61*('Critérios de Implantação'!S$66)),0)+IFERROR(('Resumo-Cult.Perma.'!J61*('Critérios de Implantação'!S$67)),0)+IFERROR(('Resumo-Cult.Perma.'!I61*('Critérios de Implantação'!S$68)),0)+IFERROR(('Resumo-Cult.Perma.'!H61*('Critérios de Implantação'!S$69)),0) -> 42805571 | T98: =IFERROR(('Resumo-Cult.Perma.'!Q61*('Critérios de Implantação'!T$61)),0)+IFERROR(('Resumo-Cult.Perma.'!P61*('Critérios de Implantação'!T$62)),0)+IFERROR(('Resumo-Cult.Perma.'!O61*('Critérios de Implantação'!T$63)),0)+IFERROR(('Resumo-Cult.Perma.'!N61*('Critérios de Implantação'!T$64)),0)+IFERROR(('Resumo-Cult.Perma.'!M61*('Critérios de Implantação'!T$65)),0)+IFERROR(('Resumo-Cult.Perma.'!L61*('Critérios de Implantação'!T$66)),0)+IFERROR(('Resumo-Cult.Perma.'!K61*('Critérios de Implantação'!T$67)),0)+IFERROR(('Resumo-Cult.Perma.'!J61*('Critérios de Implantação'!T$68)),0)+IFERROR(('Resumo-Cult.Perma.'!I61*('Critérios de Implantação'!T$69)),0) -> 42245692 | U98: =IFERROR(('Resumo-Cult.Perma.'!R61*('Critérios de Implantação'!U$61)),0)+IFERROR(('Resumo-Cult.Perma.'!Q61*('Critérios de Implantação'!U$62)),0)+IFERROR(('Resumo-Cult.Perma.'!P61*('Critérios de Implantação'!U$63)),0)+IFERROR(('Resumo-Cult.Perma.'!O61*('Critérios de Implantação'!U$64)),0)+IFERROR(('Resumo-Cult.Perma.'!N61*('Critérios de Implantação'!U$65)),0)+IFERROR(('Resumo-Cult.Perma.'!M61*('Critérios de Implantação'!U$66)),0)+IFERROR(('Resumo-Cult.Perma.'!L61*('Critérios de Implantação'!U$67)),0)+IFERROR(('Resumo-Cult.Perma.'!K61*('Critérios de Implantação'!U$68)),0)+IFERROR(('Resumo-Cult.Perma.'!J61*('Critérios de Implantação'!U$69)),0) -> 39899852 | V98: =IFERROR(('Resumo-Cult.Perma.'!S61*('Critérios de Implantação'!V$61)),0)+IFERROR(('Resumo-Cult.Perma.'!R61*('Critérios de Implantação'!V$62)),0)+IFERROR(('Resumo-Cult.Perma.'!Q61*('Critérios de Implantação'!V$63)),0)+IFERROR(('Resumo-Cult.Perma.'!P61*('Critérios de Implantação'!V$64)),0)+IFERROR(('Resumo-Cult.Perma.'!O61*('Critérios de Implantação'!V$65)),0)+IFERROR(('Resumo-Cult.Perma.'!N61*('Critérios de Implantação'!V$66)),0)+IFERROR(('Resumo-Cult.Perma.'!M61*('Critérios de Implantação'!V$67)),0)+IFERROR(('Resumo-Cult.Perma.'!L61*('Critérios de Implantação'!V$68)),0)+IFERROR(('Resumo-Cult.Perma.'!K61*('Critérios de Implantação'!V$69)),0) -> 43848246 | ... AK98: =IFERROR(('Resumo-Cult.Perma.'!AH61*('Critérios de Implantação'!AK$61)),0)+IFERROR(('Resumo-Cult.Perma.'!AG61*('Critérios de Implantação'!AK$62)),0)+IFERROR(('Resumo-Cult.Perma.'!AF61*('Critérios de Implantação'!AK$63)),0)+IFERROR(('Resumo-Cult.Perma.'!AE61*('Critérios de Implantação'!AK$64)),0)+IFERROR(('Resumo-Cult.Perma.'!AD61*('Critérios de Implantação'!AK$65)),0)+IFERROR(('Resumo-Cult.Perma.'!AC61*('Critérios de Implantação'!AK$66)),0)+IFERROR(('Resumo-Cult.Perma.'!AB61*('Critérios de Implantação'!AK$67)),0)+IFERROR(('Resumo-Cult.Perma.'!AA61*('Critérios de Implantação'!AK$68)),0)+IFERROR(('Resumo-Cult.Perma.'!Z61*('Critérios de Implantação'!AK$69)),0) -> 53872476
B99: Sub-total - valor da produção | D99: =SUM(D98:D98) -> 0 | E99: =SUM(E98:E98) -> 0 | F99: =SUM(F98:F98) -> 0 | G99: =SUM(G98:G98) -> 5167534.1 | H99: =SUM(H98:H98) -> 9929771.4 | I99: =SUM(I98:I98) -> 15327715 | J99: =SUM(J98:J98) -> 26151584 | K99: =SUM(K98:K98) -> 35424482 | ... AK99: =SUM(AK98:AK98) -> 53872476
A101: 4 | B101: BALANÇO Anual (Item 3 - item 1 - item 2) | D101: =D99-D95-D88 -> 0 | E101: =E99-E95-E88 -> 0 | F101: =F99-F95-F88 -> -5192117.9 | G101: =G99-G95-G88 -> -1874277 | H101: =H99-H95-H88 -> 58779.565 | I101: =I99-I95-I88 -> -2471263.2 | J101: =J99-J95-J88 -> 4979280.1 | K101: =K99-K95-K88 -> 10182030 | ... AK101: =AK99-AK95-AK88 -> 29204882
A103: 5 | B103: BALANÇO ACUMULADO | D103: =D101 -> 0 | E103: =D103+E101 -> 0 | F103: =E103+F101 -> -5192117.9 | G103: =F103+G101 -> -7066394.9 | H103: =G103+H101 -> -7007615.3 | I103: =H103+I101 -> -9478878.6 | J103: =I103+J101 -> -4499598.5 | K103: =J103+K101 -> 5682432 | L103: =K103+L101 -> 22963348 | ... AK103: =AJ103+AK101 -> 6.4088062e+08
A105: Manga
A106: Planejamento Manga
A107: ITEM | B107: COMPONENTES | C107: ANO DE IMPLANTAÇÃO DA CULTURA
C108: 1 | D108: =C108+1 -> 2 | E108: =D108+1 -> 3 | F108: =E108+1 -> 4 | G108: =F108+1 -> 5 | H108: =G108+1 -> 6 | I108: =H108+1 -> 7 | J108: =I108+1 -> 8 | K108: =J108+1 -> 9 | ... AK108: =AJ108+1 -> 35
A109: 1 | B109: INVESTIMENTOS
A110: 1.1 | B110: Supressão vegetal | D110: ='Resumo-Cult.Perma.'!C75*'Critérios de Implantação'!$D$33 -> 0 | E110: ='Resumo-Cult.Perma.'!$D75*'Critérios de Implantação'!D$33+'Resumo-Cult.Perma.'!$C75*'Critérios de Implantação'!E$33 -> 0 | F110: ='Resumo-Cult.Perma.'!$D75*'Critérios de Implantação'!E$33+'Resumo-Cult.Perma.'!$C75*'Critérios de Implantação'!F$33 -> 81416.426 | G110: ='Resumo-Cult.Perma.'!$D75*'Critérios de Implantação'!F$33+'Resumo-Cult.Perma.'!$C75*'Critérios de Implantação'!G$33 -> 81416.426 | H110: ='Resumo-Cult.Perma.'!$D75*'Critérios de Implantação'!G$33+'Resumo-Cult.Perma.'!$C75*'Critérios de Implantação'!H$33 -> 97817.822 | I110: ='Resumo-Cult.Perma.'!$D75*'Critérios de Implantação'!H$33+'Resumo-Cult.Perma.'!$C75*'Critérios de Implantação'!I$33 -> 188924.76 | J110: ='Resumo-Cult.Perma.'!$D75*'Critérios de Implantação'!I$33+'Resumo-Cult.Perma.'!$C75*'Critérios de Implantação'!J$33 -> 177253.75 | K110: ='Resumo-Cult.Perma.'!$D75*'Critérios de Implantação'!J$33+'Resumo-Cult.Perma.'!$C75*'Critérios de Implantação'!K$33 -> 182377.3 | L110: ='Resumo-Cult.Perma.'!$D75*'Critérios de Implantação'!K$33+'Resumo-Cult.Perma.'!$C75*'Critérios de Implantação'!L$33 -> 148558.37 | ... AK110: ='Resumo-Cult.Perma.'!$D75*'Critérios de Implantação'!AJ$33+'Resumo-Cult.Perma.'!$C75*'Critérios de Implantação'!AK$33 -> 0
A111: 1.2 | B111: Sistema de irrigação localizada | D111: ='Resumo-Cult.Perma.'!C76*'Critérios de Implantação'!$D$33 -> 0 | E111: ='Resumo-Cult.Perma.'!$D76*'Critérios de Implantação'!D$33+'Resumo-Cult.Perma.'!$C76*'Critérios de Implantação'!E$33 -> 0 | F111: ='Resumo-Cult.Perma.'!$D76*'Critérios de Implantação'!E$33+'Resumo-Cult.Perma.'!$C76*'Critérios de Implantação'!F$33 -> 1384554.3 | G111: ='Resumo-Cult.Perma.'!$D76*'Critérios de Implantação'!F$33+'Resumo-Cult.Perma.'!$C76*'Critérios de Implantação'!G$33 -> 1384554.3 | H111: ='Resumo-Cult.Perma.'!$D76*'Critérios de Implantação'!G$33+'Resumo-Cult.Perma.'!$C76*'Critérios de Implantação'!H$33 -> 1663473.7 | I111: ='Resumo-Cult.Perma.'!$D76*'Critérios de Implantação'!H$33+'Resumo-Cult.Perma.'!$C76*'Critérios de Implantação'!I$33 -> 3212823.2 | J111: ='Resumo-Cult.Perma.'!$D76*'Critérios de Implantação'!I$33+'Resumo-Cult.Perma.'!$C76*'Critérios de Implantação'!J$33 -> 3014348 | K111: ='Resumo-Cult.Perma.'!$D76*'Critérios de Implantação'!J$33+'Resumo-Cult.Perma.'!$C76*'Critérios de Implantação'!K$33 -> 3101478.2 | L111: ='Resumo-Cult.Perma.'!$D76*'Critérios de Implantação'!K$33+'Resumo-Cult.Perma.'!$C76*'Critérios de Implantação'!L$33 -> 2526359 | ... AK111: ='Resumo-Cult.Perma.'!$D76*'Critérios de Implantação'!AJ$33+'Resumo-Cult.Perma.'!$C76*'Critérios de Implantação'!AK$33 -> 0
A112: 1.3 | B112: Sistema de irrigação pivô central | D112: ='Resumo-Cult.Perma.'!C77*'Critérios de Implantação'!$D$33 -> 0 | E112: ='Resumo-Cult.Perma.'!$D77*'Critérios de Implantação'!D$33+'Resumo-Cult.Perma.'!$C77*'Critérios de Implantação'!E$33 -> 0 | F112: ='Resumo-Cult.Perma.'!$D77*'Critérios de Implantação'!E$33+'Resumo-Cult.Perma.'!$C77*'Critérios de Implantação'!F$33 -> 0 | G112: ='Resumo-Cult.Perma.'!$D77*'Critérios de Implantação'!F$33+'Resumo-Cult.Perma.'!$C77*'Critérios de Implantação'!G$33 -> 0 | H112: ='Resumo-Cult.Perma.'!$D77*'Critérios de Implantação'!G$33+'Resumo-Cult.Perma.'!$C77*'Critérios de Implantação'!H$33 -> 0 | I112: ='Resumo-Cult.Perma.'!$D77*'Critérios de Implantação'!H$33+'Resumo-Cult.Perma.'!$C77*'Critérios de Implantação'!I$33 -> 0 | J112: ='Resumo-Cult.Perma.'!$D77*'Critérios de Implantação'!I$33+'Resumo-Cult.Perma.'!$C77*'Critérios de Implantação'!J$33 -> 0 | K112: ='Resumo-Cult.Perma.'!$D77*'Critérios de Implantação'!J$33+'Resumo-Cult.Perma.'!$C77*'Critérios de Implantação'!K$33 -> 0 | L112: ='Resumo-Cult.Perma.'!$D77*'Critérios de Implantação'!K$33+'Resumo-Cult.Perma.'!$C77*'Critérios de Implantação'!L$33 -> 0 | ... AK112: ='Resumo-Cult.Perma.'!$D77*'Critérios de Implantação'!AJ$33+'Resumo-Cult.Perma.'!$C77*'Critérios de Implantação'!AK$33 -> 0
A113: 1.4 | B113: Demais infraestrutura | D113: ='Resumo-Cult.Perma.'!C78*'Critérios de Implantação'!$D$33 -> 0 | E113: ='Resumo-Cult.Perma.'!$D78*'Critérios de Implantação'!D$33+'Resumo-Cult.Perma.'!$C78*'Critérios de Implantação'!E$33 -> 0 | F113: ='Resumo-Cult.Perma.'!$D78*'Critérios de Implantação'!E$33+'Resumo-Cult.Perma.'!$C78*'Critérios de Implantação'!F$33 -> 803255.45 | G113: ='Resumo-Cult.Perma.'!$D78*'Critérios de Implantação'!F$33+'Resumo-Cult.Perma.'!$C78*'Critérios de Implantação'!G$33 -> 803255.45 | H113: ='Resumo-Cult.Perma.'!$D78*'Critérios de Implantação'!G$33+'Resumo-Cult.Perma.'!$C78*'Critérios de Implantação'!H$33 -> 965071.83 | I113: ='Resumo-Cult.Perma.'!$D78*'Critérios de Implantação'!H$33+'Resumo-Cult.Perma.'!$C78*'Critérios de Implantação'!I$33 -> 1863934 | J113: ='Resumo-Cult.Perma.'!$D78*'Critérios de Implantação'!I$33+'Resumo-Cult.Perma.'!$C78*'Critérios de Implantação'!J$33 -> 1748787.7 | K113: ='Resumo-Cult.Perma.'!$D78*'Critérios de Implantação'!J$33+'Resumo-Cult.Perma.'!$C78*'Critérios de Implantação'!K$33 -> 1799336.7 | L113: ='Resumo-Cult.Perma.'!$D78*'Critérios de Implantação'!K$33+'Resumo-Cult.Perma.'!$C78*'Critérios de Implantação'!L$33 -> 1465678.6 | ... AK113: ='Resumo-Cult.Perma.'!$D78*'Critérios de Implantação'!AJ$33+'Resumo-Cult.Perma.'!$C78*'Critérios de Implantação'!AK$33 -> 0
B114: Ano de formação da cultura | D114: ='Resumo-Cult.Perma.'!C79*'Critérios de Implantação'!$D$33 -> 0 | E114: ='Resumo-Cult.Perma.'!$D79*'Critérios de Implantação'!D$33+'Resumo-Cult.Perma.'!$C79*'Critérios de Implantação'!E$33 -> 0 | F114: ='Resumo-Cult.Perma.'!$D79*'Critérios de Implantação'!E$33+'Resumo-Cult.Perma.'!$C79*'Critérios de Implantação'!F$33 -> 0 | G114: ='Resumo-Cult.Perma.'!$D79*'Critérios de Implantação'!F$33+'Resumo-Cult.Perma.'!$C79*'Critérios de Implantação'!G$33 -> 0 | H114: ='Resumo-Cult.Perma.'!$D79*'Critérios de Implantação'!G$33+'Resumo-Cult.Perma.'!$C79*'Critérios de Implantação'!H$33 -> 0 | I114: ='Resumo-Cult.Perma.'!$D79*'Critérios de Implantação'!H$33+'Resumo-Cult.Perma.'!$C79*'Critérios de Implantação'!I$33 -> 0 | J114: ='Resumo-Cult.Perma.'!$D79*'Critérios de Implantação'!I$33+'Resumo-Cult.Perma.'!$C79*'Critérios de Implantação'!J$33 -> 0 | K114: ='Resumo-Cult.Perma.'!$D79*'Critérios de Implantação'!J$33+'Resumo-Cult.Perma.'!$C79*'Critérios de Implantação'!K$33 -> 0 | L114: ='Resumo-Cult.Perma.'!$D79*'Critérios de Implantação'!K$33+'Resumo-Cult.Perma.'!$C79*'Critérios de Implantação'!L$33 -> 0 | ... AK114: ='Resumo-Cult.Perma.'!$D79*'Critérios de Implantação'!AJ$33+'Resumo-Cult.Perma.'!$C79*'Critérios de Implantação'!AK$33 -> 0
A115: 1.5 | B115: Gasto com insumos | D115: ='Resumo-Cult.Perma.'!C80*'Critérios de Implantação'!$D$33 -> 0 | E115: ='Resumo-Cult.Perma.'!$D80*'Critérios de Implantação'!D$33+'Resumo-Cult.Perma.'!$C80*'Critérios de Implantação'!E$33 -> 0 | F115: ='Resumo-Cult.Perma.'!$D80*'Critérios de Implantação'!E$33+'Resumo-Cult.Perma.'!$C80*'Critérios de Implantação'!F$33 -> 1404026.1 | G115: ='Resumo-Cult.Perma.'!$D80*'Critérios de Implantação'!F$33+'Resumo-Cult.Perma.'!$C80*'Critérios de Implantação'!G$33 -> 1873840.1 | H115: ='Resumo-Cult.Perma.'!$D80*'Critérios de Implantação'!G$33+'Resumo-Cult.Perma.'!$C80*'Critérios de Implantação'!H$33 -> 2156682.2 | I115: ='Resumo-Cult.Perma.'!$D80*'Critérios de Implantação'!H$33+'Resumo-Cult.Perma.'!$C80*'Critérios de Implantação'!I$33 -> 3822465.6 | J115: ='Resumo-Cult.Perma.'!$D80*'Critérios de Implantação'!I$33+'Resumo-Cult.Perma.'!$C80*'Critérios de Implantação'!J$33 -> 4146932.2 | K115: ='Resumo-Cult.Perma.'!$D80*'Critérios de Implantação'!J$33+'Resumo-Cult.Perma.'!$C80*'Critérios de Implantação'!K$33 -> 4167940.1 | L115: ='Resumo-Cult.Perma.'!$D80*'Critérios de Implantação'!K$33+'Resumo-Cult.Perma.'!$C80*'Critérios de Implantação'!L$33 -> 3614298.1 | ... AK115: ='Resumo-Cult.Perma.'!$D80*'Critérios de Implantação'!AJ$33+'Resumo-Cult.Perma.'!$C80*'Critérios de Implantação'!AK$33 -> 0
A116: 1.6 | B116: Gasto com mão de obra | D116: ='Resumo-Cult.Perma.'!C81*'Critérios de Implantação'!$D$33 -> 0 | E116: ='Resumo-Cult.Perma.'!$D81*'Critérios de Implantação'!D$33+'Resumo-Cult.Perma.'!$C81*'Critérios de Implantação'!E$33 -> 0 | F116: ='Resumo-Cult.Perma.'!$D81*'Critérios de Implantação'!E$33+'Resumo-Cult.Perma.'!$C81*'Critérios de Implantação'!F$33 -> 278169.54 | G116: ='Resumo-Cult.Perma.'!$D81*'Critérios de Implantação'!F$33+'Resumo-Cult.Perma.'!$C81*'Critérios de Implantação'!G$33 -> 393716.88 | H116: ='Resumo-Cult.Perma.'!$D81*'Critérios de Implantação'!G$33+'Resumo-Cult.Perma.'!$C81*'Critérios de Implantação'!H$33 -> 449754.34 | I116: ='Resumo-Cult.Perma.'!$D81*'Critérios de Implantação'!H$33+'Resumo-Cult.Perma.'!$C81*'Critérios de Implantação'!I$33 -> 784309.84 | J116: ='Resumo-Cult.Perma.'!$D81*'Critérios de Implantação'!I$33+'Resumo-Cult.Perma.'!$C81*'Critérios de Implantação'!J$33 -> 873734.61 | K116: ='Resumo-Cult.Perma.'!$D81*'Critérios de Implantação'!J$33+'Resumo-Cult.Perma.'!$C81*'Critérios de Implantação'!K$33 -> 874676.2 | L116: ='Resumo-Cult.Perma.'!$D81*'Critérios de Implantação'!K$33+'Resumo-Cult.Perma.'!$C81*'Critérios de Implantação'!L$33 -> 766400.94 | ... AK116: ='Resumo-Cult.Perma.'!$D81*'Critérios de Implantação'!AJ$33+'Resumo-Cult.Perma.'!$C81*'Critérios de Implantação'!AK$33 -> 0
...

Sheet Balanço custo - receita-modelos
A2: BALANÇO RECEITA/CUSTO
G3: MODELOS | H3: Modelos | I3: Balanço receita/custo
A4: Cultura | B4: R$/ha/Ano (1) | I4: R$/ha/Ano(1)
A5: ='Resumo-Cult.Perma.'!A4 -> Banana Nanica | B5: ='Resumo-Cult.Perma.'!D35 -> 28049.03 | G5: Modelo 1 | H5: Banana Nanica | I5: =B5 -> 28049.03
A6: ='Resumo-Cult.Perma.'!A37 -> Banana Prata | B6: ='Resumo-Cult.Perma.'!D68 -> 28159.097 | G6: Modelo 2 | H6: Banana Prata | I6: =B6 -> 28159.097
A7: ='Resumo-Cult.Perma.'!A70 -> Manga | B7: ='Resumo-Cult.Perma.'!D101 -> 28623.958 | G7: Modelo 3 | H7: Manga | I7: =B7 -> 28623.958
A8: ='Resumo-Cult.Perma.'!A103 -> Limão | B8: ='Resumo-Cult.Perma.'!D134 -> 24626.385 | G8: Modelo 4 | H8: Limão | I8: =B8 -> 24626.385
A9: ='Resumo-Cult.Perma.'!A136 -> Cana | B9: ='Resumo-Cult.Perma.'!D162 -> 7441.2819 | G9: Modelo 5 | H9: Soja + Milho 2 | I9: =B10+B13 -> 13548.454
A10: ='Resumo-Cult.Temp.'!A4 -> Soja | B10: ='Resumo-Cult.Temp.'!D30 -> 6876.1567 | G10: Modelo 6 | H10: Milho 1 + Feijão | I10: =B11+B12 -> 15958.443
A11: ='Resumo-Cult.Temp.'!A32 -> Feijão | B11: ='Resumo-Cult.Temp.'!D58 -> 9006.6557 | G11: Modelo 7 | H11: Cana | I11: =B9 -> 7441.2819
A12: ='Resumo-Cult.Temp.'!A60 -> Milho 1 | B12: ='Resumo-Cult.Temp.'!D86 -> 6951.7873 | G12: (1) - Resultado médio período de 35 anos - Receita - custo
A13: ='Resumo-Cult.Temp.'!A88 -> Milho 2 | B13: ='Resumo-Cult.Temp.'!D114 -> 6672.297 | G13: custo = investimentos + operacionais
A14: (1) - Resultado médio período de 35 anos - Receita - custo
A15: custo = investimentos + operacionais

Sheet Área Plant-Colh e Produção
A2: ÁREA PLANTADA
A4: Ano | B4: Banana Nanica | C4: Banana Prata | D4: Manga | E4: Limão | F4: Soja | G4: Milho 1 | H4: Milho 2 | I4: Feijão | J4: TOTAL
A5: 2 | B5: {=TRANSPOSE('Critérios de Implantação'!$E39:$P39)} -> 0 | C5: {=TRANSPOSE('Critérios de Implantação'!$E40:$P40)} -> 0 | D5: {=TRANSPOSE('Critérios de Implantação'!$F41:$P41)} -> 0 | E5: {=TRANSPOSE('Critérios de Implantação'!$E42:$P42)} -> 0 | F5: {=TRANSPOSE('Critérios de Implantação'!$D43:$P43)} -> 0 | G5: {=TRANSPOSE('Critérios de Implantação'!$D45:$P45)} -> 0 | H5: {=TRANSPOSE('Critérios de Implantação'!$D44:$P44)} -> 0 | I5: {=TRANSPOSE('Critérios de Implantação'!$D46:$P46)} -> 0 | J5: =SUM(B5:I5) -> 0
A6: =A5+1 -> 3 | B6: 0 | C6: 0 | D6: 0 | E6: 0 | F6: 0 | G6: 0 | H6: 0 | I6: 0 | J6: =SUM(B6:I6) -> 0
A7: =A6+1 -> 4 | B7: 113.28171 | C7: 62.934285 | D7: 62.934285 | E7: 100.69486 | F7: 604.16913 | G7: 314.67142 | H7: 604.16913 | I7: 314.67142 | J7: =SUM(B7:I7) -> 2177.5262
A8: =A7+1 -> 5 | B8: 226.56342 | C8: 125.86857 | D8: 125.86857 | E8: 201.38971 | F8: 1208.3383 | G8: 629.34285 | H8: 1208.3383 | I8: 629.34285 | J8: =SUM(B8:I8) -> 4355.0525
A9: =A8+1 -> 6 | B9: 362.66582 | C9: 201.48101 | D9: 201.48101 | E9: 322.36962 | F9: 1934.2177 | G9: 1007.4051 | H9: 1934.2177 | I9: 1007.4051 | J9: =SUM(B9:I9) -> 6971.2429
A10: =A9+1 -> 7 | B10: 625.53317 | C10: 347.51843 | D10: 347.51843 | E10: 556.02949 | F10: 3336.1769 | G10: 1737.5922 | H10: 3336.1769 | I10: 1737.5922 | J10: =SUM(B10:I10) -> 12024.138
A11: =A10+1 -> 8 | B11: 872.16164 | C11: 484.53425 | D11: 484.53425 | E11: 775.25479 | F11: 4651.5288 | G11: 2422.6712 | H11: 4651.5288 | I11: 2422.6712 | J11: =SUM(B11:I11) -> 16764.885
A12: =A11+1 -> 9 | B12: 1125.9189 | C12: 625.51053 | D12: 625.51053 | E12: 1000.8168 | F12: 6004.9011 | G12: 3127.5526 | H12: 6004.9011 | I12: 3127.5526 | J12: =SUM(B12:I12) -> 21642.664
A13: =A12+1 -> 10 | B13: 1332.621 | C13: 740.34503 | D13: 740.34503 | E13: 1184.552 | F13: 7107.3122 | G13: 3701.7251 | H13: 7107.3122 | I13: 3701.7251 | J13: =SUM(B13:I13) -> 25615.938
A14: =A13+1 -> 11 | B14: 1479.1447 | C14: 821.74704 | D14: 821.74704 | E14: 1314.7953 | F14: 7888.7716 | G14: 4108.7352 | H14: 7888.7716 | I14: 4108.7352 | J14: =SUM(B14:I14) -> 28432.448
A15: =A14+1 -> 12 | B15: 1552.86 | C15: 862.7 | D15: 862.7 | E15: 1380.32 | F15: 8281.92 | G15: 4313.5 | H15: 8281.92 | I15: 4313.5 | J15: =SUM(B15:I15) -> 29849.42
A16: =A15+1 -> 13 | B16: 1552.86 | C16: 862.7 | D16: =D15 -> 862.7 | E16: 1380.32 | F16: 8281.92 | G16: 4313.5 | H16: 8281.92 | I16: 4313.5 | J16: =SUM(B16:I16) -> 29849.42
A17: =A16+1 -> 14 | B17: =B16 -> 1552.86 | C17: =C16 -> 862.7 | D17: =D16 -> 862.7 | E17: =E16 -> 1380.32 | F17: 8281.92 | G17: 4313.5 | H17: 8281.92 | I17: 4313.5 | J17: =SUM(B17:I17) -> 29849.42
A18: =A17+1 -> 15 | B18: =B17 -> 1552.86 | C18: =C17 -> 862.7 | D18: =D17 -> 862.7 | E18: =E17 -> 1380.32 | F18: =F17 -> 8281.92 | G18: =G17 -> 4313.5 | H18: =H17 -> 8281.92 | I18: =I17 -> 4313.5 | J18: =SUM(B18:I18) -> 29849.42
A19: =A18+1 -> 16 | B19: =B18 -> 1552.86 | C19: =C18 -> 862.7 | D19: =D18 -> 862.7 | E19: =E18 -> 1380.32 | F19: =F18 -> 8281.92 | G19: =G18 -> 4313.5 | H19: =H18 -> 8281.92 | I19: =I18 -> 4313.5 | J19: =SUM(B19:I19) -> 29849.42
A20: =A19+1 -> 17 | B20: =B19 -> 1552.86 | C20: =C19 -> 862.7 | D20: =D19 -> 862.7 | E20: =E19 -> 1380.32 | F20: =F19 -> 8281.92 | G20: =G19 -> 4313.5 | H20: =H19 -> 8281.92 | I20: =I19 -> 4313.5 | J20: =SUM(B20:I20) -> 29849.42
A21: =A20+1 -> 18 | B21: =B20 -> 1552.86 | C21: =C20 -> 862.7 | D21: =D20 -> 862.7 | E21: =E20 -> 1380.32 | F21: =F20 -> 8281.92 | G21: =G20 -> 4313.5 | H21: =H20 -> 8281.92 | I21: =I20 -> 4313.5 | J21: =SUM(B21:I21) -> 29849.42
A22: =A21+1 -> 19 | B22: =B21 -> 1552.86 | C22: =C21 -> 862.7 | D22: =D21 -> 862.7 | E22: =E21 -> 1380.32 | F22: =F21 -> 8281.92 | G22: =G21 -> 4313.5 | H22: =H21 -> 8281.92 | I22: =I21 -> 4313.5 | J22: =SUM(B22:I22) -> 29849.42
A23: =A22+1 -> 20 | B23: =B22 -> 1552.86 | C23: =C22 -> 862.7 | D23: =D22 -> 862.7 | E23: =E22 -> 1380.32 | F23: =F22 -> 8281.92 | G23: =G22 -> 4313.5 | H23: =H22 -> 8281.92 | I23: =I22 -> 4313.5 | J23: =SUM(B23:I23) -> 29849.42
A24: =A23+1 -> 21 | B24: =B23 -> 1552.86 | C24: =C23 -> 862.7 | D24: =D23 -> 862.7 | E24: =E23 -> 1380.32 | F24: =F23 -> 8281.92 | G24: =G23 -> 4313.5 | H24: =H23 -> 8281.92 | I24: =I23 -> 4313.5 | J24: =SUM(B24:I24) -> 29849.42
A25: =A24+1 -> 22 | B25: =B24 -> 1552.86 | C25: =C24 -> 862.7 | D25: =D24 -> 862.7 | E25: =E24 -> 1380.32 | F25: =F24 -> 8281.92 | G25: =G24 -> 4313.5 | H25: =H24 -> 8281.92 | I25: =I24 -> 4313.5 | J25: =SUM(B25:I25) -> 29849.42
A26: =A25+1 -> 23 | B26: =B25 -> 1552.86 | C26: =C25 -> 862.7 | D26: =D25 -> 862.7 | E26: =E25 -> 1380.32 | F26: =F25 -> 8281.92 | G26: =G25 -> 4313.5 | H26: =H25 -> 8281.92 | I26: =I25 -> 4313.5 | J26: =SUM(B26:I26) -> 29849.42
A27: =A26+1 -> 24 | B27: =B26 -> 1552.86 | C27: =C26 -> 862.7 | D27: =D26 -> 862.7 | E27: =E26 -> 1380.32 | F27: =F26 -> 8281.92 | G27: =G26 -> 4313.5 | H27: =H26 -> 8281.92 | I27: =I26 -> 4313.5 | J27: =SUM(B27:I27) -> 29849.42
A28: =A27+1 -> 25 | B28: =B27 -> 1552.86 | C28: =C27 -> 862.7 | D28: =D27 -> 862.7 | E28: =E27 -> 1380.32 | F28: =F27 -> 8281.92 | G28: =G27 -> 4313.5 | H28: =H27 -> 8281.92 | I28: =I27 -> 4313.5 | J28: =SUM(B28:I28) -> 29849.42
A29: =A28+1 -> 26 | B29: =B28 -> 1552.86 | C29: =C28 -> 862.7 | D29: =D28 -> 862.7 | E29: =E28 -> 1380.32 | F29: =F28 -> 8281.92 | G29: =G28 -> 4313.5 | H29: =H28 -> 8281.92 | I29: =I28 -> 4313.5 | J29: =SUM(B29:I29) -> 29849.42
... A38: =A37+1 -> 35 | B38: =B37 -> 1552.86 | C38: =C37 -> 862.7 | D38: =D37 -> 862.7 | E38: =E37 -> 1380.32 | F38: =F37 -> 8281.92 | G38: =G37 -> 4313.5 | H38: =H37 -> 8281.92 | I38: =I37 -> 4313.5 | J38: =SUM(B38:I38) -> 29849.42
A39: Obs- Anos 1 de início da obra
A41: PRODUÇÃO em Toneladas | L41: VALOR DA PRODUÇÃO /1000R$
A43: Ano | B43: Banana Nanica | C43: Banana Prata | D43: Manga | E43: Limão | F43: Soja | G43: Milho 1 | H43: Milho 2 | I43: Feijão | L43: Ano | M43: Banana Nanica | N43: Banana Prata | O43: Manga | P43: Limão | Q43: Soja | R43: Milho 1 | S43: Milho 2 | T43: Feijão | U43: TOTAL
A44: 2 | F44: {=TRANSPOSE('Planejamento Global'!D223:AK223/'Rentabilidade-Cult.Temp.'!E68)} -> 0 | G44: {=TRANSPOSE('Planejamento Global'!D285:AK285/'Rentabilidade-Cult.Temp.'!I68)} -> 0 | H44: {=TRANSPOSE('Planejamento Global'!D316:AK316/'Rentabilidade-Cult.Temp.'!K68)} -> 0 | I44: {=TRANSPOSE('Planejamento Global'!D254:AK254/'Rentabilidade-Cult.Temp.'!G68)} -> 0 | L44: 2 | Q44: {=TRANSPOSE('Planejamento Global'!D223:AK223/1000)} -> 0 | R44: {=TRANSPOSE('Planejamento Global'!D285:AK285/1000)} -> 0 | S44: {=TRANSPOSE('Planejamento Global'!D316:AK316/1000)} -> 0 | T44: {=TRANSPOSE('Planejamento Global'!D254:AK254/1000)} -> 0 | U44: =SUM(M44:T44) -> 0
A45: =A44+1 -> 3 | B45: {=TRANSPOSE('Planejamento Global'!E68:AK68/'Rentabilidade-Cult.Perma.'!AN94)} -> 0 | C45: {=TRANSPOSE('Planejamento Global'!E99:AK99/'Rentabilidade-Cult.Perma.'!AN186)} -> 0 | E45: {=TRANSPOSE('Planejamento Global'!E161:AK161/'Rentabilidade-Cult.Perma.'!AN365)} -> 0 | F45: 0 | G45: 0 | H45: 0 | I45: 0 | L45: =L44+1 -> 3 | M45: {=TRANSPOSE('Planejamento Global'!E68:AK68/1000)} -> 0 | N45: {=TRANSPOSE('Planejamento Global'!E99:AK99/1000)} -> 0 | P45: {=TRANSPOSE('Planejamento Global'!E161:AK161/1000)} -> 0 | Q45: 0 | R45: 0 | S45: 0 | T45: 0 | U45: =SUM(M45:T45) -> 0
A46: =A45+1 -> 4 | B46: 0 | C46: 0 | D46: {=TRANSPOSE('Planejamento Global'!F130:AK130/'Rentabilidade-Cult.Perma.'!AN277)} -> 0 | E46: 0 | F46: 3008.7623 | G46: 3373.2777 | H46: 5963.1493 | I46: 887.37341 | L46: =L45+1 -> 4 | M46: 0 | N46: 0 | O46: {=TRANSPOSE('Planejamento Global'!F130:AK130/1000)} -> 0 | P46: 0 | Q46: 8725.4106 | R46: 5059.9165 | S46: 8944.724 | T46: 5146.7658 | U46: =SUM(M46:T46) -> 27876.817
A47: =A46+1 -> 5 | B47: 8518.7848 | C47: 2246.754 | D47: 0 | E47: 281.9456 | F47: 6017.5246 | G47: 6746.5553 | H47: 11926.299 | I47: 1774.7468 | L47: =L46+1 -> 5 | M47: 11074.42 | N47: 5167.5341 | O47: 0 | P47: 676.66943 | Q47: 17450.821 | R47: 10119.833 | S47: 17889.448 | T47: 10293.532 | U47: =SUM(M47:T47) -> 72672.258
A48: =A47+1 -> 6 | B48: 16505.145 | C48: 4317.2919 | D48: 472.00713 | E48: 1701.7431 | F48: 9632.4041 | G48: 10799.382 | H48: 19090.729 | I48: 2840.8822 | L48: =L47+1 -> 6 | M48: 21456.689 | N48: 9929.7714 | O48: 2171.2328 | P48: 4084.1833 | Q48: 27933.972 | R48: 16199.073 | S48: 28636.093 | T48: 16477.117 | U48: =SUM(M48:T48) -> 126888.13
A49: =A48+1 -> 7 | B49: 25675.197 | C49: 6664.2241 | D49: 1063.5894 | E49: 3842.9247 | F49: 16614.161 | G49: 18626.988 | H49: 32928.066 | I49: 4900.0099 | L49: =L48+1 -> 7 | M49: 33377.757 | N49: 15327.715 | O49: 4892.5113 | P49: 9223.0193 | Q49: 48181.067 | R49: 27940.482 | S49: 49392.099 | T49: 28420.057 | U49: =SUM(M49:T49) -> 216754.71
A50: =A49+1 -> 8 | B50: 44270.717 | C50: 11370.254 | D50: 2222.265 | E50: 8703.8402 | F50: 23164.613 | G50: 25971.036 | H50: 45910.589 | I50: 6831.9329 | L50: =L49+1 -> 8 | M50: 57551.932 | N50: 26151.584 | O50: 10222.419 | P50: 20889.216 | Q50: 67177.378 | R50: 38956.553 | S50: 68865.883 | T50: 39625.211 | U50: =SUM(M50:T50) -> 329440.18
A51: =A50+1 -> 9 | B51: 60942.02 | C51: 15401.949 | D51: 4052.7916 | E51: 14458.238 | F51: 29904.407 | G51: 33527.364 | H51: 59268.373 | I51: 8819.6984 | L51: =L50+1 -> 9 | M51: 79224.626 | N51: 35424.482 | O51: 18642.841 | P51: 34699.771 | Q51: 86722.781 | R51: 50291.046 | S51: 88902.56 | T51: 51154.251 | U51: =SUM(M51:T51) -> 445062.36
A52: =A51+1 -> 10 | B52: 77097.515 | C52: 19202.798 | D52: 6340.3409 | E52: 20775.847 | F52: 35394.415 | G52: 39682.493 | H52: 70149.172 | I52: 10438.865 | L52: =L51+1 -> 10 | M52: 100226.77 | N52: 44166.436 | O52: 29165.568 | P52: 49862.033 | Q52: 102643.8 | R52: 59523.74 | S52: 105223.76 | T52: 60545.416 | U52: =SUM(M52:T52) -> 551357.52
A53: =A52+1 -> 11 | B53: 89757.276 | C53: 21926.661 | D53: 9488.5196 | E53: 29291.226 | F53: 39286.083 | G53: 44045.641 | H53: 77862.176 | I53: 11586.633 | L53: =L52+1 -> 11 | M53: 116684.46 | N53: 50431.321 | O53: 43647.19 | P53: 70298.942 | Q53: 113929.64 | R53: 66068.462 | S53: 116793.26 | T53: 67202.473 | U53: =SUM(M53:T53) -> 645055.75
A54: =A53+1 -> 12 | B54: 96374.74 | C54: 23366.927 | D54: 12573.893 | E54: 36289.284 | F54: 41243.962 | G54: 46240.72 | H54: 81742.55 | I54: 12164.07 | L54: =L53+1 -> 12 | M54: 125287.16 | N54: 53743.932 | O54: 57839.906 | P54: 87094.281 | Q54: 119607.49 | R54: 69361.08 | S54: 122613.83 | T54: 70551.606 | U54: =SUM(M54:T54) -> 706099.28
A55: =A54+1 -> 13 | B55: 96892.799 | C55: 23342.396 | D55: 15762 | E55: 41427.468 | F55: 41243.962 | G55: 46240.72 | H55: 81742.55 | I55: 12164.07 | L55: =L54+1 -> 13 | M55: 125960.64 | N55: 53687.51 | O55: 72505.199 | P55: 99425.923 | Q55: 119607.49 | R55: 69361.08 | S55: 122613.83 | T55: 70551.606 | U55: =SUM(M55:T55) -> 733713.27
A56: =A55+1 -> 14 | B56: 92247.054 | C56: 21834.326 | D56: 18387.484 | E56: 44432.417 | F56: 41243.962 | G56: 46240.72 | H56: 81742.55 | I56: 12164.07 | L56: =L55+1 -> 14 | M56: 119921.17 | N56: 50218.949 | O56: 84582.424 | P56: 106637.8 | Q56: 119607.49 | R56: 69361.08 | S56: 122613.83 | T56: 70551.606 | U56: =SUM(M56:T56) -> 743494.34
A57: =A56+1 -> 15 | B57: 85829.398 | C57: 20536.708 | D57: 20480.983 | E57: 45185.831 | F57: 41243.962 | G57: 46240.72 | H57: 81742.55 | I57: 12164.07 | L57: =L56+1 -> 15 | M57: 111578.22 | N57: 47234.429 | O57: 94212.52 | P57: 108445.99 | Q57: 119607.49 | R57: 69361.08 | S57: 122613.83 | T57: 70551.606 | U57: =SUM(M57:T57) -> 743605.16
A58: =A57+1 -> 16 | B58: 75353.144 | C58: 18444.154 | D58: 21789.726 | E58: 43835.945 | F58: 41243.962 | G58: 46240.72 | H58: 81742.55 | I58: 12164.07 | L58: =L57+1 -> 16 | M58: 97959.087 | N58: 42421.554 | O58: 100232.74 | P58: 105206.27 | Q58: 119607.49 | R58: 69361.08 | S58: 122613.83 | T58: 70551.606 | U58: =SUM(M58:T58) -> 727953.65
... A77: =A76+1 -> 35 | B77: 92528.972 | C77: 23422.816 | D77: 22138.971 | E77: 41694.156 | F77: 41243.962 | G77: 46240.72 | H77: 81742.55 | I77: 12164.07 | L77: =L76+1 -> 35 | M77: 120287.66 | N77: 53872.476 | O77: 101839.27 | P77: 100065.98 | Q77: 119607.49 | R77: 69361.08 | S77: 122613.83 | T77: 70551.606 | U77: =SUM(M77:T77) -> 758199.38
A78: Obs- Anos 1 de início da obra | K78: =SUM(B78:E78) -> 0 | L78: Obs- Anos 1 de início da obra
A82: CUSTOS INVESTIMENTO E OPERACIONAIS /1000R$
A84: Ano | B84: Banana Nanica | C84: Banana Prata | D84: Manga | E84: Limão | F84: Soja | G84: Milho 1 | H84: Milho 2 | I84: Feijão | J84: TOTAL | L84: Banana Nanica | N84: Banana Prata | P84: Manga | R84: Limão | T84: Soja | V84: Milho 1 | X84: Milho 2
A85: 2 | B85: {=TRANSPOSE('Planejamento Global'!D57:AK57+'Planejamento Global'!D64:AK64)/1000} -> 0 | C85: {=TRANSPOSE('Planejamento Global'!D88:AK88+'Planejamento Global'!D95:AK95)/1000} -> 0 | D85: {=TRANSPOSE('Planejamento Global'!D119:AK119+'Planejamento Global'!D126:AK126)/1000} -> 0 | E85: {=TRANSPOSE('Planejamento Global'!D150:AK150+'Planejamento Global'!D157:AK157)/1000} -> 0 | F85: {=TRANSPOSE('Planejamento Global'!D212:AK212+'Planejamento Global'!D219:AK219)/1000} -> 0 | G85: {=TRANSPOSE('Planejamento Global'!D274:AK274+'Planejamento Global'!D281:AK281)/1000} -> 0 | H85: {=TRANSPOSE('Planejamento Global'!D305:AK305+'Planejamento Global'!D312:AK312)/1000} -> 0 | I85: {=TRANSPOSE('Planejamento Global'!D243:AK243+'Planejamento Global'!D250:AK250)/1000} -> 0 | J85: =SUM(B85:I85) -> 0
A86: =A85+1 -> 3 | B86: 0 | C86: 0 | D86: 0 | E86: 0 | F86: 0 | G86: 0 | H86: 0 | I86: 0 | J86: =SUM(B86:I86) -> 0
A87: =A86+1 -> 4 | B87: 10865.178 | C87: 5192.1179 | D87: 4704.5769 | E87: 5442.9722 | F87: 11317.891 | G87: 6386.368 | H87: 11660.37 | I87: 5826.6089 | J87: =SUM(B87:I87) -> 61396.084
A88: =A87+1 -> 5 | B88: 15775.616 | C88: 7041.8111 | D88: 5846.3492 | E88: 7411.3193 | F88: 15690.504 | G88: 9155.4033 | H88: 16375.462 | I88: 8035.8852 | J88: =SUM(B88:I88) -> 85332.349
A89: =A88+1 -> 6 | B89: 22713.641 | C89: 9870.9919 | D89: 8964.2945 | E89: 11212.68 | F89: 22343.113 | G89: 13210.977 | H89: 23439.543 | I89: 11418.936 | J89: =SUM(B89:I89) -> 123174.18
A90: =A89+1 -> 7 | B90: 40500.571 | C90: 17798.979 | D90: 17000.624 | E90: 20785.011 | F90: 40261.584 | G90: 23684.336 | H90: 42152.728 | I90: 20593.388 | J90: =SUM(B90:I90) -> 222777.22
A91: =A90+1 -> 8 | B91: 49892.463 | C91: 21172.304 | D91: 21349.506 | E91: 26466.039 | F91: 48785.706 | G91: 29194.329 | H91: 51422.47 | I91: 24884.716 | J91: =SUM(B91:I91) -> 273167.53
A92: =A91+1 -> 9 | B92: 60612.094 | C92: 25242.452 | D92: 28026.282 | E92: 33988.738 | F92: 59017.668 | G92: 35624.761 | H92: 62421.604 | I92: 30061.256 | J92: =SUM(B92:I92) -> 334994.85
A93: =A92+1 -> 10 | B93: 66245.675 | C93: 26885.52 | D93: 33377.265 | E93: 39444.813 | F93: 64111.311 | G93: 39174.77 | H93: 68140.16 | I93: 32589.888 | J93: =SUM(B93:I93) -> 369969.4
A94: =A93+1 -> 11 | B94: 68419.568 | C94: 27087.171 | D94: 39009.54 | E94: 44162.094 | F94: 66077.513 | G94: 40834.733 | H94: 70549.34 | I94: 33525.834 | J94: =SUM(B94:I94) -> 389665.79
A95: =A94+1 -> 12 | B95: 66530.509 | C95: 25731.232 | D95: 43418.139 | E95: 46966.52 | F95: 64459.023 | G95: 40311.688 | H95: 69153.709 | I95: 32638.539 | J95: =SUM(B95:I95) -> 389209.36
A96: =A95+1 -> 13 | B96: 61332.469 | C96: 23174.042 | D96: 46912.346 | E96: 47807.482 | F96: 59939.551 | G96: 37957.796 | H96: 64634.238 | I96: 30284.648 | J96: =SUM(B96:I96) -> 372042.57
A97: =A96+1 -> 14 | B97: 60178.115 | C97: 22822.048 | D97: 51550.143 | E97: 49984.62 | F97: 59939.551 | G97: 37957.796 | H97: 64634.238 | I97: 30284.648 | J97: =SUM(B97:I97) -> 377351.16
... A118: =A117+1 -> 35 | B118: 64772.769 | C118: 24667.593 | D118: 57602.311 | E118: 51076.549 | F118: 59939.551 | G118: 37957.796 | H118: 64634.238 | I118: 30284.648 | J118: =SUM(B118:I118) -> 390935.46
A119: Obs- Anos 1 de início da obra
A120: Custos = investimentos + custos operacionais
A124: CONCOLIDAÇÃO DAS CULTURAS
A125: Cultura | B125: Banana Nanica | C125: Banana Prata | D125: Manga | E125: Limão | F125: Soja | G125: Milho 1 | H125: Milho 2 | I125: Feijão
A126: Área plantada (ha) | B126: =AVERAGE(B29:B38) -> 1552.86 | C126: =AVERAGE(C29:C38) -> 862.7 | D126: =AVERAGE(D29:D38) -> 862.7 | E126: =AVERAGE(E29:E38) -> 1380.32 | F126: =AVERAGE(F29:F38) -> 8281.92 | G126: =AVERAGE(G29:G38) -> 4313.5 | H126: =AVERAGE(H29:H38) -> 8281.92 | I126: =AVERAGE(I29:I38) -> 4313.5
A127: Produtividade Média (ton/ha) | B127: =B128/B126 -> 51.004091 | C127: =C128/C126 -> 24.934411 | D127: =D128/D126 -> 17.080075 | E127: =E128/E126 -> 25.55289 | F127: =F128/F126 -> 4.98 | G127: =G128/G126 -> 10.72 | H127: =H128/H126 -> 9.87 | I127: =I128/I126 -> 2.82
A128: Produção Total Estimada (ton) | B128: =AVERAGE(B68:B77) -> 79202.213 | C128: =AVERAGE(C68:C77) -> 21510.916 | D128: =AVERAGE(D68:D77) -> 14734.98 | E128: =AVERAGE(E68:E77) -> 35271.165 | F128: =AVERAGE(F68:F77) -> 41243.962 | G128: =AVERAGE(G68:G77) -> 46240.72 | H128: =AVERAGE(H68:H77) -> 81742.55 | I128: =AVERAGE(I68:I77) -> 12164.07
A129: Custo Total de Produção (mil R$/ano) | B129: =AVERAGE('Planejamento Global'!AB64:AK64)/1000 -> 61863.939 | C129: =AVERAGE('Planejamento Global'!AB95:AK95)/1000 -> 24055.341 | D129: =AVERAGE('Planejamento Global'!AB126:AK126)/1000 -> 46111.418 | E129: =AVERAGE('Planejamento Global'!AB157:AK157)/1000 -> 46858.481 | F129: =AVERAGE('Planejamento Global'!AB219:AK219)/1000 -> 59939.551 | G129: =AVERAGE('Planejamento Global'!AB281:AK281)/1000 -> 37957.796 | H129: =AVERAGE('Planejamento Global'!AB312:AK312)/1000 -> 64634.238 | I129: =AVERAGE('Planejamento Global'!AB250:AK250)/1000 -> 30284.648
A130: Custo Unitário por hectare (mil R$/ha) | B130: =AVERAGE('Resumo-Cult.Perma.'!AB25:AK25)/1000 -> 39.059351 | C130: =AVERAGE('Resumo-Cult.Perma.'!AB58:AK58)/1000 -> 26.841533 | D130: =AVERAGE('Resumo-Cult.Perma.'!AB91:AK91)/1000 -> 65.013899 | E130: =AVERAGE('Resumo-Cult.Perma.'!AB124:AK124)/1000 -> 36.558164 | F130: =AVERAGE('Resumo-Cult.Temp.'!AB20:AK20)/1000 -> 7.237398 | G130: =AVERAGE('Resumo-Cult.Temp.'!AB76:AK76)/1000 -> 8.7997673 | H130: =AVERAGE('Resumo-Cult.Temp.'!AB104:AK104)/1000 -> 7.8042577 | I130: =AVERAGE('Resumo-Cult.Temp.'!AB48:AK48)/1000 -> 7.0208989
A131: Preço de Venda Estimado (mil R$/ton) | B131: ='Rentabilidade-Cult.Perma.'!AN94/1000 -> 1.3 | C131: ='Rentabilidade-Cult.Perma.'!AN186/1000 -> 2.3 | D131: ='Rentabilidade-Cult.Perma.'!AN277/1000 -> 4.6 | E131: ='Rentabilidade-Cult.Perma.'!AN365/1000 -> 2.4 | F131: ='Rentabilidade-Cult.Temp.'!E68/1000 -> 2.9 | G131: ='Rentabilidade-Cult.Temp.'!I68/1000 -> 1.5 | H131: ='Rentabilidade-Cult.Temp.'!K68/1000 -> 1.5 | I131: ='Rentabilidade-Cult.Temp.'!G68/1000 -> 5.8
A132: Receita Bruta (mil R$) | B132: =AVERAGE('Planejamento Global'!AB68:AK68)/1000 -> 102962.88 | C132: =AVERAGE('Planejamento Global'!AB99:AK99)/1000 -> 49475.107 | D132: =AVERAGE('Planejamento Global'!AB130:AK130)/1000 -> 67780.91 | E132: =AVERAGE('Planejamento Global'!AB161:AK161)/1000 -> 84650.796 | F132: =AVERAGE('Planejamento Global'!AB223:AK223)/1000 -> 119607.49 | G132: =AVERAGE('Planejamento Global'!AB285:AK285)/1000 -> 69361.08 | H132: =AVERAGE('Planejamento Global'!AB316:AK316)/1000 -> 122613.83 | I132: =AVERAGE('Planejamento Global'!AB254:AK254)/1000 -> 70551.606
A133: Margem Líquida ou Saldo (mil R$) | B133: =B132-B129 -> 41098.938 | C133: =C132-C129 -> 25419.766 | D133: =D132-D129 -> 21669.492 | E133: =E132-E129 -> 37792.314 | F133: =F132-F129 -> 59667.937 | G133: =G132-G129 -> 31403.284 | H133: =H132-H129 -> 57979.588 | I133: =I132-I129 -> 40266.958

Sheet Resumos ->

Sheet Resumo-Cult.Perma.
A2: RESUMO - Culturas Permanentes
A4: Banana Nanica
A5: Custo 1 Ha
A6: ITEM | B6: COMPONENTES | C6: ANO DE IMPLANTAÇÃO DA CULTURA
C7: 1 | D7: =C7+1 -> 2 | E7: =D7+1 -> 3 | F7: =E7+1 -> 4 | G7: =F7+1 -> 5 | H7: =G7+1 -> 6 | I7: =H7+1 -> 7 | J7: =I7+1 -> 8 | K7: =J7+1 -> 9 | ... AK7: =AJ7+1 -> 35
A8: 1 | B8: INVESTIMENTOS
A9: 1.1 | B9: Supressão vegetal | C9: ='Custos Diversos'!E164 -> 1293.6736
A10: 1.2 | B10: Sistema de irrigação localizada | C10: ='Rentabilidade-Cult.Perma.'!AN65 -> 22500 | AA10: =O10 -> 0
A11: 1.3 | B11: Sistema de irrigação pivô central
A12: 1.4 | B12: Demais infraestrutura | C12: ='Rentabilidade-Cult.Perma.'!AN70-'Rentabilidade-Cult.Perma.'!AN65 -> 23438.4 | AA12: =O12 -> 0
B13: Ano 1 do plantio | O13: =C13 -> 0 | AA13: =O13 -> 0
A14: 1.5 | B14: Gasto com insumos | C14: ='Rentabilidade-Cult.Perma.'!AN23 -> 28262.63 | AA14: =O14 -> 0
A15: 1.6 | B15: Gasto com mão de obra | C15: ='Rentabilidade-Cult.Perma.'!AN44 -> 8787 | AA15: =O15 -> 0
A16: 1.7 | B16: Gasto com trator e equipamentos e avaição agrícola | C16: ='Rentabilidade-Cult.Perma.'!AN60 -> 7635 | AA16: =O16 -> 0
A17: 1.8 | B17: Outros custos | C17: =SUM('Rentabilidade-Cult.Perma.'!AN75:AN82) -> 3996.2008 | AA17: =O17 -> 0
B18: Sub-total - Investimentos | C18: =SUM(C9:C17) -> 95912.905 | D18: =SUM(D9:D17) -> 0 | E18: =SUM(E9:E17) -> 0 | F18: =SUM(F9:F17) -> 0 | G18: =SUM(G9:G17) -> 0 | H18: =SUM(H9:H17) -> 0 | I18: =SUM(I9:I17) -> 0 | J18: =SUM(J9:J17) -> 0 | ... AK18: =SUM(AK9:AK17) -> 0
A20: 2 | B20: CUSTOS OPERACIONAIS
A21: 2.1 | B21: Gasto com insumos | D21: ='Rentabilidade-Cult.Perma.'!AO23 -> 16388.242 | E21: ='Rentabilidade-Cult.Perma.'!AP23 -> 16378.492 | F21: ='Rentabilidade-Cult.Perma.'!AQ23 -> 16378.492 | G21: ='Rentabilidade-Cult.Perma.'!AR23 -> 14951.649 | H21: ='Rentabilidade-Cult.Perma.'!AS23 -> 14951.649 | I21: ='Rentabilidade-Cult.Perma.'!AT23 -> 14951.649 | J21: ='Rentabilidade-Cult.Perma.'!AU23 -> 14951.649 | K21: ='Rentabilidade-Cult.Perma.'!AV23 -> 14951.649 | ... AK21: ='Rentabilidade-Cult.Perma.'!BV23 -> 14951.649
A22: 2.2 | B22: Gasto com mão de obra | D22: ='Rentabilidade-Cult.Perma.'!AO44 -> 19308 | E22: ='Rentabilidade-Cult.Perma.'!AP44 -> 18342.312 | F22: ='Rentabilidade-Cult.Perma.'!AQ44 -> 17434.625 | G22: ='Rentabilidade-Cult.Perma.'!AR44 -> 17434.625 | H22: ='Rentabilidade-Cult.Perma.'!AS44 -> 17434.625 | I22: ='Rentabilidade-Cult.Perma.'!AT44 -> 16526.938 | J22: ='Rentabilidade-Cult.Perma.'!AU44 -> 16526.938 | K22: ='Rentabilidade-Cult.Perma.'!AV44 -> 13803.875 | ... AK22: ='Rentabilidade-Cult.Perma.'!BV44 -> 12896.188
A23: 2.3 | B23: Gasto com trator e equipamentos e avaição agrícola | D23: ='Rentabilidade-Cult.Perma.'!AO60 -> 3425 | E23: ='Rentabilidade-Cult.Perma.'!AP60 -> 2862.5 | F23: ='Rentabilidade-Cult.Perma.'!AQ60 -> 2800 | G23: ='Rentabilidade-Cult.Perma.'!AR60 -> 2862.5 | H23: ='Rentabilidade-Cult.Perma.'!AS60 -> 2800 | I23: ='Rentabilidade-Cult.Perma.'!AT60 -> 2862.5 | J23: ='Rentabilidade-Cult.Perma.'!AU60 -> 2800 | K23: ='Rentabilidade-Cult.Perma.'!AV60 -> 2862.5 | ... AK23: ='Rentabilidade-Cult.Perma.'!BV60 -> 2862.5
A24: 2.4 | B24: Outros custos | D24: =SUM('Rentabilidade-Cult.Perma.'!AO75:AO82) -> 4225.8928 | E24: =SUM('Rentabilidade-Cult.Perma.'!AP75:AP82) -> 4340.7388 | F24: =SUM('Rentabilidade-Cult.Perma.'!AQ75:AQ82) -> 4340.7388 | G24: =SUM('Rentabilidade-Cult.Perma.'!AR75:AR82) -> 4455.5848 | H24: =SUM('Rentabilidade-Cult.Perma.'!AS75:AS82) -> 4455.5848 | I24: =SUM('Rentabilidade-Cult.Perma.'!AT75:AT82) -> 4685.2768 | J24: =SUM('Rentabilidade-Cult.Perma.'!AU75:AU82) -> 4685.2768 | K24: =SUM('Rentabilidade-Cult.Perma.'!AV75:AV82) -> 4685.2768 | ... AK24: =SUM('Rentabilidade-Cult.Perma.'!BV75:BV82) -> 4685.2768
B25: Sub-total - custos operacionais | C25: =SUM(C21:C24) -> 0 | D25: =SUM(D21:D24) -> 43347.135 | E25: =SUM(E21:E24) -> 41924.044 | F25: =SUM(F21:F24) -> 40953.856 | G25: =SUM(G21:G24) -> 39704.359 | H25: =SUM(H21:H24) -> 39641.859 | I25: =SUM(I21:I24) -> 39026.364 | J25: =SUM(J21:J24) -> 38963.864 | ... AK25: =SUM(AK21:AK24) -> 35395.614
A27: 3 | B27: ENTRADA - VALOR DA PRODUÇÃO
A28: 3.1 | B28: Valor da produção banana nanica | C28: ='Rentabilidade-Cult.Perma.'!AN90 -> 0 | D28: ='Rentabilidade-Cult.Perma.'!AO90 -> 97760 | E28: ='Rentabilidade-Cult.Perma.'!AP90 -> 91650 | F28: ='Rentabilidade-Cult.Perma.'!AQ90 -> 85540 | G28: ='Rentabilidade-Cult.Perma.'!AR90 -> 85540 | H28: ='Rentabilidade-Cult.Perma.'!AS90 -> 85540 | I28: ='Rentabilidade-Cult.Perma.'!AT90 -> 79430 | J28: ='Rentabilidade-Cult.Perma.'!AU90 -> 79430 | ... AK28: ='Rentabilidade-Cult.Perma.'!BV90 -> 54990
B29: Sub-total - valor da produção | C29: =SUM(C28:C28) -> 0 | D29: =SUM(D28:D28) -> 97760 | E29: =SUM(E28:E28) -> 91650 | F29: =SUM(F28:F28) -> 85540 | G29: =SUM(G28:G28) -> 85540 | H29: =SUM(H28:H28) -> 85540 | I29: =SUM(I28:I28) -> 79430 | J29: =SUM(J28:J28) -> 79430 | ... AK29: =SUM(AK28:AK28) -> 54990
A31: 4 | B31: BALANÇO anual(Item 3 - item 1-item2) | C31: =C29-C25-C18 -> -95912.905 | D31: =D29-D25-D18 -> 54412.865 | E31: =E29-E25-E18 -> 49725.956 | F31: =F29-F25-F18 -> 44586.144 | G31: =G29-G25-G18 -> 45835.641 | H31: =H29-H25-H18 -> 45898.141 | I31: =I29-I25-I18 -> 40403.636 | J31: =J29-J25-J18 -> 40466.136 | ... AK31: =AK29-AK25-AK18 -> 19594.386
A33: 5 | B33: BALANÇO ACUMULADO | C33: =C31 -> -95912.905 | D33: =C33+D31 -> -41500.04 | E33: =D33+E31 -> 8225.9162 | F33: =E33+F31 -> 52812.06 | G33: =F33+G31 -> 98647.701 | H33: =G33+H31 -> 144545.84 | I33: =H33+I31 -> 184949.48 | J33: =I33+J31 -> 225415.61 | K33: =J33+K31 -> 250212.31 | ... AK33: =AJ33+AK31 -> 981716.06
C35: R$/ha/ano = | D35: =AK33/AK7 -> 28049.03 | E35: 35 anos
A37: Banana Prata
A38: Custo 1 Ha
A39: ITEM | B39: COMPONENTES | C39: ANO DE IMPLANTAÇÃO DA CULTURA
C40: 1 | D40: =C40+1 -> 2 | E40: =D40+1 -> 3 | F40: =E40+1 -> 4 | G40: =F40+1 -> 5 | H40: =G40+1 -> 6 | I40: =H40+1 -> 7 | J40: =I40+1 -> 8 | K40: =J40+1 -> 9 | ... AK40: =AJ40+1 -> 35
A41: 1 | B41: INVESTIMENTOS
A42: 1.1 | B42: Supressão vegetal | C42: ='Custos Diversos'!E164 -> 1293.6736
A43: 1.2 | B43: Sistema de irrigação localizada | C43: ='Rentabilidade-Cult.Perma.'!AN157 -> 22500
A44: 1.3 | B44: Sistema de irrigação pivô central
A45: 1.4 | B45: Demais infraestrutura | C45: ='Rentabilidade-Cult.Perma.'!AN162-'Rentabilidade-Cult.Perma.'!AN157 -> 23438.4
B46: Ano 1 do plantio
A47: 1.5 | B47: Gasto com insumos | C47: ='Rentabilidade-Cult.Perma.'!AN115 -> 15865.352
A48: 1.6 | B48: Gasto com mão de obra | C48: ='Rentabilidade-Cult.Perma.'!AN136 -> 7772
A49: 1.7 | B49: Gasto com trator e equipamentos e avaição agrícola | C49: ='Rentabilidade-Cult.Perma.'!AN152 -> 7635
A50: 1.8 | B50: Outros custos | C50: =SUM('Rentabilidade-Cult.Perma.'!AN167:AN174) -> 3996.2008
B51: Sub-total - Investimentos | C51: =SUM(C42:C50) -> 82500.626
A53: 2 | B53: CUSTOS OPERACIONAIS
A54: 2.1 | B54: Gasto com insumos | D54: ='Rentabilidade-Cult.Perma.'!AO115 -> 10060.412 | E54: ='Rentabilidade-Cult.Perma.'!AP115 -> 10050.662 | F54: ='Rentabilidade-Cult.Perma.'!AQ115 -> 10050.662 | G54: ='Rentabilidade-Cult.Perma.'!AR115 -> 9338.846 | H54: ='Rentabilidade-Cult.Perma.'!AS115 -> 9338.846 | I54: ='Rentabilidade-Cult.Perma.'!AT115 -> 9338.846 | J54: ='Rentabilidade-Cult.Perma.'!AU115 -> 9338.846 | K54: ='Rentabilidade-Cult.Perma.'!AV115 -> 9338.846 | ... AK54: ='Rentabilidade-Cult.Perma.'!BV115 -> 9338.846
A55: 2.2 | B55: Gasto com mão de obra | D55: ='Rentabilidade-Cult.Perma.'!AO136 -> 11679.562 | E55: ='Rentabilidade-Cult.Perma.'!AP136 -> 11080.812 | F55: ='Rentabilidade-Cult.Perma.'!AQ136 -> 10540.062 | G55: ='Rentabilidade-Cult.Perma.'!AR136 -> 10173.125 | H55: ='Rentabilidade-Cult.Perma.'!AS136 -> 9806.1875 | I55: ='Rentabilidade-Cult.Perma.'!AT136 -> 9265.4375 | J55: ='Rentabilidade-Cult.Perma.'!AU136 -> 9265.4375 | K55: ='Rentabilidade-Cult.Perma.'!AV136 -> 9265.4375 | ... AK55: ='Rentabilidade-Cult.Perma.'!BV136 -> 8357.75
A56: 2.3 | B56: Gasto com trator e equipamentos e avaição agrícola | D56: ='Rentabilidade-Cult.Perma.'!AO152 -> 3425 | E56: ='Rentabilidade-Cult.Perma.'!AP152 -> 2862.5 | F56: ='Rentabilidade-Cult.Perma.'!AQ152 -> 2800 | G56: ='Rentabilidade-Cult.Perma.'!AR152 -> 2862.5 | H56: ='Rentabilidade-Cult.Perma.'!AS152 -> 2800 | I56: ='Rentabilidade-Cult.Perma.'!AT152 -> 2862.5 | J56: ='Rentabilidade-Cult.Perma.'!AU152 -> 2800 | K56: ='Rentabilidade-Cult.Perma.'!AV152 -> 2862.5 | ... AK56: ='Rentabilidade-Cult.Perma.'!BV152 -> 2862.5
A57: 2.4 | B57: Outros custos | D57: =SUM('Rentabilidade-Cult.Perma.'!AO167:AO174) -> 4225.8928 | E57: =SUM('Rentabilidade-Cult.Perma.'!AP167:AP174) -> 4340.7388 | F57: =SUM('Rentabilidade-Cult.Perma.'!AQ167:AQ174) -> 4340.7388 | G57: =SUM('Rentabilidade-Cult.Perma.'!AR167:AR174) -> 4455.5848 | H57: =SUM('Rentabilidade-Cult.Perma.'!AS167:AS174) -> 4455.5848 | I57: =SUM('Rentabilidade-Cult.Perma.'!AT167:AT174) -> 4685.2768 | J57: =SUM('Rentabilidade-Cult.Perma.'!AU167:AU174) -> 4685.2768 | K57: =SUM('Rentabilidade-Cult.Perma.'!AV167:AV174) -> 4685.2768 | ... AK57: =SUM('Rentabilidade-Cult.Perma.'!BV167:BV174) -> 4685.2768
B58: Sub-total - custos operacionais | C58: =SUM(C54:C57) -> 0 | D58: =SUM(D54:D57) -> 29390.867 | E58: =SUM(E54:E57) -> 28334.713 | F58: =SUM(F54:F57) -> 27731.463 | G58: =SUM(G54:G57) -> 26830.056 | H58: =SUM(H54:H57) -> 26400.618 | I58: =SUM(I54:I57) -> 26152.06 | J58: =SUM(J54:J57) -> 26089.56 | ... AK58: =SUM(AK54:AK57) -> 25244.373
A60: 3 | B60: ENTRADA - VALOR DA PRODUÇÃO
A61: 3.1 | B61: Valor da produção banana prata | C61: ='Rentabilidade-Cult.Perma.'!AN182 -> 0 | D61: ='Rentabilidade-Cult.Perma.'!AO182 -> 82110 | E61: ='Rentabilidade-Cult.Perma.'!AP182 -> 75670 | F61: ='Rentabilidade-Cult.Perma.'!AQ182 -> 69230 | G61: ='Rentabilidade-Cult.Perma.'!AR182 -> 64860 | H61: ='Rentabilidade-Cult.Perma.'!AS182 -> 60490 | I61: ='Rentabilidade-Cult.Perma.'!AT182 -> 54050 | J61: ='Rentabilidade-Cult.Perma.'!AU182 -> 54050 | ... AK61: ='Rentabilidade-Cult.Perma.'!BV182 -> 56120
B62: Sub-total - valor da produção | C62: =SUM(C61:C61) -> 0 | D62: =SUM(D61:D61) -> 82110 | E62: =SUM(E61:E61) -> 75670 | F62: =SUM(F61:F61) -> 69230 | G62: =SUM(G61:G61) -> 64860 | H62: =SUM(H61:H61) -> 60490 | I62: =SUM(I61:I61) -> 54050 | J62: =SUM(J61:J61) -> 54050 | ... AK62: =SUM(AK61:AK61) -> 56120
AM63: =AK63/35 -> 0
A64: 4 | B64: BALANÇO anual(Item 3 - item 1-item2) | C64: =C62-C58-C51 -> -82500.626 | D64: =D62-D58-D51 -> 52719.133 | E64: =E62-E58-E51 -> 47335.287 | F64: =F62-F58-F51 -> 41498.537 | G64: =G62-G58-G51 -> 38029.944 | H64: =H62-H58-H51 -> 34089.382 | I64: =I62-I58-I51 -> 27897.94 | J64: =J62-J58-J51 -> 27960.44 | ... AK64: =AK62-AK58-AK51 -> 30875.627
A66: 5 | B66: BALANÇO ACUMULADO | C66: =C64 -> -82500.626 | D66: =C66+D64 -> -29781.494 | E66: =D66+E64 -> 17553.793 | F66: =E66+F64 -> 59052.33 | G66: =F66+G64 -> 97082.274 | H66: =G66+H64 -> 131171.66 | I66: =H66+I64 -> 159069.6 | J66: =I66+J64 -> 187030.03 | K66: =J66+K64 -> 214927.97 | ... AK66: =AJ66+AK64 -> 985568.4
C68: R$/ha/ano = | D68: =AK66/AK40 -> 28159.097 | E68: 35 anos
A70: Manga
A71: Custo 1 Ha
A72: ITEM | B72: COMPONENTES | C72: ANO DE IMPLANTAÇÃO DA CULTURA
C73: 1 | D73: =C73+1 -> 2 | E73: =D73+1 -> 3 | F73: =E73+1 -> 4 | G73: =F73+1 -> 5 | H73: =G73+1 -> 6 | I73: =H73+1 -> 7 | J73: =I73+1 -> 8 | K73: =J73+1 -> 9 | ... AK73: =AJ73+1 -> 35
A74: 1 | B74: INVESTIMENTOS
A75: 1.1 | B75: Supressão vegetal | C75: ='Custos Diversos'!E164 -> 1293.6736
A76: 1.2 | B76: Sistema de irrigação localizada | C76: ='Rentabilidade-Cult.Perma.'!AN248 -> 22000
A77: 1.3 | B77: Sistema de irrigação pivô central
A78: 1.4 | B78: Demais infraestrutura | C78: ='Rentabilidade-Cult.Perma.'!AN252-'Rentabilidade-Cult.Perma.'!AN248 -> 12763.4
B79: Ano de formação da cultura
A80: 1.5 | B80: Gasto com insumos | C80: ='Rentabilidade-Cult.Perma.'!AN210 -> 22309.4 | D80: ='Rentabilidade-Cult.Perma.'!AO210 -> 7465.152
A81: 1.6 | B81: Gasto com mão de obra | C81: ='Rentabilidade-Cult.Perma.'!AN227 -> 4420 | D81: ='Rentabilidade-Cult.Perma.'!AO227 -> 1836
A82: 1.7 | B82: Gasto com trator e equipamentos e avaição agrícola | C82: ='Rentabilidade-Cult.Perma.'!AN243 -> 7550 | D82: ='Rentabilidade-Cult.Perma.'!AO243 -> 4250
A83: 1.8 | B83: Outros custos | C83: =SUM('Rentabilidade-Cult.Perma.'!AN257:AN265) -> 4417.3258 | D83: =SUM('Rentabilidade-Cult.Perma.'!AO257:AO265) -> 4591.1428
B84: Sub-total - Investimentos | C84: =SUM(C75:C83) -> 74753.799 | D84: =SUM(D75:D83) -> 18142.295
A86: 2 | B86: CUSTOS OPERACIONAIS
A87: 2.1 | B87: Gasto com insumos | E87: ='Rentabilidade-Cult.Perma.'!AP210 -> 12222.24 | F87: ='Rentabilidade-Cult.Perma.'!AQ210 -> 15257.852 | G87: ='Rentabilidade-Cult.Perma.'!AR210 -> 17315.004 | H87: ='Rentabilidade-Cult.Perma.'!AS210 -> 19658.468 | I87: ='Rentabilidade-Cult.Perma.'!AT210 -> 20282.372 | J87: ='Rentabilidade-Cult.Perma.'!AU210 -> 20282.372 | K87: ='Rentabilidade-Cult.Perma.'!AV210 -> 20282.372 | L87: ='Rentabilidade-Cult.Perma.'!AW210 -> 20282.372 | ... AK87: ='Rentabilidade-Cult.Perma.'!BV210 -> 20282.372
A88: 2.2 | B88: Gasto com mão de obra | E88: ='Rentabilidade-Cult.Perma.'!AP227 -> 4370.875 | F88: ='Rentabilidade-Cult.Perma.'!AQ227 -> 4952 | G88: ='Rentabilidade-Cult.Perma.'!AR227 -> 6977 | H88: ='Rentabilidade-Cult.Perma.'!AS227 -> 7490 | I88: ='Rentabilidade-Cult.Perma.'!AT227 -> 8759 | J88: ='Rentabilidade-Cult.Perma.'!AU227 -> 10028 | K88: ='Rentabilidade-Cult.Perma.'!AV227 -> 10028 | L88: ='Rentabilidade-Cult.Perma.'!AW227 -> 10028 | ... AK88: ='Rentabilidade-Cult.Perma.'!BV227 -> 7490
A89: 2.3 | B89: Gasto com trator e equipamentos e avaição agrícola | E89: ='Rentabilidade-Cult.Perma.'!AP243 -> 5712.5 | F89: ='Rentabilidade-Cult.Perma.'!AQ243 -> 6100 | G89: ='Rentabilidade-Cult.Perma.'!AR243 -> 6612.5 | H89: ='Rentabilidade-Cult.Perma.'!AS243 -> 6550 | I89: ='Rentabilidade-Cult.Perma.'!AT243 -> 6612.5 | J89: ='Rentabilidade-Cult.Perma.'!AU243 -> 6550 | K89: ='Rentabilidade-Cult.Perma.'!AV243 -> 6612.5 | L89: ='Rentabilidade-Cult.Perma.'!AW243 -> 6550 | ... AK89: ='Rentabilidade-Cult.Perma.'!BV243 -> 6612.5
A90: 2.4 | B90: Outros custos | E90: =SUM('Rentabilidade-Cult.Perma.'!AP257:AP265) -> 12178.051 | F90: =SUM('Rentabilidade-Cult.Perma.'!AQ257:AQ265) -> 14078.051 | G90: =SUM('Rentabilidade-Cult.Perma.'!AR257:AR265) -> 21664.96 | H90: =SUM('Rentabilidade-Cult.Perma.'!AS257:AS265) -> 23564.96 | I90: =SUM('Rentabilidade-Cult.Perma.'!AT257:AT265) -> 28438.777 | J90: =SUM('Rentabilidade-Cult.Perma.'!AU257:AU265) -> 33138.777 | K90: =SUM('Rentabilidade-Cult.Perma.'!AV257:AV265) -> 33138.777 | L90: =SUM('Rentabilidade-Cult.Perma.'!AW257:AW265) -> 33138.777 | ... AK90: =SUM('Rentabilidade-Cult.Perma.'!BV257:BV265) -> 23738.777
B91: Sub-total - custos operacionais | C91: =SUM(C87:C90) -> 0 | D91: =SUM(D87:D90) -> 0 | E91: =SUM(E87:E90) -> 34483.666 | F91: =SUM(F87:F90) -> 40387.903 | G91: =SUM(G87:G90) -> 52569.464 | H91: =SUM(H87:H90) -> 57263.428 | I91: =SUM(I87:I90) -> 64092.649 | J91: =SUM(J87:J90) -> 69999.149 | ... AK91: =SUM(AK87:AK90) -> 58123.649
A93: 3 | B93: ENTRADA - VALOR DA PRODUÇÃO
A94: 3.1 | B94: Valor da produção manga | C94: ='Rentabilidade-Cult.Perma.'!AN273 -> 0 | D94: ='Rentabilidade-Cult.Perma.'!AO273 -> 0 | E94: ='Rentabilidade-Cult.Perma.'!AP273 -> 34500 | F94: ='Rentabilidade-Cult.Perma.'!AQ273 -> 43240 | G94: ='Rentabilidade-Cult.Perma.'!AR273 -> 77740 | H94: ='Rentabilidade-Cult.Perma.'!AS273 -> 86480 | I94: ='Rentabilidade-Cult.Perma.'!AT273 -> 108100 | J94: ='Rentabilidade-Cult.Perma.'!AU273 -> 129720 | ... AK94: ='Rentabilidade-Cult.Perma.'!BV273 -> 86480
B95: Sub-total - valor da produção | C95: =SUM(C94:C94) -> 0 | D95: =SUM(D94:D94) -> 0 | E95: =SUM(E94:E94) -> 34500 | F95: =SUM(F94:F94) -> 43240 | G95: =SUM(G94:G94) -> 77740 | H95: =SUM(H94:H94) -> 86480 | I95: =SUM(I94:I94) -> 108100 | J95: =SUM(J94:J94) -> 129720 | ... AK95: =SUM(AK94:AK94) -> 86480
A97: 4 | B97: BALANÇO anual(Item 3 - item 1-item2) | C97: =C95-C91-C84 -> -74753.799 | D97: =D95-D91-D84 -> -18142.295 | E97: =E95-E91-E84 -> 16.333679 | F97: =F95-F91-F84 -> 2852.0967 | G97: =G95-G91-G84 -> 25170.536 | H97: =H95-H91-H84 -> 29216.572 | I97: =I95-I91-I84 -> 44007.351 | J97: =J95-J91-J84 -> 59720.851 | ... AK97: =AK95-AK91-AK84 -> 28356.351
A99: 5 | B99: BALANÇO ACUMULADO | C99: =C97 -> -74753.799 | D99: =C99+D97 -> -92896.094 | E99: =D99+E97 -> -92879.761 | F99: =E99+F97 -> -90027.664 | G99: =F99+G97 -> -64857.128 | H99: =G99+H97 -> -35640.556 | I99: =H99+I97 -> 8366.7956 | J99: =I99+J97 -> 68087.647 | K99: =J99+K97 -> 127746 | ... AK99: =AJ99+AK97 -> 1001838.5
C101: R$/ha/ano = | D101: =AK99/35 -> 28623.958 | E101: 35 anos
A103: Limão
A104: Custo 1 Ha
A105: ITEM | B105: COMPONENTES | C105: ANO DE IMPLANTAÇÃO DA CULTURA
C106: 1 | D106: =C106+1 -> 2 | E106: =D106+1 -> 3 | F106: =E106+1 -> 4 | G106: =F106+1 -> 5 | H106: =G106+1 -> 6 | I106: =H106+1 -> 7 | J106: =I106+1 -> 8 | K106: =J106+1 -> 9 | ... AK106: =AJ106+1 -> 35
A107: 1 | B107: INVESTIMENTOS
A108: 1.1 | B108: Supressão vegetal | C108: ='Custos Diversos'!E164 -> 1293.6736
A109: 1.2 | B109: Sistema de irrigação localizada | C109: ='Rentabilidade-Cult.Perma.'!AN339 -> 20000
A110: 1.3 | B110: Sistema de irrigação pivô central
A111: 1.4 | B111: Demais infraestrutura | C111: ='Rentabilidade-Cult.Perma.'!AN342-'Rentabilidade-Cult.Perma.'!AN339 -> 4263.4
B112: Ano de formação da cultura
A113: 1.5 | B113: Gasto com insumos | C113: ='Rentabilidade-Cult.Perma.'!AN301 -> 11708.225
A114: 1.6 | B114: Gasto com mão de obra | C114: ='Rentabilidade-Cult.Perma.'!AN318 -> 4828
A115: 1.7 | B115: Gasto com trator e equipamentos e avaição agrícola | C115: ='Rentabilidade-Cult.Perma.'!AN334 -> 7550
A116: 1.8 | B116: Outros custos | C116: =SUM('Rentabilidade-Cult.Perma.'!AN347:AN354) -> 4410.8258
B117: Sub-total - Investimentos | C117: =SUM(C108:C116) -> 54054.124
A119: 2 | B119: CUSTOS OPERACIONAIS
A120: 2.1 | B120: Gasto com insumos | D120: ='Rentabilidade-Cult.Perma.'!AO301 -> 6491.5 | E120: ='Rentabilidade-Cult.Perma.'!AP301 -> 8963.5 | F120: ='Rentabilidade-Cult.Perma.'!AQ301 -> 12119.7 | G120: ='Rentabilidade-Cult.Perma.'!AR301 -> 15126.4 | H120: ='Rentabilidade-Cult.Perma.'!AS301 -> 17036.8 | I120: ='Rentabilidade-Cult.Perma.'!AT301 -> 17372.2 | J120: ='Rentabilidade-Cult.Perma.'!AU301 -> 17372.2 | K120: ='Rentabilidade-Cult.Perma.'!AV301 -> 17372.2 | ... AK120: ='Rentabilidade-Cult.Perma.'!BV301 -> 17372.2
...

Sheet Resumo-Cult.Temp.
A2: RESUMO - Culturas Temporárias
A4: Soja
A5: Custo 1 Ha
A6: ITEM | B6: COMPONENTES | C6: ANO DE IMPLANTAÇÃO DA CULTURA
C7: 1 | D7: =C7+1 -> 2 | E7: =D7+1 -> 3 | F7: =E7+1 -> 4 | G7: =F7+1 -> 5 | H7: =G7+1 -> 6 | I7: =H7+1 -> 7 | J7: =I7+1 -> 8 | K7: =J7+1 -> 9 | ... AJ7: =AI7+1 -> 34 | AK7: 35
A8: 1 | B8: INVESTIMENTOS
A9: 1.1 | B9: Supressão vegetal | C9: ='Custos Diversos'!E165 -> 646.83682
A10: 1.2 | B10: Sistema de irrigação localizada
A11: 1.3 | B11: Sistema de irrigação pivô central | C11: ='Rentabilidade-Cult.Temp.'!E42 -> 9250
A12: 1.4 | B12: Demais infraestrutura | C12: ='Rentabilidade-Cult.Temp.'!E45-'Rentabilidade-Cult.Temp.'!E42 -> 1598.75
B13: Sub-total - Investimentos | C13: =SUM(C9:C12) -> 11495.587
A15: 2 | B15: CUSTOS OPERACIONAIS
A16: 2.1 | B16: Gasto com insumos | C16: ='Rentabilidade-Cult.Temp.'!E19 -> 3075 | D16: =C16 -> 3075 | E16: =D16 -> 3075 | F16: =E16 -> 3075 | G16: =F16 -> 3075 | H16: =G16 -> 3075 | I16: =H16 -> 3075 | J16: =I16 -> 3075 | K16: =J16 -> 3075 | ... AK16: =AJ16 -> 3075
A17: 2.2 | B17: Gasto com mão de obra | C17: ='Rentabilidade-Cult.Temp.'!E26 -> 795 | D17: =C17 -> 795 | E17: =D17 -> 795 | F17: =E17 -> 795 | G17: =F17 -> 795 | H17: =G17 -> 795 | I17: =H17 -> 795 | J17: =I17 -> 795 | K17: =J17 -> 795 | ... AK17: =AJ17 -> 795
A18: 2.3 | B18: Gasto com trator e equipamentos e avaição agrícola | C18: ='Rentabilidade-Cult.Temp.'!E38 -> 2042.5 | D18: =C18 -> 2042.5 | E18: =D18 -> 2042.5 | F18: =E18 -> 2042.5 | G18: =F18 -> 2042.5 | H18: =G18 -> 2042.5 | I18: =H18 -> 2042.5 | J18: =I18 -> 2042.5 | K18: =J18 -> 2042.5 | ... AK18: =AJ18 -> 2042.5
A19: 2.4 | B19: Outros custos | C19: =SUM('Rentabilidade-Cult.Temp.'!E50:E58) -> 1324.898 | D19: =C19 -> 1324.898 | E19: =D19 -> 1324.898 | F19: =E19 -> 1324.898 | G19: =F19 -> 1324.898 | H19: =G19 -> 1324.898 | I19: =H19 -> 1324.898 | J19: =I19 -> 1324.898 | K19: =J19 -> 1324.898 | ... AK19: =AJ19 -> 1324.898
B20: Sub-total - custos operacionais | C20: =SUM(C16:C19) -> 7237.398 | D20: =SUM(D16:D19) -> 7237.398 | E20: =SUM(E16:E19) -> 7237.398 | F20: =SUM(F16:F19) -> 7237.398 | G20: =SUM(G16:G19) -> 7237.398 | H20: =SUM(H16:H19) -> 7237.398 | I20: =SUM(I16:I19) -> 7237.398 | J20: =SUM(J16:J19) -> 7237.398 | ... AK20: =SUM(AK16:AK19) -> 7237.398
C21: =C20-7129 -> 108.39799
A22: 3 | B22: ENTRADA - VALOR DA PRODUÇÃO
A23: 3.1 | B23: Valor da produção soja | C23: ='Rentabilidade-Cult.Temp.'!E64 -> 14442 | D23: =C23 -> 14442 | E23: =D23 -> 14442 | F23: =E23 -> 14442 | G23: =F23 -> 14442 | H23: =G23 -> 14442 | I23: =H23 -> 14442 | J23: =I23 -> 14442 | K23: =J23 -> 14442 | ... AK23: =AJ23 -> 14442
B24: Sub-total - valor da produção | C24: =SUM(C23:C23) -> 14442 | D24: =SUM(D23:D23) -> 14442 | E24: =SUM(E23:E23) -> 14442 | F24: =SUM(F23:F23) -> 14442 | G24: =SUM(G23:G23) -> 14442 | H24: =SUM(H23:H23) -> 14442 | I24: =SUM(I23:I23) -> 14442 | J24: =SUM(J23:J23) -> 14442 | ... AK24: =SUM(AK23:AK23) -> 14442
