Workbook

Sheet base
A1: Nº PROPRIE- DADE | B1: ÁREA PROPRIEDADE (ha) | C1: PASTO (ha) | D1: VEGETAÇÃO NATIVA (ha) | E1: % EXPLORAÇÃO | G1: PIVÔ (ha) | H1: Possui PIVÔ (ha) | I1: IRRIGAÇÃO LOCALIZADA (ha) | J1: Possui IRRIGAÇÃO LOCALIZADA (ha) | K1: CULTURA EXPLORADA | L1: PAINEL SOLAR (m²) | M1: Possui PAINEL SOLAR (m²) | N1: BENFEITORIAS | O1: RECURSOS HÍDRICOS | P1: ENERGIA
E2: PASTO | F2: VEG.NAT.
A3: 1 | B3: 1206.7749 | C3: 572.96761 | D3: 633.80734 | E3: =C3/B3 -> 0.47479243 | F3: =D3/B3 -> 0.52520757 | N3: Casa Alvenaria; Curral; Bebedouro; Viveiro de Mudas; | P3: X
A4: 2 | B4: 3666.8488 | C4: 2600.6799 | D4: 1066.1689 | E4: =C4/B4 -> 0.70924111 | F4: =D4/B4 -> 0.29075889 | L4: 511.7231 | M4: X | N4: Estrutura Diversa; Casa Alvenaria; Estrutura Metálica; Reservatório; | O4: X | P4: X
A5: 3 | B5: 12.146215 | C5: 12.054604 | D5: 0.09161116 | E5: =C5/B5 -> 0.99245764 | F5: =D5/B5 -> 0.0075423626 | P5: X
A6: 4 | B6: 15.914785 | C6: 15.914785 | E6: =C6/B6 -> 1 | F6: =D6/B6 -> 0 | P6: X
A7: 5 | B7: 93.414859 | C7: 82.127624 | D7: 11.287235 | E7: =C7/B7 -> 0.87917088 | F7: =D7/B7 -> 0.12082912 | N7: Bebedouro; | P7: X
A8: 6 | B8: 108.07807 | C8: 22.476286 | D8: 81.009443 | E8: =C8/B8 -> 0.20796343 | F8: =D8/B8 -> 0.74954562 | I8: 4.59234 | J8: X | K8: Banana | N8: Estrutura Diversa; Casa Alvenaria; Estrutura Metálica; Reservatório; | O8: X | P8: X
A9: 7 | B9: 53.319423 | C9: 17.032642 | D9: 36.286781 | E9: =C9/B9 -> 0.31944536 | F9: =D9/B9 -> 0.68055464 | P9: X
A10: 8 | B10: 30.146132 | C10: 9.3378293 | D10: 20.808303 | E10: =C10/B10 -> 0.30975215 | F10: =D10/B10 -> 0.69024785 | P10: X
A11: 9 | B11: 223.79593 | C11: 204.09329 | D11: 19.702639 | E11: =C11/B11 -> 0.91196159 | F11: =D11/B11 -> 0.088038414 | N11: Estrutura Diversa; Casa Alvenaria; Estrutura de Concreto; Reservatório; Curral; | O11: X | P11: X
A12: 10 | B12: 20.086431 | C12: 16.377264 | D12: 2.8160724 | E12: =C12/B12 -> 0.81533965 | F12: =D12/B12 -> 0.14019775 | I12: 0.89309493 | J12: X | K12: Limão | P12: X
A13: 11 | B13: 31.177793 | C13: 7.1158069 | D13: 24.061986 | E13: =C13/B13 -> 0.22823318 | F13: =D13/B13 -> 0.77176682 | N13: Estrutura Diversa; Casa Alvenaria; Reservatório; | O13: X | P13: X
A14: 12 | B14: 30.077264 | C14: 7.2797137 | D14: 22.797551 | E14: =C14/B14 -> 0.24203377 | F14: =D14/B14 -> 0.75796623 | N14: Estrutura Diversa; Casa Alvenaria; Reservatório; | O14: X | P14: X
A15: 13 | B15: 49.176021 | C15: 9.1121382 | D15: 40.063883 | E15: =C15/B15 -> 0.18529637 | F15: =D15/B15 -> 0.81470363 | N15: Estrutura Diversa; Casa Alvenaria; Reservatório; | O15: X | P15: X
A16: 14 | B16: 28.103318 | D16: 28.103318 | E16: =C16/B16 -> 0 | F16: =D16/B16 -> 1 | P16: X
A17: 15 | B17: 31.473609 | C17: 1.7939745 | D17: 26.481062 | E17: =C17/B17 -> 0.056999324 | F17: =D17/B17 -> 0.84137352 | I17: 3.1985733 | J17: X | K17: Limão | N17: Estrutura Diversa; Casa Alvenaria; Reservatório; | O17: X | P17: X
A18: 16 | B18: 29.811365 | C18: 3.3303031 | D18: 26.481062 | E18: =C18/B18 -> 0.11171253 | F18: =D18/B18 -> 0.88828747 | N18: Casa Alvenaria; Bebedouro; | P18: X
A19: 17 | B19: 29.640944 | C19: 9.8787929 | D19: 12.515501 | E19: =C19/B19 -> 0.33328199 | F19: =D19/B19 -> 0.42223693 | G19: 2.2801 | H19: X | I19: 4.9665502 | J19: X | K19: Ciclo Anual | N19: Estrutura Diversa; Casa Alvenaria; Reservatório; | O19: X | P19: X
A20: 18 | B20: 8.0706058 | C20: 3.7902881 | D20: 4.2803176 | E20: =C20/B20 -> 0.46964109 | F20: =D20/B20 -> 0.53035891 | P20: X
A21: 19* | B21: 97.47998 | C21: 69.9936 | D21: 3.4863802 | E21: =C21/B21 -> 0.71803051 | F21: =D21/B21 -> 0.035765089 | G21: 20 | H21: X | I21: 4 | J21: X | K21: Banana | N21: Estrutura Diversa; Casa Alvenaria; Reservatório; | O21: X | P21: X | Q21: **Obs.: A Propriedade 19 possui áreas com CAR e áreas sem CAR.
A22: 20 | B22: 43.60409 | D22: 43.60409 | E22: =C22/B22 -> 0 | F22: =D22/B22 -> 1 | P22: X
A23: 21 | B23: 38.616421 | C23: 9.4852664 | D23: 29.131154 | E23: =C23/B23 -> 0.2456278 | F23: =D23/B23 -> 0.7543722 | N23: Estrutura Diversa; Casa Alvenaria; | P23: X
A24: 22 | B24: 33.659597 | C24: 9.4253462 | D24: 24.234251 | E24: =C24/B24 -> 0.28001958 | F24: =D24/B24 -> 0.71998042 | N24: Estrutura Diversa; Casa Alvenaria; | P24: X
A25: 23 | B25: 148.72492 | C25: 5.343799 | D25: 143.38112 | E25: =C25/B25 -> 0.035930758 | F25: =D25/B25 -> 0.96406924 | N25: Estrutura Diversa; Casa Alvenaria; | P25: X
A26: 24 | B26: 146.2572 | C26: 129.50176 | D26: 16.755433 | E26: =C26/B26 -> 0.88543857 | F26: =D26/B26 -> 0.11456143 | N26: Estrutura Diversa; Casa Alvenaria; | P26: X
A27: 25 | B27: 45.43599 | C27: 28.228487 | D27: 17.207503 | E27: =C27/B27 -> 0.62128033 | F27: =D27/B27 -> 0.37871967 | P27: X
A28: 26 | B28: 693.41037 | C28: 283.40072 | D28: 390.80334 | E28: =C28/B28 -> 0.40870563 | F28: =D28/B28 -> 0.56359604 | I28: 19.206314 | J28: X | K28: Limão | N28: Casa Alvenaria; Reservatório; | O28: X | P28: X
A29: 27 | B29: 81.972571 | D29: 81.972571 | E29: =C29/B29 -> 0 | F29: =D29/B29 -> 1 | N29: Casa Alvenaria; Reservatório; | O29: X | P29: X
A30: 28 | B30: 244.45631 | C30: 5.9094185 | D30: 238.54689 | E30: =C30/B30 -> 0.024173721 | F30: =D30/B30 -> 0.97582628 | P30: X
A31: 29 | B31: 40.615095 | C31: 40.615095 | E31: =C31/B31 -> 1 | F31: =D31/B31 -> 0 | N31: Casa Alvenaria; Curral; | P31: X
A32: 30 | B32: 40.576268 | C32: 18.468836 | D32: 22.107432 | E32: =C32/B32 -> 0.4551635 | F32: =D32/B32 -> 0.5448365 | N32: Casa Alvenaria; | P32: X
A33: 31 | B33: 82.712954 | C33: 22.779882 | D33: 59.933072 | E33: =C33/B33 -> 0.27540888 | F33: =D33/B33 -> 0.72459112 | P33: X
A34: 32 | B34: 44.620108 | C34: 26.202262 | D34: 18.417846 | E34: =C34/B34 -> 0.58722991 | F34: =D34/B34 -> 0.41277009 | N34: Casa Alvenaria; | P34: X
A35: 33 | B35: 80.644455 | C35: 6.4966872 | D35: 74.147768 | E35: =C35/B35 -> 0.080559626 | F35: =D35/B35 -> 0.91944037 | N35: Casa Alvenaria; Reservatório; | O35: X | P35: X
A36: 34 | B36: 1369.7731 | C36: 1222.9325 | D36: 146.84067 | E36: =C36/B36 -> 0.89279928 | F36: =D36/B36 -> 0.10720072 | N36: Estrutura Diversa; Casa Alvenaria; Estrutura de Concreto; Bebedouro; | P36: X
A37: 35 | B37: 26.870599 | C37: 21.349982 | D37: 5.5206169 | E37: =C37/B37 -> 0.79454805 | F37: =D37/B37 -> 0.20545195 | P37: X
A38: 36 | B38: 26.870026 | C38: 21.096398 | D38: 5.7736282 | E38: =C38/B38 -> 0.78512755 | F38: =D38/B38 -> 0.21487245 | N38: Casa Alvenaria; Estrutura Metálica; Reservatório; | O38: X | P38: X
A39: 37 | B39: 0.50077895 | C39: 0.50077895 | E39: =C39/B39 -> 1 | F39: =D39/B39 -> 0 | P39: X
A40: 38 | B40: 3.9824501 | C40: 0.53543386 | D40: 3.4470163 | E40: =C40/B40 -> 0.13444835 | F40: =D40/B40 -> 0.86555165 | P40: X
A41: 39 | B41: 15.661688 | C41: 6.255086 | D41: 9.4066024 | E41: =C41/B41 -> 0.39938772 | F41: =D41/B41 -> 0.60061228 | P41: X
A42: 40 | B42: 25.845583 | C42: 12.095402 | D42: 13.750181 | E42: =C42/B42 -> 0.46798721 | F42: =D42/B42 -> 0.53201279 | P42: X
A43: 41 | B43: 30.547732 | C43: 10.719933 | D43: 19.827799 | E43: =C43/B43 -> 0.35092403 | F43: =D43/B43 -> 0.64907597 | N43: Estrutura Diversa; Casa Alvenaria; Reservatório; | O43: X | P43: X
A44: 42 | B44: 244.97123 | C44: 44.108171 | D44: 200.86306 | E44: =C44/B44 -> 0.18005449 | F44: =D44/B44 -> 0.81994551 | N44: Estrutura Diversa; Casa Alvenaria; Reservatório; Curral; | O44: X | P44: X
A45: 43 | B45: 29.850349 | C45: 18.008717 | E45: =C45/B45 -> 0.60330004 | F45: =D45/B45 -> 0 | L45: 118416.32 | M45: X | P45: X
A46: 44 | B46: 59.734008 | D46: 59.734008 | E46: =C46/B46 -> 0 | F46: =D46/B46 -> 1 | P46: X
A47: 45 | B47: 27.410207 | C47: 19.740562 | D47: 7.669645 | E47: =C47/B47 -> 0.72019018 | F47: =D47/B47 -> 0.27980982 | N47: Estrutura Diversa; Casa Alvenaria; | P47: X
A48: 46 | B48: 29.865446 | C48: 29.865446 | E48: =C48/B48 -> 1 | F48: =D48/B48 -> 0 | N48: Casa Alvenaria; Bebedouro; | P48: X
A49: 47 | B49: 153.33063 | C49: 20.29323 | D49: 133.0374 | E49: =C49/B49 -> 0.13234949 | F49: =D49/B49 -> 0.86765051 | P49: X
A50: 48 | B50: 10.840117 | C50: 10.840117 | E50: =C50/B50 -> 1 | F50: =D50/B50 -> 0 | P50: X
A51: 49 | B51: 20.453242 | C51: 20.453242 | E51: =C51/B51 -> 1 | F51: =D51/B51 -> 0 | N51: Estrutura Diversa; | P51: X
A52: 50 | B52: 41.573141 | C52: 2.67539 | D52: 27.642814 | E52: =C52/B52 -> 0.064353809 | F52: =D52/B52 -> 0.66492002 | L52: 112549.37 | M52: X | P52: X
A53: 51 | B53: 31.415908 | C53: 13.972915 | D53: 17.442993 | E53: =C53/B53 -> 0.44477196 | F53: =D53/B53 -> 0.55522804 | N53: Estrutura Diversa; Casa Alvenaria; Reservatório; | O53: X | P53: X
A54: 52 | B54: 10.693703 | C54: 6.4317115 | D54: 4.2619916 | E54: =C54/B54 -> 0.60144848 | F54: =D54/B54 -> 0.39855152 | L54: 25.5894 | M54: X | N54: Estrutura Diversa; Casa Alvenaria; Reservatório; Curral; | O54: X | P54: X
A55: 53 | B55: 80.856749 | C55: 71.987821 | D55: 8.8689284 | E55: =C55/B55 -> 0.89031307 | F55: =D55/B55 -> 0.10968693 | N55: Casa Alvenaria; Curral; | P55: X
A56: 54 | B56: 80.335977 | C56: 70.614149 | D56: 9.7218281 | E56: =C56/B56 -> 0.87898538 | F56: =D56/B56 -> 0.12101462 | P56: X
A57: 55 | B57: 72.790069 | C57: 68.134162 | D57: 4.6559075 | E57: =C57/B57 -> 0.9360365 | F57: =D57/B57 -> 0.063963499 | P57: X
A58: 56 | B58: 80.064317 | C58: 48.38884 | D58: 31.675477 | E58: =C58/B58 -> 0.60437461 | F58: =D58/B58 -> 0.39562539 | N58: Casa Alvenaria; Estrutura de Concreto; Estrutura Metálica; | P58: X
A59: 57 | B59: 91.414957 | C59: 4.1386031 | D59: 87.276353 | E59: =C59/B59 -> 0.045272713 | F59: =D59/B59 -> 0.95472729 | P59: X
A60: 58 | B60: 331.19828 | C60: 160.03871 | D60: 171.15957 | E60: =C60/B60 -> 0.48321116 | F60: =D60/B60 -> 0.51678884 | N60: Casa Alvenaria; | P60: X
A61: 59 | B61: 54.68618 | C61: 52.166535 | D61: 2.5196452 | E61: =C61/B61 -> 0.95392537 | F61: =D61/B61 -> 0.046074625 | P61: X
A62: 60 | B62: 26.111792 | C62: 7.8436717 | D62: 18.26812 | E62: =C62/B62 -> 0.30038811 | F62: =D62/B62 -> 0.69961189 | N62: Casa Alvenaria; | P62: X
A63: 61 | B63: 22.027228 | C63: 3.4141521 | D63: 3.6998078 | E63: =C63/B63 -> 0.1549969 | F63: =D63/B63 -> 0.1679652 | I63: 14.913269 | J63: X | K63: Banana | N63: Casa Alvenaria; | P63: X
A64: 62 | B64: 53.376153 | C64: 43.483829 | D64: 9.8923236 | E64: =C64/B64 -> 0.81466773 | F64: =D64/B64 -> 0.18533227 | P64: X
A65: 63 | B65: 55.269748 | C65: 27.059797 | D65: 28.209951 | E65: =C65/B65 -> 0.48959509 | F65: =D65/B65 -> 0.51040491 | N65: Casa Alvenaria; | P65: X
A66: 64 | B66: 24.368638 | C66: 23.156024 | D66: 1.2126135 | E66: =C66/B66 -> 0.95023877 | F66: =D66/B66 -> 0.049761232 | N66: Casa Alvenaria; Curral; | P66: X
A67: 65 | B67: 25.130103 | C67: 24.11718 | D67: 1.0129235 | E67: =C67/B67 -> 0.95969282 | F67: =D67/B67 -> 0.040307176 | N67: Casa Alvenaria; Estrutura Metálica; Curral; | P67: X
A68: 66 | B68: 12.444945 | C68: 4.1346074 | D68: 4.5184025 | E68: =C68/B68 -> 0.33223187 | F68: =D68/B68 -> 0.36307131 | I68: 3.7919351 | J68: X | K68: S/Cultura | N68: Estrutura Diversa; Casa Alvenaria; Estrutura Metálica; Reservatório; | O68: X | P68: X
A69: 67 | B69: 8.2753131 | C69: 7.0022253 | D69: 1.2730878 | E69: =C69/B69 -> 0.84615835 | F69: =D69/B69 -> 0.15384165 | P69: X
A70: 68 | B70: 6.3863365 | C70: 6.3863365 | E70: =C70/B70 -> 1 | F70: =D70/B70 -> 0 | P70: X
A71: 69 | B71: 4.4716998 | C71: 4.4716998 | E71: =C71/B71 -> 1 | F71: =D71/B71 -> 0 | N71: Casa Alvenaria; Reservatório; | O71: X | P71: X
A72: 70 | B72: 23.537019 | C72: 6.0422799 | D72: 10.870061 | E72: =C72/B72 -> 0.2567139 | F72: =D72/B72 -> 0.46182827 | I72: 6.6246783 | J72: X | K72: Banana | N72: Casa Alvenaria; Reservatório; | O72: X | P72: X
A73: 71 | B73: 9.4526087 | C73: 4.1137945 | E73: =C73/B73 -> 0.43520203 | F73: =D73/B73 -> 0 | I73: 5.3388142 | J73: X | K73: Banana | N73: Casa Alvenaria; | P73: X
A74: 72 | B74: 4.693059 | C74: 1.8445774 | D74: 0.79817454 | E74: =C74/B74 -> 0.39304373 | F74: =D74/B74 -> 0.17007554 | I74: 2.0503071 | J74: X | K74: Banana | N74: Casa Alvenaria; | P74: X
A75: 73 | B75: 24.578736 | C75: 19.742389 | D75: 1.5940451 | E75: =C75/B75 -> 0.80323047 | F75: =D75/B75 -> 0.06485464 | I75: 3.2423012 | J75: X | K75: Banana | N75: Estrutura Diversa; Casa Alvenaria; Viveiro de Mudas; | P75: X
A76: 74 | B76: 9.9284991 | C76: 9.9284991 | E76: =C76/B76 -> 1 | F76: =D76/B76 -> 0 | N76: Estrutura Diversa; Casa Alvenaria; Estrutura Metálica; Reservatório; Curral; Viveiro de Mudas; | O76: X | P76: X
A77: 75 | B77: 19.798656 | C77: 1.8609939 | D77: 1.7391985 | E77: =C77/B77 -> 0.093995975 | F77: =D77/B77 -> 0.087844274 | I77: 16.198463 | J77: X | K77: Banana | P77: X
A78: 76 | B78: 47.811448 | C78: 47.811448 | E78: =C78/B78 -> 1 | F78: =D78/B78 -> 0 | P78: X
A79: 77 | B79: 37.709054 | C79: 29.050627 | D79: 8.6584275 | E79: =C79/B79 -> 0.77038863 | F79: =D79/B79 -> 0.22961137 | P79: X
A80: 78 | B80: 5.8431239 | C80: 5.8431239 | E80: =C80/B80 -> 1 | F80: =D80/B80 -> 0 | P80: X
A81: 79 | B81: 4.453493 | C81: 4.453493 | E81: =C81/B81 -> 1 | F81: =D81/B81 -> 0 | N81: Casa Alvenaria; | P81: X
A82: 80 | B82: 4.2890869 | C82: 4.2890869 | E82: =C82/B82 -> 1 | F82: =D82/B82 -> 0 | N82: Estrutura Diversa; Casa Alvenaria; | P82: X
A83: 81 | B83: 25.169105 | C83: 18.593632 | D83: 3.9698468 | E83: =C83/B83 -> 0.73874824 | F83: =D83/B83 -> 0.15772697 | I83: 2.6056261 | J83: X | K83: Banana | N83: Casa Alvenaria; | P83: X
A84: 82 | B84: 85.282298 | C84: 85.282298 | E84: =C84/B84 -> 1 | F84: =D84/B84 -> 0 | P84: X
A85: 83 | B85: 152.22302 | C85: 121.15452 | D85: 31.068508 | E85: =C85/B85 -> 0.79590139 | F85: =D85/B85 -> 0.20409861 | P85: X
A86: 84 | B86: 31.1133 | C86: 31.1133 | E86: =C86/B86 -> 1 | F86: =D86/B86 -> 0 | P86: X
A87: 85 | B87: 87.209039 | C87: 20.824199 | D87: 66.38484 | E87: =C87/B87 -> 0.23878487 | F87: =D87/B87 -> 0.76121513 | N87: Estrutura Diversa; Casa Alvenaria; Cisterna; | O87: X | P87: X
A88: 86 | B88: 90.685413 | C88: 64.247784 | D88: 26.437628 | E88: =C88/B88 -> 0.70846879 | F88: =D88/B88 -> 0.29153121 | N88: Estrutura Diversa; Casa Alvenaria; Reservatório; | O88: X | P88: X
A89: 87 | B89: 200.28119 | C89: 166.72913 | D89: 33.552056 | E89: =C89/B89 -> 0.83247525 | F89: =D89/B89 -> 0.16752475 | N89: Casa Alvenaria; | P89: X
A90: 88 | B90: 120.59786 | C90: 120.59786 | E90: =C90/B90 -> 1 | F90: =D90/B90 -> 0 | N90: Estrutura Diversa; Casa Alvenaria; Curral; | P90: X
A91: 89 | B91: 119.6151 | C91: 19.615774 | D91: 99.999327 | E91: =C91/B91 -> 0.16399078 | F91: =D91/B91 -> 0.83600922 | N91: Casa Alvenaria; | P91: X
A92: 90 | B92: 161.86653 | D92: 161.86653 | E92: =C92/B92 -> 0 | F92: =D92/B92 -> 1 | P92: X
A93: 91 | B93: 23.932703 | C93: 17.546275 | E93: =C93/B93 -> 0.73315057 | F93: =D93/B93 -> 0 | I93: 6.3864281 | J93: X | K93: Banana | N93: Estrutura Diversa; Casa Alvenaria; | P93: X
A94: 92 | B94: 133.5128 | C94: 122.60897 | D94: 10.903828 | E94: =C94/B94 -> 0.91833122 | F94: =D94/B94 -> 0.08166878 | N94: Estrutura Diversa; Casa Alvenaria; Curral; | P94: X
A95: 93 | B95: 47.114609 | C95: 47.114609 | E95: =C95/B95 -> 1 | F95: =D95/B95 -> 0 | P95: X
A96: 94 | B96: 23.430115 | C96: 22.729059 | D96: 0.70105688 | E96: =C96/B96 -> 0.97007881 | F96: =D96/B96 -> 0.029921188 | P96: X
A97: 95 | B97: 26.982164 | C97: 22.95699 | D97: 4.025174 | E97: =C97/B97 -> 0.85082094 | F97: =D97/B97 -> 0.14917906 | N97: Casa Alvenaria; | P97: X
A98: 96 | B98: 88.269565 | C98: 79.556213 | D98: 2.5916612 | E98: =C98/B98 -> 0.90128702 | F98: =D98/B98 -> 0.029360757 | I98: 6.1216904 | J98: X | K98: Banana | N98: Estrutura Diversa; Casa Alvenaria; Curral; | P98: X
A99: 97 | B99: 50.328843 | C99: 39.166191 | D99: 11.162652 | E99: =C99/B99 -> 0.77820567 | F99: =D99/B99 -> 0.22179433 | N99: Estrutura Diversa; Casa Alvenaria; | P99: X
A100: 98 | B100: 27.70558 | C100: 18.691002 | D100: 9.0145777 | E100: =C100/B100 -> 0.67462952 | F100: =D100/B100 -> 0.32537048 | N100: Estrutura Diversa; Casa Alvenaria; | P100: X
...

Sheet Lista de Abas
A1: LISTA DE ABAS
A2: Capa | B2: Identificação do documento.
A3: Cálculo Depre.-Sist. Irrig. | B3: Memória de cálculo do valor avaliado dos sistemas de irrigação baseado na depreciação.
A4: Estimativa Valores-Painéis Sol. | B4: Base da estimativa dos valores dos painéis solares.
A5: Cálculo Valor Avaliação-Cultura | B5: Memória de cálculo do valor de avaliação das culturas de Banana, Limão e Manga.
A6: Cálculo Geral de Propriedades | B6: Planilha geral do cálculo dos valores por propriedade.
A7: Valores Est. por Propriedade | B7: Planilha resumo dos valores estimados das propriedades geral.
A8: Valores Est. por Prop. ET.3e4 | B8: Planilha resumo dos valores estimados das propriedades nas Etapas 3 e 4.

Sheet Capa
B8: Fundo de Desenvolvimento da Infraestrutura Sustentável – FDIRS
B14: Serviços Técnicos relativos à Estruturação e o Desenvolvimento de Concessão do Perímetro Irrigado do Jaíba (Etapas III e IV) da Companhia de Desenvolvimento dos Vales do São Francisco e do Parnaíba - CODEVASF
B19: CONTRATO: 01/2025
B25: RELATÓRIO TÉCNICO-AVALIAÇÃO FUNDIÁRIA
B31: MEMÓRIA DE CÁLCULO DO VALOR DE CADA PROPRIEDADE
K45: 46204
A51: CONSÓRCIO Nova Irrigação Jaíba/MG
A63: JB_E3-4.05.TOP.PL.002_R1-Mem. Cálculo vl propriedades

Sheet Cálculo Depre.-Sist. Irrig.
E2: DISCRIMINAÇÃO | F2: IDADE APARENTE | G2: VIDA ÚTIL - ANOS | H2: C.M. | I2: C.T. | J2: VALOR RESIDUAL (% DO VALOR TOTAL) | K2: VALOR DO BEM USADO / REFORM. (R$) | L2: VALOR DO BEM NOVO (R$) | M2: VALOR DEPREC. (R$) | N2: F.L. (%) | O2: VALOR DEPREC. x FATOR DE LIQUIDEZ (R$) | P2: VALOR AVALIADO UNITÁRIO (R$) | Q2: VALOR AVALIADO UNITÁRIO / VALOR NOVO (%) | R2: VALOR AVALIADO TOTAL (R$)
E3: sistema de irrigação-Microaspersão | F3: 12 | G3: 25 | H3: 10 | I3: 10 | J3: 0 | L3: =L20 -> 24000 | M3: =((1-J3/100)*1.347961431/(1+0.347961431*EXP(3.579760093*(F3/G3)*0.85308171*EXP(0.067348748*I3-0.041679277*H3-0.00102286*I3*H3)))+J3/100)*L3 -> 11060.23 | N3: 0.7 | O3: =M3*N3 -> 7742.1613 | P3: =+ROUND(O3,-2) -> 7700 | R3: =P3*D3 -> 0
E4: sistema de irrigação- Pivô central | F4: 12 | G4: 25 | H4: 10 | I4: 10 | J4: 0 | L4: =H22 -> 21000 | M4: =((1-J4/100)*1.347961431/(1+0.347961431*EXP(3.579760093*(F4/G4)*0.85308171*EXP(0.067348748*I4-0.041679277*H4-0.00102286*I4*H4)))+J4/100)*L4 -> 9677.7016 | N4: 0.7 | O4: =M4*N4 -> 6774.3911 | P4: =+ROUND(O4,-2) -> 6800 | R4: =P4*D4 -> 0
B6: CÁLCULO DA DEPRECIAÇÃO PELO MÉTODO DE CAIRES
B8: Equação:
B9: VB = ( ( 1 - VR ) x 1,347961431 / ( 1 + 0,347961431 x EXP ( 3,579760093 x ( IA / VU ) x 0,853081710 x EXP ( 0,067348748 x CT - 0,041679277 x CM - 0,001022860 x CT x CM ) ) ) + VR ) x VN
C11: onde: | E11: VB = Valor do bem avaliando, em R$ | G11: Coeficiente de Trabalho | J11: Coeficiente de Manutenção | M11: Fator de Liquidez
E12: VR = Valor residual, em %, do bem avaliando | G12: 0 | H12: Nulo | J12: 0 | K12: Inexistente | M12: 90 | N12: Médio
E13: IA = Idade aparente do bem avaliando, em anos | G13: 5 | H13: Leve | J13: 5 | K13: Sofrível | M13: 80 | N13: Baixo
E14: VU = Vida útil total do bem avaliando, em anos | G14: 10 | H14: Normal | J14: 10 | K14: Normal | M14: 70 | N14: Baixíssimo
E15: CT = Coeficiente de trabalho do bem avaliando | G15: 15 | H15: Pesado | J15: 15 | K15: Rigorosa
E16: CM = Coeficiente de manutenção do bem avaliando | G16: 20 | H16: Extremo | J16: 20 | K16: Perfeita
E17: VN = Valor de similar novo, em R$
B20: Valor médio de um sistema novo de Microaspersão (para atender cultura de limão, manga, banana), para 16 ha (média das pr0priedades) - R$/ha = | L20: 24000
B22: Valor médio de um sistema novo de Pivô central para 28 ha(média das propriedades) - R$/ha = | H22: 21000
B24: Fonte do valor novo sistema de Irrigação - Tecminas -irrigação (038)991138754

Sheet Estimativa Valores-Painéis Sol.
B2: ESTIMATIVA DE VALOR DE m² DE PLACA DE PAINEL SOLAR
B3: Propriedade | C3: Área - m² | D3: Valor da Placa | E3: Valor / m²
B4: 2 | C4: 511.7231 | D4: 72000 | E4: =D4/C4 -> 140.70109
B5: 50 | C5: 112549.37 | D5: 10200000 | E5: =D5/C5 -> 90.626892
B6: 52 | C6: 25.5894 | D6: 6600 | E6: =D6/C6 -> 257.91929
B7: 172 | C7: 330.6577 | D7: 68000 | E7: =D7/C7 -> 205.65074
B8: 194 | C8: 20.602 | D8: 5300 | E8: =D8/C8 -> 257.25658
B9: 263 | C9: 612 | D9: 87000 | E9: =D9/C9 -> 142.15686
B10: 301 | C10: 35 | D10: 9000 | E10: =D10/C10 -> 257.14286
B11: 314 | C11: 2833.6 | D11: 348000 | E11: =D11/C11 -> 122.81197
B12: 324 | C12: 569.6373 | D12: 81000 | E12: =D12/C12 -> 142.19574
B13: 333 | C13: 19.5516 | D13: 7300 | E13: =D13/C13 -> 373.37098
B14: 336 | C14: 175.0993 | D14: 36000 | E14: =D14/C14 -> 205.59762
B15: 339 | C15: 549.3691 | D15: 78000 | E15: =D15/C15 -> 141.98105
... B24: 375 | C24: 12.2172 | D24: 4500 | E24: =D24/C24 -> 368.33317
B26: *OBS: Fonte Painel Solar = PORTAL SOLAR- 31-972132657 - Contato@portalsolar.com.br - Data de Referência- Janeiro/2025 - Valores médios praticados no Brasil.

Sheet Cálculo Valor Avaliação-Cultura
A1: Banana 1/ | G1: Manga 2/ | O1: Limão 3/
A2: GASTO COM INSUMOS | G2: GASTO COM INSUMOS | O2: GASTO COM INSUMOS
A3: Descrição | B3: Unidade | C3: Custo Unit. | D3: Quantidade por ha | E3: Custo por ano - R$ | G3: Descrição | H3: Unidade | I3: Custo Unit. | J3: Quantidade por ha por ano | L3: Custo por ano - R$ | O3: Descrição | P3: Unidade | Q3: Custo Unit. | R3: Quantidade por ha | T3: Custo por ano - R$
D4: 1 | E4: 1 | J4: 1 | K4: 2 | L4: 1 | M4: 2 | R4: 1 | S4: 2 | T4: 1 | U4: 2
A5: Ácido Bórico | B5: KG | C5: 7.5 | D5: 133.3 | E5: =C5*D5 -> 999.75 | G5: Ácido Bórico | H5: KG | I5: 7.5 | J5: 15.52 | K5: 46.56 | L5: =I5*J5 -> 116.4 | M5: =I5*K5 -> 349.2 | O5: Ácido Bórico | P5: KG | Q5: 7.5 | R5: 5.25 | S5: 21 | T5: =$Q5*R5 -> 39.375 | U5: =$Q5*S5 -> 157.5
A6: Calcário | B6: T | C6: 450 | D6: 1.3 | E6: =C6*D6 -> 585 | G6: Calcário | H6: T | I6: 450 | J6: 1 | K6: 1 | L6: =I6*J6 -> 450 | M6: =I6*K6 -> 450 | O6: Calcário | P6: T | Q6: 450 | R6: 1 | S6: 1 | T6: =$Q6*R6 -> 450 | U6: =$Q6*S6 -> 450
A7: Fosfatado | B7: T | C7: 2650 | D7: 1 | E7: =C7*D7 -> 2650 | G7: Fosfatado | H7: T | I7: 2650 | J7: 1 | K7: 1 | L7: =I7*J7 -> 2650 | M7: =I7*K7 -> 2650 | O7: Fosfatado | P7: T | Q7: 2650 | R7: 1 | S7: 1 | T7: =$Q7*R7 -> 2650 | U7: =$Q7*S7 -> 2650
A8: Foliar Completo | B8: L | C8: 25 | D8: 2 | E8: =C8*D8 -> 50 | G8: Foliar Completo | H8: L | I8: 25 | J8: 3 | K8: 12 | L8: =I8*J8 -> 75 | M8: =I8*K8 -> 300 | O8: Foliar Completo | P8: L | Q8: 25 | R8: 3 | S8: 12 | T8: =$Q8*R8 -> 75 | U8: =$Q8*S8 -> 300
A9: KCL | B9: T | C9: 2700 | D9: 1.27968 | E9: =C9*D9 -> 3455.136 | G9: KCL | H9: T | I9: 2700 | J9: 0.194 | K9: 0.27936 | L9: =I9*J9 -> 523.8 | M9: =I9*K9 -> 754.272 | O9: KCL | P9: T | Q9: 2700 | R9: 0.063 | S9: 0.126 | T9: =$Q9*R9 -> 170.1 | U9: =$Q9*S9 -> 340.2
A10: Sulfato de Magnésio | B10: KG | C10: 1.5 | D10: 199.95 | E10: =C10*D10 -> 299.925 | G10: Sulfato de Magnésio | H10: KG | I10: 1.5 | J10: 116.4 | K10: 186.24 | L10: =I10*J10 -> 174.6 | M10: =I10*K10 -> 279.36 | O10: Nitrato de Potássio | P10: KG | Q10: 8.9 | R10: 0 | S10: 0 | T10: =$Q10*R10 -> 0 | U10: =$Q10*S10 -> 0
A11: Sulfato de Zinco | B11: KG | C11: 6 | D11: 99.975 | E11: =C11*D11 -> 599.85 | G11: Sulfato de Zinco | H11: KG | I11: 6 | J11: 77.6 | K11: 93.12 | L11: =I11*J11 -> 465.6 | M11: =I11*K11 -> 558.72 | O11: Sulfato de Magnésio | P11: KG | Q11: 1.5 | R11: 31.5 | S11: 84 | T11: =$Q11*R11 -> 47.25 | U11: =$Q11*S11 -> 126
A12: Esterco de Gado | B12: M3 | C12: 80 | D12: 39.99 | E12: =C12*D12 -> 3199.2 | G12: Esterco de Gado | H12: M3 | I12: 80 | J12: 7.76 | K12: 7.76 | L12: =I12*J12 -> 620.8 | M12: =I12*K12 -> 620.8 | O12: Sulfato de Zinco | P12: KG | Q12: 6 | R12: 10.5 | S12: 42 | T12: =$Q12*R12 -> 63 | U12: =$Q12*S12 -> 252
A13: Nitrato de Amonia | B13: T | C13: 2200 | D13: 1.023744 | E13: =C13*D13 -> 2252.2368 | G13: Nitrato de Amonia | H13: T | I13: 2200 | J13: 0.194 | K13: 0.194 | L13: =I13*J13 -> 426.8 | M13: =I13*K13 -> 426.8 | O13: Esterco de Gado | P13: M3 | Q13: 80 | R13: 7 | S13: 7 | T13: =$Q13*R13 -> 560 | U13: =$Q13*S13 -> 560
A14: Fungicida | B14: L | C14: 85 | D14: 0.5 | E14: =C14*D14 -> 42.5 | G14: Fungicida | H14: L | I14: 85 | J14: 3 | K14: 8 | L14: =I14*J14 -> 255 | M14: =I14*K14 -> 680 | O14: Nitrato de Amonia | P14: T | Q14: 2200 | R14: 0.0105 | S14: 0.063 | T14: =$Q14*R14 -> 23.1 | U14: =$Q14*S14 -> 138.6
A15: Inseticida | B15: L | C15: 40 | D15: 1 | E15: =C15*D15 -> 40 | G15: Inseticida | H15: L | I15: 40 | J15: 3 | K15: 4 | L15: =I15*J15 -> 120 | M15: =I15*K15 -> 160 | O15: Fungicida | P15: L | Q15: 85 | R15: 3 | S15: 12 | T15: =$Q15*R15 -> 255 | U15: =$Q15*S15 -> 1020
A16: Espalhante | B16: L | C16: 15 | D16: 0.25 | E16: =C16*D16 -> 3.75 | G16: Espalhante | H16: L | I16: 15 | J16: 0.36 | K16: 0.4 | L16: =I16*J16 -> 5.4 | M16: =I16*K16 -> 6 | O16: Inseticida | P16: L | Q16: 40 | R16: 6 | S16: 6 | T16: =$Q16*R16 -> 240 | U16: =$Q16*S16 -> 240
... A19: Muda Banana | B19: UD | C19: 4 | D19: 2000 | E19: =C19*D19 -> 8000 | G19: Muda Manga | H19: UD | I19: 21 | J19: 776 | K19: 0 | L19: =I19*J19 -> 16296 | M19: =I19*K19 -> 0 | O19: Óleo Mineral | P19: L | Q19: 10 | R19: 3 | S19: 24 | T19: =$Q19*R19 -> 30 | U19: =$Q19*S19 -> 240
A20: SUB-TOTAL-INSUMOS = | E20: =SUM(E5:E19) -> 22364.848 | G20: SUB-TOTAL-INSUMOS = | L20: =SUM(L5:L19) -> 22379.4 | M20: =SUM(M5:M19) -> 7585.152 | O20: Muda Limao | P20: UD | Q20: 20 | R20: 350 | S20: 0 | T20: =$Q20*R20 -> 7000 | U20: =$Q20*S20 -> 0
O21: SUB-TOTAL-INSUMOS = | T21: =SUM(T5:T20) -> 11778.225 | U21: =SUM(U5:U20) -> 6651.5
A23: GASTO COM MÃO DE OBRA | G23: GASTO COM MÃO DE OBRA | O23: GASTO COM MÃO DE OBRA
A24: Descrição | B24: Unidade | C24: Custo Unit. | D24: Quantidade por ha | E24: Custo por ano - R$ | G24: Descrição | H24: Unidade | I24: Custo Unit. | J24: Quantidade por ha | L24: Custo por ano - R$ | O24: Descrição | P24: Unidade | Q24: Custo Unit. | R24: Quantidade por ha | T24: Custo por ano - R$
D25: 1 | E25: 1 | J25: 1 | K25: 2 | L25: 1 | M25: 2 | R25: 1 | S25: 2 | T25: 1 | U25: 2
A26: Preparao cova | B26: dh | C26: 145 | D26: 15 | E26: =C26*D26 -> 2175 | G26: Preparao cova | H26: dh | I26: 136 | J26: 8 | L26: =I26*J26 -> 1088 | M26: =I26*K26 -> 0 | O26: Preparao cova | P26: dh | Q26: 136 | R26: 8 | T26: =$Q26*R26 -> 1088 | U26: =$Q26*S26 -> 0
A27: plantio | B27: dh | C27: 145 | D27: 12 | E27: =C27*D27 -> 1740 | G27: plantio | H27: dh | I27: 136 | J27: 8 | L27: =I27*J27 -> 1088 | M27: =I27*K27 -> 0 | O27: plantio | P27: dh | Q27: 136 | R27: 8 | T27: =$Q27*R27 -> 1088 | U27: =$Q27*S27 -> 0
A28: ad. Manual | B28: dh | C28: 145 | D28: 8 | E28: =C28*D28 -> 1160 | G28: ad. Manual | H28: dh | I28: 136 | J28: 4 | L28: =I28*J28 -> 544 | M28: =I28*K28 -> 0 | O28: ad. Manual | P28: dh | Q28: 136 | R28: 4 | T28: =$Q28*R28 -> 544 | U28: =$Q28*S28 -> 0
A29: herbicida | B29: dh | C29: 145 | D29: 0.5 | E29: =C29*D29 -> 72.5 | G29: herbicida | H29: dh | I29: 136 | J29: 0.5 | K29: 0.5 | L29: =I29*J29 -> 68 | M29: =I29*K29 -> 68 | O29: herbicida | P29: dh | Q29: 136 | R29: 0.5 | S29: 0.5 | T29: =$Q29*R29 -> 68 | U29: =$Q29*S29 -> 68
A30: isca | B30: dh | C30: 145 | D30: 0.1 | E30: =C30*D30 -> 14.5 | G30: Apoio a pulveizações | H30: dh | I30: 136 | J30: 1 | K30: 1.5 | L30: =I30*J30 -> 136 | M30: =I30*K30 -> 204 | O30: Apoio a pulveizações | P30: dh | Q30: 136 | R30: 1 | S30: 1.5 | T30: =$Q30*R30 -> 136 | U30: =$Q30*S30 -> 204
A31: Aplicação defensivo | B31: dh | C31: 145 | D31: 0.5 | E31: =C31*D31 -> 72.5 | G31: rocada manual | H31: dh | I31: 136 | J31: 1 | K31: 0.25 | L31: =I31*J31 -> 136 | M31: =I31*K31 -> 34 | O31: rocada manual | P31: dh | Q31: 136 | R31: 1 | S31: 0.25 | T31: =$Q31*R31 -> 136 | U31: =$Q31*S31 -> 34
A32: rocada manual | B32: dh | C32: 145 | D32: 1 | E32: =C32*D32 -> 145 | G32: Aplicação esterco/calcário/fosfatado | H32: dh | I32: 136 | J32: 3 | K32: 0.25 | L32: =I32*J32 -> 408 | M32: =I32*K32 -> 34 | O32: desbrota | P32: dh | Q32: 136 | R32: 3 | S32: 3 | T32: =$Q32*R32 -> 408 | U32: =$Q32*S32 -> 408
A33: desfolha | B33: dh | C33: 145 | D33: 5 | E33: =C33*D33 -> 725 | G33: Manejo do sist irrigação | H33: dh | I33: 136 | J33: 4 | K33: 6 | L33: =I33*J33 -> 544 | M33: =I33*K33 -> 816 | O33: colheita | P33: dh | Q33: 145 | R33: 0 | S33: 15 | T33: =$Q33*R33 -> 0 | U33: =$Q33*S33 -> 2175
A34: desbrota | B34: dh | C34: 145 | D34: 3 | E34: =C34*D34 -> 435 | G34: Atividades diversa | H34: dh | I34: 136 | J34: 3 | K34: 5 | L34: =I34*J34 -> 408 | M34: =I34*K34 -> 680 | O34: Aplicação esterco/calcário/fosfatado | P34: dh | Q34: 136 | R34: 3 | S34: 0.25 | T34: =$Q34*R34 -> 408 | U34: =$Q34*S34 -> 34
A35: contaagem cachos | B35: dh | C35: 145 | D35: 3 | E35: =C35*D35 -> 435 | G35: SUB-TOTAL- MÃO DE OBRA = | L35: =SUM(L26:L34) -> 4420 | M35: =SUM(M26:M34) -> 1836 | O35: Manejo do sist irrigação | P35: dh | Q35: 136 | R35: 4 | S35: 6 | T35: =$Q35*R35 -> 544 | U35: =$Q35*S35 -> 816
A36: Controle moleque | B36: dh | C36: 145 | D36: 1.5 | E36: =C36*D36 -> 217.5 | O36: Atividades diversa | P36: dh | Q36: 136 | R36: 3 | S36: 5 | T36: =$Q36*R36 -> 408 | U36: =$Q36*S36 -> 680
A37: Aplicação esterco/calcário/fosfatado | B37: dh | C37: 145 | D37: 3 | E37: =C37*D37 -> 435 | O37: SUB-TOTAL- MÃO DE OBRA = | T37: =SUM(T26:T36) -> 4828 | U37: =SUM(U26:U36) -> 4419
A38: Manejo do sist irrigação | B38: dh | C38: 145 | D38: 5 | E38: =C38*D38 -> 725
A39: Atividades diversa | B39: dh | C39: 145 | D39: 3 | E39: =C39*D39 -> 435
A40: SUB-TOTAL- MÃO DE OBRA = | E40: =SUM(E26:E39) -> 8787
A42: GASTO COM TRATOR E EQUIPAMENTOS E AVIAÇÃO AGRÍCOLA | G42: GASTO COM TRATOR E EQUIPAMENTOS E AVIAÇÃO AGRÍCOLA | O42: GASTO COM TRATOR E EQUIPAMENTOS E AVIAÇÃO AGRÍCOLA
A43: Descrição | B43: Unidade | C43: Custo Unit. | D43: Quantidade por ha | E43: Custo por ano - R$ | G43: Descrição | H43: Unidade | I43: Custo Unit. | J43: Quantidade por ha | L43: Custo por ano - R$ | O43: Descrição | P43: Unidade | Q43: Custo Unit. | R43: Quantidade por ha | T43: Custo por ano - R$
D44: 1 | E44: 1 | J44: 1 | K44: 2 | L44: 1 | M44: 2 | R44: 1 | S44: 2 | T44: 1 | U44: 2
A45: Preparo de solo | B45: HMPP | C45: 400 | D45: 4 | E45: =C45*D45 -> 1600 | G45: Preparo de solo | H45: HMPP | I45: 400 | J45: 4 | L45: =I45*J45 -> 1600 | M45: =I45*K45 -> 0 | O45: Preparo de solo | P45: HMPP | Q45: 400 | R45: 4 | T45: =$Q45*R45 -> 1600 | U45: =$Q45*S45 -> 0
A46: Distribuição de cálcario | B46: HMPM | C46: 250 | D46: 2 | E46: =C46*D46 -> 500 | G46: Distribuição de cálcario | H46: HMPM | I46: 250 | J46: 2 | K46: 2 | L46: =I46*J46 -> 500 | M46: =I46*K46 -> 500 | O46: Distribuição de cálcario | P46: HMPM | Q46: 250 | R46: 2 | S46: 2 | T46: =$Q46*R46 -> 500 | U46: =$Q46*S46 -> 500
A47: Distribuição de fosfato | B47: HMPM | C47: 250 | D47: 2 | E47: =C47*D47 -> 500 | G47: Distribuição de fosfato | H47: HMPM | I47: 250 | J47: 2 | K47: 2 | L47: =I47*J47 -> 500 | M47: =I47*K47 -> 500 | O47: Distribuição de fosfato | P47: HMPM | Q47: 250 | R47: 2 | S47: 2 | T47: =$Q47*R47 -> 500 | U47: =$Q47*S47 -> 500
A48: Incorporação corretivos | B48: HMPP | C48: 400 | D48: 3 | E48: =C48*D48 -> 1200 | G48: Incorporação corretivos | H48: HMPP | I48: 400 | J48: 3 | L48: =I48*J48 -> 1200 | M48: =I48*K48 -> 0 | O48: Incorporação corretivos | P48: HMPP | Q48: 400 | R48: 3 | T48: =$Q48*R48 -> 1200 | U48: =$Q48*S48 -> 0
A49: Abertura de sulcos | B49: HMPM | C49: 250 | D49: 3 | E49: =C49*D49 -> 750 | G49: Abertura de sulcos | H49: HMPM | I49: 250 | J49: 3 | L49: =I49*J49 -> 750 | M49: =I49*K49 -> 0 | O49: Abertura de sulcos | P49: HMPM | Q49: 250 | R49: 3 | T49: =$Q49*R49 -> 750 | U49: =$Q49*S49 -> 0
A50: Aplicação de defensivos / foliar | B50: HMPM | C50: 250 | D50: 4 | E50: =C50*D50 -> 1000 | G50: Aplicação de defensivos / foliar | H50: HMPM | I50: 250 | J50: 4 | K50: 10 | L50: =I50*J50 -> 1000 | M50: =I50*K50 -> 2500 | O50: Aplicação de defensivos / foliar | P50: HMPM | Q50: 250 | R50: 4 | S50: 10 | T50: =$Q50*R50 -> 1000 | U50: =$Q50*S50 -> 2500
A51: Apoio distribuição adubo orgânico | B51: HMPM | C51: 250 | D51: 1.5 | E51: =C51*D51 -> 375 | G51: Apoio distribuição adubo orgânico | H51: HMPM | I51: 250 | J51: 1.5 | L51: =I51*J51 -> 375 | M51: =I51*K51 -> 0 | O51: Apoio distribuição adubo orgânico | P51: HMPM | Q51: 250 | R51: 1.5 | T51: =$Q51*R51 -> 375 | U51: =$Q51*S51 -> 0
A52: Roçada | B52: HMPM | C52: 250 | D52: 6 | E52: =C52*D52 -> 1500 | G52: Roçada | H52: HMPM | I52: 250 | J52: 6 | K52: 3 | L52: =I52*J52 -> 1500 | M52: =I52*K52 -> 750 | O52: Roçada | P52: HMPM | Q52: 250 | R52: 6 | S52: 3 | T52: =$Q52*R52 -> 1500 | U52: =$Q52*S52 -> 750
A53: Aviação agrícola | B53: ha | C53: 90 | D53: 1 | E53: =C53*D53 -> 90 | G53: Drenagem parcelar | H53: HMR | I53: 250 | J53: 0.5 | L53: =I53*J53 -> 125 | M53: =I53*K53 -> 0 | O53: Drenagem parcelar | P53: HMR | Q53: 250 | R53: 0.5 | T53: =$Q53*R53 -> 125 | U53: =$Q53*S53 -> 0
A54: Drenagem parcelar | B54: HMR | C54: 250 | D54: 0.5 | E54: =C54*D54 -> 125 | G54: SUB-TOTAL - GASTO COM TRATOR E EQUIPAMENTOS E AVIAÇÃO AGRÍCOLA = | L54: =SUM(L45:L53) -> 7550 | M54: =SUM(M45:M53) -> 4250 | O54: SUB-TOTAL - GASTO COM TRATOR E EQUIPAMENTOS E AVIAÇÃO AGRÍCOLA = | T54: =SUM(T45:T53) -> 7550 | U54: =SUM(U45:U53) -> 4250
A55: SUB-TOTAL - EQUIPAMENTOS = | E55: =SUM(E45:E54) -> 7640
A57: OUTRAS DESPESAS | G57: OUTRAS DESPESAS | O57: OUTRAS DESPESAS
A58: Descrição | B58: Unidade | C58: Custo Unit. | D58: Quantidade por ha | E58: Custo por ano - R$ | G58: Descrição | H58: Unidade | I58: Custo Unit. | J58: Quantidade por ha | L58: Custo por ano - R$ | O58: Descrição | P58: Unidade | Q58: Custo Unit. | R58: Quantidade por ha | T58: Custo por ano - R$
D59: 1 | E59: 1 | J59: 1 | K59: 2 | L59: 1 | M59: 2 | R59: 1 | S59: 2 | T59: 1 | U59: 2
A60: Energia | B60: R$/ha/ano | C60: 850 | D60: 1 | E60: =C60*D60 -> 850 | G60: Energia | H60: R$/ha/ano | I60: 680 | J60: 1 | K60: 1 | L60: 580 | M60: 580 | O60: Energia | P60: R$/ha/ano | Q60: 650 | R60: 1 | S60: 1 | T60: =$Q60*R60 -> 650 | U60: =$Q60*S60 -> 650
A61: man sist irrig | B61: vb/ha/ano | C61: 225 | D61: 1 | E61: =C61*D61 -> 225 | G61: man sist irrig | H61: vb/ha/ano | I61: 220 | J61: 0.5 | K61: 1 | L61: =I61*J61 -> 110 | M61: =I61*K61 -> 220 | O61: man sist irrig | P61: vb/ha/ano | Q61: 42.634 | R61: 0.5 | S61: 1 | T61: =$Q61*R61 -> 21.317 | U61: =$Q61*S61 -> 42.634
A62: man estrutura | B62: vb/ha/ano | C62: 234.384 | D62: 1 | E62: =C62*D62 -> 234.384 | G62: man estrutura | H62: vb/ha/ano | I62: 127.634 | J62: 0.5 | K62: 1 | L62: =I62*J62 -> 63.817 | M62: =I62*K62 -> 127.634 | O62: man estrutura | P62: vb/ha/ano | Q62: 1100 | R62: 1 | S62: 1 | T62: =$Q62*R62 -> 1100 | U62: =$Q62*S62 -> 1100
A63: Ferramentas diversas | B63: vb/ha/ano | C63: 600 | D63: 1 | E63: =C63*D63 -> 600 | G63: Ferramentas diversas | H63: vb/ha/ano | I63: 1100 | J63: 1 | K63: 1 | L63: =I63*J63 -> 1100 | M63: =I63*K63 -> 1100 | O63: Ferramentas diversas | P63: vb/ha/ano | Q63: 580 | R63: 1 | S63: 1 | T63: =$Q63*R63 -> 580 | U63: =$Q63*S63 -> 580
A64: Transporte funcionários | B64: vb/ha/ano | C64: 580 | D64: 1 | E64: =C64*D64 -> 580 | G64: Transporte funcionários | H64: vb/ha/ano | I64: 580 | J64: 1 | K64: 1 | L64: =I64*J64 -> 580 | M64: =I64*K64 -> 580 | O64: Transporte funcionários | P64: vb/ha/ano | Q64: 300 | R64: 1 | S64: 1 | T64: =$Q64*R64 -> 300 | U64: =$Q64*S64 -> 300
A65: Assistência Técnica - consultoria | B65: vb/ha/ano | C65: 300 | D65: 1 | E65: =C65*D65 -> 300 | G65: Assistência Técnica - consultoria | H65: vb/ha/ano | I65: 300 | J65: 1 | K65: 1 | L65: =I65*J65 -> 300 | M65: =I65*K65 -> 300 | O65: Assistência Técnica - consultoria | P65: vb/ha/ano | Q65: 1636.5088 | R65: 1 | S65: 1 | T65: =$Q65*R65 -> 1636.5088 | U65: =$Q65*S65 -> 1636.5088
A66: Administrativo | B66: vb/ha/ano | C66: 1600 | D66: 1 | E66: =C66*D66 -> 1600 | G66: Administrativo | H66: vb/ha/ano | I66: 1600 | J66: 1 | K66: 1 | L66: =I66*J66 -> 1600 | M66: =I66*K66 -> 1600 | O66: Administrativo | P66: vb/ha/ano | Q66: 1600 | R66: 1 | S66: 1 | T66: =$Q66*R66 -> 1600 | U66: =$Q66*S66 -> 1600
A67: SUB-TOTAL OUTRAS DESPESAS = | E67: =SUM(E60:E66) -> 4389.384 | G67: SUB-TOTAL OUTRAS DESPESAS = | L67: =SUM(L60:L66) -> 4333.817 | M67: =SUM(M60:M66) -> 4507.634 | O67: SUB-TOTAL OUTRAS DESPESAS = | T67: 5452.8258 | U67: 5574.1428
A68: 1/ Estimativa de custo - período - julho/agosto -2025 para formação de 1 ha de banana, sendo 50% Prata e 50% nanica- Custo de investimento para alta tecnologia | G68: 2/ Estimativa de custo - período - julho/agosto -2025 para formação de 1 ha de Manga- Custo de investimento para alta tecnologia | O68: 3/ Estimativa de custo - período - julho/agosto -2025 para formação de 1 ha de Limão- Custo de investimento para alta tecnologia
A70: TOTAIS | E70: =E20+E40+E55+E67 -> 43181.232 | G70: TOTAIS | L70: =L20+L35+L54+L67 -> 38683.217 | M70: =M20+M35+M54+M67 -> 18178.786 | O70: TOTAIS | T70: =T21+T37+T54+T67 -> 29609.051 | U70: =U21+U37+U54+U67 -> 20894.643
G72: Custo para formação de 1 ha de Manga- ano 1 +ano 2 | L72: =L70+M70 -> 56862.003 | O72: Custo para formação de 1 ha de Limão- ano 1 +ano 2 | T72: =T70+U70 -> 50503.694
A74: Situação atual dos bananais, avaliado oleas imagens aéreas e visita de campo | G74: Situação atual dos mangueirais, avaliado pelas imagens aéreas e visita de campo | O74: Situação atual da cultura do limão, avaliado pelas imagens aéreas e visita de campo
A75: Idade média -anos | B75: 8 | G75: Idade média -anos | H75: 14 | O75: Idade média -anos | P75: 8
A76: Situação média aspectos fitossanitário | B76: Média a boa | G76: Situação média aspectos fitossanitário | H76: Média a boa | O76: Situação média aspectos fitossanitário | P76: Média a boa
A77: Vida útil de um bananal na região - anos | B77: 12 | G77: Vida útil de um bananal na região - anos | H77: 18 | O77: Vida útil de um bananal na região - anos | P77: 15
A78: Fator de aproveitamento | B78: =1-(B75/B77) -> 0.33333333 | G78: Fator de aproveitamento | H78: =1-(H75/H77) -> 0.22222222 | O78: Fator de aproveitamento | P78: =1-(P75/P77) -> 0.46666667
A79: Valor de avaliação | B79: =B78*E70 -> 14393.744 | G79: Valor de avaliação | H79: =H78*L72 -> 12636.001 | O79: Valor de avaliação | P79: =P78*T72 -> 23568.39

Sheet Cálculo Geral de Propriedades
A1: Nº PROPRIE- DADE | B1: ÁREA PROPRIEDADE (ha) | C1: ÍNDICE | D1: RECURSOS HÍDRICOS | E1: ENERGIA | F1: PASTO (ha) | G1: VEGETAÇÃO NATIVA (ha) | H1: % EXPLORAÇÃO | J1: VALOR | K1: FATOR OFERTA 2/ | L1: FATOR DE AJUSTE - ACESSO 1 - 3/ | M1: VALOR COM | N1: VALOR TOTAL R$ 5/ | O1: PIVÔ (ha) | P1: VALOR | Q1: IRRIGAÇÃO LOCALIZADA (ha) | R1: VALOR | S1: CULTURA EXPLORADA | T1: ÁREA DA CULTURA EXPLORADA | U1: VALOR | V1: PAINEL SOLAR (m²) | W1: VALOR | X1: VALOR | Y1: BENFEITORIAS
C2: BENFEITORIA | H2: PASTO | I2: VEG.NAT. | J2: UNITÁRIO-HA 1/ | M2: FATOR OFERTA E LOCALIZAÇÃO 4/ | P2: PIVO 6/ | R2: IRRIGAÇÃO 7/ | U2: CULTURA 8/ | W2: PAINEL 9/ | X2: TOTAL GERAL 10/
A3: 1 | B3: 984.9005 | C3: 1 | E3: X | F3: 351.09316 | G3: 633.80734 | H3: =F3/B3 -> 0.35647577 | I3: =G3/B3 -> 0.64352423 | J3: 6534.5 | K3: =$B$318 -> 0.95 | L3: =$B$320 -> 1.15 | M3: =J3*K3*L3 -> 7138.9412 | N3: =B3*M3 -> 7031146.8 | X3: =N3+P3+R3+U3+W3 -> 7031146.8
A4: 2 | B4: 3666.8488 | C4: 3 | D4: X | E4: X | F4: 2600.6799 | G4: 1066.1689 | H4: =F4/B4 -> 0.70924111 | I4: =G4/B4 -> 0.29075889 | J4: 8354.59 | K4: =$B$318 -> 0.95 | L4: =$B$320 -> 1.15 | M4: =J4*K4*L4 -> 9127.3896 | N4: =B4*M4 -> 33468757 | V4: 511.7231 | W4: =VLOOKUP(V4,'Estimativa Valores-Painéis Sol.'!$C$4:$D$24,2,FALSE) -> 72000 | X4: =N4+P4+R4+U4+W4 -> 33540757 | Y4: Estrutura Diversa; Casa Alvenaria; Estrutura Metálica; Reservatório;
A5: 22 | B5: 33.659597 | C5: 2 | E5: X | F5: 9.4253462 | G5: 24.234251 | H5: =F5/B5 -> 0.28001958 | I5: =G5/B5 -> 0.71998042 | J5: 14989.84 | K5: =$B$318 -> 0.95 | L5: =$B$321 -> 1 | M5: =J5*K5*L5 -> 14240.348 | N5: =B5*M5 -> 479324.37 | X5: =N5+P5+R5+U5+W5 -> 479324.37 | Y5: Estrutura Diversa; Casa Alvenaria;
A6: 23 | B6: 148.72492 | C6: 2 | E6: X | F6: 5.343799 | G6: 143.38112 | H6: =F6/B6 -> 0.035930758 | I6: =G6/B6 -> 0.96406924 | J6: 14768.69 | K6: =$B$318 -> 0.95 | L6: =$B$321 -> 1 | M6: =J6*K6*L6 -> 14030.255 | N6: =B6*M6 -> 2086648.6 | X6: =N6+P6+R6+U6+W6 -> 2086648.6 | Y6: Estrutura Diversa; Casa Alvenaria;
A7: 24 | B7: 146.2572 | C7: 2 | E7: X | F7: 129.50176 | G7: 16.755433 | H7: =F7/B7 -> 0.88543857 | I7: =G7/B7 -> 0.11456143 | J7: 16272.19 | K7: =$B$318 -> 0.95 | L7: =$B$321 -> 1 | M7: =J7*K7*L7 -> 15458.581 | N7: =B7*M7 -> 2260928.6 | X7: =N7+P7+R7+U7+W7 -> 2260928.6 | Y7: Estrutura Diversa; Casa Alvenaria;
A8: 25 | B8: 45.43599 | C8: 1 | E8: X | F8: 28.228487 | G8: 17.207503 | H8: =F8/B8 -> 0.62128033 | I8: =G8/B8 -> 0.37871967 | J8: 8960.41 | K8: =$B$318 -> 0.95 | L8: =$B$321 -> 1 | M8: =J8*K8*L8 -> 8512.3895 | N8: =B8*M8 -> 386768.85 | X8: =N8+P8+R8+U8+W8 -> 386768.85
A9: 26 | B9: 662.64008 | C9: 2 | D9: X | E9: X | F9: 271.83674 | G9: 390.80334 | H9: =F9/B9 -> 0.41023287 | I9: =G9/B9 -> 0.58976713 | J9: 13750.15 | K9: =$B$318 -> 0.95 | L9: =$B$321 -> 1 | M9: =J9*K9*L9 -> 13062.642 | N9: =M9*B9 -> 8655830.5 | Q9: 19.206314 | R9: ='Cálculo Depre.-Sist. Irrig.'!$P$3*Q9 -> 147888.62 | S9: Limão | T9: =Q9 -> 19.206314 | U9: ='Cálculo Valor Avaliação-Cultura'!$P$79*T9 -> 452661.91 | X9: =N9+P9+R9+U9+W9 -> 9256381 | Y9: Casa Alvenaria; Reservatório;
A10: 27 | B10: 81.972571 | C10: 2 | D10: X | E10: X | G10: 81.972571 | H10: =F10/B10 -> 0 | I10: =G10/B10 -> 1 | J10: 15717.96 | K10: =$B$319 -> 0.9 | L10: =$B$321 -> 1 | M10: =J10*K10*L10 -> 14146.164 | N10: =M10*B10 -> 1159597.4 | X10: =N10+P10+R10+U10+W10 -> 1159597.4 | Y10: Casa Alvenaria; Reservatório;
A11: 28 | B11: 244.45631 | C11: 1 | E11: X | F11: 5.9094185 | G11: 238.54689 | H11: =F11/B11 -> 0.024173721 | I11: =G11/B11 -> 0.97582628 | J11: 6475.63 | K11: =$B$318 -> 0.95 | L11: =$B$320 -> 1.15 | M11: =J11*K11*L11 -> 7074.6258 | N11: =B11*M11 -> 1729436.9 | X11: =N11+P11+R11+U11+W11 -> 1729436.9
A12: 29 | B12: 40.615095 | C12: 2 | E12: X | F12: 40.615095 | H12: =F12/B12 -> 1 | I12: =G12/F12 -> 0 | J12: 9684.66 | K12: =$B$318 -> 0.95 | L12: =$B$320 -> 1.15 | M12: =J12*K12*L12 -> 10580.491 | N12: =M12*F12 -> 429727.65 | X12: =N12+P12+R12+U12+W12 -> 429727.65 | Y12: Casa Alvenaria; Curral;
A13: 30 | B13: 40.576268 | C13: 2 | E13: X | F13: 18.468836 | G13: 22.107432 | H13: =F13/B13 -> 0.4551635 | I13: =G13/B13 -> 0.5448365 | J13: 8998.53 | K13: =$B$318 -> 0.95 | L13: =$B$320 -> 1.15 | M13: =J13*K13*L13 -> 9830.894 | N13: =B13*M13 -> 398900.99 | X13: =N13+P13+R13+U13+W13 -> 398900.99 | Y13: Casa Alvenaria;
A14: 31 | B14: 82.712954 | C14: 1 | E14: X | F14: 22.779882 | G14: 59.933072 | H14: =F14/B14 -> 0.27540888 | I14: =G14/B14 -> 0.72459112 | J14: 6539.07 | K14: =$B$318 -> 0.95 | L14: =$B$320 -> 1.15 | M14: =J14*K14*L14 -> 7143.934 | N14: =B14*M14 -> 590895.88 | X14: =N14+P14+R14+U14+W14 -> 590895.88
A15: 32 | B15: 44.620108 | C15: 1 | E15: X | F15: 26.202262 | G15: 18.417846 | H15: =F15/B15 -> 0.58722991 | I15: =G15/B15 -> 0.41277009 | J15: 6554.19 | K15: =$B$318 -> 0.95 | L15: =$B$320 -> 1.15 | M15: =J15*K15*L15 -> 7160.4526 | N15: =B15*M15 -> 319500.17 | X15: =N15+P15+R15+U15+W15 -> 319500.17
A16: 33 | B16: 80.644455 | C16: 2 | D16: X | E16: X | F16: 6.4966872 | G16: 74.147768 | H16: =F16/B16 -> 0.080559626 | I16: =G16/B16 -> 0.91944037 | J16: 9645.45 | K16: =$B$318 -> 0.95 | L16: =$B$320 -> 1.15 | M16: =J16*K16*L16 -> 10537.654 | N16: =B16*M16 -> 849803.37 | X16: =N16+P16+R16+U16+W16 -> 849803.37 | Y16: Casa Alvenaria; Reservatório;
A17: 34 | B17: 1369.7731 | C17: 2 | E17: X | F17: 1222.9325 | G17: 146.84067 | H17: =F17/B17 -> 0.89279928 | I17: =G17/B17 -> 0.10720072 | J17: 8101.33 | K17: =$B$318 -> 0.95 | L17: =$B$320 -> 1.15 | M17: =J17*K17*L17 -> 8850.703 | N17: =B17*M17 -> 12123455 | X17: =N17+P17+R17+U17+W17 -> 12123455 | Y17: Estrutura Diversa; Casa Alvenaria; Estrutura de Concreto; Bebedouro;
A18: 45 | B18: 27.410207 | C18: 2 | E18: X | F18: 19.740562 | G18: 7.669645 | H18: =F18/B18 -> 0.72019018 | I18: =G18/B18 -> 0.27980982 | J18: 16569.01 | K18: =$B$318 -> 0.95 | L18: =$B$321 -> 1 | M18: =J18*K18*L18 -> 15740.559 | N18: =B18*M18 -> 431451.99 | X18: =N18+P18+R18+U18+W18 -> 431451.99 | Y18: Estrutura Diversa; Casa Alvenaria;
A19: 46 | B19: 29.865446 | C19: 2 | E19: X | F19: 29.865446 | H19: =F19/B19 -> 1 | I19: =G19/F19 -> 0 | J19: 16562.66 | K19: =$B$318 -> 0.95 | L19: =$B$321 -> 1 | M19: =J19*K19*L19 -> 15734.527 | N19: =M19*F19 -> 469918.67 | X19: =N19+P19+R19+U19+W19 -> 469918.67 | Y19: Casa Alvenaria; Bebedouro;
A20: 47 | B20: 153.33063 | C20: 1 | E20: X | F20: 20.29323 | G20: 133.0374 | H20: =F20/B20 -> 0.13234949 | I20: =G20/B20 -> 0.86765051 | J20: 8875.93 | K20: =$B$318 -> 0.95 | L20: =$B$321 -> 1 | M20: =J20*K20*L20 -> 8432.1335 | N20: =B20*M20 -> 1292904.3 | X20: =N20+P20+R20+U20+W20 -> 1292904.3
A21: 48 | B21: 10.840117 | C21: 2 | E21: X | F21: 10.840117 | H21: =F21/B21 -> 1 | I21: =G21/F21 -> 0 | J21: 15034.13 | K21: =$B$318 -> 0.95 | L21: =$B$321 -> 1 | M21: =J21*K21*L21 -> 14282.423 | N21: =M21*F21 -> 154823.14 | X21: =N21+P21+R21+U21+W21 -> 154823.14
A22: 49 | B22: 20.453242 | C22: 2 | E22: X | F22: 20.453242 | H22: =F22/B22 -> 1 | I22: =G22/F22 -> 0 | J22: 16586.57 | K22: =$B$318 -> 0.95 | L22: =$B$321 -> 1 | M22: =J22*K22*L22 -> 15757.241 | N22: =M22*F22 -> 322286.67 | X22: =N22+P22+R22+U22+W22 -> 322286.67 | Y22: Estrutura Diversa;
A23: 50 | B23: 41.573141 | C23: 1 | E23: X | F23: 2.67539 | G23: 27.642814 | H23: =F23/B23 -> 0.064353809 | I23: =G23/B23 -> 0.66492002 | J23: 8963.4 | K23: =$B$318 -> 0.95 | L23: =$B$321 -> 1 | M23: =J23*K23*L23 -> 8515.23 | N23: =B23*M23 -> 354004.86 | V23: 112549.37 | W23: =VLOOKUP(V23,'Estimativa Valores-Painéis Sol.'!$C$4:$D$24,2,FALSE) -> 10200000 | X23: =N23+P23+R23+U23+W23 -> 10554005
A24: 51 | B24: 31.415908 | C24: 2 | D24: X | E24: X | F24: 13.972915 | G24: 17.442993 | H24: =F24/B24 -> 0.44477196 | I24: =G24/B24 -> 0.55522804 | J24: 14994.28 | K24: =$B$318 -> 0.95 | L24: =$B$321 -> 1 | M24: =J24*K24*L24 -> 14244.566 | N24: =B24*M24 -> 447505.97 | X24: =N24+P24+R24+U24+W24 -> 447505.97 | Y24: Estrutura Diversa; Casa Alvenaria; Reservatório;
A25: 52 | B25: 10.693703 | C25: 2 | D25: X | E25: X | F25: 6.4317115 | G25: 4.2619916 | H25: =F25/B25 -> 0.60144848 | I25: =G25/B25 -> 0.39855152 | J25: 18558.54 | K25: =$B$318 -> 0.95 | L25: =$B$321 -> 1 | M25: =J25*K25*L25 -> 17630.613 | N25: =B25*M25 -> 188536.54 | V25: 25.5894 | W25: =VLOOKUP(V25,'Estimativa Valores-Painéis Sol.'!$C$4:$D$24,2,FALSE) -> 6600 | X25: =N25+P25+R25+U25+W25 -> 195136.54 | Y25: Estrutura Diversa; Casa Alvenaria; Reservatório; Curral;
A26: 53 | B26: 80.856749 | C26: 2 | E26: X | F26: 71.987821 | G26: 8.8689284 | H26: =F26/B26 -> 0.89031307 | I26: =G26/B26 -> 0.10968693 | J26: 16434.13 | K26: =$B$318 -> 0.95 | L26: =$B$321 -> 1 | M26: =J26*K26*L26 -> 15612.424 | N26: =B26*M26 -> 1262369.8 | X26: =N26+P26+R26+U26+W26 -> 1262369.8 | Y26: Casa Alvenaria; Curral;
A27: 54 | B27: 80.335977 | C27: 1 | E27: X | F27: 70.614149 | G27: 9.7218281 | H27: =F27/B27 -> 0.87898538 | I27: =G27/B27 -> 0.12101462 | J27: 9779.83 | K27: =$B$318 -> 0.95 | L27: =$B$321 -> 1 | M27: =J27*K27*L27 -> 9290.8385 | N27: =B27*M27 -> 746388.59 | X27: =N27+P27+R27+U27+W27 -> 746388.59
A28: 55 | B28: 72.790069 | C28: 1 | E28: X | F28: 68.134162 | G28: 4.6559075 | H28: =F28/B28 -> 0.9360365 | I28: =G28/B28 -> 0.063963499 | J28: 6893.61 | K28: =$B$318 -> 0.95 | L28: =$B$320 -> 1.15 | M28: =J28*K28*L28 -> 7531.2689 | N28: =B28*M28 -> 548201.59 | X28: =N28+P28+R28+U28+W28 -> 548201.59
A29: 56 | B29: 80.064317 | C29: 2 | E29: X | F29: 48.38884 | G29: 31.675477 | H29: =F29/B29 -> 0.60437461 | I29: =G29/B29 -> 0.39562539 | J29: 9645.94 | K29: =$B$318 -> 0.95 | L29: =$B$320 -> 1.15 | M29: =J29*K29*L29 -> 10538.189 | N29: =B29*M29 -> 843732.94 | X29: =N29+P29+R29+U29+W29 -> 843732.94 | Y29: Casa Alvenaria; Estrutura de Concreto; Estrutura Metálica;
A30: 57 | B30: 91.414957 | C30: 1 | E30: X | F30: 4.1386031 | G30: 87.276353 | H30: =F30/B30 -> 0.045272713 | I30: =G30/B30 -> 0.95472729 | J30: 6451.16 | K30: =$B$318 -> 0.95 | L30: =$B$320 -> 1.15 | M30: =J30*K30*L30 -> 7047.8923 | N30: =B30*M30 -> 644282.77 | X30: =N30+P30+R30+U30+W30 -> 644282.77
A31: 58 | B31: 331.19828 | C31: 2 | E31: X | F31: 160.03871 | G31: 171.15957 | H31: =F31/B31 -> 0.48321116 | I31: =G31/B31 -> 0.51678884 | J31: 8238.9 | K31: =$B$318 -> 0.95 | L31: =$B$320 -> 1.15 | M31: =J31*K31*L31 -> 9000.9982 | N31: =B31*M31 -> 2981115.1 | X31: =N31+P31+R31+U31+W31 -> 2981115.1 | Y31: Casa Alvenaria;
A32: 81 | B32: 25.169105 | C32: 2 | E32: X | F32: 18.593632 | G32: 3.9698468 | H32: =F32/B32 -> 0.73874824 | I32: =G32/B32 -> 0.15772697 | J32: 16574.6 | K32: =$B$318 -> 0.95 | L32: =$B$321 -> 1 | M32: =J32*K32*L32 -> 15745.87 | N32: =M32*B32 -> 396309.46 | Q32: 2.6056261 | R32: ='Cálculo Depre.-Sist. Irrig.'!$P$3*Q32 -> 20063.321 | S32: Banana | T32: =Q32 -> 2.6056261 | U32: ='Cálculo Valor Avaliação-Cultura'!$B$79*T32 -> 37504.716 | X32: =N32+P32+R32+U32+W32 -> 453877.5 | Y32: Casa Alvenaria;
A33: 82 | B33: 85.282298 | C33: 2 | E33: X | F33: 85.282298 | H33: =F33/B33 -> 1 | I33: =G33/F33 -> 0 | J33: 14890.35 | K33: =$B$318 -> 0.95 | L33: =$B$321 -> 1 | M33: =J33*K33*L33 -> 14145.833 | N33: =M33*F33 -> 1206389.1 | X33: =N33+P33+R33+U33+W33 -> 1206389.1
A34: 83 | B34: 152.22302 | C34: 1 | E34: X | F34: 121.15452 | G34: 31.068508 | H34: =F34/B34 -> 0.79590139 | I34: =G34/B34 -> 0.20409861 | J34: 9716.57 | K34: =$B$318 -> 0.95 | L34: =$B$321 -> 1 | M34: =J34*K34*L34 -> 9230.7415 | N34: =B34*M34 -> 1405131.4 | X34: =N34+P34+R34+U34+W34 -> 1405131.4
A35: 84 | B35: 31.1133 | C35: 2 | E35: X | F35: 31.1133 | H35: =F35/B35 -> 1 | I35: =G35/F35 -> 0 | J35: 14994.86 | K35: =$B$318 -> 0.95 | L35: =$B$321 -> 1 | M35: =J35*K35*L35 -> 14245.117 | N35: =M35*F35 -> 443212.6 | X35: =N35+P35+R35+U35+W35 -> 443212.6
A36: 85 | B36: 87.209039 | C36: 2 | D36: X | E36: X | F36: 20.824199 | G36: 66.38484 | H36: =F36/B36 -> 0.23878487 | I36: =G36/B36 -> 0.76121513 | J36: 14886.69 | K36: =$B$318 -> 0.95 | L36: =$B$321 -> 1 | M36: =J36*K36*L36 -> 14142.355 | N36: =B36*M36 -> 1233341.2 | X36: =N36+P36+R36+U36+W36 -> 1233341.2 | Y36: Estrutura Diversa; Casa Alvenaria; Cisterna;
A37: 86 | B37: 90.685413 | C37: 2 | D37: X | E37: X | F37: 64.247784 | G37: 26.437628 | H37: =F37/B37 -> 0.70846879 | I37: =G37/B37 -> 0.29153121 | J37: 16409.65 | K37: =$B$318 -> 0.95 | L37: =$B$321 -> 1 | M37: =J37*K37*L37 -> 15589.168 | N37: =B37*M37 -> 1413710.1 | X37: =N37+P37+R37+U37+W37 -> 1413710.1 | Y37: Estrutura Diversa; Casa Alvenaria; Reservatório;
A38: 87 | B38: 200.28119 | C38: 2 | E38: X | F38: 166.72913 | G38: 33.552056 | H38: =F38/B38 -> 0.83247525 | I38: =G38/B38 -> 0.16752475 | J38: 16140.87 | K38: =$B$318 -> 0.95 | L38: =$B$321 -> 1 | M38: =J38*K38*L38 -> 15333.826 | N38: =B38*M38 -> 3071077 | X38: =N38+P38+R38+U38+W38 -> 3071077 | Y38: Casa Alvenaria;
A39: 88 | B39: 120.59786 | C39: 2 | E39: X | F39: 120.59786 | H39: =F39/B39 -> 1 | I39: =G39/F39 -> 0 | J39: 16335.44 | K39: =$B$318 -> 0.95 | L39: =$B$321 -> 1 | M39: =J39*K39*L39 -> 15518.668 | N39: =M39*F39 -> 1871518.2 | X39: =N39+P39+R39+U39+W39 -> 1871518.2 | Y39: Estrutura Diversa; Casa Alvenaria; Curral;
A40: 89 | B40: 119.6151 | C40: 2 | E40: X | F40: 19.615774 | G40: 99.999327 | H40: =F40/B40 -> 0.16399078 | I40: =G40/B40 -> 0.83600922 | J40: 14824.45 | K40: =$B$318 -> 0.95 | L40: =$B$321 -> 1 | M40: =J40*K40*L40 -> 14083.228 | N40: =B40*M40 -> 1684566.7 | X40: =N40+P40+R40+U40+W40 -> 1684566.7 | Y40: Casa Alvenaria;
A41: 90 | B41: 161.86653 | C41: 0.3 | E41: X | G41: 161.86653 | H41: =F41/B41 -> 0 | I41: =G41/B41 -> 1 | J41: 4314.71 | K41: =$B$319 -> 0.9 | L41: =$B$320 -> 1.15 | M41: =J41*K41*L41 -> 4465.7248 | N41: =M41*B41 -> 722851.37 | X41: =N41+P41+R41+U41+W41 -> 722851.37
A42: 98 | B42: 27.70558 | C42: 2 | E42: X | F42: 18.691002 | G42: 9.0145777 | H42: =F42/B42 -> 0.67462952 | I42: =G42/B42 -> 0.32537048 | J42: 16568.25 | K42: =$B$318 -> 0.95 | L42: =$B$321 -> 1 | M42: =J42*K42*L42 -> 15739.837 | N42: =B42*M42 -> 436081.33 | X42: =N42+P42+R42+U42+W42 -> 436081.33 | Y42: Estrutura Diversa; Casa Alvenaria;
A43: 99 | B43: 29.488914 | C43: 2 | E43: X | F43: 21.69262 | G43: 7.7962948 | H43: =F43/B43 -> 0.73561947 | I43: =G43/B43 -> 0.26438053 | J43: 16563.67 | K43: =$B$318 -> 0.95 | L43: =$B$321 -> 1 | M43: =J43*K43*L43 -> 15735.486 | N43: =B43*M43 -> 464022.41 | X43: =N43+P43+R43+U43+W43 -> 464022.41 | Y43: Estrutura Diversa; Casa Alvenaria; Curral;
A44: 100 | B44: 14.790568 | C44: 2 | E44: X | F44: 6.7123877 | H44: =F44/B44 -> 0.45382894 | I44: =G44/B44 -> 0 | J44: 15026.39 | K44: =$B$318 -> 0.95 | L44: =$B$321 -> 1 | M44: =J44*K44*L44 -> 14275.07 | N44: =M44*B44 -> 211136.4 | Q44: 8.07818 | R44: ='Cálculo Depre.-Sist. Irrig.'!$P$3*Q44 -> 62201.986 | S44: Banana | T44: =Q44 -> 8.07818 | U44: ='Cálculo Valor Avaliação-Cultura'!$B$79*T44 -> 116275.25 | X44: =N44+P44+R44+U44+W44 -> 389613.64 | Y44: Curral;
A45: 101 | B45: 30.498454 | C45: 2 | D45: X | E45: X | F45: 10.467775 | G45: 20.030679 | H45: =F45/B45 -> 0.34322315 | I45: =G45/B45 -> 0.65677685 | J45: 14996.02 | K45: =$B$318 -> 0.95 | L45: =$B$321 -> 1 | M45: =J45*K45*L45 -> 14246.219 | N45: =B45*M45 -> 434487.65 | X45: =N45+P45+R45+U45+W45 -> 434487.65 | Y45: Estrutura Diversa; Casa Alvenaria; Reservatório;
A46: 102 | B46: 121.09812 | C46: 2 | E46: X | F46: 121.09812 | H46: =F46/B46 -> 1 | I46: =G46/F46 -> 0 | J46: 14821.57 | K46: =$B$318 -> 0.95 | L46: =$B$321 -> 1 | M46: =J46*K46*L46 -> 14080.491 | N46: =M46*F46 -> 1705121.1 | X46: =N46+P46+R46+U46+W46 -> 1705121.1
A47: 103 | B47: 40.121761 | C47: 1 | E47: X | F47: 13.463065 | G47: 26.658696 | H47: =F47/B47 -> 0.33555518 | I47: =G47/B47 -> 0.66444482 | J47: 8964.58 | K47: =$B$318 -> 0.95 | L47: =$B$321 -> 1 | M47: =J47*K47*L47 -> 8516.351 | N47: =B47*M47 -> 341691 | X47: =N47+P47+R47+U47+W47 -> 341691
A48: 104 | B48: 38.28985 | C48: 0.3 | E48: X | G48: 38.28985 | H48: =F48/B48 -> 0 | I48: =G48/B48 -> 1 | J48: 5491.23 | K48: =$B$319 -> 0.9 | L48: =$B$321 -> 1 | M48: =J48*K48*L48 -> 4942.107 | N48: =M48*B48 -> 189232.53 | X48: =N48+P48+R48+U48+W48 -> 189232.53
A49: 105 | B49: 40.456106 | C49: 0.3 | E49: X | G49: 40.456106 | H49: =F49/B49 -> 0 | I49: =G49/B49 -> 1 | J49: 4339.74 | K49: =$B$319 -> 0.9 | L49: =$B$320 -> 1.15 | M49: =J49*K49*L49 -> 4491.6309 | N49: =M49*B49 -> 181713.89 | X49: =N49+P49+R49+U49+W49 -> 181713.89
A50: 106 | B50: 40.774437 | C50: 2 | E50: X | F50: 12.374565 | G50: 28.399872 | H50: =F50/B50 -> 0.30348831 | I50: =G50/B50 -> 0.69651169 | J50: 8403.08 | K50: =$B$318 -> 0.95 | L50: =$B$320 -> 1.15 | M50: =J50*K50*L50 -> 9180.3649 | N50: =B50*M50 -> 374324.21 | X50: =N50+P50+R50+U50+W50 -> 374324.21 | Y50: Casa Alvenaria;
A51: 119 | B51: 26.876677 | C51: 2 | E51: X | F51: 19.507994 | G51: 7.3686829 | H51: =F51/B51 -> 0.72583356 | I51: =G51/B51 -> 0.27416644 | J51: 16570.28 | K51: =$B$318 -> 0.95 | L51: =$B$321 -> 1 | M51: =J51*K51*L51 -> 15741.766 | N51: =B51*M51 -> 423086.36 | X51: =N51+P51+R51+U51+W51 -> 423086.36 | Y51: Estrutura Diversa; Casa Alvenaria;
A52: 120 | B52: 4.9629928 | C52: 2 | E52: X | F52: 4.9629928 | H52: =F52/B52 -> 1 | I52: =G52/F52 -> 0 | J52: 15045.36 | K52: =$B$318 -> 0.95 | L52: =$B$321 -> 1 | M52: =J52*K52*L52 -> 14293.092 | N52: =M52*F52 -> 70936.513 | X52: =N52+P52+R52+U52+W52 -> 70936.513
A53: 121 | B53: 900.65542 | C53: 2 | E53: X | F53: 369.14508 | G53: 531.51034 | H53: =F53/B53 -> 0.40986272 | I53: =G53/B53 -> 0.59013728 | J53: 14597.6 | K53: =$B$318 -> 0.95 | L53: =$B$321 -> 1 | M53: =J53*K53*L53 -> 13867.72 | N53: =B53*M53 -> 12490037 | X53: =N53+P53+R53+U53+W53 -> 12490037 | Y53: Casa Alvenaria;
A54: 122 | B54: 20.163496 | C54: 0.3 | E54: X | G54: 20.163496 | H54: =F54/B54 -> 0 | I54: =G54/B54 -> 1 | J54: 5497.31 | K54: =$B$319 -> 0.9 | L54: =$B$321 -> 1 | M54: =J54*K54*L54 -> 4947.579 | N54: =M54*B54 -> 99760.49 | X54: =N54+P54+R54+U54+W54 -> 99760.49
A55: 123 | B55: 39.840795 | C55: 2 | E55: X | F55: 39.840795 | H55: =F55/B55 -> 1 | I55: =G55/F55 -> 0 | J55: 4978.06 | K55: =$B$318 -> 0.95 | L55: =$B$321 -> 1 | M55: =J55*K55*L55 -> 4729.157 | N55: =M55*F55 -> 188413.37 | X55: =N55+P55+R55+U55+W55 -> 188413.37
A56: 124 | B56: 208.99011 | C56: 1 | E56: X | F56: 64.348891 | G56: 144.64122 | H56: =F56/B56 -> 0.307904 | I56: =G56/B56 -> 0.692096 | J56: 6489.45 | K56: =$B$318 -> 0.95 | L56: =$B$320 -> 1.15 | M56: =J56*K56*L56 -> 7089.7241 | N56: =B56*M56 -> 1481682.2 | X56: =N56+P56+R56+U56+W56 -> 1481682.2
A57: 125 | B57: 34.184194 | C57: 0.3 | E57: X | G57: 34.184194 | H57: =F57/B57 -> 0 | I57: =G57/B57 -> 1 | J57: 4341.04 | K57: =$B$319 -> 0.9 | L57: =$B$320 -> 1.15 | M57: =J57*K57*L57 -> 4492.9764 | N57: =M57*B57 -> 153588.78 | X57: =N57+P57+R57+U57+W57 -> 153588.78
A58: 126 | B58: 41.365695 | C58: 2 | E58: X | F58: 41.365695 | H58: =F58/B58 -> 1 | I58: =G58/F58 -> 0 | J58: 16533.5 | K58: =$B$318 -> 0.95 | L58: =$B$321 -> 1 | M58: =J58*K58*L58 -> 15706.825 | N58: =M58*F58 -> 649723.73 | X58: =N58+P58+R58+U58+W58 -> 649723.73 | Y58: Casa Alvenaria;
A59: 127 | B59: 3.150576 | C59: 2 | E59: X | F59: 3.150576 | H59: =F59/B59 -> 1 | I59: =G59/F59 -> 0 | J59: 16630.75 | K59: =$B$318 -> 0.95 | L59: =$B$321 -> 1 | M59: =J59*K59*L59 -> 15799.212 | N59: =M59*F59 -> 49776.62 | X59: =N59+P59+R59+U59+W59 -> 49776.62 | Y59: Casa Alvenaria;
A60: 128 | B60: 3.0386007 | C60: 1 | E60: X | F60: 2.6303058 | G60: 0.40829494 | H60: =F60/B60 -> 0.8656306 | I60: =G60/B60 -> 0.1343694 | J60: 9848.77 | K60: =$B$318 -> 0.95 | L60: =$B$321 -> 1 | M60: =J60*K60*L60 -> 9356.3315 | N60: =B60*M60 -> 28430.156 | X60: =N60+P60+R60+U60+W60 -> 28430.156
A61: 129 | B61: 3.0334601 | C61: 1 | E61: X | F61: 2.1616603 | G61: 0.87179988 | H61: =F61/B61 -> 0.71260546 | I61: =G61/B61 -> 0.28739454 | J61: 9848.77 | K61: =$B$318 -> 0.95 | L61: =$B$321 -> 1 | M61: =J61*K61*L61 -> 9356.3315 | N61: =B61*M61 -> 28382.059 | X61: =N61+P61+R61+U61+W61 -> 28382.059
A62: 130 | B62: 3.0334601 | C62: 1 | E62: X | F62: 1.2018139 | G62: 1.8316462 | H62: =F62/B62 -> 0.39618584 | I62: =G62/B62 -> 0.60381416 | J62: 8993.8 | K62: =$B$318 -> 0.95 | L62: =$B$321 -> 1 | M62: =J62*K62*L62 -> 8544.11 | N62: =B62*M62 -> 25918.217 | X62: =N62+P62+R62+U62+W62 -> 25918.217
A63: 131 | B63: 3.0358713 | C63: 1 | E63: X | F63: 2.7867701 | G63: 0.24910121 | H63: =F63/B63 -> 0.91794737 | I63: =G63/B63 -> 0.082052626 | J63: 9848.77 | K63: =$B$318 -> 0.95 | L63: =$B$321 -> 1 | M63: =J63*K63*L63 -> 9356.3315 | N63: =B63*M63 -> 28404.618 | X63: =N63+P63+R63+U63+W63 -> 28404.618
A64: 132 | B64: 3.0393746 | C64: 1 | E64: X | F64: 2.9492057 | G64: 0.09016893 | H64: =F64/B64 -> 0.97033306 | I64: =G64/B64 -> 0.029666935 | J64: 9848.77 | K64: =$B$318 -> 0.95 | L64: =$B$321 -> 1 | M64: =J64*K64*L64 -> 9356.3315 | N64: =B64*M64 -> 28437.397 | X64: =N64+P64+R64+U64+W64 -> 28437.397
A65: 133 | B65: 3.7630201 | C65: 0.3 | E65: X | G65: 3.7630201 | H65: =F65/B65 -> 0 | I65: =G65/B65 -> 1 | J65: 5502.82 | K65: =$B$319 -> 0.9 | L65: =$B$321 -> 1 | M65: =J65*K65*L65 -> 4952.538 | N65: =M65*B65 -> 18636.5 | X65: =N65+P65+R65+U65+W65 -> 18636.5
A66: 134 | B66: 4.0574915 | C66: 1 | E66: X | F66: 0.26814534 | G66: 3.7893462 | H66: =F66/B66 -> 0.066086481 | I66: =G66/B66 -> 0.93391352 | J66: 8992.93 | K66: =$B$318 -> 0.95 | L66: =$B$321 -> 1 | M66: =J66*K66*L66 -> 8543.2835 | N66: =B66*M66 -> 34664.301 | X66: =N66+P66+R66+U66+W66 -> 34664.301
A67: 135 | B67: 30.00853 | C67: 2 | D67: X | E67: X | F67: 5.9647866 | G67: 24.043743 | H67: =F67/B67 -> 0.1987697 | I67: =G67/B67 -> 0.8012303 | J67: 14996.99 | K67: =$B$318 -> 0.95 | L67: =$B$321 -> 1 | M67: =J67*K67*L67 -> 14247.14 | N67: =B67*M67 -> 427535.74 | X67: =N67+P67+R67+U67+W67 -> 427535.74 | Y67: Estrutura Diversa; Casa Alvenaria; Cisterna;
A68: 136 | B68: 15.246781 | C68: 2 | E68: X | F68: 6.0689074 | G68: 9.1778738 | H68: =F68/B68 -> 0.39804516 | I68: =G68/B68 -> 0.60195484 | J68: 15025.61 | K68: =$B$318 -> 0.95 | L68: =$B$321 -> 1 | M68: =J68*K68*L68 -> 14274.329 | N68: =B68*M68 -> 217637.58 | X68: =N68+P68+R68+U68+W68 -> 217637.58 | Y68: Estrutura Diversa; Casa Alvenaria;
A69: 137 | B69: 14.782297 | C69: 2 | E69: X | F69: 4.99169 | G69: 9.7906071 | H69: =F69/B69 -> 0.33768026 | I69: =G69/B69 -> 0.66231974 | J69: 15026.39 | K69: =$B$318 -> 0.95 | L69: =$B$321 -> 1 | M69: =J69*K69*L69 -> 14275.07 | N69: =B69*M69 -> 211018.33 | X69: =N69+P69+R69+U69+W69 -> 211018.33 | Y69: Estrutura Diversa; Casa Alvenaria;
A70: 138 | B70: 6.4309966 | C70: 2 | E70: X | F70: 4.5616151 | G70: 1.8693815 | H70: =F70/B70 -> 0.70931698 | I70: =G70/B70 -> 0.29068302 | J70: 16622.56 | K70: =$B$318 -> 0.95 | L70: =$B$321 -> 1 | M70: =J70*K70*L70 -> 15791.432 | N70: =B70*M70 -> 101554.65 | X70: =N70+P70+R70+U70+W70 -> 101554.65 | Y70: Casa Alvenaria; Curral;
A71: 139 | B71: 4.0596773 | C71: 2 | E71: X | F71: 2.7020672 | G71: 1.3576101 | H71: =F71/B71 -> 0.66558669 | I71: =G71/B71 -> 0.33441331 | J71: 16628.45 | K71: =$B$318 -> 0.95 | L71: =$B$321 -> 1 | M71: =J71*K71*L71 -> 15797.028 | N71: =B71*M71 -> 64130.834 | X71: =N71+P71+R71+U71+W71 -> 64130.834 | Y71: Casa Alvenaria;
A72: 140 | B72: 7.5719372 | C72: 2 | E72: X | F72: 3.2525228 | G72: 4.3194145 | H72: =F72/B72 -> 0.42954962 | I72: =G72/B72 -> 0.57045038 | J72: 15040.32 | K72: =$B$318 -> 0.95 | L72: =$B$321 -> 1 | M72: =J72*K72*L72 -> 14288.304 | N72: =B72*M72 -> 108190.14 | X72: =N72+P72+R72+U72+W72 -> 108190.14 | Y72: Estrutura Diversa;
A73: 141 | B73: 21.751743 | C73: 2 | E73: X | F73: 11.613183 | G73: 10.138559 | H73: =F73/B73 -> 0.53389669 | I73: =G73/B73 -> 0.46610331 | J73: 15012.84 | K73: =$B$318 -> 0.95 | L73: =$B$321 -> 1 | M73: =J73*K73*L73 -> 14262.198 | N73: =B73*M73 -> 310227.66 | X73: =N73+P73+R73+U73+W73 -> 310227.66 | Y73: Casa Alvenaria;
A74: 142 | B74: 23.244266 | C74: 1 | E74: X | F74: 15.043471 | G74: 5.3351169 | H74: =F74/B74 -> 0.64719063 | I74: =G74/B74 -> 0.229524 | J74: 16579.69 | K74: =$B$318 -> 0.95 | L74: =$B$321 -> 1 | M74: =J74*K74*L74 -> 15750.705 | N74: =M74*B74 -> 366113.59 | Q74: 2.8656781 | R74: ='Cálculo Depre.-Sist. Irrig.'!$P$3*Q74 -> 22065.721 | S74: Limão | T74: =Q74 -> 2.8656781 | U74: ='Cálculo Valor Avaliação-Cultura'!$P$79*T74 -> 67539.42 | X74: =N74+P74+R74+U74+W74 -> 455718.73
A75: 143 | B75: 30.267353 | C75: 2 | E75: X | F75: 30.267353 | H75: =F75/B75 -> 1 | I75: =G75/F75 -> 0 | J75: 14996.41 | K75: =$B$318 -> 0.95 | L75: =$B$321 -> 1 | M75: =J75*K75*L75 -> 14246.59 | N75: =M75*F75 -> 431206.56 | X75: =N75+P75+R75+U75+W75 -> 431206.56
A76: 144 | B76: 39.985386 | C76: 2 | E76: X | F76: 11.042046 | G76: 26.602158 | H76: =F76/B76 -> 0.27615205 | I76: =G76/B76 -> 0.66529703 | J76: 14977.67 | K76: =$B$318 -> 0.95 | L76: =$B$321 -> 1 | M76: =J76*K76*L76 -> 14228.787 | N76: =M76*B76 -> 568943.52 | Q76: 2.341181 | R76: ='Cálculo Depre.-Sist. Irrig.'!$P$3*Q76 -> 18027.094 | S76: Banana | T76: =Q76 -> 2.341181 | U76: ='Cálculo Valor Avaliação-Cultura'!$B$79*T76 -> 33698.36 | X76: =N76+P76+R76+U76+W76 -> 620668.97 | Y76: Casa Alvenaria;
A77: 145 | B77: 41.616622 | C77: 2 | E77: X | F77: 41.616622 | H77: =F77/B77 -> 1 | I77: =G77/F77 -> 0 | J77: 8402.62 | K77: =$B$318 -> 0.95 | L77: =$B$320 -> 1.15 | M77: =J77*K77*L77 -> 9179.8623 | N77: =M77*F77 -> 382034.86 | X77: =N77+P77+R77+U77+W77 -> 382034.86
A78: 146 | B78: 41.810684 | C78: 2 | E78: X | F78: 35.447156 | G78: 6.3635282 | H78: =F78/B78 -> 0.84780138 | I78: =G78/B78 -> 0.15219862 | J78: 16532.49 | K78: =$B$318 -> 0.95 | L78: =$B$321 -> 1 | M78: =J78*K78*L78 -> 15705.865 | N78: =B78*M78 -> 656672.98 | X78: =N78+P78+R78+U78+W78 -> 656672.98 | Y78: Casa Alvenaria;
A79: 147 | B79: 14.277669 | C79: 2 | E79: X | F79: 14.277669 | H79: =F79/B79 -> 1 | I79: =G79/F79 -> 0 | J79: 9710.7 | K79: =$B$318 -> 0.95 | L79: =$B$320 -> 1.15 | M79: =J79*K79*L79 -> 10608.94 | N79: =M79*F79 -> 151470.93 | X79: =N79+P79+R79+U79+W79 -> 151470.93 | Y79: Estrutura Diversa; Casa Alvenaria;
A80: 148 | B80: 26.276417 | C80: 2 | E80: X | F80: 10.204236 | G80: 16.07218 | H80: =F80/B80 -> 0.388342 | I80: =G80/B80 -> 0.611658 | J80: 8308 | K80: =$B$318 -> 0.95 | L80: =$B$320 -> 1.15 | M80: =J80*K80*L80 -> 9076.49 | N80: =B80*M80 -> 238497.63 | X80: =N80+P80+R80+U80+W80 -> 238497.63 | Y80: Casa Alvenaria;
A81: 149 | B81: 29.449041 | C81: 2 | E81: X | F81: 19.682183 | G81: 9.7668583 | H81: =F81/B81 -> 0.66834715 | I81: =G81/B81 -> 0.33165285 | J81: 16563.93 | K81: =$B$318 -> 0.95 | L81: =$B$321 -> 1 | M81: =J81*K81*L81 -> 15735.734 | N81: =B81*M81 -> 463402.26 | X81: =N81+P81+R81+U81+W81 -> 463402.26 | Y81: Estrutura Diversa; Casa Alvenaria;
A82: 150 | B82: 7.1737662 | C82: 2 | E82: X | F82: 7.1737662 | H82: =F82/B82 -> 1 | I82: =G82/F82 -> 0 | J82: 15041.1 | K82: =$B$318 -> 0.95 | L82: =$B$321 -> 1 | M82: =J82*K82*L82 -> 14289.045 | N82: =M82*F82 -> 102506.27 | X82: =N82+P82+R82+U82+W82 -> 102506.27
A83: 151 | B83: 1.783 | C83: 2 | E83: X | F83: 1.783 | H83: =F83/B83 -> 1 | I83: =G83/F83 -> 0 | J83: 16634.34 | K83: =$B$318 -> 0.95 | L83: =$B$321 -> 1 | M83: =J83*K83*L83 -> 15802.623 | N83: =M83*F83 -> 28176.077 | X83: =N83+P83+R83+U83+W83 -> 28176.077 | Y83: Casa Alvenaria;
A84: 152 | B84: 19.644972 | C84: 2 | D84: X | E84: X | F84: 19.644972 | H84: =F84/B84 -> 1 | I84: =G84/F84 -> 0 | J84: 18528.1 | K84: =$B$318 -> 0.95 | L84: =$B$321 -> 1 | M84: =J84*K84*L84 -> 17601.695 | N84: =M84*F84 -> 345784.81 | X84: =N84+P84+R84+U84+W84 -> 345784.81 | Y84: Estrutura Diversa; Casa Alvenaria; Reservatório;
A85: 153 | B85: 91.252374 | C85: 1 | E85: X | F85: 88.414094 | G85: 2.83828 | H85: =F85/B85 -> 0.96889637 | I85: =G85/B85 -> 0.031103629 | J85: 9770.1 | K85: =$B$318 -> 0.95 | L85: =$B$321 -> 1 | M85: =J85*K85*L85 -> 9281.595 | N85: =B85*M85 -> 846967.58 | X85: =N85+P85+R85+U85+W85 -> 846967.58
A86: 154 | B86: 52.525309 | C86: 1 | E86: X | F86: 35.908761 | G86: 16.616549 | H86: =F86/B86 -> 0.68364682 | I86: =G86/B86 -> 0.31635318 | J86: 9804.51 | K86: =$B$318 -> 0.95 | L86: =$B$321 -> 1 | M86: =J86*K86*L86 -> 9314.2845 | N86: =B86*M86 -> 489235.68 | X86: =N86+P86+R86+U86+W86 -> 489235.68
A87: 155 | B87: 39.455232 | C87: 2 | E87: X | F87: 20.87718 | G87: 18.578051 | H87: =F87/B87 -> 0.52913592 | I87: =G87/B87 -> 0.47086408 | J87: 14978.64 | K87: =$B$318 -> 0.95 | L87: =$B$321 -> 1 | M87: =J87*K87*L87 -> 14229.708 | N87: =B87*M87 -> 561436.43 | X87: =N87+P87+R87+U87+W87 -> 561436.43 | Y87: Estrutura Diversa; Casa Alvenaria;
A88: 156 | B88: 13.878615 | C88: 1 | E88: X | F88: 4.3008093 | G88: 9.577806 | H88: =F88/B88 -> 0.30988749 | I88: =G88/B88 -> 0.69011251 | J88: 9838.99 | K88: =$B$318 -> 0.95 | L88: =$B$321 -> 1 | M88: =J88*K88*L88 -> 9347.0405 | N88: =B88*M88 -> 129723.98 | X88: =N88+P88+R88+U88+W88 -> 129723.98
A89: 157 | B89: 19.952166 | C89: 2 | E89: X | F89: 11.04911 | G89: 8.903056 | H89: =F89/B89 -> 0.55377998 | I89: =G89/B89 -> 0.44622002 | J89: 8414.83 | K89: =$B$318 -> 0.95 | L89: =$B$320 -> 1.15 | M89: =J89*K89*L89 -> 9193.2018 | N89: =B89*M89 -> 183424.29 | X89: =N89+P89+R89+U89+W89 -> 183424.29 | Y89: Casa Alvenaria;
A90: 158 | B90: 5.9686736 | C90: 2 | E90: X | F90: 3.1194497 | G90: 2.8492239 | H90: =F90/B90 -> 0.52263701 | I90: =G90/B90 -> 0.47736299 | J90: 9542.37 | K90: =$B$318 -> 0.95 | L90: =$B$320 -> 1.15 | M90: =J90*K90*L90 -> 10425.039 | N90: =B90*M90 -> 62223.656 | X90: =N90+P90+R90+U90+W90 -> 62223.656 | Y90: Estrutura Diversa;
A91: 159 | B91: 37.094694 | C91: 1 | E91: X | F91: 29.88709 | G91: 7.2076035 | H91: =F91/B91 -> 0.80569718 | I91: =G91/B91 -> 0.19430282 | J91: 6909.48 | K91: =$B$318 -> 0.95 | L91: =$B$320 -> 1.15 | M91: =J91*K91*L91 -> 7548.6069 | N91: =B91*M91 -> 280013.26 | X91: =N91+P91+R91+U91+W91 -> 280013.26
A92: 160 | B92: 26.711123 | C92: 2 | E92: X | H92: =F92/B92 -> 0 | I92: =G92/B92 -> 0 | J92: 15003.37 | K92: =$B$318 -> 0.95 | L92: =$B$321 -> 1 | M92: =J92*K92*L92 -> 14253.201 | N92: =M92*B92 -> 380719.02 | Q92: 26.711123 | R92: ='Cálculo Depre.-Sist. Irrig.'!$P$3*Q92 -> 205675.65 | S92: Limão | T92: =Q92 -> 26.711123 | U92: ='Cálculo Valor Avaliação-Cultura'!$P$79*T92 -> 629538.17 | X92: =N92+P92+R92+U92+W92 -> 1215932.8 | Y92: Estrutura Diversa; Casa Alvenaria;
A93: 161 | B93: 28.839177 | C93: 2 | E93: X | F93: 5.7681254 | G93: 4.2730476 | H93: =F93/B93 -> 0.20001005 | I93: =G93/B93 -> 0.14816815 | J93: 14999.31 | K93: =$B$318 -> 0.95 | L93: =$B$321 -> 1 | M93: =J93*K93*L93 -> 14249.344 | N93: =M93*B93 -> 410939.37 | Q93: 18.798004 | R93: ='Cálculo Depre.-Sist. Irrig.'!$P$3*Q93 -> 144744.63 | S93: Banana | T93: =Q93 -> 18.798004 | U93: ='Cálculo Valor Avaliação-Cultura'!$B$79*T93 -> 270573.66 | X93: =N93+P93+R93+U93+W93 -> 826257.67 | Y93: Estrutura Diversa; Casa Alvenaria; Curral;
A94: 162 | B94: 29.682149 | C94: 1 | E94: X | F94: 5.2610401 | G94: 24.421108 | H94: =F94/B94 -> 0.17724593 | I94: =G94/B94 -> 0.82275407 | J94: 9824.84 | K94: =$B$318 -> 0.95 | L94: =$B$321 -> 1 | M94: =J94*K94*L94 -> 9333.598 | N94: =B94*M94 -> 277041.24 | X94: =N94+P94+R94+U94+W94 -> 277041.24
A95: 163 | B95: 40.858197 | C95: 2 | E95: X | F95: 26.517417 | G95: 14.34078 | H95: =F95/B95 -> 0.64901094 | I95: =G95/B95 -> 0.35098906 | J95: 16534.77 | K95: =$B$318 -> 0.95 | L95: =$B$321 -> 1 | M95: =J95*K95*L95 -> 15708.031 | N95: =B95*M95 -> 641801.85 | X95: =N95+P95+R95+U95+W95 -> 641801.85 | Y95: Estrutura Diversa; Casa Alvenaria;
A96: 164 | B96: 41.465656 | C96: 0.3 | E96: X | G96: 41.465656 | H96: =F96/B96 -> 0 | I96: =G96/B96 -> 1 | J96: 4339.53 | K96: =$B$319 -> 0.9 | L96: =$B$320 -> 1.15 | M96: =J96*K96*L96 -> 4491.4135 | N96: =M96*B96 -> 186239.41 | X96: =N96+P96+R96+U96+W96 -> 186239.41
A97: 165 | B97: 44.299642 | C97: 2 | E97: X | F97: 14.855147 | G97: 29.444495 | H97: =F97/B97 -> 0.33533333 | I97: =G97/B97 -> 0.66466667 | J97: 8466.84 | K97: =$B$318 -> 0.95 | L97: =$B$320 -> 1.15 | M97: =J97*K97*L97 -> 9250.0227 | N97: =B97*M97 -> 409772.69 | X97: =N97+P97+R97+U97+W97 -> 409772.69 | Y97: Estrutura Diversa; Casa Alvenaria;
A98: 166 | B98: 35.027604 | C98: 2 | E98: X | F98: 19.311347 | G98: 15.716257 | H98: =F98/B98 -> 0.55131797 | I98: =G98/B98 -> 0.44868203 | J98: 9512.6 | K98: =$B$318 -> 0.95 | L98: =$B$320 -> 1.15 | M98: =J98*K98*L98 -> 10392.515 | N98: =B98*M98 -> 364024.92 | X98: =N98+P98+R98+U98+W98 -> 364024.92 | Y98: Estrutura Diversa; Casa Alvenaria; Curral;
A99: 167 | B99: 53.993946 | C99: 2 | E99: X | F99: 47.123611 | G99: 0.93435941 | H99: =F99/B99 -> 0.87275731 | I99: =G99/B99 -> 0.017304892 | J99: 16501.67 | K99: =$B$318 -> 0.95 | L99: =$B$321 -> 1 | M99: =J99*K99*L99 -> 15676.586 | N99: =M99*B99 -> 846440.77 | O99: 5.9359757 | P99: ='Cálculo Depre.-Sist. Irrig.'!$P$4 *O99 -> 40364.635 | S99: Cultura Anual | T99: =O99 -> 5.9359757 | X99: =N99+P99+R99+U99+W99 -> 886805.41
A100: 168 | B100: 29.844954 | C100: 2 | E100: X | F100: 23.875423 | G100: 5.9695307 | H100: =F100/B100 -> 0.79998191 | I100: =G100/B100 -> 0.20001809 | J100: 16562.91 | K100: =$B$318 -> 0.95 | L100: =$B$321 -> 1 | M100: =J100*K100*L100 -> 15734.764 | N100: =B100*M100 -> 469603.32 | X100: =N100+P100+R100+U100+W100 -> 469603.32 | Y100: Casa Alvenaria; Curral; | AA100: 138976.11 | AB100: =AA100=X100 -> FALSE
...

Sheet Valores Est. por Propriedade
G2: Parte 01/03
B3: Nº PROPRIEDADE | C3: VALOR ESTIMADO (R$) | D3: Nº PROPRIEDADE | E3: VALOR ESTIMADO (R$) | F3: Nº PROPRIEDADE | G3: VALOR ESTIMADO (R$)
B4: ='Cálculo Geral de Propriedades'!A3 -> 1 | C4: =VLOOKUP(B4,'Cálculo Geral de Propriedades'!A:X,24,FALSE) -> 7031146.8 | D4: ='Cálculo Geral de Propriedades'!A29 -> 56 | E4: =VLOOKUP(D4,'Cálculo Geral de Propriedades'!A:X,24,FALSE) -> 843732.94 | F4: ='Cálculo Geral de Propriedades'!A55 -> 123 | G4: =VLOOKUP(F4,'Cálculo Geral de Propriedades'!A:X,24,FALSE) -> 188413.37
B5: ='Cálculo Geral de Propriedades'!A4 -> 2 | C5: =VLOOKUP(B5,'Cálculo Geral de Propriedades'!A:X,24,FALSE) -> 33540757 | D5: ='Cálculo Geral de Propriedades'!A30 -> 57 | E5: =VLOOKUP(D5,'Cálculo Geral de Propriedades'!A:X,24,FALSE) -> 644282.77 | F5: ='Cálculo Geral de Propriedades'!A56 -> 124 | G5: =VLOOKUP(F5,'Cálculo Geral de Propriedades'!A:X,24,FALSE) -> 1481682.2
B6: ='Cálculo Geral de Propriedades'!A5 -> 22 | C6: =VLOOKUP(B6,'Cálculo Geral de Propriedades'!A:X,24,FALSE) -> 479324.37 | D6: ='Cálculo Geral de Propriedades'!A31 -> 58 | E6: =VLOOKUP(D6,'Cálculo Geral de Propriedades'!A:X,24,FALSE) -> 2981115.1 | F6: ='Cálculo Geral de Propriedades'!A57 -> 125 | G6: =VLOOKUP(F6,'Cálculo Geral de Propriedades'!A:X,24,FALSE) -> 153588.78
B7: ='Cálculo Geral de Propriedades'!A6 -> 23 | C7: =VLOOKUP(B7,'Cálculo Geral de Propriedades'!A:X,24,FALSE) -> 2086648.6 | D7: ='Cálculo Geral de Propriedades'!A32 -> 81 | E7: =VLOOKUP(D7,'Cálculo Geral de Propriedades'!A:X,24,FALSE) -> 453877.5 | F7: ='Cálculo Geral de Propriedades'!A58 -> 126 | G7: =VLOOKUP(F7,'Cálculo Geral de Propriedades'!A:X,24,FALSE) -> 649723.73
B8: ='Cálculo Geral de Propriedades'!A7 -> 24 | C8: =VLOOKUP(B8,'Cálculo Geral de Propriedades'!A:X,24,FALSE) -> 2260928.6 | D8: ='Cálculo Geral de Propriedades'!A33 -> 82 | E8: =VLOOKUP(D8,'Cálculo Geral de Propriedades'!A:X,24,FALSE) -> 1206389.1 | F8: ='Cálculo Geral de Propriedades'!A59 -> 127 | G8: =VLOOKUP(F8,'Cálculo Geral de Propriedades'!A:X,24,FALSE) -> 49776.62
B9: ='Cálculo Geral de Propriedades'!A8 -> 25 | C9: =VLOOKUP(B9,'Cálculo Geral de Propriedades'!A:X,24,FALSE) -> 386768.85 | D9: ='Cálculo Geral de Propriedades'!A34 -> 83 | E9: =VLOOKUP(D9,'Cálculo Geral de Propriedades'!A:X,24,FALSE) -> 1405131.4 | F9: ='Cálculo Geral de Propriedades'!A60 -> 128 | G9: =VLOOKUP(F9,'Cálculo Geral de Propriedades'!A:X,24,FALSE) -> 28430.156
B10: ='Cálculo Geral de Propriedades'!A9 -> 26 | C10: =VLOOKUP(B10,'Cálculo Geral de Propriedades'!A:X,24,FALSE) -> 9256381 | D10: ='Cálculo Geral de Propriedades'!A35 -> 84 | E10: =VLOOKUP(D10,'Cálculo Geral de Propriedades'!A:X,24,FALSE) -> 443212.6 | F10: ='Cálculo Geral de Propriedades'!A61 -> 129 | G10: =VLOOKUP(F10,'Cálculo Geral de Propriedades'!A:X,24,FALSE) -> 28382.059
B11: ='Cálculo Geral de Propriedades'!A10 -> 27 | C11: =VLOOKUP(B11,'Cálculo Geral de Propriedades'!A:X,24,FALSE) -> 1159597.4 | D11: ='Cálculo Geral de Propriedades'!A36 -> 85 | E11: =VLOOKUP(D11,'Cálculo Geral de Propriedades'!A:X,24,FALSE) -> 1233341.2 | F11: ='Cálculo Geral de Propriedades'!A62 -> 130 | G11: =VLOOKUP(F11,'Cálculo Geral de Propriedades'!A:X,24,FALSE) -> 25918.217
B12: ='Cálculo Geral de Propriedades'!A11 -> 28 | C12: =VLOOKUP(B12,'Cálculo Geral de Propriedades'!A:X,24,FALSE) -> 1729436.9 | D12: ='Cálculo Geral de Propriedades'!A37 -> 86 | E12: =VLOOKUP(D12,'Cálculo Geral de Propriedades'!A:X,24,FALSE) -> 1413710.1 | F12: ='Cálculo Geral de Propriedades'!A63 -> 131 | G12: =VLOOKUP(F12,'Cálculo Geral de Propriedades'!A:X,24,FALSE) -> 28404.618
B13: ='Cálculo Geral de Propriedades'!A12 -> 29 | C13: =VLOOKUP(B13,'Cálculo Geral de Propriedades'!A:X,24,FALSE) -> 429727.65 | D13: ='Cálculo Geral de Propriedades'!A38 -> 87 | E13: =VLOOKUP(D13,'Cálculo Geral de Propriedades'!A:X,24,FALSE) -> 3071077 | F13: ='Cálculo Geral de Propriedades'!A64 -> 132 | G13: =VLOOKUP(F13,'Cálculo Geral de Propriedades'!A:X,24,FALSE) -> 28437.397
B14: ='Cálculo Geral de Propriedades'!A13 -> 30 | C14: =VLOOKUP(B14,'Cálculo Geral de Propriedades'!A:X,24,FALSE) -> 398900.99 | D14: ='Cálculo Geral de Propriedades'!A39 -> 88 | E14: =VLOOKUP(D14,'Cálculo Geral de Propriedades'!A:X,24,FALSE) -> 1871518.2 | F14: ='Cálculo Geral de Propriedades'!A65 -> 133 | G14: =VLOOKUP(F14,'Cálculo Geral de Propriedades'!A:X,24,FALSE) -> 18636.5
B15: ='Cálculo Geral de Propriedades'!A14 -> 31 | C15: =VLOOKUP(B15,'Cálculo Geral de Propriedades'!A:X,24,FALSE) -> 590895.88 | D15: ='Cálculo Geral de Propriedades'!A40 -> 89 | E15: =VLOOKUP(D15,'Cálculo Geral de Propriedades'!A:X,24,FALSE) -> 1684566.7 | F15: ='Cálculo Geral de Propriedades'!A66 -> 134 | G15: =VLOOKUP(F15,'Cálculo Geral de Propriedades'!A:X,24,FALSE) -> 34664.301
... B28: ='Cálculo Geral de Propriedades'!A27 -> 54 | C28: =VLOOKUP(B28,'Cálculo Geral de Propriedades'!A:X,24,FALSE) -> 746388.59 | D28: ='Cálculo Geral de Propriedades'!A53 -> 121 | E28: =VLOOKUP(D28,'Cálculo Geral de Propriedades'!A:X,24,FALSE) -> 12490037 | F28: ='Cálculo Geral de Propriedades'!A79 -> 147 | G28: =VLOOKUP(F28,'Cálculo Geral de Propriedades'!A:X,24,FALSE) -> 151470.93
B29: ='Cálculo Geral de Propriedades'!A28 -> 55 | C29: =VLOOKUP(B29,'Cálculo Geral de Propriedades'!A:X,24,FALSE) -> 548201.59 | D29: ='Cálculo Geral de Propriedades'!A54 -> 122 | E29: =VLOOKUP(D29,'Cálculo Geral de Propriedades'!A:X,24,FALSE) -> 99760.49
B30: SUBTOTAL = | C30: =SUM(C4:C29) -> 89068265 | D30: SUBTOTAL = | E30: =SUM(E4:E29) -> 35574914 | F30: SUBTOTAL = | G30: =SUM(G4:G28) -> 6854125.9
G32: Parte 02/03
B33: Nº PROPRIEDADE | C33: VALOR ESTIMADO (R$) | D33: Nº PROPRIEDADE | E33: VALOR ESTIMADO (R$) | F33: Nº PROPRIEDADE | G33: VALOR ESTIMADO (R$)
B34: ='Cálculo Geral de Propriedades'!A80 -> 148 | C34: =VLOOKUP(B34,'Cálculo Geral de Propriedades'!A:X,24,FALSE) -> 238497.63 | D34: ='Cálculo Geral de Propriedades'!A129 -> 197 | E34: =VLOOKUP(D34,'Cálculo Geral de Propriedades'!A:X,24,FALSE) -> 214461.17 | F34: ='Cálculo Geral de Propriedades'!A178 -> 246 | G34: =VLOOKUP(F34,'Cálculo Geral de Propriedades'!A:X,24,FALSE) -> 325008.64
B35: ='Cálculo Geral de Propriedades'!A81 -> 149 | C35: =VLOOKUP(B35,'Cálculo Geral de Propriedades'!A:X,24,FALSE) -> 463402.26 | D35: ='Cálculo Geral de Propriedades'!A130 -> 198 | E35: =VLOOKUP(D35,'Cálculo Geral de Propriedades'!A:X,24,FALSE) -> 240394.45 | F35: ='Cálculo Geral de Propriedades'!A179 -> 247 | G35: =VLOOKUP(F35,'Cálculo Geral de Propriedades'!A:X,24,FALSE) -> 461519.38
B36: ='Cálculo Geral de Propriedades'!A82 -> 150 | C36: =VLOOKUP(B36,'Cálculo Geral de Propriedades'!A:X,24,FALSE) -> 102506.27 | D36: ='Cálculo Geral de Propriedades'!A131 -> 199 | E36: =VLOOKUP(D36,'Cálculo Geral de Propriedades'!A:X,24,FALSE) -> 212667.71 | F36: ='Cálculo Geral de Propriedades'!A180 -> 248 | G36: =VLOOKUP(F36,'Cálculo Geral de Propriedades'!A:X,24,FALSE) -> 156922.38
B37: ='Cálculo Geral de Propriedades'!A83 -> 151 | C37: =VLOOKUP(B37,'Cálculo Geral de Propriedades'!A:X,24,FALSE) -> 28176.077 | D37: ='Cálculo Geral de Propriedades'!A132 -> 200 | E37: =VLOOKUP(D37,'Cálculo Geral de Propriedades'!A:X,24,FALSE) -> 284805.15 | F37: ='Cálculo Geral de Propriedades'!A181 -> 249 | G37: =VLOOKUP(F37,'Cálculo Geral de Propriedades'!A:X,24,FALSE) -> 152471.08
B38: ='Cálculo Geral de Propriedades'!A84 -> 152 | C38: =VLOOKUP(B38,'Cálculo Geral de Propriedades'!A:X,24,FALSE) -> 345784.81 | D38: ='Cálculo Geral de Propriedades'!A133 -> 201 | E38: =VLOOKUP(D38,'Cálculo Geral de Propriedades'!A:X,24,FALSE) -> 579139.36 | F38: ='Cálculo Geral de Propriedades'!A182 -> 250 | G38: =VLOOKUP(F38,'Cálculo Geral de Propriedades'!A:X,24,FALSE) -> 158966.22
B39: ='Cálculo Geral de Propriedades'!A85 -> 153 | C39: =VLOOKUP(B39,'Cálculo Geral de Propriedades'!A:X,24,FALSE) -> 846967.58 | D39: ='Cálculo Geral de Propriedades'!A134 -> 202 | E39: =VLOOKUP(D39,'Cálculo Geral de Propriedades'!A:X,24,FALSE) -> 176537.14 | F39: ='Cálculo Geral de Propriedades'!A183 -> 251 | G39: =VLOOKUP(F39,'Cálculo Geral de Propriedades'!A:X,24,FALSE) -> 5769700.9
B40: ='Cálculo Geral de Propriedades'!A86 -> 154 | C40: =VLOOKUP(B40,'Cálculo Geral de Propriedades'!A:X,24,FALSE) -> 489235.68 | D40: ='Cálculo Geral de Propriedades'!A135 -> 203 | E40: =VLOOKUP(D40,'Cálculo Geral de Propriedades'!A:X,24,FALSE) -> 326022.62 | F40: ='Cálculo Geral de Propriedades'!A184 -> 252 | G40: =VLOOKUP(F40,'Cálculo Geral de Propriedades'!A:X,24,FALSE) -> 4401082.3
B41: ='Cálculo Geral de Propriedades'!A87 -> 155 | C41: =VLOOKUP(B41,'Cálculo Geral de Propriedades'!A:X,24,FALSE) -> 561436.43 | D41: ='Cálculo Geral de Propriedades'!A136 -> 204 | E41: =VLOOKUP(D41,'Cálculo Geral de Propriedades'!A:X,24,FALSE) -> 16475.441 | F41: ='Cálculo Geral de Propriedades'!A185 -> 253 | G41: =VLOOKUP(F41,'Cálculo Geral de Propriedades'!A:X,24,FALSE) -> 3658061.5
B42: ='Cálculo Geral de Propriedades'!A88 -> 156 | C42: =VLOOKUP(B42,'Cálculo Geral de Propriedades'!A:X,24,FALSE) -> 129723.98 | D42: ='Cálculo Geral de Propriedades'!A137 -> 205 | E42: =VLOOKUP(D42,'Cálculo Geral de Propriedades'!A:X,24,FALSE) -> 16418.961 | F42: ='Cálculo Geral de Propriedades'!A186 -> 254 | G42: =VLOOKUP(F42,'Cálculo Geral de Propriedades'!A:X,24,FALSE) -> 1293850.2
B43: ='Cálculo Geral de Propriedades'!A89 -> 157 | C43: =VLOOKUP(B43,'Cálculo Geral de Propriedades'!A:X,24,FALSE) -> 183424.29 | D43: ='Cálculo Geral de Propriedades'!A138 -> 206 | E43: =VLOOKUP(D43,'Cálculo Geral de Propriedades'!A:X,24,FALSE) -> 44024.909 | F43: ='Cálculo Geral de Propriedades'!A187 -> 255 | G43: =VLOOKUP(F43,'Cálculo Geral de Propriedades'!A:X,24,FALSE) -> 794646.73
B44: ='Cálculo Geral de Propriedades'!A90 -> 158 | C44: =VLOOKUP(B44,'Cálculo Geral de Propriedades'!A:X,24,FALSE) -> 62223.656 | D44: ='Cálculo Geral de Propriedades'!A139 -> 207 | E44: =VLOOKUP(D44,'Cálculo Geral de Propriedades'!A:X,24,FALSE) -> 16456.175 | F44: ='Cálculo Geral de Propriedades'!A188 -> 256 | G44: =VLOOKUP(F44,'Cálculo Geral de Propriedades'!A:X,24,FALSE) -> 1170495.3
B45: ='Cálculo Geral de Propriedades'!A91 -> 159 | C45: =VLOOKUP(B45,'Cálculo Geral de Propriedades'!A:X,24,FALSE) -> 280013.26 | D45: ='Cálculo Geral de Propriedades'!A140 -> 208 | E45: =VLOOKUP(D45,'Cálculo Geral de Propriedades'!A:X,24,FALSE) -> 47798.892 | F45: ='Cálculo Geral de Propriedades'!A189 -> 257 | G45: =VLOOKUP(F45,'Cálculo Geral de Propriedades'!A:X,24,FALSE) -> 1534018.8
... B82: ='Cálculo Geral de Propriedades'!A128 -> 196 | C82: =VLOOKUP(B82,'Cálculo Geral de Propriedades'!A:X,24,FALSE) -> 86755.563 | D82: ='Cálculo Geral de Propriedades'!A177 -> 245 | E82: =VLOOKUP(D82,'Cálculo Geral de Propriedades'!A:X,24,FALSE) -> 2005455 | F82: ='Cálculo Geral de Propriedades'!A226 -> 294 | G82: =VLOOKUP(F82,'Cálculo Geral de Propriedades'!A:X,24,FALSE) -> 502013.85
B83: SUBTOTAL = | C83: =SUM(C34:C82) -> 18788279 | D83: SUBTOTAL = | E83: =SUM(E34:E82) -> 48878638 | F83: SUBTOTAL = | G83: =SUM(G34:G82) -> 63182309
G85: Parte 03/03
B86: Nº PROPRIEDADE | C86: VALOR ESTIMADO (R$) | D86: Nº PROPRIEDADE | E86: VALOR ESTIMADO (R$) | F86: Nº PROPRIEDADE | G86: VALOR ESTIMADO (R$)
B87: ='Cálculo Geral de Propriedades'!A227 -> 295 | C87: =VLOOKUP(B87,'Cálculo Geral de Propriedades'!A:X,24,FALSE) -> 550399.7 | D87: ='Cálculo Geral de Propriedades'!A256 -> 324 | E87: =VLOOKUP(D87,'Cálculo Geral de Propriedades'!A:X,24,FALSE) -> 2551001 | F87: ='Cálculo Geral de Propriedades'!A285 -> 353 | G87: =VLOOKUP(F87,'Cálculo Geral de Propriedades'!A:X,24,FALSE) -> 14535.868
B88: ='Cálculo Geral de Propriedades'!A228 -> 296 | C88: =VLOOKUP(B88,'Cálculo Geral de Propriedades'!A:X,24,FALSE) -> 278487.43 | D88: ='Cálculo Geral de Propriedades'!A257 -> 325 | E88: =VLOOKUP(D88,'Cálculo Geral de Propriedades'!A:X,24,FALSE) -> 726973.35 | F88: ='Cálculo Geral de Propriedades'!A286 -> 354 | G88: =VLOOKUP(F88,'Cálculo Geral de Propriedades'!A:X,24,FALSE) -> 732682.68
B89: ='Cálculo Geral de Propriedades'!A229 -> 297 | C89: =VLOOKUP(B89,'Cálculo Geral de Propriedades'!A:X,24,FALSE) -> 919405.69 | D89: ='Cálculo Geral de Propriedades'!A258 -> 326 | E89: =VLOOKUP(D89,'Cálculo Geral de Propriedades'!A:X,24,FALSE) -> 656150.01 | F89: ='Cálculo Geral de Propriedades'!A287 -> 355 | G89: =VLOOKUP(F89,'Cálculo Geral de Propriedades'!A:X,24,FALSE) -> 253934
B90: ='Cálculo Geral de Propriedades'!A230 -> 298 | C90: =VLOOKUP(B90,'Cálculo Geral de Propriedades'!A:X,24,FALSE) -> 584378.24 | D90: ='Cálculo Geral de Propriedades'!A259 -> 327 | E90: =VLOOKUP(D90,'Cálculo Geral de Propriedades'!A:X,24,FALSE) -> 249961.58 | F90: ='Cálculo Geral de Propriedades'!A288 -> 356 | G90: =VLOOKUP(F90,'Cálculo Geral de Propriedades'!A:X,24,FALSE) -> 89930.71
B91: ='Cálculo Geral de Propriedades'!A231 -> 299 | C91: =VLOOKUP(B91,'Cálculo Geral de Propriedades'!A:X,24,FALSE) -> 1026058.2 | D91: ='Cálculo Geral de Propriedades'!A260 -> 328 | E91: =VLOOKUP(D91,'Cálculo Geral de Propriedades'!A:X,24,FALSE) -> 735647.19 | F91: ='Cálculo Geral de Propriedades'!A289 -> 357 | G91: =VLOOKUP(F91,'Cálculo Geral de Propriedades'!A:X,24,FALSE) -> 149188.29
B92: ='Cálculo Geral de Propriedades'!A232 -> 300 | C92: =VLOOKUP(B92,'Cálculo Geral de Propriedades'!A:X,24,FALSE) -> 2249886.9 | D92: ='Cálculo Geral de Propriedades'!A261 -> 329 | E92: =VLOOKUP(D92,'Cálculo Geral de Propriedades'!A:X,24,FALSE) -> 2082152.9 | F92: ='Cálculo Geral de Propriedades'!A290 -> 358 | G92: =VLOOKUP(F92,'Cálculo Geral de Propriedades'!A:X,24,FALSE) -> 286111.92
B93: ='Cálculo Geral de Propriedades'!A233 -> 301 | C93: =VLOOKUP(B93,'Cálculo Geral de Propriedades'!A:X,24,FALSE) -> 795854.87 | D93: ='Cálculo Geral de Propriedades'!A262 -> 330 | E93: =VLOOKUP(D93,'Cálculo Geral de Propriedades'!A:X,24,FALSE) -> 370609.39 | F93: ='Cálculo Geral de Propriedades'!A291 -> 359 | G93: =VLOOKUP(F93,'Cálculo Geral de Propriedades'!A:X,24,FALSE) -> 1532516.9
B94: ='Cálculo Geral de Propriedades'!A234 -> 302 | C94: =VLOOKUP(B94,'Cálculo Geral de Propriedades'!A:X,24,FALSE) -> 418156.22 | D94: ='Cálculo Geral de Propriedades'!A263 -> 331 | E94: =VLOOKUP(D94,'Cálculo Geral de Propriedades'!A:X,24,FALSE) -> 512824.59 | F94: ='Cálculo Geral de Propriedades'!A292 -> 360 | G94: =VLOOKUP(F94,'Cálculo Geral de Propriedades'!A:X,24,FALSE) -> 3389811.1
B95: ='Cálculo Geral de Propriedades'!A235 -> 303 | C95: =VLOOKUP(B95,'Cálculo Geral de Propriedades'!A:X,24,FALSE) -> 469947.61 | D95: ='Cálculo Geral de Propriedades'!A264 -> 332 | E95: =VLOOKUP(D95,'Cálculo Geral de Propriedades'!A:X,24,FALSE) -> 440781.3 | F95: ='Cálculo Geral de Propriedades'!A293 -> 361 | G95: =VLOOKUP(F95,'Cálculo Geral de Propriedades'!A:X,24,FALSE) -> 1598747
B96: ='Cálculo Geral de Propriedades'!A236 -> 304 | C96: =VLOOKUP(B96,'Cálculo Geral de Propriedades'!A:X,24,FALSE) -> 876922.39 | D96: ='Cálculo Geral de Propriedades'!A265 -> 333 | E96: =VLOOKUP(D96,'Cálculo Geral de Propriedades'!A:X,24,FALSE) -> 459335.75 | F96: ='Cálculo Geral de Propriedades'!A294 -> 362 | G96: =VLOOKUP(F96,'Cálculo Geral de Propriedades'!A:X,24,FALSE) -> 61006.282
B97: ='Cálculo Geral de Propriedades'!A237 -> 305 | C97: =VLOOKUP(B97,'Cálculo Geral de Propriedades'!A:X,24,FALSE) -> 561654.1 | D97: ='Cálculo Geral de Propriedades'!A266 -> 334 | E97: =VLOOKUP(D97,'Cálculo Geral de Propriedades'!A:X,24,FALSE) -> 1026401.8 | F97: ='Cálculo Geral de Propriedades'!A295 -> 363 | G97: =VLOOKUP(F97,'Cálculo Geral de Propriedades'!A:X,24,FALSE) -> 177343.63
B98: ='Cálculo Geral de Propriedades'!A238 -> 306 | C98: =VLOOKUP(B98,'Cálculo Geral de Propriedades'!A:X,24,FALSE) -> 783858.74 | D98: ='Cálculo Geral de Propriedades'!A267 -> 335 | E98: =VLOOKUP(D98,'Cálculo Geral de Propriedades'!A:X,24,FALSE) -> 937299.03 | F98: ='Cálculo Geral de Propriedades'!A296 -> 364 | G98: =VLOOKUP(F98,'Cálculo Geral de Propriedades'!A:X,24,FALSE) -> 511326.45
... B115: ='Cálculo Geral de Propriedades'!A255 -> 323 | C115: =VLOOKUP(B115,'Cálculo Geral de Propriedades'!A:X,24,FALSE) -> 1492951.4 | D115: ='Cálculo Geral de Propriedades'!A284 -> 352 | E115: =VLOOKUP(D115,'Cálculo Geral de Propriedades'!A:X,24,FALSE) -> 620336.15 | F115: ='Cálculo Geral de Propriedades'!A313 -> 381 | G115: =VLOOKUP(F115,'Cálculo Geral de Propriedades'!A:X,24,FALSE) -> 382544.73
B116: SUBTOTAL = | C116: =SUM(C87:C115) -> 32316812 | D116: SUBTOTAL = | E116: =SUM(E87:E115) -> 27663717 | F116: SUBTOTAL = | G116: =SUM(G87:G115) -> 17003210
F118: TOTAL GERAL = | G118: =SUM(C30,E30,G30,C83,E83,G83,C116,E116,G116) -> 3.3933027e+08
F370: ='Cálculo Geral de Propriedades'!X315 -> 3.3933027e+08
F371: =F370=#REF! -> #REF!

Sheet Valores Est. por Prop. ET.3e4
B1: ETAPA 3
G4: Parte 01/02
B5: Nº PROPRIEDADE | C5: VALOR ESTIMADO (R$) | D5: Nº PROPRIEDADE | E5: VALOR ESTIMADO (R$) | F5: Nº PROPRIEDADE | G5: VALOR ESTIMADO (R$)
B6: ='Cálculo Geral de Propriedades'!A3 -> 1 | C6: =VLOOKUP(B6,'Cálculo Geral de Propriedades'!A:X,24,FALSE) -> 7031146.8 | D6: ='Cálculo Geral de Propriedades'!A29 -> 56 | E6: =VLOOKUP(D6,'Cálculo Geral de Propriedades'!A:X,24,FALSE) -> 843732.94 | F6: ='Cálculo Geral de Propriedades'!A55 -> 123 | G6: =VLOOKUP(F6,'Cálculo Geral de Propriedades'!A:X,24,FALSE) -> 188413.37
B7: ='Cálculo Geral de Propriedades'!A4 -> 2 | C7: =VLOOKUP(B7,'Cálculo Geral de Propriedades'!A:X,24,FALSE) -> 33540757 | D7: ='Cálculo Geral de Propriedades'!A30 -> 57 | E7: =VLOOKUP(D7,'Cálculo Geral de Propriedades'!A:X,24,FALSE) -> 644282.77 | F7: ='Cálculo Geral de Propriedades'!A56 -> 124 | G7: =VLOOKUP(F7,'Cálculo Geral de Propriedades'!A:X,24,FALSE) -> 1481682.2
B8: ='Cálculo Geral de Propriedades'!A5 -> 22 | C8: =VLOOKUP(B8,'Cálculo Geral de Propriedades'!A:X,24,FALSE) -> 479324.37 | D8: ='Cálculo Geral de Propriedades'!A31 -> 58 | E8: =VLOOKUP(D8,'Cálculo Geral de Propriedades'!A:X,24,FALSE) -> 2981115.1 | F8: ='Cálculo Geral de Propriedades'!A57 -> 125 | G8: =VLOOKUP(F8,'Cálculo Geral de Propriedades'!A:X,24,FALSE) -> 153588.78
B9: ='Cálculo Geral de Propriedades'!A6 -> 23 | C9: =VLOOKUP(B9,'Cálculo Geral de Propriedades'!A:X,24,FALSE) -> 2086648.6 | D9: ='Cálculo Geral de Propriedades'!A32 -> 81 | E9: =VLOOKUP(D9,'Cálculo Geral de Propriedades'!A:X,24,FALSE) -> 453877.5 | F9: ='Cálculo Geral de Propriedades'!A58 -> 126 | G9: =VLOOKUP(F9,'Cálculo Geral de Propriedades'!A:X,24,FALSE) -> 649723.73
B10: ='Cálculo Geral de Propriedades'!A7 -> 24 | C10: =VLOOKUP(B10,'Cálculo Geral de Propriedades'!A:X,24,FALSE) -> 2260928.6 | D10: ='Cálculo Geral de Propriedades'!A33 -> 82 | E10: =VLOOKUP(D10,'Cálculo Geral de Propriedades'!A:X,24,FALSE) -> 1206389.1 | F10: ='Cálculo Geral de Propriedades'!A59 -> 127 | G10: =VLOOKUP(F10,'Cálculo Geral de Propriedades'!A:X,24,FALSE) -> 49776.62
B11: ='Cálculo Geral de Propriedades'!A8 -> 25 | C11: =VLOOKUP(B11,'Cálculo Geral de Propriedades'!A:X,24,FALSE) -> 386768.85 | D11: ='Cálculo Geral de Propriedades'!A34 -> 83 | E11: =VLOOKUP(D11,'Cálculo Geral de Propriedades'!A:X,24,FALSE) -> 1405131.4 | F11: ='Cálculo Geral de Propriedades'!A60 -> 128 | G11: =VLOOKUP(F11,'Cálculo Geral de Propriedades'!A:X,24,FALSE) -> 28430.156
B12: ='Cálculo Geral de Propriedades'!A9 -> 26 | C12: =VLOOKUP(B12,'Cálculo Geral de Propriedades'!A:X,24,FALSE) -> 9256381 | D12: ='Cálculo Geral de Propriedades'!A35 -> 84 | E12: =VLOOKUP(D12,'Cálculo Geral de Propriedades'!A:X,24,FALSE) -> 443212.6 | F12: ='Cálculo Geral de Propriedades'!A61 -> 129 | G12: =VLOOKUP(F12,'Cálculo Geral de Propriedades'!A:X,24,FALSE) -> 28382.059
B13: ='Cálculo Geral de Propriedades'!A10 -> 27 | C13: =VLOOKUP(B13,'Cálculo Geral de Propriedades'!A:X,24,FALSE) -> 1159597.4 | D13: ='Cálculo Geral de Propriedades'!A36 -> 85 | E13: =VLOOKUP(D13,'Cálculo Geral de Propriedades'!A:X,24,FALSE) -> 1233341.2 | F13: ='Cálculo Geral de Propriedades'!A62 -> 130 | G13: =VLOOKUP(F13,'Cálculo Geral de Propriedades'!A:X,24,FALSE) -> 25918.217
B14: ='Cálculo Geral de Propriedades'!A11 -> 28 | C14: =VLOOKUP(B14,'Cálculo Geral de Propriedades'!A:X,24,FALSE) -> 1729436.9 | D14: ='Cálculo Geral de Propriedades'!A37 -> 86 | E14: =VLOOKUP(D14,'Cálculo Geral de Propriedades'!A:X,24,FALSE) -> 1413710.1 | F14: ='Cálculo Geral de Propriedades'!A63 -> 131 | G14: =VLOOKUP(F14,'Cálculo Geral de Propriedades'!A:X,24,FALSE) -> 28404.618
B15: ='Cálculo Geral de Propriedades'!A12 -> 29 | C15: =VLOOKUP(B15,'Cálculo Geral de Propriedades'!A:X,24,FALSE) -> 429727.65 | D15: ='Cálculo Geral de Propriedades'!A38 -> 87 | E15: =VLOOKUP(D15,'Cálculo Geral de Propriedades'!A:X,24,FALSE) -> 3071077 | F15: ='Cálculo Geral de Propriedades'!A64 -> 132 | G15: =VLOOKUP(F15,'Cálculo Geral de Propriedades'!A:X,24,FALSE) -> 28437.397
B16: ='Cálculo Geral de Propriedades'!A13 -> 30 | C16: =VLOOKUP(B16,'Cálculo Geral de Propriedades'!A:X,24,FALSE) -> 398900.99 | D16: ='Cálculo Geral de Propriedades'!A39 -> 88 | E16: =VLOOKUP(D16,'Cálculo Geral de Propriedades'!A:X,24,FALSE) -> 1871518.2 | F16: ='Cálculo Geral de Propriedades'!A65 -> 133 | G16: =VLOOKUP(F16,'Cálculo Geral de Propriedades'!A:X,24,FALSE) -> 18636.5
B17: ='Cálculo Geral de Propriedades'!A14 -> 31 | C17: =VLOOKUP(B17,'Cálculo Geral de Propriedades'!A:X,24,FALSE) -> 590895.88 | D17: ='Cálculo Geral de Propriedades'!A40 -> 89 | E17: =VLOOKUP(D17,'Cálculo Geral de Propriedades'!A:X,24,FALSE) -> 1684566.7 | F17: ='Cálculo Geral de Propriedades'!A66 -> 134 | G17: =VLOOKUP(F17,'Cálculo Geral de Propriedades'!A:X,24,FALSE) -> 34664.301
... B30: ='Cálculo Geral de Propriedades'!A27 -> 54 | C30: =VLOOKUP(B30,'Cálculo Geral de Propriedades'!A:X,24,FALSE) -> 746388.59 | D30: ='Cálculo Geral de Propriedades'!A53 -> 121 | E30: =VLOOKUP(D30,'Cálculo Geral de Propriedades'!A:X,24,FALSE) -> 12490037 | F30: ='Cálculo Geral de Propriedades'!A79 -> 147 | G30: =VLOOKUP(F30,'Cálculo Geral de Propriedades'!A:X,24,FALSE) -> 151470.93
B31: ='Cálculo Geral de Propriedades'!A28 -> 55 | C31: =VLOOKUP(B31,'Cálculo Geral de Propriedades'!A:X,24,FALSE) -> 548201.59 | D31: ='Cálculo Geral de Propriedades'!A54 -> 122 | E31: =VLOOKUP(D31,'Cálculo Geral de Propriedades'!A:X,24,FALSE) -> 99760.49
B32: SUBTOTAL = | C32: =SUM(C6:C31) -> 89068265 | D32: SUBTOTAL = | E32: =SUM(E6:E31) -> 35574914 | F32: SUBTOTAL = | G32: =SUM(G6:G30) -> 6854125.9
G34: Parte 02/02
B35: Nº PROPRIEDADE | C35: VALOR ESTIMADO (R$) | D35: Nº PROPRIEDADE | E35: VALOR ESTIMADO (R$) | F35: Nº PROPRIEDADE | G35: VALOR ESTIMADO (R$)
B36: ='Cálculo Geral de Propriedades'!A80 -> 148 | C36: =VLOOKUP(B36,'Cálculo Geral de Propriedades'!A:X,24,FALSE) -> 238497.63 | D36: ='Cálculo Geral de Propriedades'!A109 -> 177 | E36: =VLOOKUP(D36,'Cálculo Geral de Propriedades'!A:X,24,FALSE) -> 74538.371 | F36: ='Cálculo Geral de Propriedades'!A138 -> 206 | G36: =VLOOKUP(F36,'Cálculo Geral de Propriedades'!A:X,24,FALSE) -> 44024.909
B37: ='Cálculo Geral de Propriedades'!A81 -> 149 | C37: =VLOOKUP(B37,'Cálculo Geral de Propriedades'!A:X,24,FALSE) -> 463402.26 | D37: ='Cálculo Geral de Propriedades'!A110 -> 178 | E37: =VLOOKUP(D37,'Cálculo Geral de Propriedades'!A:X,24,FALSE) -> 72254.277 | F37: ='Cálculo Geral de Propriedades'!A139 -> 207 | G37: =VLOOKUP(F37,'Cálculo Geral de Propriedades'!A:X,24,FALSE) -> 16456.175
B38: ='Cálculo Geral de Propriedades'!A82 -> 150 | C38: =VLOOKUP(B38,'Cálculo Geral de Propriedades'!A:X,24,FALSE) -> 102506.27 | D38: ='Cálculo Geral de Propriedades'!A111 -> 179 | E38: =VLOOKUP(D38,'Cálculo Geral de Propriedades'!A:X,24,FALSE) -> 77509.872 | F38: ='Cálculo Geral de Propriedades'!A140 -> 208 | G38: =VLOOKUP(F38,'Cálculo Geral de Propriedades'!A:X,24,FALSE) -> 47798.892
B39: ='Cálculo Geral de Propriedades'!A83 -> 151 | C39: =VLOOKUP(B39,'Cálculo Geral de Propriedades'!A:X,24,FALSE) -> 28176.077 | D39: ='Cálculo Geral de Propriedades'!A112 -> 180 | E39: =VLOOKUP(D39,'Cálculo Geral de Propriedades'!A:X,24,FALSE) -> 206867.81 | F39: ='Cálculo Geral de Propriedades'!A141 -> 209 | G39: =VLOOKUP(F39,'Cálculo Geral de Propriedades'!A:X,24,FALSE) -> 52897.934
B40: ='Cálculo Geral de Propriedades'!A84 -> 152 | C40: =VLOOKUP(B40,'Cálculo Geral de Propriedades'!A:X,24,FALSE) -> 345784.81 | D40: ='Cálculo Geral de Propriedades'!A113 -> 181 | E40: =VLOOKUP(D40,'Cálculo Geral de Propriedades'!A:X,24,FALSE) -> 215348.25 | F40: ='Cálculo Geral de Propriedades'!A142 -> 210 | G40: =VLOOKUP(F40,'Cálculo Geral de Propriedades'!A:X,24,FALSE) -> 494695.92
B41: ='Cálculo Geral de Propriedades'!A85 -> 153 | C41: =VLOOKUP(B41,'Cálculo Geral de Propriedades'!A:X,24,FALSE) -> 846967.58 | D41: ='Cálculo Geral de Propriedades'!A114 -> 182 | E41: =VLOOKUP(D41,'Cálculo Geral de Propriedades'!A:X,24,FALSE) -> 313513.51 | F41: ='Cálculo Geral de Propriedades'!A143 -> 211 | G41: =VLOOKUP(F41,'Cálculo Geral de Propriedades'!A:X,24,FALSE) -> 330492.13
B42: ='Cálculo Geral de Propriedades'!A86 -> 154 | C42: =VLOOKUP(B42,'Cálculo Geral de Propriedades'!A:X,24,FALSE) -> 489235.68 | D42: ='Cálculo Geral de Propriedades'!A115 -> 183 | E42: =VLOOKUP(D42,'Cálculo Geral de Propriedades'!A:X,24,FALSE) -> 284685.24 | F42: ='Cálculo Geral de Propriedades'!A144 -> 212 | G42: =VLOOKUP(F42,'Cálculo Geral de Propriedades'!A:X,24,FALSE) -> 37378.72
B43: ='Cálculo Geral de Propriedades'!A87 -> 155 | C43: =VLOOKUP(B43,'Cálculo Geral de Propriedades'!A:X,24,FALSE) -> 561436.43 | D43: ='Cálculo Geral de Propriedades'!A116 -> 184 | E43: =VLOOKUP(D43,'Cálculo Geral de Propriedades'!A:X,24,FALSE) -> 205627.25 | F43: ='Cálculo Geral de Propriedades'!A145 -> 213 | G43: =VLOOKUP(F43,'Cálculo Geral de Propriedades'!A:X,24,FALSE) -> 214450.16
B44: ='Cálculo Geral de Propriedades'!A88 -> 156 | C44: =VLOOKUP(B44,'Cálculo Geral de Propriedades'!A:X,24,FALSE) -> 129723.98 | D44: ='Cálculo Geral de Propriedades'!A117 -> 185 | E44: =VLOOKUP(D44,'Cálculo Geral de Propriedades'!A:X,24,FALSE) -> 216210.08 | F44: ='Cálculo Geral de Propriedades'!A146 -> 214 | G44: =VLOOKUP(F44,'Cálculo Geral de Propriedades'!A:X,24,FALSE) -> 152978.25
B45: ='Cálculo Geral de Propriedades'!A89 -> 157 | C45: =VLOOKUP(B45,'Cálculo Geral de Propriedades'!A:X,24,FALSE) -> 183424.29 | D45: ='Cálculo Geral de Propriedades'!A118 -> 186 | E45: =VLOOKUP(D45,'Cálculo Geral de Propriedades'!A:X,24,FALSE) -> 648465.84 | F45: ='Cálculo Geral de Propriedades'!A147 -> 215 | G45: =VLOOKUP(F45,'Cálculo Geral de Propriedades'!A:X,24,FALSE) -> 104613.83
B46: ='Cálculo Geral de Propriedades'!A90 -> 158 | C46: =VLOOKUP(B46,'Cálculo Geral de Propriedades'!A:X,24,FALSE) -> 62223.656 | D46: ='Cálculo Geral de Propriedades'!A119 -> 187 | E46: =VLOOKUP(D46,'Cálculo Geral de Propriedades'!A:X,24,FALSE) -> 1701175.9 | F46: ='Cálculo Geral de Propriedades'!A148 -> 216 | G46: =VLOOKUP(F46,'Cálculo Geral de Propriedades'!A:X,24,FALSE) -> 404944.34
B47: ='Cálculo Geral de Propriedades'!A91 -> 159 | C47: =VLOOKUP(B47,'Cálculo Geral de Propriedades'!A:X,24,FALSE) -> 280013.26 | D47: ='Cálculo Geral de Propriedades'!A120 -> 188 | E47: =VLOOKUP(D47,'Cálculo Geral de Propriedades'!A:X,24,FALSE) -> 413699.57 | F47: ='Cálculo Geral de Propriedades'!A149 -> 217 | G47: =VLOOKUP(F47,'Cálculo Geral de Propriedades'!A:X,24,FALSE) -> 257865.05
... B63: ='Cálculo Geral de Propriedades'!A107 -> 175 | C63: =VLOOKUP(B63,'Cálculo Geral de Propriedades'!A:X,24,FALSE) -> 818679.02 | D63: ='Cálculo Geral de Propriedades'!A136 -> 204 | E63: =VLOOKUP(D63,'Cálculo Geral de Propriedades'!A:X,24,FALSE) -> 16475.441 | F63: ='Cálculo Geral de Propriedades'!A165 -> 233 | G63: =VLOOKUP(F63,'Cálculo Geral de Propriedades'!A:X,24,FALSE) -> 405598.93
B64: ='Cálculo Geral de Propriedades'!A108 -> 176 | C64: =VLOOKUP(B64,'Cálculo Geral de Propriedades'!A:X,24,FALSE) -> 132146.36 | D64: ='Cálculo Geral de Propriedades'!A137 -> 205 | E64: =VLOOKUP(D64,'Cálculo Geral de Propriedades'!A:X,24,FALSE) -> 16418.961
B65: SUBTOTAL = | C65: =SUM(C36:C64) -> 12592766 | D65: SUBTOTAL = | E65: =SUM(E36:E64) -> 8262435.6 | F65: SUBTOTAL = | G65: =SUM(G36:G64) -> 19824601
F67: ETAPA 3 - TOTAL = | G67: =SUM(C32,E32,G32,C65,E65,G65) -> 1.7217711e+08
B71: ETAPA 4
G73: Parte 01/01
B74: Nº PROPRIEDADE | C74: VALOR ESTIMADO (R$) | D74: Nº PROPRIEDADE | E74: VALOR ESTIMADO (R$) | F74: Nº PROPRIEDADE | G74: VALOR ESTIMADO (R$)
B75: ='Cálculo Geral de Propriedades'!A166 -> 234 | C75: =VLOOKUP(B75,'Cálculo Geral de Propriedades'!A:X,24,FALSE) -> 4436819.2 | D75: ='Cálculo Geral de Propriedades'!A216 -> 284 | E75: =VLOOKUP(D75,'Cálculo Geral de Propriedades'!A:X,24,FALSE) -> 2508780.7 | F75: ='Cálculo Geral de Propriedades'!A265 -> 333 | G75: =VLOOKUP(F75,'Cálculo Geral de Propriedades'!A:X,24,FALSE) -> 459335.75
B76: ='Cálculo Geral de Propriedades'!A167 -> 235 | C76: =VLOOKUP(B76,'Cálculo Geral de Propriedades'!A:X,24,FALSE) -> 38765.602 | D76: ='Cálculo Geral de Propriedades'!A217 -> 285 | E76: =VLOOKUP(D76,'Cálculo Geral de Propriedades'!A:X,24,FALSE) -> 784587.15 | F76: ='Cálculo Geral de Propriedades'!A266 -> 334 | G76: =VLOOKUP(F76,'Cálculo Geral de Propriedades'!A:X,24,FALSE) -> 1026401.8
B77: ='Cálculo Geral de Propriedades'!A168 -> 236 | C77: =VLOOKUP(B77,'Cálculo Geral de Propriedades'!A:X,24,FALSE) -> 1654392.7 | D77: ='Cálculo Geral de Propriedades'!A218 -> 286 | E77: =VLOOKUP(D77,'Cálculo Geral de Propriedades'!A:X,24,FALSE) -> 1034238.7 | F77: ='Cálculo Geral de Propriedades'!A267 -> 335 | G77: =VLOOKUP(F77,'Cálculo Geral de Propriedades'!A:X,24,FALSE) -> 937299.03
B78: ='Cálculo Geral de Propriedades'!A169 -> 237 | C78: =VLOOKUP(B78,'Cálculo Geral de Propriedades'!A:X,24,FALSE) -> 180544.22 | D78: ='Cálculo Geral de Propriedades'!A219 -> 287 | E78: =VLOOKUP(D78,'Cálculo Geral de Propriedades'!A:X,24,FALSE) -> 486932.48 | F78: ='Cálculo Geral de Propriedades'!A268 -> 336 | G78: =VLOOKUP(F78,'Cálculo Geral de Propriedades'!A:X,24,FALSE) -> 555418.2
B79: ='Cálculo Geral de Propriedades'!A170 -> 238 | C79: =VLOOKUP(B79,'Cálculo Geral de Propriedades'!A:X,24,FALSE) -> 573395.87 | D79: ='Cálculo Geral de Propriedades'!A220 -> 288 | E79: =VLOOKUP(D79,'Cálculo Geral de Propriedades'!A:X,24,FALSE) -> 434198.83 | F79: ='Cálculo Geral de Propriedades'!A269 -> 337 | G79: =VLOOKUP(F79,'Cálculo Geral de Propriedades'!A:X,24,FALSE) -> 372944.07
B80: ='Cálculo Geral de Propriedades'!A171 -> 239 | C80: =VLOOKUP(B80,'Cálculo Geral de Propriedades'!A:X,24,FALSE) -> 547505.95 | D80: ='Cálculo Geral de Propriedades'!A221 -> 289 | E80: =VLOOKUP(D80,'Cálculo Geral de Propriedades'!A:X,24,FALSE) -> 449084.91 | F80: ='Cálculo Geral de Propriedades'!A270 -> 338 | G80: =VLOOKUP(F80,'Cálculo Geral de Propriedades'!A:X,24,FALSE) -> 239463.61
B81: ='Cálculo Geral de Propriedades'!A172 -> 240 | C81: =VLOOKUP(B81,'Cálculo Geral de Propriedades'!A:X,24,FALSE) -> 536709.97 | D81: ='Cálculo Geral de Propriedades'!A222 -> 290 | E81: =VLOOKUP(D81,'Cálculo Geral de Propriedades'!A:X,24,FALSE) -> 824980.27 | F81: ='Cálculo Geral de Propriedades'!A271 -> 339 | G81: =VLOOKUP(F81,'Cálculo Geral de Propriedades'!A:X,24,FALSE) -> 1352043.7
B82: ='Cálculo Geral de Propriedades'!A173 -> 241 | C82: =VLOOKUP(B82,'Cálculo Geral de Propriedades'!A:X,24,FALSE) -> 6739164.8 | D82: ='Cálculo Geral de Propriedades'!A223 -> 291 | E82: =VLOOKUP(D82,'Cálculo Geral de Propriedades'!A:X,24,FALSE) -> 1861598.9 | F82: ='Cálculo Geral de Propriedades'!A272 -> 340 | G82: =VLOOKUP(F82,'Cálculo Geral de Propriedades'!A:X,24,FALSE) -> 4576746
B83: ='Cálculo Geral de Propriedades'!A174 -> 242 | C83: =VLOOKUP(B83,'Cálculo Geral de Propriedades'!A:X,24,FALSE) -> 8208536.3 | D83: ='Cálculo Geral de Propriedades'!A224 -> 292 | E83: =VLOOKUP(D83,'Cálculo Geral de Propriedades'!A:X,24,FALSE) -> 621042.37 | F83: ='Cálculo Geral de Propriedades'!A273 -> 341 | G83: =VLOOKUP(F83,'Cálculo Geral de Propriedades'!A:X,24,FALSE) -> 420633.76
B84: ='Cálculo Geral de Propriedades'!A175 -> 243 | C84: =VLOOKUP(B84,'Cálculo Geral de Propriedades'!A:X,24,FALSE) -> 1274387 | D84: ='Cálculo Geral de Propriedades'!A225 -> 293 | E84: =VLOOKUP(D84,'Cálculo Geral de Propriedades'!A:X,24,FALSE) -> 856733.24 | F84: ='Cálculo Geral de Propriedades'!A274 -> 342 | G84: =VLOOKUP(F84,'Cálculo Geral de Propriedades'!A:X,24,FALSE) -> 367130.66
B85: ='Cálculo Geral de Propriedades'!A176 -> 244 | C85: =VLOOKUP(B85,'Cálculo Geral de Propriedades'!A:X,24,FALSE) -> 791438.29 | D85: ='Cálculo Geral de Propriedades'!A226 -> 294 | E85: =VLOOKUP(D85,'Cálculo Geral de Propriedades'!A:X,24,FALSE) -> 502013.85 | F85: ='Cálculo Geral de Propriedades'!A275 -> 343 | G85: =VLOOKUP(F85,'Cálculo Geral de Propriedades'!A:X,24,FALSE) -> 1771196.5
B86: ='Cálculo Geral de Propriedades'!A177 -> 245 | C86: =VLOOKUP(B86,'Cálculo Geral de Propriedades'!A:X,24,FALSE) -> 2005455 | D86: ='Cálculo Geral de Propriedades'!A227 -> 295 | E86: =VLOOKUP(D86,'Cálculo Geral de Propriedades'!A:X,24,FALSE) -> 550399.7 | F86: ='Cálculo Geral de Propriedades'!A276 -> 344 | G86: =VLOOKUP(F86,'Cálculo Geral de Propriedades'!A:X,24,FALSE) -> 591371.88
... B123: ='Cálculo Geral de Propriedades'!A214 -> 282 | C123: =VLOOKUP(B123,'Cálculo Geral de Propriedades'!A:X,24,FALSE) -> 831424.81 | D123: ='Cálculo Geral de Propriedades'!A264 -> 332 | E123: =VLOOKUP(D123,'Cálculo Geral de Propriedades'!A:X,24,FALSE) -> 440781.3 | F123: ='Cálculo Geral de Propriedades'!A313 -> 381 | G123: =VLOOKUP(F123,'Cálculo Geral de Propriedades'!A:X,24,FALSE) -> 382544.73
B124: ='Cálculo Geral de Propriedades'!A215 -> 283 | C124: =VLOOKUP(B124,'Cálculo Geral de Propriedades'!A:X,24,FALSE) -> 1855213.6
B125: SUBTOTAL = | C125: =SUM(C75:C124) -> 79805233 | D125: SUBTOTAL = | E125: =SUM(E75:E124) -> 51007105 | F125: SUBTOTAL = | G125: =SUM(G75:G124) -> 36340826
F127: ETAPA 4 - TOTAL = | G127: =SUM(C125,E125,G125) -> 1.6715316e+08
G131: =G127+G67 -> 3.3933027e+08
G132: =G131='Valores Est. por Propriedade'!G118 -> TRUE
F286: ='Cálculo Geral de Propriedades'!X315 -> 3.3933027e+08
F287: =F286=#REF! -> #REF!
